Workbook
Name _Hlk13573816: субаренда!#REF!
Name Подразделения: [1]Списки!$A$26:$A$56

Sheet субаренда
B2: № ТТ | C2: адрес | D2: субарендатор | F2: ОКПО | G2: площадь, мкв | H2: Группа товара | I2: акт пп | J2: № договора | K2: Счетчик | L2: 45777 | M2: 45808 | N2: 45838 | O2: 45869 | P2: 45870 | Q2: 45901 | R2: 45931 | S2: 45962 | T2: 45992 | U2: 46023 | V2: Коэф. | W2: Потребление травень 2025 | X2: Потребление червень 2025 | Y2: Потребление липень 2025 | Z2: Потребления сентябрь 2025 | AA2: Потребления октбярь 2025 | AB2: Потребления ноябрь 2025 | AC2: Потребления декабрь 2025 | AD2: Потребления січень 2026 | AE2: Стоимость | AF2: Итого
A3: л | B3: 1-1 | C3: Житомирська обл., м. Житомир, проспект Миру, буд. 15 | D3: ТОВ "Подорожник Житомир" | E3: электроэнергия | F3: 41087452 | G3: 74.8 | H3: аптека | I3: 44795 | J3: № 17/07 від 19 серпня 2022 року | L3: 157082 | M3: 158047 | N3: 158695 | O3: 159785.6 | P3: 160610.5 | Q3: 161338 | R3: 162542 | S3: 163725 | T3: 165551 | U3: 168328 | V3: 1 | W3: =M3-L3 -> 965 | X3: =N3-M3 -> 648 | Y3: =P3-O3 -> 824.9 | Z3: =Q3-P3 -> 727.5 | AA3: =R3-Q3 -> 1204 | AB3: =S3-R3 -> 1183 | AC3: =T3-S3 -> 1826 | AD3: =U3-T3 -> 2777 | AE3: 14.60538 | AF3: =V3*AD3*AE3 -> 40559.14
A4: л | B4: 1-1 | C4: Житомирська обл., м. Житомир, проспект Миру, буд. 15 | E4: Вода | L4: 56 | M4: 58 | N4: 60 | O4: 62 | P4: 64 | Q4: 66 | R4: 68 | S4: 70 | T4: 71 | U4: 71 | V4: 1 | W4: =M4-L4 -> 2 | X4: =N4-M4 -> 2 | Y4: =P4-O4 -> 2 | Z4: =Q4-P4 -> 2 | AA4: =R4-Q4 -> 2 | AB4: =S4-R4 -> 2 | AC4: =T4-S4 -> 1 | AD4: =U4-T4 -> 0 | AE4: 83.177101 | AF4: =V4*AD4*AE4 -> 0
A5: л | B5: 2 | C5: м. Київ, вул. Володимирська, 73/77 | D5: ФОП Ільєнко О.М. | E5: Вода | F5: 2653404868 | G5: 1 | H5: водомат | I5: 45689 | J5: № СУБ-25/ІОМ-Л від 01 лютого 2025 року | L5: 1678.41 | M5: 1699.51 | N5: 1722.02 | O5: 1742.89 | P5: 1765.61 | Q5: 1787.07 | R5: 1811.24 | S5: 1840.66 | T5: 1863.28 | U5: 1885.23 | V5: 1 | W5: =M5-L5 -> 21.1 | X5: =N5-M5 -> 22.51 | Y5: =P5-O5 -> 22.72 | Z5: =Q5-P5 -> 21.46 | AA5: =R5-Q5 -> 24.17 | AB5: =S5-R5 -> 29.42 | AC5: =T5-S5 -> 22.62 | AD5: =U5-T5 -> 21.95 | AE5: 49.691667 | AF5: =V5*AD5*AE5 -> 1090.7321
A6: л | B6: 3 | C6: м. Київ, вул. Раїси Окіпної, будинок 3 | D6: ФОП Красій Я.М. | E6: электроэнергия | F6: 3092608596 | G6: 12 | H6: кофе-чай | I6: 45627 | J6: № СУБ-24/М-3/1 від 01 грудня 2024 року | L6: 713382 | M6: 713960.57 | N6: 714695 | O6: 715651.35 | P6: 716539.85 | Q6: 717295.41 | R6: 717609.95 | S6: 717974.67 | T6: 718481.49 | U6: 719102.6 | V6: 1 | W6: =M6-L6 -> 578.57 | X6: =N6-M6 -> 734.43 | Y6: =P6-O6 -> 888.5 | Z6: =Q6-P6 -> 755.56 | AA6: =R6-Q6 -> 314.54 | AB6: =S6-R6 -> 364.72 | AC6: =T6-S6 -> 506.82 | AD6: =U6-T6 -> 621.11 | AE6: 11.5641 | AF6: =V6*AD6*AE6 -> 7182.5782 | AH6: =1.2*9.92662 -> 11.911944
A7: л | B7: 3 | C7: м. Київ, вул. Раїси Окіпної, будинок 3 | E7: Вода | L7: 129.31 | M7: 130.55 | N7: 131.6 | O7: 132.67 | P7: 133.83 | Q7: 135.23 | R7: 136.11 | S7: 137.09 | T7: 138.24 | U7: 140.25 | V7: 1 | W7: =M7-L7 -> 1.24 | X7: =N7-M7 -> 1.05 | Y7: =P7-O7 -> 1.16 | Z7: =Q7-P7 -> 1.4 | AA7: =R7-Q7 -> 0.88 | AB7: =S7-R7 -> 0.98 | AC7: =T7-S7 -> 1.15 | AD7: =U7-T7 -> 2.01 | AE7: 53.478667 | AF7: =V7*AD7*AE7 -> 107.49212
A8: л | B8: 4-1 | C8: Київська обл., м. Ірпінь, смт. Коцюбинське, вул. Пономарьова, 28-а | D8: ФОП Ільєнко О.М. | E8: Вода | F8: 2653404868 | G8: 1 | H8: водомат | I8: 45717 | J8: № СУБ-25/ІОМ-Л від 01 лютого 2025 року | L8: 27.32 | M8: 38.88 | N8: 50.14 | O8: 63.91 | P8: 74.09 | Q8: 86.05 | R8: 99.13 | S8: 112.8 | T8: 128.1 | U8: 133.35 | V8: 1 | W8: =M8-L8 -> 11.56 | X8: =N8-M8 -> 11.26 | Y8: =P8-O8 -> 10.18 | Z8: =Q8-P8 -> 11.96 | AA8: =R8-Q8 -> 13.08 | AB8: =S8-R8 -> 13.67 | AC8: =T8-S8 -> 15.3 | AD8: =U8-T8 -> 5.25 | AE8: 59.287826 | AF8: =V8*AD8*AE8 -> 311.26109
A9: л | B9: 4-1 | C9: Київська обл., м. Ірпінь, смт. Коцюбинське, вул. Пономарьова, 28-а | D9: ФОП Морозова І.В. | E9: Вода | F9: 2679220364 | G9: 1 | H9: кавовий апарат | I9: 45359 | J9: № СУБ-24/М-4/1 від 08 березня 2024 року | V9: 1 | W9: =M9-L9 -> 0 | X9: =N9-M9 -> 0 | Y9: =P9-O9 -> 0 | Z9: =Q9-P9 -> 0 | AA9: =R9-Q9 -> 0 | AB9: =S9-R9 -> 0 | AC9: =T9-S9 -> 0 | AD9: =U9-T9 -> 0 | AE9: -
A10: л | B10: 5 | C10: м. Київ, вул. Якуба Колоса, № 2 (Літера А) | D10: ФОП Ільєнко О.М. | E10: Вода | F10: 2653404868 | G10: 1 | H10: водомат | I10: 45689 | J10: № СУБ-25/ІОМ-Л від 01 лютого 2025 року | L10: 2372 | M10: 2395 | N10: 2413 | O10: 2431 | P10: 2447.54 | Q10: 2464 | R10: 2476 | S10: 2488 | T10: 2503 | U10: 2517 | V10: 1 | W10: =M10-L10 -> 23 | X10: =N10-M10 -> 18 | Y10: =P10-O10 -> 16.54 | Z10: =Q10-P10 -> 16.46 | AA10: =R10-Q10 -> 12 | AB10: =S10-R10 -> 12 | AC10: =T10-S10 -> 15 | AD10: =U10-T10 -> 14 | AE10: 57.37543 | AF10: =V10*AD10*AE10 -> 803.25602
A11: л | B11: 5 | C11: м. Київ, вул. Якуба Колоса, № 2 (Літера А) | D11: ФОП Капійчук О.С. | E11: электроэнергия | F11: 3556512845 | G11: 1 | H11: кавовий апарат | I11: 45814 | J11: № СУБ-25/М-5/2 від 06 червня 2025 року | L11: 56.9 | M11: 56.9 | N11: 112 | O11: 221 | P11: 324.7 | Q11: 441 | R11: 538 | S11: 665 | T11: 884 | U11: 1086 | V11: 1 | W11: =M11-L11 -> 0 | X11: =N11-M11 -> 55.1 | Y11: =P11-O11 -> 103.7 | Z11: =Q11-P11 -> 116.3 | AA11: =R11-Q11 -> 97 | AB11: =S11-R11 -> 127 | AC11: =T11-S11 -> 219 | AD11: =U11-T11 -> 202 | AE11: 11.911944 | AF11: =V11*AD11*AE11 -> 2406.2127 | AH11: =1.2*9.92662 -> 11.911944
A12: л | B12: 6 | C12: м. Київ, вул. Сікорського Ігоря авіаконструктора, буд. 1-А | D12: ФОП Педаш С.В. | E12: электроэнергия | F12: 2798219324 | G12: 1 | H12: кавовий апарат | I12: 45392 | J12: № СУБ-24/М-6/2 від 10 квітня 2024 року | N12: 0 | O12: 0 | P12: 108 | Q12: 212 | R12: 329 | S12: 445 | T12: 558 | U12: 673 | V12: 1 | W12: =M12-L12 -> 0 | X12: =N12-M12 -> 0 | Y12: =P12-O12 -> 108 | Z12: =Q12-P12 -> 104 | AA12: =R12-Q12 -> 117 | AB12: =S12-R12 -> 116 | AC12: =T12-S12 -> 113 | AD12: =U12-T12 -> 115 | AE12: 11.891892 | AF12: =V12*AD12*AE12 -> 1367.5676 | AH12: =1.2*9.90991 -> 11.891892
A13: л | B13: 6 | C13: м. Київ, вул. Сікорського Ігоря авіаконструктора, буд. 1-А | D13: ФОП Ільєнко О.М. | E13: Вода | F13: 2653404868 | G13: 1 | H13: водомат | I13: 45689 | J13: № СУБ-25/ІОМ-Л від 01 лютого 2025 року | L13: 408 | M13: 438 | N13: 463 | O13: 484 | P13: 495.09 | Q13: 521 | R13: 558 | S13: 592 | T13: 641 | U13: 695 | V13: 1 | W13: =M13-L13 -> 30 | X13: =N13-M13 -> 25 | Y13: =P13-O13 -> 11.09 | Z13: =Q13-P13 -> 25.91 | AA13: =R13-Q13 -> 37 | AB13: =S13-R13 -> 34 | AC13: =T13-S13 -> 49 | AD13: =U13-T13 -> 54 | AE13: 54.505165 | AF13: =V13*AD13*AE13 -> 2943.2789
A14: р | B14: 9/1 | C14: м.Київ, вул. Сім'ї Ідзиковських, 4 | D14: ФОП Маркович О.П. | E14: Вода | F14: 2638518679 | G14: 1 | O14: 0 | P14: 1.79 | Q14: 7 | R14: 12.29 | S14: 18.81 | T14: 26.81 | U14: 34.05 | V14: 1 | Y14: =P14-O14 -> 1.79 | Z14: =Q14-P14 -> 5.21 | AA14: =R14-Q14 -> 5.29 | AB14: =S14-R14 -> 6.52 | AC14: =T14-S14 -> 8 | AD14: =U14-T14 -> 7.24 | AE14: 57.37543 | AF14: =V14*AD14*AE14 -> 415.39811
A15: л | B15: 10 | C15: м. Київ, проспект Героїв Сталінграда, 65-Б | D15: ФОП Ісаков А.О. | E15: электроэнергия | F15: 2915508435 | G15: 10 | H15: рибалка | I15: 45200 | J15: № ОР-23/М-10/1 від 01 жовтня 2023 року | L15: 7101 | M15: 7177 | N15: 7314 | O15: 7481 | P15: 7628 | Q15: 7706 | R15: 7814 | S15: 7856 | T15: 7964 | U15: 8058 | V15: 1 | W15: =M15-L15 -> 76 | X15: =N15-M15 -> 137 | Y15: =P15-O15 -> 147 | Z15: =Q15-P15 -> 78 | AA15: =R15-Q15 -> 108 | AB15: =S15-R15 -> 42 | AC15: =T15-S15 -> 108 | AD15: =U15-T15 -> 94 | AE15: 11.911944 | AF15: 1120
A16: л | B16: 10 | C16: м. Київ, проспект Героїв Сталінграда, 65-Б | D16: ФОП Хуторна А.М. | E16: электроэнергия | G16: 10 | H16: кофе-чай | L16: 53603 | M16: 54350 | N16: 55265 | O16: 56312 | P16: 57114 | Q16: 57785 | R16: 58312 | S16: 58818 | T16: 59401 | U16: 59401 | V16: 1 | W16: =M16-L16 -> 747 | X16: =N16-M16 -> 915 | Y16: =P16-O16 -> 802 | Z16: =Q16-P16 -> 671 | AA16: =R16-Q16 -> 527 | AB16: =S16-R16 -> 506 | AC16: =T16-S16 -> 583 | AD16: =U16-T16 -> 0 | AE16: =AE15 -> 11.911944 | AF16: =V16*AD16*AE16 -> 0
A17: л | B17: 10 | C17: м. Київ, проспект Героїв Сталінграда, 65-Б | E17: Вода | F17: 2880311305 | I17: 45778 | J17: № ОР-25/М-10/6 від 01 травня 2025 року | L17: 70 | M17: 72 | N17: 74 | O17: 75 | P17: 76 | Q17: 78 | R17: 80 | S17: 81 | T17: 83 | U17: 83 | V17: 1 | W17: =M17-L17 -> 2 | X17: =N17-M17 -> 2 | Y17: =P17-O17 -> 1 | Z17: =Q17-P17 -> 2 | AA17: =R17-Q17 -> 2 | AB17: =S17-R17 -> 1 | AC17: =T17-S17 -> 2 | AD17: =U17-T17 -> 0 | AE17: 49.98 | AF17: =V17*AD17*AE17 -> 0
A18: л | B18: 10 | C18: м. Київ, проспект Героїв Сталінграда, 65-Б | D18: ФОП Наумчук М.Г. | E18: электроэнергия | F18: 3388709882 | G18: 18 | H18: зоомагазин | I18: 45352 | J18: № ОР-24/М-10/2 від 01 березня 2024 року | L18: 13297 | M18: 13361 | N18: 13414 | O18: 13478 | P18: 13537 | Q18: 13591 | R18: 13644 | S18: 13697 | T18: 13743 | U18: 13883 | V18: 1 | W18: =M18-L18 -> 64 | X18: =N18-M18 -> 53 | Y18: =P18-O18 -> 59 | Z18: =Q18-P18 -> 54 | AA18: =R18-Q18 -> 53 | AB18: =S18-R18 -> 53 | AC18: =T18-S18 -> 46 | AD18: =U18-T18 -> 140 | AE18: =AE15 -> 11.911944 | AF18: =V18*AD18*AE18 -> 1667.6722
B19: 10 | C19: м. Київ, проспект Героїв Сталінграда, 65-Б | D19: ФОП Трегубова М.А. | E19: электроэнергия | F19: 3142718569 | S19: 1040 | T19: 1114 | U19: 1114 | V19: 1 | AC19: =T19-S19 -> 74 | AD19: =U19-T19 -> 0 | AE19: =AE16 -> 11.911944 | AF19: =V19*AD19*AE19 -> 0
A20: л | B20: 10 | C20: м. Київ, проспект Героїв Сталінграда, 65-Б | D20: ТОВ Массмарт | E20: электроэнергия | F20: 41747891 | G20: 130 | H20: белое/сухое | L20: 381253 | M20: 383658 | N20: 386424 | O20: 390122 | P20: 393305 | Q20: 395914 | R20: 398016 | S20: 399645 | T20: 401912 | U20: 404497 | V20: 1 | W20: =M20-L20 -> 2405 | X20: =N20-M20 -> 2766 | Y20: =P20-O20 -> 3183 | Z20: =Q20-P20 -> 2609 | AA20: =R20-Q20 -> 2102 | AB20: =S20-R20 -> 1629 | AC20: =T20-S20 -> 2267 | AD20: =U20-T20 -> 2585 | AE20: =AE15 -> 11.911944 | AF20: =V20*AD20*AE20 -> 30792.375
A21: л | B21: 10 | C21: м. Київ, проспект Героїв Сталінграда, 65-Б | E21: Вода | F21: 41747891 | I21: 45413 | J21: № ОР-24/М-10/3 від 01 травня 2024 року | L21: 1287 | M21: 1481 | N21: 1651 | O21: 1824 | P21: 1989 | Q21: 2161 | R21: 2282 | S21: 2525 | T21: 2782 | U21: 2940 | V21: 1 | W21: =M21-L21 -> 194 | X21: =N21-M21 -> 170 | Y21: =P21-O21 -> 165 | Z21: =Q21-P21 -> 172 | AA21: =R21-Q21 -> 121 | AB21: =S21-R21 -> 243 | AC21: =T21-S21 -> 257 | AD21: =U21-T21 -> 158 | AE21: =AE17 -> 49.98 | AF21: =V21*AD21*AE21 -> 7896.84
A22: р | B22: 11-1 | C22: м. Київ, вул. Автозаводська, 27 | D22: ФОП Ільєнко О.М. | E22: Вода | F22: 2653404868 | G22: 1 | H22: водомат | I22: 45689 | J22: № СУБ-25/ІОМ-Р від 01 лютого 2025 року | L22: 512.53 | M22: 532.35 | N22: 556 | O22: 579.72 | P22: 601.44 | Q22: 629.5 | R22: 654.2 | S22: 675.03 | T22: 698.24 | U22: 706.77 | V22: 1 | W22: =M22-L22 -> 19.82 | X22: =N22-M22 -> 23.65 | Y22: =P22-O22 -> 21.72 | Z22: =Q22-P22 -> 28.06 | AA22: =R22-Q22 -> 24.7 | AB22: =S22-R22 -> 20.83 | AC22: =T22-S22 -> 23.21 | AD22: =U22-T22 -> 8.53 | AE22: =AE21 -> 49.98 | AF22: =V22*AD22*AE22 -> 426.3294
A23: р | B23: 11-1 | C23: м. Київ, вул. Автозаводська, 27 | D23: ФОП Педаш С.В. | E23: электроэнергия | F23: 2798219324 | G23: 1 | H23: кавовий апарат | I23: 45392 | J23: № СУБ-24/М-11/1 від 10 квітня 2024 року | O23: 1 | P23: 39.9 | Q23: 140.2 | R23: 254.2 | S23: 369.4 | T23: 484.3 | U23: 644 | V23: 1 | W23: =M23-L23 -> 0 | X23: =N23-M23 -> 0 | Y23: =P23-O23 -> 38.9 | Z23: =Q23-P23 -> 100.3 | AA23: =R23-Q23 -> 114 | AB23: =S23-R23 -> 115.2 | AC23: =T23-S23 -> 114.9 | AD23: =U23-T23 -> 159.7 | AE23: 11.91194 | AF23: =V23*AD23*AE23 -> 1902.3368
A24: л | B24: 12 | C24: м. Київ, вул. Антоновича, 115-Д | D24: ТОВ Лайфселл | E24: электроэнергия | F24: 22859846 | G24: 3 | H24: антенна | I24: 44986 | J24: № М12-СО від 01 березня 2023 року | L24: 40619 | M24: 41398.3 | N24: 42138 | O24: 42877.9 | P24: 0 | Q24: 585.91 | R24: 1303.9 | S24: 1994.92 | T24: 2689.01 | U24: 3416.2 | V24: 1 | W24: =M24-L24 -> 779.3 | X24: =N24-M24 -> 739.7 | Y24: 790 | Z24: 710 | AA24: =R24-Q24 -> 717.99 | AB24: =S24-R24 -> 691.02 | AC24: =T24-S24 -> 694.09 | AD24: =U24-T24 -> 727.19 | AE24: 11.91194 | AF24: =V24*AD24*AE24 -> 8662.2436
A25: л | B25: 12 | C25: м. Київ, вул. Антоновича, 115-Д | D25: ТОВ "Юкрейн Таувер Компані" | E25: электроэнергия | F25: 44281999 | G25: 3 | H25: антенна | I25: 45693 | J25: № TUA3725 від 05 лютого 2025 року | L25: 27659.7 | M25: 28621.5 | N25: 29610 | O25: 30601.6 | P25: 31668.7 | Q25: 33065.1 | R25: 34631.1 | S25: 36331.5 | T25: 38033.1 | U25: 39692.8 | V25: 1 | W25: =M25-L25 -> 961.8 | X25: =N25-M25 -> 988.5 | Y25: =P25-O25 -> 1067.1 | Z25: =Q25-P25 -> 1396.4 | AA25: =R25-Q25 -> 1566 | AB25: =S25-R25 -> 1700.4 | AC25: =T25-S25 -> 1701.6 | AD25: =U25-T25 -> 1659.7 | AE25: =AE24 -> 11.91194 | AF25: =V25*AD25*AE25 -> 19770.247
A26: р | B26: 13-1 | C26: Київська обл., Києво-Святошинський район, с. Тарасівка, вул. Братів Чмілів, буд. 3-А | D26: ФОП Басов Е. А. | E26: Вода | F26: 2634610713 | G26: 1 | H26: водомат | I26: 45627 | J26: № СУБ-24/БЕА-Р від 01 грудня 2024 року | L26: 1126 | M26: 1143 | N26: 1158 | O26: 1174 | P26: 1194 | Q26: 1220 | R26: 1237 | S26: 1259 | T26: 1283 | U26: 1309 | V26: 1 | W26: =M26-L26 -> 17 | X26: =N26-M26 -> 15 | Y26: =P26-O26 -> 20 | Z26: =Q26-P26 -> 26 | AA26: =R26-Q26 -> 17 | AB26: =S26-R26 -> 22 | AC26: =T26-S26 -> 24 | AD26: =U26-T26 -> 26 | AE26: 108.33048 | AF26: =V26*AD26*AE26 -> 2816.5924
A27: р | B27: 13-1 | C27: Київська обл., Києво-Святошинський район, с. Тарасівка, вул. Братів Чмілів, буд. 3-А | D27: ФОП Литвиненко О.М. | E27: электроэнергия | F27: 2959508626 | G27: 40 | H27: зоотовары и моб.аксессуары | I27: 45627 | J27: № СУБ-24/М-13/2 від 01 грудня 2024 року | L27: 12469 | M27: 12636 | N27: 12819 | O27: 12990 | P27: 13168 | Q27: 13349 | R27: 13515 | S27: 13733 | T27: 13931 | U27: 14230 | V27: 1 | W27: =M27-L27 -> 167 | X27: =N27-M27 -> 183 | Y27: =P27-O27 -> 178 | Z27: =Q27-P27 -> 181 | AA27: =R27-Q27 -> 166 | AB27: =S27-R27 -> 218 | AC27: =T27-S27 -> 198 | AD27: =U27-T27 -> 299 | AE27: 12.197472 | AF27: =V27*AD27*AE27 -> 3647.0441 | AH27: =1.2*10.16456 -> 12.197472
A28: р | B28: 13-1 | C28: Київська обл., Києво-Святошинський район, с. Тарасівка, вул. Братів Чмілів, буд. 3-А | E28: Вода | L28: 33 | M28: 34 | N28: 35 | O28: 36 | P28: 37 | Q28: 40 | R28: 41 | S28: 43 | T28: 46 | U28: 48 | V28: 1 | W28: =M28-L28 -> 1 | X28: =N28-M28 -> 1 | Y28: =P28-O28 -> 1 | Z28: =Q28-P28 -> 3 | AA28: =R28-Q28 -> 1 | AB28: =S28-R28 -> 2 | AC28: =T28-S28 -> 3 | AD28: =U28-T28 -> 2 | AE28: =AE26 -> 108.33048 | AF28: =V28*AD28*AE28 -> 216.66095
A29: р | B29: 13-1 | C29: Київська обл., Києво-Святошинський район, с. Тарасівка, вул. Братів Чмілів, буд. 3-А | D29: ФОП Войтов П.О. | E29: электроэнергия | F29: 3081921694 | G29: 1 | H29: кавовий апарат | I29: 45793 | J29: № СУБ-25/М-13/1 від 16 травня 2025 року | M29: 0 | N29: 0 | O29: 53.2 | P29: 106 | Q29: 160 | R29: 211 | S29: 254 | T29: 289 | U29: 375 | V29: 1 | W29: =M29-L29 -> 0 | X29: =N29-M29 -> 0 | Y29: =P29-O29 -> 52.8 | Z29: =Q29-P29 -> 54 | AA29: =R29-Q29 -> 51 | AB29: =S29-R29 -> 43 | AC29: =T29-S29 -> 35 | AD29: =U29-T29 -> 86 | AE29: =AE27 -> 12.197472 | AF29: =V29*AD29*AE29 -> 1048.9826
A30: л | B30: 14 | C30: м. Київ, вул. Світла, буд. 3-Д, корп. 1, приміщення 2013 | D30: ФОП Ридван І. Г. | E30: Вода | F30: 3016517362 | G30: 1 | H30: водомат | I30: 45627 | J30: № СУБ-24/РІГ-Л від 01 грудня 2024 року | L30: 2684 | M30: 2697 | N30: 2708 | O30: 2718 | P30: 2729 | Q30: 2741 | R30: 2752 | S30: 2765 | T30: 2776.3 | U30: 2785 | V30: 1 | W30: =M30-L30 -> 13 | X30: =N30-M30 -> 11 | Y30: =P30-O30 -> 11 | Z30: =Q30-P30 -> 12 | AA30: =R30-Q30 -> 11 | AB30: =S30-R30 -> 13 | AC30: =T30-S30 -> 11.3 | AD30: =U30-T30 -> 8.7 | AE30: 49.98 | AF30: =V30*AD30*AE30 -> 434.826
A31: л | B31: 15 | C31: м. Київ, вул. Шолом-Алейхема, буд. 10-А | D31: ФОП Ільєнко О.М. | E31: Вода | F31: 2653404868 | G31: 1 | H31: водомат | I31: 45689 | J31: № ОР-25/ІОМ від 01 лютого 2025 року | L31: 1226.76 | M31: 1233.82 | N31: 1240.9 | O31: 1247.61 | P31: 1253.3 | Q31: 1259.99 | R31: 1267.74 | S31: 1273.46 | T31: 1281.66 | U31: 1291.54 | V31: 1 | W31: =M31-L31 -> 7.06 | X31: =N31-M31 -> 7.08 | Y31: =P31-O31 -> 5.69 | Z31: =Q31-P31 -> 6.69 | AA31: =R31-Q31 -> 7.75 | AB31: =S31-R31 -> 5.72 | AC31: =T31-S31 -> 8.2 | AD31: =U31-T31 -> 9.88 | AE31: 54.89 | AF31: =V31*AD31*AE31 -> 542.3132
A32: л | B32: 15 | C32: м. Київ, вул. Шолом-Алейхема, буд. 10-А | D32: ТОВ ПНМЕК "ТОКА" | E32: электроэнергия | F32: 40062282 | G32: 1 | H32: электрозаправка | I32: 45261 | J32: № ОР-23/М-15/1 від 01 грудня 2023 року | L32: 36811.16 | M32: 37019.03 | N32: 37204.34 | O32: 37633.31 | P32: 38273.78 | Q32: 38855.12 | R32: 39731.75 | S32: 40076.7 | T32: 40952.94 | U32: 41432.1 | V32: 1 | W32: =M32-L32 -> 207.87 | X32: =N32-M32 -> 185.31 | Y32: =P32-O32 -> 640.47 | Z32: =Q32-P32 -> 581.34 | AA32: =R32-Q32 -> 876.63 | AB32: =S32-R32 -> 344.95 | AC32: =T32-S32 -> 876.24 | AD32: =U32-T32 -> 479.16 | AE32: 11.974956 | AF32: =V32*AD32*AE32 -> 5737.9199 | AH32: =1.2*9.97913 -> 11.974956
A33: л | B33: 15 | C33: м. Київ, вул. Шолом-Алейхема, буд. 10-А | D33: ПАТ Київстар | E33: электроэнергия | F33: 21673832 | G33: 5 | H33: антенна | I33: 45292 | J33: № 01/01/2024 -СО від 01 січня 2024 року | L33: 59790.7 | M33: 61444.2 | N33: 63020.3 | O33: 64712.1 | P33: 66329.9 | Q33: 67879.5 | R33: 69545.7 | S33: 70902.4 | T33: 72474.9 | U33: 74774.5 | V33: 1 | W33: =M33-L33 -> 1653.5 | X33: =N33-M33 -> 1576.1 | Y33: =P33-O33 -> 1617.8 | Z33: =Q33-P33 -> 1549.6 | AA33: =R33-Q33 -> 1666.2 | AB33: =S33-R33 -> 1356.7 | AC33: =T33-S33 -> 1572.5 | AD33: =U33-T33 -> 2299.6 | AE33: =AE32 -> 11.974956 | AF33: =V33*AD33*AE33 -> 27537.609
A34: л | B34: 15 | C34: м. Київ, вул. Шолом-Алейхема, буд. 10-А | D34: ТОВ Лайфселл | E34: электроэнергия | F34: 22859846 | G34: 3 | H34: антенна | I34: 44986 | J34: № М15-О від 01 березня 2023 року | L34: 53920 | M34: 53952 | N34: 54720.4 | O34: 55532.4 | P34: 56314.5 | Q34: 57081.7 | R34: 57935 | S34: 58458 | T34: 59028.6 | U34: 59545.6 | V34: 1 | W34: =M34-L34 -> 32 | X34: =N34-M34 -> 768.4 | Y34: =P34-O34 -> 782.1 | Z34: =Q34-P34 -> 767.2 | AA34: =R34-Q34 -> 853.3 | AB34: =S34-R34 -> 523 | AC34: =T34-S34 -> 570.6 | AD34: =U34-T34 -> 517 | AE34: =AE32 -> 11.974956 | AF34: =V34*AD34*AE34 -> 6191.0523
A35: л | B35: 15 | C35: м. Київ, вул. Шолом-Алейхема, буд. 10-А | D35: ПАТ "ВФ Україна" | E35: электроэнергия | F35: 14333937 | G35: 3 | H35: антенна | I35: 45231 | J35: № RC-23-510915 від 01 листопада 2023 року | L35: 25688.46 | M35: 27199.04 | N35: 28620.33 | O35: 30197.49 | P35: 31708.06 | Q35: 33188.43 | R35: 34848.64 | S35: 36078.44 | T35: 37493.99 | U35: 38672.72 | V35: 1 | W35: =M35-L35 -> 1510.58 | X35: =N35-M35 -> 1421.29 | Y35: =P35-O35 -> 1510.57 | Z35: =Q35-P35 -> 1480.37 | AA35: =R35-Q35 -> 1660.21 | AB35: =S35-R35 -> 1229.8 | AC35: =T35-S35 -> 1415.55 | AD35: =U35-T35 -> 1178.73 | AE35: =AE32 -> 11.974956 | AF35: =V35*AD35*AE35 -> 14115.24
A36: л | B36: 15 | C36: м. Київ, вул. Шолом-Алейхема, буд. 10-А | D36: ТОВ "ЕКО ВОДА" | E36: электроэнергия | F36: 40971728 | G36: 8 | H36: пункт разлива воды | I36: 45371 | J36: № ОР-24/М-15/2 від 20 березня 2024 року | L36: 3699.9 | M36: 3882.6 | N36: 4071.4 | O36: 4291.4 | P36: 4491.2 | Q36: 4686.9 | R36: 4949.5 | S36: 5285.7 | T36: 5904.1 | U36: 6608.6 | V36: 1 | W36: =M36-L36 -> 182.7 | X36: =N36-M36 -> 188.8 | Y36: =P36-O36 -> 199.8 | Z36: =Q36-P36 -> 195.7 | AA36: =R36-Q36 -> 262.6 | AB36: =S36-R36 -> 336.2 | AC36: =T36-S36 -> 618.4 | AD36: =U36-T36 -> 704.5 | AE36: =AE32 -> 11.974956 | AF36: =V36*AD36*AE36 -> 8436.3565
A37: л | B37: 15 | C37: м. Київ, вул. Шолом-Алейхема, буд. 10-А | E37: Вода | L37: 608.1 | M37: 672.02 | N37: 742.88 | O37: 826.7 | P37: 897.38 | Q37: 971.68 | R37: 1058.75 | S37: 1134.44 | T37: 1228.98 | U37: 1314.13 | V37: 1 | W37: =M37-L37 -> 63.92 | X37: =N37-M37 -> 70.86 | Y37: =P37-O37 -> 70.68 | Z37: =Q37-P37 -> 74.3 | AA37: =R37-Q37 -> 87.07 | AB37: =S37-R37 -> 75.69 | AC37: =T37-S37 -> 94.54 | AD37: =U37-T37 -> 85.15 | AE37: =AE31 -> 54.89 | AF37: =V37*AD37*AE37 -> 4673.8835
A38: л | B38: 15 | C38: м. Київ, вул. Шолом-Алейхема, буд. 10-А | D38: ФОП Ковальова А.О. | E38: электроэнергия | F38: 3380916566 | G38: 1 | H38: кавовий апарат | I38: 45474 | J38: № ОР-24/М-15/3 від 01 липня 2024 року | M38: 1.5 | N38: 1.5 | O38: 5.4 | P38: 69.5 | Q38: 132.9 | R38: 182.3 | S38: 182.3 | T38: 240.7 | U38: 285.9 | V38: 1 | W38: =M38-L38 -> 1.5 | X38: =N38-M38 -> 0 | Y38: =P38-O38 -> 64.1 | Z38: =Q38-P38 -> 63.4 | AA38: =R38-Q38 -> 49.4 | AB38: =S38-R38 -> 0 | AC38: =T38-S38 -> 58.4 | AD38: =U38-T38 -> 45.2 | AE38: =AE34 -> 11.974956 | AF38: =V38*AD38*AE38 -> 541.26801
A39: р | B39: 17-1 | C39: Київська обл., Бориспільський район, м. Бориспіль, вулиця Головатого, 64, приміщення 156 | D39: ФОП Ткач Ю.С. | E39: электроэнергия | F39: 3704207084 | G39: 1 | H39: кавовий апарат | I39: 45336 | J39: № СУБ-24/М-17/2 від 14 лютого 2024 року | V39: 1 | W39: =M39-L39 -> 0 | X39: =N39-M39 -> 0 | Y39: =P39-O39 -> 0 | Z39: =Q39-P39 -> 0 | AA39: =R39-Q39 -> 0 | AB39: =S39-R39 -> 0 | AC39: =T39-S39 -> 0 | AD39: =U39-T39 -> 0 | AE39: -
A40: л | B40: 18 | C40: м. Київ, вул. Челябінська, 15-А | D40: ФОП Ридван І. Г. | E40: Вода | F40: 3016517362 | G40: 1 | H40: водомат | I40: 45627 | J40: № СУБ-24/РІГ-Л від 01 грудня 2024 року | L40: 1014.5 | M40: 1020.45 | N40: 1024.81 | O40: 1029.63 | P40: 1034.93 | Q40: 1039.11 | R40: 1041.78 | S40: 1044.19 | T40: 1046.24 | U40: 1048.25 | V40: 1 | W40: =M40-L40 -> 5.95 | X40: =N40-M40 -> 4.36 | Y40: =P40-O40 -> 5.3 | Z40: =Q40-P40 -> 4.18 | AA40: =R40-Q40 -> 2.67 | AB40: =S40-R40 -> 2.41 | AC40: =T40-S40 -> 2.05 | AD40: =U40-T40 -> 2.01 | AE40: 52.979167 | AF40: =V40*AD40*AE40 -> 106.48812
A41: л | B41: 18 | C41: м. Київ, вул. Челябінська, 15-А | D41: ФОП Шамахмудов Р.Х. | E41: электроэнергия | F41: 2912901337 | G41: 1 | H41: кавовий апарат | I41: 45775 | J41: № СУБ-25/М-18/2 від 28 квітня 2025 року | L41: 182 | M41: 288.6 | N41: 398 | O41: 534 | P41: 661.6 | Q41: 778.8 | R41: 893.5 | S41: 991.7 | T41: 1090.3 | U41: 1090.3 | V41: 1 | W41: =M41-L41 -> 106.6 | X41: =N41-M41 -> 109.4 | Y41: =P41-O41 -> 127.6 | Z41: =Q41-P41 -> 117.2 | AA41: =R41-Q41 -> 114.7 | AB41: =S41-R41 -> 98.2 | AC41: =T41-S41 -> 98.6 | AD41: =U41-T41 -> 0 | AE41: 12.779568 | AF41: =V41*AD41*AE41 -> 0 | AH41: =1.2*10.64964 -> 12.779568
A42: л | B42: 20 | C42: м. Київ, Дарницький район, вул. Бориспільська, 32-А | D42: ФОП Басов Е. А. | E42: Вода | F42: 2634610713 | G42: 1 | H42: водомат | I42: 45627 | J42: № СУБ-24/БАЕ-Л від 01 грудня 2024 року | L42: 1327 | M42: 1343 | N42: 1357 | O42: 1368 | P42: 1381 | Q42: 1399 | R42: 1423 | S42: 1448 | T42: 1475 | U42: 1499 | V42: 1 | W42: =M42-L42 -> 16 | X42: =N42-M42 -> 14 | Y42: =P42-O42 -> 13 | Z42: =Q42-P42 -> 18 | AA42: =R42-Q42 -> 24 | AB42: =S42-R42 -> 25 | AC42: =T42-S42 -> 27 | AD42: =U42-T42 -> 24 | AE42: 56.47 | AF42: =V42*AD42*AE42 -> 1355.28
A43: л | B43: 21 | C43: Київська обл., м. Ірпінь, вулиця Тургенівська, буд. 50Б | D43: ФОП Ільєнко О.М. | E43: Вода | F43: 2653404868 | G43: 1 | H43: водомат | I43: 45689 | J43: № СУБ-25/ІОМ-Л від 01 лютого 2025 року | L43: 3957.15 | M43: 4014.32 | N43: 4047.81 | O43: 4087.41 | P43: 4137.27 | Q43: 4181.64 | R43: 4227 | S43: 4273.41 | T43: 4311.72 | U43: 4348.63 | V43: 1 | W43: =M43-L43 -> 57.17 | X43: =N43-M43 -> 33.49 | Y43: =P43-O43 -> 49.86 | Z43: =Q43-P43 -> 44.37 | AA43: =R43-Q43 -> 45.36 | AB43: =S43-R43 -> 46.41 | AC43: =T43-S43 -> 38.31 | AD43: =U43-T43 -> 36.91 | AE43: 67.28 | AF43: =V43*AD43*AE43 -> 2483.3048
A44: л | B44: 21 | C44: Київська обл., м. Ірпінь, вулиця Тургенівська, буд. 50Б | D44: ФОП Христич А.В. | E44: Вода | F44: 3420415308 | G44: 1 | H44: кавовий апарат | I44: 45778 | J44: № СУБ-25/М-21/1 від 01 травня 2025 року | V44: 1 | W44: =M44-L44 -> 0 | X44: =N44-M44 -> 0 | Y44: =P44-O44 -> 0 | Z44: =Q44-P44 -> 0 | AA44: =R44-Q44 -> 0 | AB44: =S44-R44 -> 0 | AC44: =T44-S44 -> 0 | AD44: =U44-T44 -> 0 | AE44: -
A45: л | B45: 21 | C45: Київська обл., м. Ірпінь, вулиця Тургенівська, буд. 50Б | D45: ТОВ "ВИЖН ТРЕЙД" | E45: электроэнергия | F45: 45602852 | G45: 3 | H45: вейпи | I45: 45784 | J45: № СУБ-25/М-21/2 від 01 травня 2025 року | L45: 11992 | M45: 11992 | N45: 12271.6 | O45: 12667.6 | P45: 12968 | Q45: 13217.1 | R45: 13628 | S45: 13953 | T45: 14159.6 | U45: 14285.9 | V45: 1 | W45: =M45-L45 -> 0 | X45: =N45-M45 -> 279.6 | Y45: =P45-O45 -> 300.4 | Z45: =Q45-P45 -> 249.1 | AA45: =R45-Q45 -> 410.9 | AB45: =S45-R45 -> 325 | AC45: =T45-S45 -> 206.6 | AD45: =U45-T45 -> 126.3 | AE45: 11.781108 | AF45: =V45*AD45*AE45 -> 1487.9539 | AH45: =1.2*9.81759 -> 11.781108
A46: л | B46: 22 | C46: м. Київ, вул. Вітряні Гори, будинок 21/7 (літера А) | D46: ФОП Ільєнко О.М. | E46: Вода | F46: 2653404868 | G46: 1 | H46: водомат | I46: 45689 | J46: № СУБ-25/ІОМ-Л від 01 лютого 2025 року | L46: 988 | M46: 997 | N46: 1003 | O46: 1010 | P46: 1015 | Q46: 1021 | R46: 1028 | S46: 1034 | T46: 1040 | U46: 1046 | V46: 1 | W46: =M46-L46 -> 9 | X46: =N46-M46 -> 6 | Y46: =P46-O46 -> 5 | Z46: =Q46-P46 -> 6 | AA46: =R46-Q46 -> 7 | AB46: =S46-R46 -> 6 | AC46: =T46-S46 -> 6 | AD46: =U46-T46 -> 6 | AE46: 56.47 | AF46: =V46*AD46*AE46 -> 338.82
A47: л | B47: 23 | C47: м. Київ, бул. В. Гавела, 18 | D47: ФОП Ільєнко О.М. | E47: Вода | F47: 2653404868 | G47: 1 | H47: водомат | I47: 45717 | J47: № СУБ-25/ІОМ-Л від 01 лютого 2025 року | L47: 36.54 | M47: 52.56 | N47: 67.05 | O47: 80.73 | P47: 94.89 | Q47: 111.46 | R47: 133.29 | S47: 160.68 | T47: 189.54 | U47: 218.59 | V47: 1 | W47: =M47-L47 -> 16.02 | X47: =N47-M47 -> 14.49 | Y47: =P47-O47 -> 14.16 | Z47: =Q47-P47 -> 16.57 | AA47: =R47-Q47 -> 21.83 | AB47: =S47-R47 -> 27.39 | AC47: =T47-S47 -> 28.86 | AD47: =U47-T47 -> 29.05 | AE47: 49.980008 | AF47: =V47*AD47*AE47 -> 1451.9192 | AH47: =1.2*41.65 -> 49.98
A48: л | B48: 23 | C48: м. Київ, бул. В. Гавела, 18 | D48: ФОП Драгомирецька І.Ю. | E48: электроэнергия | F48: 3454605546 | G48: 2 | H48: кавовий апарат | I48: 45079 | J48: № М23-Д-СО від 26 травня 2023 року | M48: 1 | N48: 1 | O48: 58.3 | P48: 164.3 | Q48: 266.9 | R48: 369.7 | S48: 470.1 | T48: 586.9 | U48: 687.6 | V48: 1 | W48: =M48-L48 -> 1 | X48: =N48-M48 -> 0 | Y48: =P48-O48 -> 106 | Z48: =Q48-P48 -> 102.6 | AA48: =R48-Q48 -> 102.8 | AB48: =S48-R48 -> 100.4 | AC48: =T48-S48 -> 116.8 | AD48: =U48-T48 -> 100.7 | AE48: 12.061584 | AF48: =V48*AD48*AE48 -> 1214.6015 | AH48: =1.2*10.05132 -> 12.061584
A49: л | B49: 23 | C49: м. Київ, бул. В. Гавела, 18 | D49: ФОП Даниловська О. М. | E49: электроэнергия | F49: 3096407201 | G49: 7.2 | H49: кофе-чай | I49: 45413 | J49: № СУБ-24/М-23/3 від 01 травня 2024 року | L49: 29977.8 | M49: 30374.6 | N49: 30786.5 | O49: 31188 | P49: 31583.7 | Q49: 31982.6 | R49: 32405.8 | S49: 32832 | T49: 33286.1 | U49: - | V49: 1 | W49: =M49-L49 -> 396.8 | X49: =N49-M49 -> 411.9 | Y49: =P49-O49 -> 395.7 | Z49: =Q49-P49 -> 398.9 | AA49: =R49-Q49 -> 423.2 | AB49: =S49-R49 -> 426.2 | AC49: =T49-S49 -> 454.1 | AD49: =U49-T49 -> #VALUE! | AE49: =AE48 -> 12.061584
A50: л | B50: 23 | C50: м. Київ, бул. В. Гавела, 18 | E50: Вода | L50: 106.11 | M50: 106.79 | N50: 107.73 | O50: 108.78 | P50: 109.62 | Q50: 110.37 | R50: 110.96 | S50: 111.52 | T50: 112.14 | U50: - | V50: 1 | W50: =M50-L50 -> 0.68 | X50: =N50-M50 -> 0.94 | Y50: =P50-O50 -> 0.84 | Z50: =Q50-P50 -> 0.75 | AA50: =R50-Q50 -> 0.59 | AB50: =S50-R50 -> 0.56 | AC50: =T50-S50 -> 0.62 | AD50: =U50-T50 -> #VALUE! | AE50: =AE47 -> 49.980008
A51: л | B51: 23 | C51: м. Київ, бул. В. Гавела, 18 | D51: ТОВ "ФДСІ ГРУП" | E51: электроэнергия | F51: 44368744 | G51: 41 | H51: заморожені напівфабрикати | I51: 45516 | J51: № СУБ-24/М-23/5 від 12 серпня 2024 року | L51: 45977.5 | M51: 50615 | N51: 56130.8 | O51: 61898.9 | P51: 67466.4 | Q51: 72996.3 | R51: 77933.5 | S51: 83269.2 | T51: 88773.7 | U51: 93744.7 | V51: 1 | W51: =M51-L51 -> 4637.5 | X51: =N51-M51 -> 5515.8 | Y51: =P51-O51 -> 5567.5 | Z51: =Q51-P51 -> 5529.9 | AA51: =R51-Q51 -> 4937.2 | AB51: =S51-R51 -> 5335.7 | AC51: =T51-S51 -> 5504.5 | AD51: =U51-T51 -> 4971 | AE51: =AE48 -> 12.061584 | AF51: =V51*AD51*AE51 -> 59958.134
A52: л | B52: 23 | C52: м. Київ, бул. В. Гавела, 18 | D52: ТОВ "ВИЖН ТРЕЙД" | E52: электроэнергия | F52: 45602852 | G52: 3 | H52: вейпи | I52: 45719 | J52: № СУБ-25/М-23/6 від 03 березня 2025 року | L52: 0 | M52: 251 | N52: 292.3 | O52: 382.9 | P52: 462.4 | Q52: 539.3 | R52: 617.5 | S52: 695.9 | T52: 780.1 | U52: 904 | V52: 1 | W52: =M52-L52 -> 251 | X52: =N52-M52 -> 41.3 | Y52: =P52-O52 -> 79.5 | Z52: =Q52-P52 -> 76.9 | AA52: =R52-Q52 -> 78.2 | AB52: =S52-R52 -> 78.4 | AC52: =T52-S52 -> 84.2 | AD52: =U52-T52 -> 123.9 | AE52: =AE48 -> 12.061584 | AF52: =V52*AD52*AE52 -> 1494.4303
A53: л | B53: 23 | C53: м. Київ, бул. В. Гавела, 18 | D53: ФОП Міхно І.В. | E53: электроэнергия | F53: 3524706936 | G53: 1 | H53: кавовий апарат | I53: 45762 | J53: №СУБ-25/М-23/7 від 15 квітня 20025 року | L53: 39.5 | M53: 118.3 | N53: 197.9 | O53: 197.9 | P53: 197.9 | Q53: 197.9 | R53: 369.7 | S53: 470.1 | T53: 586.9 | U53: 687.6 | V53: 1 | W53: =M53-L53 -> 78.8 | X53: =N53-M53 -> 79.6 | Y53: =P53-O53 -> 0 | Z53: =Q53-P53 -> 0 | AA53: =R53-Q53 -> 171.8 | AB53: =S53-R53 -> 100.4 | AC53: =T53-S53 -> 116.8 | AD53: =U53-T53 -> 100.7 | AE53: =AE48 -> 12.061584 | AF53: =V53*AD53*AE53 -> 1214.6015
A54: р | B54: 24-1 | C54: Київська обл., Васильківський район, с.м.т. Глеваха, вул. Ботанична, 34 | D54: ФОП Титомир Ю.Г. | E54: электроэнергия | F54: 3313917618 | G54: 1 | H54: кавовий апарат | I54: 45644 | J54: № СУБ-24/М-24/1 від 10 грудня 2024 року | L54: 147 | M54: 196 | N54: 245 | O54: 265 | P54: 350 | Q54: 388 | R54: 435 | S54: 477.7 | T54: 517 | U54: 546 | V54: 1 | W54: =M54-L54 -> 49 | X54: =N54-M54 -> 49 | Y54: =P54-O54 -> 85 | Z54: =Q54-P54 -> 38 | AA54: =R54-Q54 -> 47 | AB54: =S54-R54 -> 42.7 | AC54: =T54-S54 -> 39.3 | AD54: =U54-T54 -> 29 | AE54: 13.517328 | AF54: =V54*AD54*AE54 -> 392.00251 | AH54: =1.2*11.26444 -> 13.517328
B55: 24-1 | D55: ФОП Щуровський Сергій Володимирович | E55: Вода | F55: 3003603474 | R55: 0 | S55: 99.6 | T55: 112 | U55: 132 | V55: 1 | AB55: =S55-R55 -> 99.6 | AC55: =T55-S55 -> 12.4 | AD55: =U55-T55 -> 20 | AF55: =V55*AD55*AE55 -> 0
A56: р | B56: 25 | C56: Київська обл., Бучанський район, с. Софіївська Борщагівка, вул. Чубинського Павла, буд. 8-В, приміщення 541 | D56: ФОП Ільєнко О.М. | E56: Вода | F56: 2653404868 | G56: 1 | H56: водомат | I56: 45689 | J56: № СУБ-25/ІОМ-Р від 01 лютого 2025 року | L56: 917 | M56: 928 | N56: 935 | O56: 941 | P56: 946 | Q56: 951 | R56: 958 | S56: 964 | T56: 971 | U56: 978 | V56: 1 | W56: =M56-L56 -> 11 | X56: =N56-M56 -> 7 | Y56: =P56-O56 -> 5 | Z56: =Q56-P56 -> 5 | AA56: =R56-Q56 -> 7 | AB56: =S56-R56 -> 6 | AC56: =T56-S56 -> 7 | AD56: =U56-T56 -> 7 | AE56: 50.28 | AF56: =V56*AD56*AE56 -> 351.96
A57: р | B57: 25 | C57: Київська обл., Бучанський район, с. Софіївська Борщагівка, вул. Чубинського Павла, буд. 8-В, приміщення 541 | D57: ФОП Москаленко О. | E57: электроэнергия | G57: 1 | H57: кавовий апарат | M57: 0 | N57: 38.2 | O57: 145.9 | P57: 256.1 | Q57: 353.1 | R57: 469 | S57: 538.1 | T57: 620.4 | U57: 830 | V57: 1 | X57: =N57-M57 -> 38.2 | Y57: =P57-O57 -> 110.2 | Z57: =Q57-P57 -> 97 | AA57: =R57-Q57 -> 115.9 | AB57: =S57-R57 -> 69.1 | AC57: =T57-S57 -> 82.3 | AD57: =U57-T57 -> 209.6 | AE57: 11.781108 | AF57: =V57*AD57*AE57 -> 2469.3202 | AH57: =1.2*9.81759 -> 11.781108
A58: р | B58: 26 | C58: м. Київ, вул. Данченка, буд. 30, приміщення 279 | D58: ФОП Педаш С.В. | E58: электроэнергия | F58: 2798219324 | G58: 1 | H58: кавовий апарат | I58: 45405 | J58: № СУБ-24/М-11/1 від 10 квітня 2024 року | O58: 1 | P58: 1 | Q58: 63 | R58: 131 | S58: 187 | T58: 270 | U58: 386 | V58: 1 | W58: =M58-L58 -> 0 | X58: =N58-M58 -> 0 | Y58: =P58-O58 -> 0 | Z58: =Q58-P58 -> 62 | AA58: =R58-Q58 -> 68 | AB58: =S58-R58 -> 56 | AC58: =T58-S58 -> 83 | AD58: =U58-T58 -> 116 | AE58: 11.911944 | AF58: =V58*AD58*AE58 -> 1381.7855 | AH58: =1.2*9.92662 -> 11.911944
A59: р | B59: 27 | C59: м. Київ, Деснянський район, вул. Радистів, буд. 14 | D59: ФОП Басов Е. А. | E59: Вода | F59: 2634610713 | G59: 1 | H59: водомат | I59: 45627 | J59: № СУБ-24/БЕА-Р від 01 грудня 2024 року | L59: 146.27 | M59: 168.53 | N59: 192.34 | O59: 218.71 | P59: 253.35 | Q59: 280.99 | R59: 294.09 | S59: 307.75 | T59: 323.18 | U59: 341.52 | V59: 1 | W59: =M59-L59 -> 22.26 | X59: =N59-M59 -> 23.81 | Y59: =P59-O59 -> 34.64 | Z59: =Q59-P59 -> 27.64 | AA59: =R59-Q59 -> 13.1 | AB59: =S59-R59 -> 13.66 | AC59: =T59-S59 -> 15.43 | AD59: =U59-T59 -> 18.34 | AE59: 46.87 | AF59: =V59*AD59*AE59 -> 859.5958
A60: р | B60: 32 | D60: ФОП Кривенко Ю.О. | E60: электроэнергия | AD60: =U60-T60 -> 0 | AF60: =V60*AD60*AE60 -> 0
A61: р | B61: 33 | C61: Київська обл., м. Бровари, вул. Київська, 95 | D61: ФОП Басов Е. А. | E61: Вода | F61: 2634610713 | G61: 1 | H61: водомат | I61: 45627 | J61: № СУБ-24/БЕА-Р від 01 грудня 2024 року | L61: 44.92 | M61: 128.7 | N61: 153.07 | O61: 196.53 | P61: 240.77 | Q61: 275.32 | R61: 317.34 | S61: 352.85 | T61: 394.81 | U61: 411.65 | V61: 1 | W61: =M61-L61 -> 83.78 | X61: =N61-M61 -> 24.37 | Y61: =P61-O61 -> 44.24 | Z61: =Q61-P61 -> 34.55 | AA61: =R61-Q61 -> 42.02 | AB61: =S61-R61 -> 35.51 | AC61: =T61-S61 -> 41.96 | AD61: =U61-T61 -> 16.84 | AE61: 26.676 | AF61: =V61*AD61*AE61 -> 449.22384
A62: р | B62: 33 | C62: Київська обл., м. Бровари, вул. Київська, 95 | D62: ФОП Скоробагатько В.М. | E62: электроэнергия | F62: 1999405761 | G62: 1 | H62: кавовий апарат | I62: 45770 | J62: № СУБ-25/М-33/1 від 15 квітня 2025 року | V62: 1 | W62: =M62-L62 -> 0 | X62: =N62-M62 -> 0 | Y62: =P62-O62 -> 0 | Z62: =Q62-P62 -> 0 | AA62: =R62-Q62 -> 0 | AB62: =S62-R62 -> 0 | AC62: =T62-S62 -> 0 | AD62: =U62-T62 -> 0 | AE62: 13.62 | AF62: =V62*AD62*AE62 -> 0
A63: р | B63: 35 | C63: м. Київ, вул. Олени Пчілки, 7-Б | D63: ФОП Басов Е. А. | E63: Вода | F63: 2634610713 | G63: 1 | H63: водомат | I63: 45717 | J63: № СУБ-24/БЕА-Р від 01 грудня 2024 року | L63: 1261 | M63: 1301 | N63: 1336 | O63: 1382 | P63: 1435 | Q63: 1485 | R63: 1524 | S63: 1567 | T63: 1617 | U63: 1657 | V63: 1 | W63: =M63-L63 -> 40 | X63: =N63-M63 -> 35 | Y63: =P63-O63 -> 53 | Z63: =Q63-P63 -> 50 | AA63: =R63-Q63 -> 39 | AB63: =S63-R63 -> 43 | AC63: =T63-S63 -> 50 | AD63: =U63-T63 -> 40 | AE63: 49.98 | AF63: =V63*AD63*AE63 -> 1999.2
A64: р | B64: 35 | C64: м. Київ, вул. Олени Пчілки, 7-Б | D64: ТОВ “ФК “Альфа-Інвест Груп“ | E64: электроэнергия | F64: 39013808 | G64: 5 | H64: обмен валют | I64: 45658 | J64: № СУБ-25/М-35/5 від 01 січня 2024 року | L64: 299 | M64: 509 | N64: 606 | O64: 695 | P64: 782 | Q64: 873 | R64: 964 | S64: 1059 | T64: 1158 | U64: 1251 | V64: 1 | W64: =M64-L64 -> 210 | X64: =N64-M64 -> 97 | Y64: =P64-O64 -> 87 | Z64: =Q64-P64 -> 91 | AA64: =R64-Q64 -> 91 | AB64: =S64-R64 -> 95 | AC64: =T64-S64 -> 99 | AD64: =U64-T64 -> 93 | AE64: 11.653872 | AF64: =V64*AD64*AE64 -> 1083.8101
A65: р | B65: 35 | C65: м. Київ, вул. Олени Пчілки, 7-Б | D65: ФОП Вигівський Є.В. | E65: электроэнергия | F65: 3874010199 | G65: 1 | H65: кавовий апарат | I65: 45642 | J65: № СУБ-24/М-35/4 від 16 грудня 2024 року | L65: 398 | M65: 391 | N65: 478 | O65: 566 | P65: 651 | Q65: 736 | R65: 819 | S65: 886 | T65: 948 | U65: 999 | V65: 1 | W65: =M65-L65 -> -7 | X65: =N65-M65 -> 87 | Y65: =P65-O65 -> 85 | Z65: =Q65-P65 -> 85 | AA65: =R65-Q65 -> 83 | AB65: =S65-R65 -> 67 | AC65: =T65-S65 -> 62 | AD65: =U65-T65 -> 51 | AE65: =AE64 -> 11.653872 | AF65: =V65*AD65*AE65 -> 594.34747
A66: р | B66: 36 | C66: Київська обл., м. Буча, провулок Олекси Тихого, будинок 4, секція 2, нежитлове приміщення № 236 | D66: ФОП Ільєнко О.М. | E66: Вода | F66: 2653404868 | G66: 1 | H66: водомат | I66: 45689 | J66: № СУБ-25/ІОМ-Р від 01 лютого 2025 року | L66: 1232 | M66: 1259 | N66: 1285 | O66: 1313 | P66: 1342 | Q66: 1373 | R66: 1405 | S66: 1451 | T66: 1499 | U66: 1552 | V66: 1 | W66: =M66-L66 -> 27 | X66: =N66-M66 -> 26 | Y66: =P66-O66 -> 29 | Z66: =Q66-P66 -> 31 | AA66: =R66-Q66 -> 32 | AB66: =S66-R66 -> 46 | AC66: =T66-S66 -> 48 | AD66: =U66-T66 -> 53 | AE66: 56.802581 | AF66: =V66*AD66*AE66 -> 3010.5368
A67: р | B67: 36 | C67: Київська обл., м. Буча, провулок Олекси Тихого, будинок 4, секція 2, нежитлове приміщення № 236 | D67: ФОП Конотовський О.В. | E67: электроэнергия | F67: 3086512930 | G67: 1 | H67: кавовий апарат | I67: 45803 | J67: № СУБ-25/М-36/1 від 26 травня 2025 року | L67: 171.5 | M67: 176.9 | N67: 176.9 | O67: 234.1 | P67: 341 | Q67: 420 | R67: 587.7 | S67: 803.1 | T67: 1062.4 | U67: 1278.4 | V67: 1 | W67: =M67-L67 -> 5.4 | X67: =N67-M67 -> 0 | Y67: =P67-O67 -> 106.9 | Z67: =Q67-P67 -> 79 | AA67: =R67-Q67 -> 167.7 | AB67: =S67-R67 -> 215.4 | AC67: =T67-S67 -> 259.3 | AD67: =U67-T67 -> 216 | AE67: 12.684984 | AF67: =V67*AD67*AE67 -> 2739.9565
A68: р | B68: 38 | C68: м. Чернігів, вул. Всіхсвятська, 5 | D68: ТОВ "РУШ" | E68: электроэнергия | F68: 33007740 | G68: 36 | H68: цветы/подарки | I68: 44939 | J68: № М38-М-СО від 13 січня 2023 року | L68: 4149 | M68: 4263 | N68: 4276 | O68: 4287 | P68: 4288 | Q68: 4288 | R68: 13.1 | S68: 391.1 | T68: 2086.2 | U68: 4499 | V68: 1 | W68: =M68-L68 -> 114 | X68: =N68-M68 -> 13 | Y68: =P68-O68 -> 1 | Z68: =Q68-P68 -> 0 | AA68: =R68-Q68 -> -4274.9 | AB68: =S68-R68 -> 378 | AC68: =T68-S68 -> 1695.1 | AD68: =U68-T68 -> 2412.8 | AE68: 15.068676 | AF68: =V68*AD68*AE68 -> 36357.701
A69: р | B69: 38 | C69: м. Чернігів, вул. Всіхсвятська, 5 | E69: Вода | F69: 33007740 | L69: 6.5 | M69: 6.7 | N69: 6.8 | O69: 6.8 | P69: 6.93 | Q69: 6.93 | R69: 6.934 | S69: 9.51 | T69: 12.37 | U69: 15.49 | V69: 1 | W69: =M69-L69 -> 0.2 | X69: =N69-M69 -> 0.1 | Y69: =P69-O69 -> 0.13 | Z69: =Q69-P69 -> 0 | AA69: =R69-Q69 -> 0.004 | AB69: =S69-R69 -> 2.576 | AC69: =T69-S69 -> 2.86 | AD69: =U69-T69 -> 3.12 | AE69: 66.431967 | AF69: =V69*AD69*AE69 -> 207.26774
A70: р | B70: 38 | C70: м. Чернігів, вул. Всіхсвятська, 5 | D70: ФОП Глушко Т.Д. | E70: электроэнергия | F70: 3253716900 | G70: 1 | H70: кавовий апарат | I70: 45748 | J70: № СУБ-25/М-38/7 від 01 квітня 2025 року | O70: 0 | P70: 0 | Q70: 24.7 | R70: 24.7 | S70: 46.9 | T70: 65.3 | U70: 79 | V70: 1 | W70: =M70-L70 -> 0 | X70: =N70-M70 -> 0 | Y70: =P70-O70 -> 0 | Z70: =Q70-P70 -> 24.7 | AA70: =R70-Q70 -> 0 | AB70: =S70-R70 -> 22.2 | AC70: =T70-S70 -> 18.4 | AD70: =U70-T70 -> 13.7 | AE70: =AE68 -> 15.068676 | AF70: =V70*AD70*AE70 -> 206.44086 | AH70: =1.2*12.55723 -> 15.068676
B71: 40 | D71: ФОП Щуровський Сергій Володимирович | E71: вода | F71: 3003603474 | R71: 0 | S71: 4.06 | T71: 8 | U71: 19 | V71: 1 | AB71: =S71-R71 -> 4.06 | AC71: =T71-S71 -> 3.94 | AD71: =U71-T71 -> 11 | AE71: 86.49 | AF71: =V71*AD71*AE71 -> 951.39
A72: р | B72: 40 | C72: Київська обл., м. Біла Церква, вул. Митрофанова, 8 | D72: ФОП Чуб Н.В. | E72: электроэнергия | F72: 3028318005 | G72: 1 | H72: кавовий апарат | I72: 45284 | J72: № СУБ-23/М41/1 від 14 листопада 2023 року | S72: 10.05 | T72: 37.8 | U72: 78.5 | V72: 1 | W72: =M72-L72 -> 0 | X72: =N72-M72 -> 0 | Y72: =P72-O72 -> 0 | Z72: =Q72-P72 -> 0 | AA72: =R72-Q72 -> 0 | AB72: =S72-R72 -> 10.05 | AC72: =T72-S72 -> 27.75 | AD72: =U72-T72 -> 40.7 | AE72: =1.2*11.57176 -> 13.886112 | AF72: =V72*AD72*AE72 -> 565.16476 | AH72: =1.2*11.57176 -> 13.886112
A73: р | B73: 41 | C73: Київська обл., Білоцерківський район, м. Біла Церква, Сквирське шосе, будинок 223 | D73: ФОП Чуб Н.В. | E73: электроэнергия | F73: 3028318005 | G73: 1 | H73: кавовий апарат | I73: 45244 | J73: № СУБ-23/М41/1 від 14 листопада 2023 року | V73: 1 | W73: =M73-L73 -> 0 | X73: =N73-M73 -> 0 | Y73: =P73-O73 -> 0 | Z73: =Q73-P73 -> 0 | AA73: =R73-Q73 -> 0 | AB73: =S73-R73 -> 0 | AC73: =T73-S73 -> 0 | AD73: =U73-T73 -> 0 | AE73: -
A74: р | B74: 41 | C74: Київська обл., Білоцерківський район, м. Біла Церква, Сквирське шосе, будинок 223 | D74: ООО ИОНИТИ | E74: электроэнергия | G74: 4 | H74: зарядка | L74: 28204.06 | M74: 29380.04 | N74: 30822.82 | O74: 31705.74 | P74: 32655.72 | Q74: 33313.7 | R74: 33891.85 | S74: 35075.82 | T74: 35576.48 | U74: 36442.45 | V74: 1 | W74: =M74-L74 -> 1175.98 | X74: =N74-M74 -> 1442.78 | Y74: =P74-O74 -> 949.98 | Z74: =Q74-P74 -> 657.98 | AA74: =R74-Q74 -> 578.15 | AB74: =S74-R74 -> 1183.97 | AC74: =T74-S74 -> 500.66 | AD74: =U74-T74 -> 865.97 | AE74: 13.44511 | AF74: =V74*AD74*AE74 -> 11643.062 | AH74: =1.2*11.20426 -> 13.445112
R75: 34430.17 | V75: 1 | W75: =M75-L75 -> 0 | X75: =N75-M75 -> 0 | Y75: =P75-O75 -> 0 | Z75: =Q75-P75 -> 0 | AA75: =R75-Q75 -> 34430.17 | AB75: =S75-R75 -> -34430.17 | AD75: =U75-T75 -> 0 | AF75: =V75*AD75*AE75 -> 0
A76: л | B76: 42 | C76: Київська обл., Бориспільський район, с. Гора, вул. Центральна, 20А | D76: ФОП Басов Е. А. | E76: Вода | F76: 2634610713 | G76: 1 | H76: водомат | I76: 45627 | J76: № СУБ-24/БАЕ-Л від 01 грудня 2024 року | L76: 388.81 | M76: 411.53 | N76: 434.24 | O76: 461.24 | P76: 487.59 | Q76: 510.45 | R76: 535.33 | S76: 561.78 | T76: 592.93 | U76: 621.84 | V76: 1 | W76: =M76-L76 -> 22.72 | X76: =N76-M76 -> 22.71 | Y76: =P76-O76 -> 26.35 | Z76: =Q76-P76 -> 22.86 | AA76: =R76-Q76 -> 24.88 | AB76: =S76-R76 -> 26.45 | AC76: =T76-S76 -> 31.15 | AD76: =U76-T76 -> 28.91 | AE76: 129.64 | AF76: =V76*AD76*AE76 -> 3747.8924
A77: л | B77: 42 | C77: Київська обл., Бориспільський район, с. Гора, вул. Центральна, 20А | D77: ПП «РОММЕД» | E77: электроэнергия | F77: 32512959 | G77: 52.4 | H77: Аптека | I77: 44795 | J77: № М42-1-СО від 22 серпня 2022 року | L77: 12900.7 | M77: 13407.6 | N77: 13949.7 | O77: 14588.5 | P77: 15270.9 | Q77: 15889.6 | R77: 16425.9 | S77: 16923.3 | T77: 17383.3 | U77: 17822.3 | V77: 1 | W77: =M77-L77 -> 506.9 | X77: =N77-M77 -> 542.1 | Y77: =P77-O77 -> 682.4 | Z77: =Q77-P77 -> 618.7 | AA77: =R77-Q77 -> 536.3 | AB77: =S77-R77 -> 497.4 | AC77: =T77-S77 -> 460 | AD77: =U77-T77 -> 439 | AE77: 13.53756 | AF77: =V77*AD77*AE77 -> 5942.9888 | AH77: =1.2*11.2813 -> 13.53756
A78: л | B78: 42 | C78: Київська обл., Бориспільський район, с. Гора, вул. Центральна, 20А | E78: Вода | F78: 32512959 | L78: 36.62 | M78: 38.14 | N78: 39.6 | O78: 40.94 | P78: 42.18 | Q78: 43.22 | R78: 44.55 | S78: 45.83 | T78: 47.04 | U78: 48.72 | V78: 1 | W78: =M78-L78 -> 1.52 | X78: =N78-M78 -> 1.46 | Y78: =P78-O78 -> 1.24 | Z78: =Q78-P78 -> 1.04 | AA78: =R78-Q78 -> 1.33 | AB78: =S78-R78 -> 1.28 | AC78: =T78-S78 -> 1.21 | AD78: =U78-T78 -> 1.68 | AE78: =AE76 -> 129.64 | AF78: =V78*AD78*AE78 -> 217.7952
A79: л | B79: 42 | C79: Київська обл., Бориспільський район, с. Гора, вул. Центральна, 20А | E79: Вывеска | F79: 32512959 | L79: - | M79: - | S79: - | T79: - | V79: - | W79: - | Z79: =Q79-P79 -> 0 | AA79: =R79-Q79 -> 0 | AB79: =S79-R79 -> #VALUE! | AC79: - | AD79: 2000 | AE79: - | AF79: 2000
A80: л | B80: 42 | C80: Київська обл., Бориспільський район, с. Гора, вул. Центральна, 20А | D80: ФОП Майок Ю.В. | E80: электроэнергия | F80: 3305418720 | G80: 14.2 | H80: Магазин розливного пива | I80: 44827 | J80: № М42-М-СО від 06 вересня 2022 року | L80: 38458.7 | M80: 39892.3 | N80: 41225 | O80: 42574.6 | P80: 44037.1 | Q80: 45467.6 | R80: 46742.2 | S80: 47874.9 | T80: 48575.3 | U80: 48968.4 | V80: 1 | W80: =M80-L80 -> 1433.6 | X80: =N80-M80 -> 1332.7 | Y80: =P80-O80 -> 1462.5 | Z80: =Q80-P80 -> 1430.5 | AA80: =R80-Q80 -> 1274.6 | AB80: =S80-R80 -> 1132.7 | AC80: =T80-S80 -> 700.4 | AD80: =U80-T80 -> 393.1 | AE80: =AE77 -> 13.53756 | AF80: =V80*AD80*AE80 -> 5321.6148
A81: л | B81: 42 | C81: Київська обл., Бориспільський район, с. Гора, вул. Центральна, 20А | D81: ФОП Майок Ю.В. | E81: электроэнергия | F81: 3305418720 | G81: 14.2 | H81: суши | I81: 45282 | J81: № СУБ-23/М-42/2 від 22 грудня 2023 року | L81: 6162.3 | M81: 6482.7 | N81: 6777.9 | O81: 7087.5 | P81: 7451.8 | Q81: 7886 | R81: 8300.6 | S81: 8667.8 | T81: 8957.4 | U81: 9125.5 | V81: 1 | W81: =M81-L81 -> 320.4 | X81: =N81-M81 -> 295.2 | Y81: =P81-O81 -> 364.3 | Z81: =Q81-P81 -> 434.2 | AA81: =R81-Q81 -> 414.6 | AB81: =S81-R81 -> 367.2 | AC81: =T81-S81 -> 289.6 | AD81: =U81-T81 -> 168.1 | AE81: =AE77 -> 13.53756 | AF81: =V81*AD81*AE81 -> 2275.6638
A82: л | B82: 42 | C82: Київська обл., Бориспільський район, с. Гора, вул. Центральна, 20А | E82: Вода | L82: 55.62 | M82: 58.38 | N82: 59.94 | O82: 61.68 | P82: 63.4 | Q82: 64.98 | R82: 66.54 | S82: 68.4 | T82: 70.25 | U82: 71.91 | V82: 1 | W82: =M82-L82 -> 2.76 | X82: =N82-M82 -> 1.56 | Y82: =P82-O82 -> 1.72 | Z82: =Q82-P82 -> 1.58 | AA82: =R82-Q82 -> 1.56 | AB82: =S82-R82 -> 1.86 | AC82: =T82-S82 -> 1.85 | AD82: =U82-T82 -> 1.66 | AE82: =AE76 -> 129.64 | AF82: =V82*AD82*AE82 -> 215.2024
A83: л | B83: 42 | C83: Київська обл., Бориспільський район, с. Гора, вул. Центральна, 20А | D83: ФОП Майок Ю.В. | E83: Вода | F83: 3305418720 | G83: 14 | H83: раки | I83: 45366 | J83: № СУБ-24/М-42/3 від 15 березня 2024 року | V83: 1 | W83: =M83-L83 -> 0 | X83: =N83-M83 -> 0 | Y83: =P83-O83 -> 0 | Z83: =Q83-P83 -> 0 | AA83: =R83-Q83 -> 0 | AB83: =S83-R83 -> 0 | AC83: =T83-S83 -> 0 | AD83: =U83-T83 -> 0 | AF83: =V83*AD83*AE83 -> 0
A84: л | B84: 43 | C84: Київська обл., Фастівський район, м. Боярка, вул. Бульварна, будинок 2/50 | D84: ФОП Тимошенко А.В. | E84: электроэнергия | F84: 3001124330 | G84: 1 | H84: кавовий апарат | I84: 45641 | J84: № СУБ-24/М-43/1 від 20 листопада 2024 року | L84: 272 | M84: 361.8 | N84: 457.4 | O84: 556.4 | P84: 656 | Q84: 754 | R84: 858.1 | S84: 959 | T84: 1062.8 | U84: 1150 | V84: 1 | W84: =M84-L84 -> 89.8 | X84: =N84-M84 -> 95.6 | Y84: =P84-O84 -> 99.6 | Z84: =Q84-P84 -> 98 | AA84: =R84-Q84 -> 104.1 | AB84: =S84-R84 -> 100.9 | AC84: =T84-S84 -> 103.8 | AD84: =U84-T84 -> 87.2 | AE84: 15.8 | AF84: =V84*AD84*AE84 -> 1377.76
A85: Б | B85: РЦ (Б) | C85: c.Білогородка, вул.Аграрна,1 | D85: ТОВ Перша Чарівна Скриня | E85: электроэнергия | F85: 35791225 | H85: кавовий апарат | P85: 14301.5 | Q85: 14355 | R85: 14462 | S85: 14515 | T85: 14603.7 | U85: 14725.8 | V85: 1 | Z85: =Q85-P85 -> 53.5 | AA85: =R85-Q85 -> 107 | AB85: =S85-R85 -> 53 | AC85: =T85-S85 -> 88.7 | AD85: =U85-T85 -> 122.1 | AE85: 13.419192 | AF85: =V85*AD85*AE85 -> 1638.4833 | AH85: =1.2*11.18266 -> 13.419192
B86: ИТОГО | G86: =SUBTOTAL(9,G3:G84) -> 556.8 | AF86: =SUM(AF3:AF85) -> 364470.41
R89: =S85-R85 -> 53

Sheet М3
O1: Предприятие
A2: Расход электроэнергии/воды за август 2023г. | O2: Легіон 2015
A3: Местоположение: | C3: М34 магазин "Пчелка маркет" г. Киев, ул. Р.Окипной, 3
L4: з ПДВ
A5: № п/п | B5: Название потребителя | C5: Юридическое лицо | D5: № счетчика | E5: Энергоноситель | F5: Показатели счетчика | J5: Коэф. | K5: Потребление, кВт/ч, м3/ч | L5: Стоимость 1кВт/ч, м3/ч | M5: Итого
F6: Дата снятия | G6: Показатели | H6: Дата снятия | I6: Показатели
A7: 1 | B7: Субпотребитель | C7: ТОВ "Аврора" | D7: НІК 2303 АРП1 №0222299 | E7: Активная э.э. | F7: 45138 | G7: 59884.28 | H7: 45170 | I7: 60012.64 | J7: 1 | K7: =I7-G7 -> 128.36 | L7: 6.610763 | M7: =K7*L7*J7 -> 848.55753
L9: ИТОГО: | M9: =SUM(M7:M7) -> 848.55753 | N9: грн.
A10: Расход электроэнергии/воды за сентябр 2023г. | O10: Легіон 2015
A11: Местоположение: | C11: М3 магазин "Пчелка маркет" г. Киев, ул. Р.Окипной, 3
A13: № п/п | B13: Название потребителя | C13: Юридическое лицо | D13: № счетчика | E13: Энергоноситель | F13: Показатели счетчика | J13: Коэф. | K13: Потребление, кВт/ч, м3/ч | L13: Стоимость 1кВт/ч, м3/ч | M13: Итого
F14: Дата снятия | G14: Показатели | H14: Дата снятия | I14: Показатели
A15: 1 | B15: Субпотребитель | C15: ТОВ "Аврора" | D15: НІК 2303 АРП1 №0222299 | E15: Активная э.э. | F15: 45170 | G15: 60012.64 | H15: 45170 | I15: 61391.57 | J15: 1 | K15: =I15-G15 -> 1378.93 | L15: 6.3494518 | M15: =K15*L15*J15 -> 8755.4496
L17: ИТОГО: | M17: =SUM(M15:M15) -> 8755.4496 | N17: грн.
O18: Легіон 2015
A19: Расход электроэнергии/воды за октябрь 2023г.
A20: Местоположение: | C20: М3 магазин "Пчелка маркет" г. Киев, ул. Р.Окипной, 3
A22: № п/п | B22: Название потребителя | C22: Юридическое лицо | D22: № счетчика | E22: Энергоноситель | F22: Показатели счетчика | J22: Коэф. | K22: Потребление, кВт/ч, м3/ч | L22: Стоимость 1кВт/ч, м3/ч | M22: Итого
F23: Дата снятия | G23: Показатели | H23: Дата снятия | I23: Показатели
A24: 1 | B24: Субпотребитель | C24: ТОВ "Аврора" | D24: НІК 2303 АРП1 №0222299 | E24: Активная э.э. | F24: 45170 | G24: 61391.57 | H24: 45230 | I24: 62937.75 | J24: 1 | K24: =I24-G24 -> 1546.18 | L24: 6.25944 | M24: =K24*L24*J24 -> 9678.2209
L26: ИТОГО: | M26: =SUM(M24:M24) -> 9678.2209 | N26: грн.
A28: Расход электроэнергии/воды за ноябрь 2023г.
A29: Местоположение: | C29: М3 магазин "Пчелка маркет" г. Киев, ул. Р.Окипной, 3
A31: № п/п | B31: Название потребителя | C31: Юридическое лицо | D31: № счетчика | E31: Энергоноситель | F31: Показатели счетчика | J31: Коэф. | K31: Потребление, кВт/ч, м3/ч | L31: Стоимость 1кВт/ч, м3/ч | M31: Итого
F32: Дата снятия | G32: Показатели | H32: Дата снятия | I32: Показатели
A33: 1 | B33: Субпотребитель | C33: ТОВ "Аврора" | D33: НІК 2303 АРП1 №0222299 | E33: Активная э.э. | F33: 45230 | G33: 62937.75 | H33: 45260 | I33: 64806.42 | J33: 1 | K33: =I33-G33 -> 1868.67 | L33: 6.7596598 | M33: =K33*L33*J33 -> 12631.574
L35: ИТОГО: | M35: =SUM(M33:M33) -> 12631.574 | N35: грн.
B36: Отправили счет на ФОП "Воробйова"
A37: Расход электроэнергии/воды за декабрь 2023г.
A38: Местоположение: | C38: М3 магазин "Пчелка маркет" г. Киев, ул. Р.Окипной, 3
A40: № п/п | B40: Название потребителя | C40: Юридическое лицо | D40: № счетчика | E40: Энергоноситель | F40: Показатели счетчика | J40: Коэф. | K40: Потребление, кВт/ч, м3/ч | L40: Стоимость 1кВт/ч, м3/ч | M40: Итого
F41: Дата снятия | G41: Показатели | H41: Дата снятия | I41: Показатели
A42: 1 | B42: Субпотребитель | C42: ТОВ "Аврора" | D42: НІК 2303 АРП1 №0222299 | E42: Активная э.э. | F42: 45260 | G42: 64806.42 | H42: 45291 | I42: 67341.92 | J42: 1 | K42: =I42-G42 -> 2535.5 | L42: 6.4951202 | M42: =K42*L42*J42 -> 16468.377
L44: ИТОГО: | M44: =SUM(M42:M42) -> 16468.377 | N44: грн.
A46: Расход электроэнергии/воды за январь 2024 г.
A47: Местоположение: | C47: М3 магазин "Пчелка маркет" г. Киев, ул. Р.Окипной, 3
A49: № п/п | B49: Название потребителя | C49: Юридическое лицо | D49: № счетчика | E49: Энергоноситель | F49: Показатели счетчика | J49: Коэф. | K49: Потребление, кВт/ч, м3/ч | L49: Стоимость 1кВт/ч, м3/ч | M49: Итого
F50: Дата снятия | G50: Показатели | H50: Дата снятия | I50: Показатели
A51: 1 | B51: Субпотребитель | C51: ТОВ "Аврора" | D51: НІК 2303 АРП1 №0222299 | E51: Активная э.э. | F51: 45291 | G51: 67341.92 | H51: 45323 | I51: 70250.76 | J51: 1 | K51: =I51-G51 -> 2908.84 | L51: =[2]Арендаторы!M15 -> #REF! | M51: =K51*L51*J51 -> #REF!
L53: ИТОГО: | M53: =SUM(M51:M51) -> #REF! | N53: грн.
A56: Расход электроэнергии/воды за февраль 2024 г.
A57: Местоположение: | C57: М3 магазин "Пчелка маркет" г. Киев, ул. Р.Окипной, 3
A59: № п/п | B59: Название потребителя | C59: Юридическое лицо | D59: № счетчика | E59: Энергоноситель | F59: Показатели счетчика | J59: Коэф. | K59: Потребление, кВт/ч, м3/ч | L59: Стоимость 1кВт/ч, м3/ч | M59: Итого
F60: Дата снятия | G60: Показатели | H60: Дата снятия | I60: Показатели
A61: 1 | B61: Субпотребитель | C61: ТОВ "Аврора" | D61: НІК 2303 АРП1 №0222299 | E61: Активная э.э. | F61: 45323 | G61: 70250.76 | H61: 45351 | I61: 72187.23 | J61: 1 | K61: =I61-G61 -> 1936.47 | L61: 5.5075804 | M61: =K61*L61*J61 -> 10665.264
L63: ИТОГО: | M63: =SUM(M61:M61) -> 10665.264 | N63: грн.
A66: Расход электроэнергии/воды за март 2024 г.
A67: Местоположение: | C67: М3 магазин "Пчелка маркет" г. Киев, ул. Р.Окипной, 3
A69: № п/п | B69: Название потребителя | C69: Юридическое лицо | D69: № счетчика | E69: Энергоноситель | F69: Показатели счетчика | J69: Коэф. | K69: Потребление, кВт/ч, м3/ч | L69: Стоимость 1кВт/ч, м3/ч | M69: Итого
F70: Дата снятия | G70: Показатели | H70: Дата снятия | I70: Показатели
A71: 1 | B71: Субпотребитель | C71: ТОВ "Аврора" | D71: НІК 2303 АРП1 №0222299 | E71: Активная э.э. | F71: 45352 | G71: 72187.23 | H71: 45351 | I71: 73951.55 | J71: 1 | K71: =I71-G71 -> 1764.32 | L71: 5.50758 | M71: =K71*L71*J71 -> 9717.1336
L73: ИТОГО: | M73: =SUM(M71:M71) -> 9717.1336 | N73: грн.
A76: Расход электроэнергии/воды за апрель 2024 г.
A77: Местоположение: | C77: М3 магазин "Пчелка маркет" г. Киев, ул. Р.Окипной, 3
A79: № п/п | B79: Название потребителя | C79: Юридическое лицо | D79: № счетчика | E79: Энергоноситель | F79: Показатели счетчика | J79: Коэф. | K79: Потребление, кВт/ч, м3/ч | L79: Стоимость 1кВт/ч, м3/ч | M79: Итого
F80: Дата снятия | G80: Показатели | H80: Дата снятия | I80: Показатели
A81: 1 | B81: Субпотребитель | C81: ТОВ "Аврора" | D81: НІК 2303 АРП1 №0222299 | E81: Активная э.э. | F81: 45382 | G81: 73951.55 | H81: 45412 | I81: 75563.71 | J81: 1 | K81: =I81-G81 -> 1612.16 | L81: 5.439 | M81: =K81*L81*J81 -> 8768.5382
L83: ИТОГО: | M83: =SUM(M81:M81) -> 8768.5382 | N83: грн.
A86: Расход электроэнергии/воды за май 2024 г.
A87: Местоположение: | C87: М3 магазин "Пчелка маркет" г. Киев, ул. Р.Окипной, 3
A89: № п/п | B89: Название потребителя | C89: Юридическое лицо | D89: № счетчика | E89: Энергоноситель | F89: Показатели счетчика | J89: Коэф. | K89: Потребление, кВт/ч, м3/ч | L89: Стоимость 1кВт/ч, м3/ч | M89: Итого
F90: Дата снятия | G90: Показатели | H90: Дата снятия | I90: Показатели
A91: 1 | B91: Субпотребитель | C91: ТОВ "Аврора" | D91: НІК 2303 АРП1 №0222299 | E91: Активная э.э. | F91: 45412 | G91: 75563.71 | H91: 45443 | I91: 77387.82 | J91: 1 | K91: =I91-G91 -> 1824.11 | L91: 6.4400163 | M91: =K91*L91*J91 -> 11747.298
L93: ИТОГО: | M93: =SUM(M91:M91) -> 11747.298 | N93: грн.
A96: Расход электроэнергии/воды за июнь 2024 г.
A97: Местоположение: | C97: М3 магазин "Пчелка маркет" г. Киев, ул. Р.Окипной, 3
A99: № п/п | B99: Название потребителя | C99: Юридическое лицо | D99: № счетчика | E99: Энергоноситель | F99: Показатели счетчика | J99: Коэф. | K99: Потребление, кВт/ч, м3/ч | L99: Стоимость 1кВт/ч, м3/ч | M99: Итого
F100: Дата снятия | G100: Показатели | H100: Дата снятия | I100: Показатели
A101: 1 | B101: Субпотребитель | C101: ТОВ "Аврора" | D101: НІК 2303 АРП1 №0222299 | E101: Активная э.э. | F101: 45443 | G101: 77387.82 | H101: 45473 | I101: 79181.66 | J101: 1 | K101: =I101-G101 -> 1793.84 | L101: 7.4135397 | M101: =K101*L101*J101 -> 13298.704
L103: ИТОГО: | M103: =SUM(M101:M101) -> 13298.704 | N103: грн.
A106: Расход электроэнергии/воды за июль 2024 г.
A107: Местоположение: | C107: М3 магазин "Пчелка маркет" г. Киев, ул. Р.Окипной, 3
A109: № п/п | B109: Название потребителя | C109: Юридическое лицо | D109: № счетчика | E109: Энергоноситель | F109: Показатели счетчика | J109: Коэф. | K109: Потребление, кВт/ч, м3/ч | L109: Стоимость 1кВт/ч, м3/ч | M109: Итого
F110: Дата снятия | G110: Показатели | H110: Дата снятия | I110: Показатели
A111: 1 | B111: Субпотребитель | C111: ТОВ "Аврора" | D111: НІК 2303 АРП1 №0222299 | E111: Активная э.э.1.8.0 | F111: 45473 | G111: 79181.66 | H111: 45504 | I111: 81837.31 | J111: 1 | K111: =I111-G111 -> 2655.65 | L111: 7.888284 | M111: =K111*L111*J111 -> 20948.521
L113: ИТОГО: | M113: =SUM(M111:M111) -> 20948.521 | N113: грн.
A116: Расход электроэнергии/воды за август 2024 г.
A117: Местоположение: | C117: М3 магазин "Пчелка маркет" г. Киев, ул. Р.Окипной, 3
A119: № п/п | B119: Название потребителя | C119: Юридическое лицо | D119: № счетчика | E119: Энергоноситель | F119: Показатели счетчика | J119: Коэф. | K119: Потребление, кВт/ч, м3/ч | L119: Стоимость 1кВт/ч, м3/ч | M119: Итого
F120: Дата снятия | G120: Показатели | H120: Дата снятия | I120: Показатели
A121: 1 | B121: Субпотребитель | C121: ТОВ "Аврора" | D121: НІК 2303 АРП1 №0222299 | E121: Активная э.э.1.8.0 | F121: 45504 | G121: 81837.31 | H121: 45535 | I121: 83615.85 | J121: 1 | K121: =I121-G121 -> 1778.54 | L121: =[2]Арендаторы!M15 -> #REF! | M121: =K121*L121*J121 -> #REF!
L123: ИТОГО: | M123: =SUM(M121:M121) -> #REF! | N123: грн.
A126: Расход электроэнергии/воды за сентябрь 2024 г.
A127: Местоположение: | C127: М3 магазин "Пчелка маркет" г. Киев, ул. Р.Окипной, 3
A129: № п/п | B129: Название потребителя | C129: Юридическое лицо | D129: № счетчика | E129: Энергоноситель | F129: Показатели счетчика | J129: Коэф. | K129: Потребление, кВт/ч, м3/ч | L129: Стоимость 1кВт/ч, м3/ч | M129: Итого
F130: Дата снятия | G130: Показатели | H130: Дата снятия | I130: Показатели
A131: 1 | B131: Субпотребитель | C131: ТОВ "Аврора" | D131: НІК 2303 АРП1 №0222299 | E131: Активная э.э.1.8.0 | F131: 45535 | G131: 83615.85 | H131: 45565 | I131: 85778.56 | J131: 1 | K131: =I131-G131 -> 2162.71 | L131: 8.066436 | M131: =K131*L131*J131 -> 17445.362 | Z131: =1.2*6.72203 -> 8.066436
L133: ИТОГО: | M133: =SUM(M131:M131) -> 17445.362 | N133: грн.
A136: Расход электроэнергии/воды за октябрь 2024 г.
A137: Местоположение: | C137: М3 магазин "Пчелка маркет" г. Киев, ул. Р.Окипной, 3
A139: № п/п | B139: Название потребителя | C139: Юридическое лицо | D139: № счетчика | E139: Энергоноситель | F139: Показатели счетчика | J139: Коэф. | K139: Потребление, кВт/ч, м3/ч | L139: Стоимость 1кВт/ч, м3/ч | M139: Итого
F140: Дата снятия | G140: Показатели | H140: Дата снятия | I140: Показатели
A141: 1 | B141: Субпотребитель | C141: ТОВ "Аврора" | D141: НІК 2303 АРП1 №0222299 | E141: Активная э.э.1.8.0 | F141: 45565 | G141: 85778.56 | H141: 45596 | I141: 87507.12 | J141: 1 | K141: =I141-G141 -> 1728.56 | L141: 7.90668 | M141: =K141*L141*J141 -> 13667.171 | Z141: =1.2*6.5889 -> 7.90668
L143: ИТОГО: | M143: =SUM(M141:M141) -> 13667.171 | N143: грн.
A146: Расход электроэнергии/воды за ноябрь 2024 г.
A147: Местоположение: | C147: М3 магазин "Пчелка маркет" г. Киев, ул. Р.Окипной, 3
A149: № п/п | B149: Название потребителя | C149: Юридическое лицо | D149: № счетчика | E149: Энергоноситель | F149: Показатели счетчика | J149: Коэф. | K149: Потребление, кВт/ч, м3/ч | L149: Стоимость 1кВт/ч, м3/ч | M149: Итого
F150: Дата снятия | G150: Показатели | H150: Дата снятия | I150: Показатели
A151: 1 | B151: Субпотребитель | C151: ТОВ "Аврора" | D151: НІК 2303 АРП1 №0222299 | E151: Активная э.э.1.8.0 | F151: 45596 | G151: 87507.12 | H151: 45626 | I151: 89477.26 | J151: 1 | K151: =I151-G151 -> 1970.14 | L151: =[2]Арендаторы!M15 -> #REF! | M151: =K151*L151*J151 -> #REF!
L153: ИТОГО: | M153: =SUM(M151:M151) -> #REF! | N153: грн.
...

Sheet М5
B3: Расход электроэнергии/воды за февраль-ноябрь 2022г.
B4: Местоположение: | E4: М5 магазин "Пчелка маркет" г. Киев, ул. Коласа Якуба, 2A
B6: № п/п | C6: Название потребителя | D6: Юридическое лицо | E6: № счетчика | F6: Энергоноситель | G6: Показатели счетчика | K6: Коэф. | L6: Потребление, кВт/ч, м3/ч | M6: Стоимость 1кВт/ч, м3/ч | N6: Итого
G7: Дата снятия | H7: Показатели | I7: Дата снятия | J7: Показатели
B8: 1 | C8: Спортивный клуб | E8: Энергомера ЦЭ68038 №60142331 | F8: Активная э.э. | G8: 44593 | H8: 214140 | I8: 44896 | J8: 214528 | K8: 1 | L8: =J8-H8 -> 388 | M8: 4.9663925 | N8: =L8*M8 -> 1926.9603
E9: JS 2,5-02 №13749754 | F9: Водоснабжение | G9: 44593 | H9: 1525 | I9: 44896 | J9: 1550.69 | K9: 1 | L9: =J9-H9 -> 25.69 | M9: 30.38 | N9: =L9*M9 -> 780.4622
B10: 2 | C10: Магазин инструментов ТМ "Makita" | E10: CO-ЭЭ6706 №054494008 | F10: Активная э.э. | G10: 44593 | H10: 16853 | I10: 44896 | J10: 17993 | K10: 1 | L10: =J10-H10 -> 1140 | M10: =M8 -> 4.9663925 | N10: =L10*M10 -> 5661.6875
B11: 3 | C11: Помещение электрощитовой | E11: НІК 2102-02.M2 №4921123 | F11: Активная э.э. | G11: 44866 | H11: 28080.8 | I11: 44896 | J11: 28096.3 | K11: 1 | L11: =J11-H11 -> 15.5 | M11: =M8 -> 4.9663925 | N11: =L11*M11 -> 76.979084
H12: Потребление, кВт/ч, м3/ч | I12: Стоимость 1кВт/ч, м3/ч | J12: Итого
G13: Фев.-дек.2022 | H13: =10*8.24 -> 82.4 | I13: 30.38 | J13: =H13*I13 -> 2503.312
B15: Расход электроэнергии/воды за декабрь 2022г.
B16: Местоположение: | E16: М5 магазин "Пчелка маркет" г. Киев, ул. Коласа Якуба, 2A
B18: № п/п | C18: Название потребителя | D18: Юридическое лицо | E18: № счетчика | F18: Энергоноситель | G18: Показатели счетчика | K18: Коэф. | L18: Потребление, кВт/ч, м3/ч | M18: Стоимость 1кВт/ч, м3/ч | N18: Итого
G19: Дата снятия | H19: Показатели | I19: Дата снятия | J19: Показатели
B20: 1 | C20: Спортивный клуб | E20: Энергомера ЦЭ68038 №60142331 | F20: Активная э.э. | G20: 44896 | H20: 214528 | I20: 44927 | J20: 214942 | K20: 1 | L20: =J20-H20 -> 414 | M20: =M8 -> 4.9663925 | N20: =L20*M20 -> 2056.0865
E21: JS 2,5-02 №13749754 | F21: Водоснабжение | G21: 44593 | H21: 1550.69 | I21: 44924 | J21: 1558.93 | K21: 1 | L21: =J21-H21 -> 8.24 | M21: 30.38 | N21: =L21*M21 -> 250.3312
B22: 2 | C22: Магазин инструментов ТМ "Makita" | E22: CO-ЭЭ6706 №054494008 | F22: Активная э.э. | G22: 44896 | H22: 17993 | I22: 44927 | J22: 18109 | K22: 1 | L22: =J22-H22 -> 116 | M22: =M20 -> 4.9663925 | N22: =L22*M22 -> 576.10153
B23: 3 | C23: Помещение электрощитовой | E23: НІК 2102-02.M2 №4921123 | F23: Активная э.э. | G23: 44866 | H23: 28096.3 | I23: 44927 | J23: 28112.3 | K23: 1 | L23: =J23-H23 -> 16 | M23: =M20 -> 4.9663925 | N23: =L23*M23 -> 79.46228
B26: Расход электроэнергии/воды за январь 2023г.
B27: Местоположение: | E27: М5 магазин "Пчелка маркет" г. Киев, ул. Коласа Якуба, 2A
B29: № п/п | C29: Название потребителя | D29: Юридическое лицо | E29: № счетчика | F29: Энергоноситель | G29: Показатели счетчика | K29: Коэф. | L29: Потребление, кВт/ч, м3/ч | M29: Стоимость 1кВт/ч, м3/ч | N29: Итого
G30: Дата снятия | H30: Показатели | I30: Дата снятия | J30: Показатели
B31: 1 | C31: Спортивный клуб | E31: Энергомера ЦЭ68038 №60142331 | F31: Активная э.э. | G31: 44927 | H31: 214942 | I31: 44957 | J31: 215023 | K31: 1 | L31: =J31-H31 -> 81 | M31: =M20 -> 4.9663925 | N31: =L31*M31 -> 402.27779
E32: JS 2,5-02 №13749754 | F32: Водоснабжение | G32: 44924 | H32: 1558.93 | I32: 44957 | J32: 1567.17 | K32: 1 | L32: =J32-H32 -> 8.24 | M32: 30.38 | N32: =L32*M32 -> 250.3312
B33: 2 | C33: Магазин инструментов ТМ "Makita" | E33: CO-ЭЭ6706 №054494008 | F33: Активная э.э. | G33: 44927 | H33: 18109 | I33: 44957 | J33: 18201.9 | K33: 1 | L33: =J33-H33 -> 92.9 | M33: =M31 -> 4.9663925 | N33: =L33*M33 -> 461.37786
B34: 3 | C34: Помещение электрощитовой | E34: НІК 2102-02.M2 №4921123 | F34: Активная э.э. | G34: 44926 | H34: 28112.3 | I34: 44957 | J34: 28126.8 | K34: 1 | L34: =J34-H34 -> 14.5 | M34: =M31 -> 4.9663925 | N34: =L34*M34 -> 72.012691
B36: Расход электроэнергии/воды за февраль 2023г.
B37: Местоположение: | E37: М5 магазин "Пчелка маркет" г. Киев, ул. Коласа Якуба, 2A
B39: № п/п | C39: Название потребителя | D39: Юридическое лицо | E39: № счетчика | F39: Энергоноситель | G39: Показатели счетчика | K39: Коэф. | L39: Потребление, кВт/ч, м3/ч | M39: Стоимость 1кВт/ч, м3/ч | N39: Итого
G40: Дата снятия | H40: Показатели | I40: Дата снятия | J40: Показатели
B41: 1 | C41: Спортивный клуб | E41: Энергомера ЦЭ68038 №60142331 | F41: Активная э.э. | G41: 44957 | H41: 215023 | I41: 44985 | J41: 215093 | K41: 1 | L41: =J41-H41 -> 70 | M41: =M8 -> 4.9663925 | N41: =L41*M41 -> 347.64748
E42: JS 2,5-02 №13749754 | F42: Водоснабжение | G42: 44957 | H42: 1567.17 | I42: 44985 | J42: 1573.1 | K42: 1 | L42: =J42-H42 -> 5.93 | M42: 30.446 | N42: =L42*M42 -> 180.54478
B43: 2 | C43: Магазин инструментов ТМ "Makita" | E43: CO-ЭЭ6706 №054494008 | F43: Активная э.э. | G43: 44957 | H43: 18201.9 | I43: 44957 | J43: 18201.9 | K43: 1 | L43: =J43-H43 -> 0 | M43: =M8 -> 4.9663925 | N43: =L43*M43 -> 0
B44: 3 | C44: Помещение электрощитовой | E44: НІК 2102-02.M2 №4921123 | F44: Активная э.э. | G44: 44957 | H44: 28126.8 | I44: 44985 | J44: 28126.8 | K44: 1 | L44: =J44-H44 -> 0 | M44: =M8 -> 4.9663925 | N44: =L44*M44 -> 0
B46: Расход электроэнергии/воды за март 2023г.
B47: Местоположение: | E47: М5 магазин "Пчелка маркет" г. Киев, ул. Коласа Якуба, 2A
B49: № п/п | C49: Название потребителя | D49: Юридическое лицо | E49: № счетчика | F49: Энергоноситель | G49: Показатели счетчика | K49: Коэф. | L49: Потребление, кВт/ч, м3/ч | M49: Стоимость 1кВт/ч, м3/ч | N49: Итого
G50: Дата снятия | H50: Показатели | I50: Дата снятия | J50: Показатели
B51: 1 | C51: Спортивный клуб | E51: Энергомера ЦЭ68038 №60142331 | F51: Активная э.э. | G51: 44985 | H51: 215093 | I51: 45016 | J51: 215369 | K51: 1 | L51: =J51-H51 -> 276 | M51: 5.148 | N51: =L51*M51 -> 1420.848
E52: JS 2,5-02 №13749754 | F52: Водоснабжение | G52: 44985 | H52: 1573.1 | I52: 45016 | J52: 1580.01 | K52: 1 | L52: =J52-H52 -> 6.91 | M52: 30.446 | N52: =L52*M52 -> 210.38186
B53: 2 | C53: Магазин инструментов ТМ "Makita" | E53: CO-ЭЭ6706 №054494008 | F53: Активная э.э. | G53: 44957 | H53: 18201.9 | I53: 45016 | J53: 18461.6 | K53: 1 | L53: =J53-H53 -> 259.7 | M53: 5.148 | N53: =L53*M53 -> 1336.9356
B54: 3 | C54: Помещение электрощитовой | E54: НІК 2102-02.M2 №4921123 | F54: Активная э.э. | G54: 44985 | H54: 28126.8 | I54: 45016 | J54: 28126.8 | K54: 1 | L54: =J54-H54 -> 0 | M54: 5.148 | N54: =L54*M54 -> 0
B56: № п/п | C56: Название потребителя | E56: Энергоноситель | F56: Сумма к оплате, грн
B57: 1 | C57: Спортивный клуб | E57: Активная э.э. | F57: =N51+N41+N31+N20+N8 -> 6153.8201 | G57: =SUM(F57:F58) -> 7825.8713 | H57: Итого
E58: Водоснабжение | F58: =N52+N42+N32+N21+N9 -> 1672.0512
B59: 2 | C59: Магазин инструментов ТМ "Makita" | E59: Активная э.э. | F59: =N53+N33+N22+N10 -> 8036.1025 | H59: 4000 | I59: Сплачено
E60: ИТОГО | F60: =SUM(F57:F59) -> 15861.974
B62: Расход электроэнергии/воды за апрель 2023г.
B63: Местоположение: | E63: М5 магазин "Пчелка маркет" г. Киев, ул. Коласа Якуба, 2A
B65: № п/п | C65: Название потребителя | D65: Юридическое лицо | E65: № счетчика | F65: Энергоноситель | G65: Показатели счетчика | K65: Коэф. | L65: Потребление, кВт/ч, м3 | M65: Стоимость 1кВт/ч, м3 | N65: Итого
G66: Дата снятия | H66: Показатели | I66: Дата снятия | J66: Показатели
B67: 1 | C67: Спортивный клуб | E67: Энергомера ЦЭ68038 №60142331 | F67: Активная э.э. | G67: 45016 | H67: 215369 | I67: 45046 | J67: 215444 | K67: 1 | L67: =J67-H67 -> 75 | M67: 4.6829517 | N67: =L67*M67 -> 351.22138
E68: JS 2,5-02 №13749754 | F68: Водоснабжение | G68: 45016 | H68: 1580.01 | I68: 45046 | J68: 1586.344 | K68: 1 | L68: =J68-H68 -> 6.334 | M68: 30.38 | N68: =L68*M68 -> 192.42692
B69: 2 | C69: Магазин инструментов ТМ "Makita" | E69: CO-ЭЭ6706 №054494008 | F69: Активная э.э. | G69: 45016 | H69: 18461.6 | I69: 45046 | J69: 18554.4 | K69: 1 | L69: =J69-H69 -> 92.8 | M69: 4.6829517 | N69: =L69*M69 -> 434.57792
B70: 3 | C70: Помещение электрощитовой | E70: НІК 2102-02.M2 №4921123 | F70: Активная э.э. | G70: 45016 | H70: 28126.8 | I70: 45046 | J70: 28160.6 | K70: 1 | L70: =J70-H70 -> 33.8 | M70: 4.6829517 | N70: =L70*M70 -> 158.28377
B72: Расход электроэнергии/воды за май 2023г.
B73: Местоположение: | E73: М5 магазин "Пчелка маркет" г. Киев, ул. Коласа Якуба, 2A
B75: № п/п | C75: Название потребителя | D75: Юридическое лицо | E75: № счетчика | F75: Энергоноситель | G75: Показатели счетчика | K75: Коэф. | L75: Потребление, кВт/ч, м3 | M75: Стоимость 1кВт/ч, м3 | N75: Итого
G76: Дата снятия | H76: Показатели | I76: Дата снятия | J76: Показатели
B77: 1 | C77: Спортивный клуб | E77: Энергомера ЦЭ68038 №60142331 | F77: Активная э.э. | G77: 45046 | H77: 215444 | I77: 45077 | J77: 215490 | K77: 1 | L77: =J77-H77 -> 46 | M77: 4.819 | N77: =L77*M77 -> 221.674
E78: JS 2,5-02 №13749754 | F78: Водоснабжение | G78: 45046 | H78: 1586.344 | I78: 45077 | J78: 1591.92 | K78: 1 | L78: =J78-H78 -> 5.576 | M78: 30.38 | N78: =L78*M78 -> 169.39888
B79: 2 | C79: Магазин инструментов ТМ "Makita" | E79: CO-ЭЭ6706 №054494008 | F79: Активная э.э. | G79: 45046 | H79: 18554.4 | I79: 45077 | J79: 18683.8 | K79: 1 | L79: =J79-H79 -> 129.4 | M79: 4.819 | N79: =L79*M79 -> 623.5786
B80: 3 | C80: Помещение электрощитовой | E80: НІК 2102-02.M2 №4921123 | F80: Активная э.э. | G80: 45046 | H80: 28160.6 | I80: 45077 | J80: 28172.2 | K80: 1 | L80: =J80-H80 -> 11.6 | M80: 4.819 | N80: =L80*M80 -> 55.9004
B82: Расход электроэнергии/воды за июнь 2023г.
B83: Местоположение: | E83: М5 магазин "Пчелка маркет" г. Киев, ул. Коласа Якуба, 2A
B85: № п/п | C85: Название потребителя | D85: Юридическое лицо | E85: № счетчика | F85: Энергоноситель | G85: Показатели счетчика | K85: Коэф. | L85: Потребление, кВт/ч, м3 | M85: Стоимость 1кВт/ч, м3 | N85: Итого
G86: Дата снятия | H86: Показатели | I86: Дата снятия | J86: Показатели
B87: 1 | C87: Спортивный клуб | E87: Энергомера ЦЭ68038 №60142331 | F87: Активная э.э. | G87: 45077 | H87: 21549 | I87: 45107 | J87: 21553 | K87: 1 | L87: =J87-H87 -> 4 | M87: 4.9792 | N87: =L87*M87 -> 19.9168
E88: JS 2,5-02 №13749754 | F88: Водоснабжение | G88: 45077 | H88: 1591.92 | I88: 45107 | J88: 1598.5 | K88: 1 | L88: =J88-H88 -> 6.58 | M88: 30.38 | N88: =L88*M88 -> 199.9004
B89: 2 | C89: Магазин инструментов ТМ "Makita" | E89: CO-ЭЭ6706 №054494008 | F89: Активная э.э. | G89: 45077 | H89: 18683.8 | I89: 45107 | J89: 18809 | K89: 1 | L89: =J89-H89 -> 125.2 | M89: 4.9792 | N89: =L89*M89 -> 623.39584
B90: 3 | C90: Помещение электрощитовой | E90: НІК 2102-02.M2 №4921123 | F90: Активная э.э. | G90: 45077 | H90: 28172.2 | I90: 45107 | J90: 28180 | K90: 1 | L90: =J90-H90 -> 7.8 | M90: 4.9792 | N90: =L90*M90 -> 38.83776
B92: Расход электроэнергии/воды за июль 2023г.
B93: Местоположение: | E93: М5 магазин "Пчелка маркет" г. Киев, ул. Коласа Якуба, 2A
B95: № п/п | C95: Название потребителя | D95: Юридическое лицо | E95: № счетчика | F95: Энергоноситель | G95: Показатели счетчика | K95: Коэф. | L95: Потребление, кВт/ч, м3 | M95: Стоимость 1кВт/ч, м3 | N95: Итого | O95: Сплачено
G96: Дата снятия | H96: Показатели | I96: Дата снятия | J96: Показатели | O96: Сплачено
B97: 1 | C97: Спортивный клуб | E97: Энергомера ЦЭ68038 №60142331 | F97: Активная э.э. | G97: 45107 | H97: 21553 | I97: 45138 | J97: 21560 | K97: 1 | L97: =J97-H97 -> 7 | M97: 5.9466962 | N97: =L97*M97 -> 41.626873
E98: JS 2,5-02 №13749754 | F98: Водоснабжение | G98: 45107 | H98: 1598.5 | I98: 45138 | J98: 1604 | K98: 1 | L98: =J98-H98 -> 5.5 | M98: 30.38 | N98: =L98*M98 -> 167.09
B99: 2 | C99: Магазин инструментов ТМ "Makita" | E99: CO-ЭЭ6706 №054494008 | F99: Активная э.э. | G99: 45107 | H99: 18809 | I99: 45138 | J99: 18931 | K99: 1 | L99: =J99-H99 -> 122 | M99: 5.9466962 | N99: =L99*M99 -> 725.49693
B100: 3 | C100: Помещение электрощитовой | E100: НІК 2102-02.M2 №4921123 | F100: Активная э.э. | G100: 45107 | H100: 28180 | I100: 45138 | J100: 28181 | K100: 1 | L100: =J100-H100 -> 1 | M100: 5.9466962 | N100: =L100*M100 -> 5.9466962
B102: Расход электроэнергии/воды за август 2023г.
B103: Местоположение: | E103: М5 магазин "Пчелка маркет" г. Киев, ул. Коласа Якуба, 2A
B105: № п/п | C105: Название потребителя | D105: Юридическое лицо | E105: № счетчика | F105: Энергоноситель | G105: Показатели счетчика | K105: Коэф. | L105: Потребление, кВт/ч, м3 | M105: Стоимость 1кВт/ч, м3 | N105: Итого | O105: Сплачено
G106: Дата снятия | H106: Показатели | I106: Дата снятия | J106: Показатели | O106: Сплачено
B107: 1 | C107: Спортивный клуб | E107: Энергомера ЦЭ68038 №60142331 | F107: Активная э.э. | G107: 45138 | H107: 21560 | I107: 45169 | J107: 21570 | K107: 1 | L107: =J107-H107 -> 10 | M107: 6.6107534 | N107: =L107*M107 -> 66.107534
E108: JS 2,5-02 №13749754 | F108: Водоснабжение | G108: 45138 | H108: 1604 | I108: 45169 | J108: 1610 | K108: 1 | L108: =J108-H108 -> 6 | M108: 30.38 | N108: =L108*M108 -> 182.28
B109: 2 | C109: Магазин инструментов ТМ "Makita" | E109: CO-ЭЭ6706 №054494008 | F109: Активная э.э. | G109: 45138 | H109: 18931 | I109: 45169 | J109: 19067 | K109: 1 | L109: =J109-H109 -> 136 | M109: 6.6107534 | N109: =L109*M109 -> 899.06247
B110: 3 | C110: Помещение электрощитовой | E110: НІК 2102-02.M2 №4921123 | F110: Активная э.э. | G110: 45138 | H110: 28181 | I110: 45169 | J110: 28207 | K110: 1 | L110: =J110-H110 -> 26 | M110: 6.6107534 | N110: =L110*M110 -> 171.87959
B112: Расход электроэнергии/воды за сентябрь 2023г.
B113: Местоположение: | E113: М5 магазин "Пчелка маркет" г. Киев, ул. Коласа Якуба, 2A
B115: № п/п | C115: Название потребителя | D115: Юридическое лицо | E115: № счетчика | F115: Энергоноситель | G115: Показатели счетчика | K115: Коэф. | L115: Потребление, кВт/ч, м3 | M115: Стоимость 1кВт/ч, м3 | N115: Итого | O115: Сплачено
G116: Дата снятия | H116: Показатели | I116: Дата снятия | J116: Показатели | O116: Сплачено
B117: 1 | C117: Спортивный клуб | E117: Энергомера ЦЭ68038 №60142331 | F117: Активная э.э. | G117: 45169 | H117: 21570 | I117: 45199 | J117: 21574 | K117: 1 | L117: =J117-H117 -> 4 | M117: 6.3494522 | N117: =L117*M117 -> 25.397809
E118: JS 2,5-02 №13749754 | F118: Водоснабжение | G118: 45169 | H118: 1610 | I118: 45199 | J118: 1617 | K118: 1 | L118: =J118-H118 -> 7 | M118: 30.38 | N118: =L118*M118 -> 212.66
B119: 2 | C119: Магазин инструментов ТМ "Makita" | E119: CO-ЭЭ6706 №054494008 | F119: Активная э.э. | G119: 45169 | H119: 19067 | I119: 45199 | J119: 19194 | K119: 1 | L119: =J119-H119 -> 127 | M119: 6.3494522 | N119: =L119*M119 -> 806.38043 | O119: 53.36
B120: 3 | C120: Помещение электрощитовой | E120: НІК 2102-02.M2 №4921123 | F120: Активная э.э. | G120: 45169 | H120: 28207 | I120: 45199 | J120: 28231 | K120: 1 | L120: =J120-H120 -> 24 | M120: 6.3494522 | N120: =L120*M120 -> 152.38685
Q121: =N119+N130-O119 -> 1573.8273
B123: Расход электроэнергии/воды за октябрь 2023г.
B124: Местоположение: | E124: М5 магазин "Пчелка маркет" г. Киев, ул. Коласа Якуба, 2A
B126: № п/п | C126: Название потребителя | D126: Юридическое лицо | E126: № счетчика | F126: Энергоноситель | G126: Показатели счетчика | K126: Коэф. | L126: Потребление, кВт/ч, м3 | M126: Стоимость 1кВт/ч, м3 | N126: Итого | O126: Сплачено
G127: Дата снятия | H127: Показатели | I127: Дата снятия | J127: Показатели | O127: Сплачено
...

Sheet М11
B4: Расход электроэнергии/воды за декабрь 2023г.
B5: Местоположение: | E5: М11 магазин "Пчелка маркет" г. Киев, Автозаводська,27
B7: № п/п | C7: Название потребителя | D7: Юридическое лицо | E7: № счетчика | F7: Энергоноситель | G7: Показатели счетчика | K7: Коэф. | L7: Потребление, кВт/ч, м3/ч | M7: Стоимость 1кВт/ч, м3/ч | N7: Итого
G8: Дата снятия | H8: Показатели | I8: Дата снятия | J8: Показатели
B9: 1 | C9: ФОП ЧАХОЯН ГАЙК ЕДВАРДОВИЧ | E9: (ТП) NIK 2303 ARP1 №0198983 | F9: Активня э.э. | G9: 45291 | H9: 173.08 | I9: 45322 | J9: 219.81 | K9: 30 | L9: =J9-H9 -> 46.73 | M9: 6.3746284 | N9: =M9*L9*K9 -> 8936.5915
M10: ИТОГО: | N10: =SUM(N9) -> 8936.5915 | O10: грн.
B13: Расход электроэнергии/воды за январь 2024г.
B14: Местоположение: | E14: М11 магазин "Пчелка маркет" г. Киев, Автозаводська,27
B16: № п/п | C16: Название потребителя | D16: Юридическое лицо | E16: № счетчика | F16: Энергоноситель | G16: Показатели счетчика | K16: Коэф. | L16: Потребление, кВт/ч, м3/ч | M16: Стоимость 1кВт/ч, м3/ч | N16: Итого
G17: Дата снятия | H17: Показатели | I17: Дата снятия | J17: Показатели
B18: 1 | C18: ФОП ЧАХОЯН ГАЙК ЕДВАРДОВИЧ | E18: (ТП) NIK 2303 ARP1 №0198983 | F18: Активня э.э. | G18: 45291 | H18: 219.81 | I18: 45322 | J18: 270.6 | K18: 30 | L18: =J18-H18 -> 50.79 | M18: 6.02688 | N18: =M18*L18*K18 -> 9183.1571
M19: ИТОГО: | N19: =SUM(N18) -> 9183.1571 | O19: грн.
B20: Расход электроэнергии/воды за февраль 2024г.
B21: Местоположение: | E21: М11 магазин "Пчелка маркет" г. Киев, Автозаводська,27
B23: № п/п | C23: Название потребителя | D23: Юридическое лицо | E23: № счетчика | F23: Энергоноситель | G23: Показатели счетчика | K23: Коэф. | L23: Потребление, кВт/ч, м3/ч | M23: Стоимость 1кВт/ч, м3/ч | N23: Итого
G24: Дата снятия | H24: Показатели | I24: Дата снятия | J24: Показатели
B25: 1 | C25: ФОП ЧАХОЯН ГАЙК ЕДВАРДОВИЧ | E25: (ТП) NIK 2303 ARP1 №0198983 | F25: Активня э.э. | G25: 45322 | H25: 270.6 | I25: 31.02.2024 | J25: 310.53 | K25: 30 | L25: =J25-H25 -> 39.93 | M25: 5.4806882 | N25: =M25*L25*K25 -> 6565.3164
M26: ИТОГО: | N26: =SUM(N25) -> 6565.3164 | O26: грн.
B27: Расход электроэнергии/воды март 2024г.
B28: Местоположение: | E28: М11 магазин "Пчелка маркет" г. Киев, Автозаводська,27
B30: № п/п | C30: Название потребителя | D30: Юридическое лицо | E30: № счетчика | F30: Энергоноситель | G30: Показатели счетчика | K30: Коэф. | L30: Потребление, кВт/ч, м3/ч | M30: Стоимость 1кВт/ч, м3/ч | N30: Итого
G31: Дата снятия | H31: Показатели | I31: Дата снятия | J31: Показатели
B32: 1 | C32: ФОП ЧАХОЯН ГАЙК ЕДВАРДОВИЧ | E32: (ТП) NIK 2303 ARP1 №0198983 | F32: Активня э.э. | G32: 31.02.2024 | H32: 310.53 | I32: 45381 | J32: 346.33 | K32: 30 | L32: =J32-H32 -> 35.8 | M32: 5.014 | N32: =M32*L32*K32 -> 5385.036
M33: ИТОГО: | N33: =SUM(N32) -> 5385.036 | O33: грн.
B34: Расход электроэнергии/воды за квітень 2024г.
B35: Местоположение: | E35: М11 магазин "Пчелка маркет" г. Киев, Автозаводська,27
B37: № п/п | C37: Название потребителя | D37: Юридическое лицо | E37: № счетчика | F37: Энергоноситель | G37: Показатели счетчика | K37: Коэф. | L37: Потребление, кВт/ч, м3/ч | M37: Стоимость 1кВт/ч, м3/ч | N37: Итого
G38: Дата снятия | H38: Показатели | I38: Дата снятия | J38: Показатели
B39: 1 | C39: ФОП ЧАХОЯН ГАЙК ЕДВАРДОВИЧ | E39: (ТП) NIK 2303 ARP1 №0198983 | F39: Активня э.э. | G39: 45382 | H39: 346.33 | I39: 31.04.2024 | J39: 354.45 | K39: 30 | L39: =J39-H39 -> 8.12 | M39: 5.551212 | N39: =M39*L39*K39 -> 1352.2752
M40: ИТОГО: | N40: =SUM(N39) -> 1352.2752 | O40: грн.
B42: Расход электроэнергии/воды май 2024г.
B43: Местоположение: | E43: М11 магазин "Пчелка маркет" г. Киев, Автозаводська,27
B45: № п/п | C45: Название потребителя | D45: Юридическое лицо | E45: № счетчика | F45: Энергоноситель | G45: Показатели счетчика | K45: Коэф. | L45: Потребление, кВт/ч, м3/ч | M45: Стоимость 1кВт/ч, м3/ч | N45: Итого
G46: Дата снятия | H46: Показатели | I46: Дата снятия | J46: Показатели
B47: 1 | C47: ФОП ЧАХОЯН ГАЙК ЕДВАРДОВИЧ | E47: (ТП) NIK 2303 ARP1 №0198983 | F47: Активня э.э. | G47: 31.04.2024 | H47: 354.45 | I47: 45442 | J47: 361.46 | K47: 30 | L47: =J47-H47 -> 7.01 | M47: 6.5632799 | N47: =M47*L47*K47 -> 1380.2578
M48: ИТОГО: | N48: =SUM(N47) -> 1380.2578 | O48: грн.
B49: Расход электроэнергии/воды июнь 2024г.
B50: Местоположение: | E50: М11 магазин "Пчелка маркет" г. Киев, Автозаводська,27
B52: № п/п | C52: Название потребителя | D52: Юридическое лицо | E52: № счетчика | F52: Энергоноситель | G52: Показатели счетчика | K52: Коэф. | L52: Потребление, кВт/ч, м3/ч | M52: Стоимость 1кВт/ч, м3/ч | N52: Итого
G53: Дата снятия | H53: Показатели | I53: Дата снятия | J53: Показатели
B54: 1 | C54: ФОП ЧАХОЯН ГАЙК ЕДВАРДОВИЧ | E54: (ТП) NIK 2303 ARP1 №0198983 | F54: Активня э.э. | G54: 45442 | H54: 361.46 | I54: 45473 | J54: 371.75 | K54: 30 | L54: =J54-H54 -> 10.29 | M54: 7.506468 | N54: =M54*L54*K54 -> 2317.2467
M55: ИТОГО: | N55: =SUM(N54) -> 2317.2467 | O55: грн.
B56: Расход электроэнергии/воды июль 2024г.
B57: Местоположение: | E57: М11 магазин "Пчелка маркет" г. Киев, Автозаводська,27
B59: № п/п | C59: Название потребителя | D59: Юридическое лицо | E59: № счетчика | F59: Энергоноситель | G59: Показатели счетчика | K59: Коэф. | L59: Потребление, кВт/ч, м3/ч | M59: Стоимость 1кВт/ч, м3/ч | N59: Итого
G60: Дата снятия | H60: Показатели | I60: Дата снятия | J60: Показатели
B61: 1 | C61: ФОП ЧАХОЯН ГАЙК ЕДВАРДОВИЧ | E61: (ТП) NIK 2303 ARP1 №0198983 | F61: Активня э.э. | G61: 45473 | H61: 371.75 | I61: 45503 | J61: 389.85 | K61: 30 | L61: =(J61-H61)*K61 -> 543 | M61: 7.9506961 | N61: =M61*L61*K61 -> 129516.84
M62: ИТОГО: | N62: =SUM(N61) -> 129516.84
B64: Расход электроэнергии/воды июль 2024г.
B65: Местоположение: | E65: М11 магазин "Пчелка маркет" г. Киев, Автозаводська,27
B67: № п/п | C67: Название потребителя | D67: Юридическое лицо | E67: № счетчика | F67: Энергоноситель | G67: Показатели счетчика | K67: Коэф. | L67: Потребление, кВт/ч, м3/ч | M67: Стоимость 1кВт/ч, м3/ч | N67: Итого
G68: Дата снятия | H68: Показатели | I68: Дата снятия | J68: Показатели
B69: 1 | C69: ФОП ЧАХОЯН ГАЙК ЕДВАРДОВИЧ | E69: (ТП) NIK 2303 ARP1 №0198983 | F69: Активня э.э. | G69: 45503 | H69: 389.85 | I69: 45534 | J69: 407.76 | K69: 30 | L69: =(J69-H69)*K69 -> 537.3 | M69: 8.008476 | N69: =M69*L69*K69 -> 129088.62
M70: ИТОГО: | N70: =SUM(N69) -> 129088.62
B72: Расход электроэнергии/воды август 2024г.
B73: Местоположение: | E73: М11 магазин "Пчелка маркет" г. Киев, Автозаводська,27
B75: № п/п | C75: Название потребителя | D75: Юридическое лицо | E75: № счетчика | F75: Энергоноситель | G75: Показатели счетчика | K75: Коэф. | L75: Потребление, кВт/ч, м3/ч | M75: Стоимость 1кВт/ч, м3/ч | N75: Итого
G76: Дата снятия | H76: Показатели | I76: Дата снятия | J76: Показатели
B77: 1 | C77: ФОП ЧАХОЯН ГАЙК ЕДВАРДОВИЧ | E77: (ТП) NIK 2303 ARP1 №0198983 | F77: Активня э.э. | G77: 45503 | H77: 389.85 | I77: 45534 | J77: 407.76 | K77: 30 | L77: =(J77-H77)*K77 -> 537.3 | M77: 8.008476 | N77: =M77*L77 -> 4302.9542
M78: ИТОГО: | N78: =SUM(N77) -> 4302.9542
B80: Расход электроэнергии/воды сентябрь 2024г.
B81: Местоположение: | E81: М11 магазин "Пчелка маркет" г. Киев, Автозаводська,27
B83: № п/п | C83: Название потребителя | D83: Юридическое лицо | E83: № счетчика | F83: Энергоноситель | G83: Показатели счетчика | K83: Коэф. | L83: Потребление, кВт/ч, м3/ч | M83: Стоимость 1кВт/ч, м3/ч | N83: Итого
G84: Дата снятия | H84: Показатели | I84: Дата снятия | J84: Показатели
B85: 1 | C85: ФОП ЧАХОЯН ГАЙК ЕДВАРДОВИЧ | E85: (ТП) NIK 2303 ARP1 №0198983 | F85: Активня э.э. | G85: 45534 | H85: 407.76 | I85: 30.092024 | J85: 418.63 | K85: 30 | L85: =(J85-H85)*K85 -> 326.1 | M85: 8.171232 | N85: =M85*L85 -> 2664.6388
M86: ИТОГО: | N86: =SUM(N85) -> 2664.6388
B88: Расход электроэнергии/воды октябрь 2024 г.
B89: Местоположение: | E89: М11 магазин "Пчелка маркет" г. Киев, Автозаводська,27
B91: № п/п | C91: Название потребителя | D91: Юридическое лицо | E91: № счетчика | F91: Энергоноситель | G91: Показатели счетчика | K91: Коэф. | L91: Потребление, кВт/ч, м3/ч | M91: Стоимость 1кВт/ч, м3/ч | N91: Итого
G92: Дата снятия | H92: Показатели | I92: Дата снятия | J92: Показатели
B93: 1 | C93: ФОП ЧАХОЯН ГАЙК ЕДВАРДОВИЧ | E93: (ТП) NIK 2303 ARP1 №0198983 | F93: Активня э.э. | G93: 30.092024 | H93: 418.63 | I93: 45596 | J93: 439.73 | K93: 30 | L93: =(J93-H93)*K93 -> 633 | M93: 8.22684 | N93: =M93*L93 -> 5207.5897 | Q93: =1.2*6.8557 -> 8.22684
M94: ИТОГО: | N94: =SUM(N93) -> 5207.5897
B96: Расход электроэнергии/воды ноябрь 2024 г.
B97: Местоположение: | E97: М11 магазин "Пчелка маркет" г. Киев, Автозаводська,27
B99: № п/п | C99: Название потребителя | D99: Юридическое лицо | E99: № счетчика | F99: Энергоноситель | G99: Показатели счетчика | K99: Коэф. | L99: Потребление, кВт/ч, м3/ч | M99: Стоимость 1кВт/ч, м3/ч | N99: Итого
G100: Дата снятия | H100: Показатели | I100: Дата снятия | J100: Показатели
B101: 1 | C101: ФОП ЧАХОЯН ГАЙК ЕДВАРДОВИЧ | E101: (ТП) NIK 2303 ARP1 №0198983 | F101: Активня э.э. | G101: 45596 | H101: 439.73 | I101: 31.11.2024 | J101: 507 | K101: 30 | L101: =(J101-H101)*K101 -> 2018.1 | M101: 8.22684 | N101: =M101*L101 -> 16602.586 | Q101: =1.2*6.8557 -> 8.22684
M102: ИТОГО: | N102: =SUM(N101) -> 16602.586
B104: Расход электроэнергии/воды декабрь 2024 г.
B105: Местоположение: | E105: М11 магазин "Пчелка маркет" г. Киев, Автозаводська,27
B107: № п/п | C107: Название потребителя | D107: Юридическое лицо | E107: № счетчика | F107: Энергоноситель | G107: Показатели счетчика | K107: Коэф. | L107: Потребление, кВт/ч, м3/ч | M107: Стоимость 1кВт/ч, м3/ч | N107: Итого
G108: Дата снятия | H108: Показатели | I108: Дата снятия | J108: Показатели
B109: 1 | C109: ФОП ЧАХОЯН ГАЙК ЕДВАРДОВИЧ | E109: (ТП) NIK 2303 ARP1 №0198983 | F109: Активня э.э. | G109: 31.11.2024 | H109: 507 | I109: 45657 | J109: 596.79 | K109: 30 | L109: =(J109-H109)*K109 -> 2693.7 | M109: 8.714496 | N109: =M109*L109 -> 23474.238 | Q109: =7.26208*1.2 -> 8.714496
M110: ИТОГО: | N110: =SUM(N109) -> 23474.238
B111: Расход электроэнергии/воды январь 2025 г.
B112: Местоположение: | E112: М11 магазин "Пчелка маркет" г. Киев, Автозаводська,27
B114: № п/п | C114: Название потребителя | D114: Юридическое лицо | E114: № счетчика | F114: Энергоноситель | G114: Показатели счетчика | K114: Коэф. | L114: Потребление, кВт/ч, м3/ч | M114: Стоимость 1кВт/ч, м3/ч | N114: Итого
G115: Дата снятия | H115: Показатели | I115: Дата снятия | J115: Показатели
B116: 1 | C116: ФОП ЧАХОЯН ГАЙК ЕДВАРДОВИЧ | E116: (ТП) NIK 2303 ARP1 №0198983 | F116: Активня э.э. | G116: 45657 | H116: 596.79 | I116: 45688 | J116: 673.42 | K116: 30 | L116: =(J116-H116)*K116 -> 2298.9 | M116: 8.5936438 | N116: =M116*L116 -> 19755.928
M117: ИТОГО: | N117: =SUM(N116) -> 19755.928
B118: Расход электроэнергии/воды февраль 2025 г.
B119: Местоположение: | E119: М11 магазин "Пчелка маркет" г. Киев, Автозаводська,27
B121: № п/п | C121: Название потребителя | D121: Юридическое лицо | E121: № счетчика | F121: Энергоноситель | G121: Показатели счетчика | K121: Коэф. | L121: Потребление, кВт/ч, м3/ч | M121: Стоимость 1кВт/ч, м3/ч | N121: Итого
G122: Дата снятия | H122: Показатели | I122: Дата снятия | J122: Показатели
B123: 1 | C123: ФОП ЧАХОЯН ГАЙК ЕДВАРДОВИЧ | E123: (ТП) NIK 2303 ARP1 №0198983 | F123: Активня э.э. | G123: 45688 | H123: 673.42 | I123: 45716 | J123: 764.34 | K123: 30 | L123: =(J123-H123)*K123 -> 2727.6 | M123: 9.277332 | N123: =M123*L123 -> 25304.851
M124: ИТОГО: | N124: =SUM(N123) -> 25304.851
B125: Расход электроэнергии/воды март 2025 г.
B126: Местоположение: | E126: М11 магазин "Пчелка маркет" г. Киев, Автозаводська,27
B128: № п/п | C128: Название потребителя | D128: Юридическое лицо | E128: № счетчика | F128: Энергоноситель | G128: Показатели счетчика | K128: Коэф. | L128: Потребление, кВт/ч, м3/ч | M128: Стоимость 1кВт/ч, м3/ч | N128: Итого
G129: Дата снятия | H129: Показатели | I129: Дата снятия | J129: Показатели
...

Sheet М40
B3: Расход электроэнергии/воды за ЛЮТИЙ 2024г.
B4: Местоположение: | E4: М40 магазин "Пчелка маркет"Б.Церковь. Ул. Метрофанова,8
B6: № п/п | C6: Название потребителя | D6: Юридическое лицо | E6: № счетчика | F6: Энергоноситель | G6: Показатели счетчика | K6: Коэф. | L6: Потребление, кВт/ч, м3/ч | M6: Стоимость 1кВт/ч, м3/ч | N6: Итого
G7: Дата снятия | H7: Показатели | I7: Дата снятия | J7: Показатели
B8: 1 | C8: РЕНТ ЛАЙН КОМПАНІ | D8: ТОВ КИЕВСКИЙ ТРЕЙД | E8: №0075071140 | F8: Активня э.э. | G8: 44592 | H8: 34363 | I8: 45351 | J8: 34984 | K8: 1 | L8: =J8-H8 -> 621 | M8: 6.737708 | N8: =M8*L8*K8 -> 4184.1167
B9: 3 | D9: АТЛАНТ СПОРТ | E9: NIK2300 №20375257 | F9: Активня э.э. | G9: 44592 | H9: 1186 | I9: 45351 | J9: 1212 | K9: 1 | L9: =J9-H9 -> 26 | M9: =M8 -> 6.737708 | N9: =M9*L9*K9 -> 175.18041
M10: ИТОГО: | N10: =SUM(N8:N9) -> 4359.2971 | O10: грн.
B11: Расход электроэнергии/воды за березень 2024г.
B12: Местоположение: | E12: М40 магазин "Пчелка маркет"Б.Церковь. Ул. Метрофанова,8
B14: № п/п | C14: Название потребителя | D14: Юридическое лицо | E14: № счетчика | F14: Энергоноситель | G14: Показатели счетчика | K14: Коэф. | L14: Потребление, кВт/ч, м3/ч | M14: Стоимость 1кВт/ч, м3/ч | N14: Итого
G15: Дата снятия | H15: Показатели | I15: Дата снятия | J15: Показатели
B16: 1 | C16: РЕНТ ЛАЙН КОМПАНІ | D16: ТОВ КИЕВСКИЙ ТРЕЙД | E16: №0075071140 | F16: Активня э.э. | G16: 45351 | H16: 34984 | I16: 45382 | J16: 35672 | K16: 1 | L16: =J16-H16 -> 688 | M16: 6.4699321 | N16: =M16*L16*K16 -> 4451.3133
B17: 3 | D17: АТЛАНТ СПОРТ | E17: NIK2300 №20375257 | F17: Активня э.э. | G17: 45351 | H17: 79.52 | I17: 45382 | J17: 149 | K17: 40 | L17: =J17-H17 -> 69.48 | M17: =M16 -> 6.4699321 | N17: =M17*L17*K17 -> 17981.235
M18: ИТОГО: | N18: 22432.548 | O18: грн.
B20: Расход электроэнергии/воды за квітень 2024г.
B21: Местоположение: | E21: М40 магазин "Пчелка маркет"Б.Церковь. Ул. Метрофанова,8
B23: № п/п | C23: Название потребителя | D23: Юридическое лицо | E23: № счетчика | F23: Энергоноситель | G23: Показатели счетчика | K23: Коэф. | L23: Потребление, кВт/ч, м3/ч | M23: Стоимость 1кВт/ч, м3/ч | N23: Итого
G24: Дата снятия | H24: Показатели | I24: Дата снятия | J24: Показатели
B25: 1 | C25: РЕНТ ЛАЙН КОМПАНІ | D25: ТОВ КИЕВСКИЙ ТРЕЙД | E25: №0075071140 | F25: Активня э.э. | G25: 45382 | H25: 35672 | I25: 45412 | J25: 36216 | K25: 1 | L25: =J25-H25 -> 544 | M25: 6.737708 | N25: =M25*L25*K25 -> 3665.3131
B26: 3 | D26: АТЛАНТ СПОРТ | E26: NIK2300 №20375257 | F26: Активня э.э. | G26: 45382 | H26: 149 | I26: 45412 | J26: 195.19 | K26: 40 | L26: =J26-H26 -> 46.19 | M26: =M25 -> 6.737708 | N26: =M26*L26*K26 -> 12448.589
M27: ИТОГО: | N27: 22432.548 | O27: грн.
B28: Расход электроэнергии/воды за травень 2024г.
B29: Местоположение: | E29: М40 магазин "Пчелка маркет"Б.Церковь. Ул. Метрофанова,8
B31: № п/п | C31: Название потребителя | D31: Юридическое лицо | E31: № счетчика | F31: Энергоноситель | G31: Показатели счетчика | K31: Коэф. | L31: Потребление, кВт/ч, м3/ч | M31: Стоимость 1кВт/ч, м3/ч | N31: Итого
G32: Дата снятия | H32: Показатели | I32: Дата снятия | J32: Показатели
B33: 1 | C33: РЕНТ ЛАЙН КОМПАНІ | D33: ТОВ КИЕВСКИЙ ТРЕЙД | E33: №0075071140 | F33: Активня э.э. | G33: 45412 | H33: 36216 | I33: 45442 | J33: 36694 | K33: 1 | L33: =J33-H33 -> 478 | M33: 7.6846319 | N33: =M33*L33*K33 -> 3673.2541 | Q33: 36980
B34: 3 | D34: АТЛАНТ СПОРТ | E34: NIK2300 №20375257 | F34: Активня э.э. | G34: 45412 | H34: 195.19 | I34: 45442 | J34: 256.69 | K34: 40 | L34: =J34-H34 -> 61.5 | M34: =M33 -> 7.6846319 | N34: =M34*L34*K34 -> 18904.195
M35: ИТОГО: | N35: 22432.548
B37: Расход электроэнергии/воды за червень 2024г.
B38: Местоположение: | E38: М40 магазин "Пчелка маркет". Б.Церковь, ул. Митрофанова,8
B40: № п/п | C40: Название потребителя | D40: Юридическое лицо | E40: № счетчика | F40: Энергоноситель | G40: Показатели счетчика | K40: Коэф. | L40: Потребление, кВт/ч, м3/ч | M40: Стоимость 1кВт/ч, м3/ч | N40: Итого
G41: Дата снятия | H41: Показатели | I41: Дата снятия | J41: Показатели
B42: 1 | C42: РЕНТ ЛАЙН КОМПАНІ | D42: ТОВ КИЕВСКИЙ ТРЕЙД | E42: №0075071140 | F42: Активня э.э. | G42: 45442 | H42: 36694 | I42: 45473 | J42: 36980 | K42: 1 | L42: =J42-H42 -> 286 | M42: 8.6037359 | N42: =M42*L42*K42 -> 2460.6685
D43: АТЛАНТ СПОРТ | E43: NIK2300 №20375257 | F43: Активня э.э. | G43: 45442 | H43: 256.69 | I43: 45473 | J43: 325.22 | K43: 40 | L43: =J43-H43 -> 68.53 | M43: =M42 -> 8.6037359 | N43: =M43*L43*K43 -> 23584.561
F44: вода | G44: 45443 | H44: 1298 | I44: 45473 | J44: 1323 | L44: =J44-H44 -> 25
M45: ИТОГО: | N45: =SUM(N42:N44) -> 26045.229
B47: Расход электроэнергии/воды за липень 2024г.
B48: Местоположение: | E48: М40 магазин "Пчелка маркет". Б.Церковь, ул. Митрофанова,8
B50: № п/п | C50: Название потребителя | D50: Юридическое лицо | E50: № счетчика | F50: Энергоноситель | G50: Показатели счетчика | K50: Коэф. | L50: Потребление, кВт/ч, м3/ч | M50: Стоимость 1кВт/ч, м3/ч | N50: Итого
G51: Дата снятия | H51: Показатели | I51: Дата снятия | J51: Показатели
B52: 1 | C52: РЕНТ ЛАЙН КОМПАНІ | D52: ТОВ КИЕВСКИЙ ТРЕЙД | E52: №0075071140 | F52: Активня э.э. | G52: 45473 | H52: 36980 | I52: 45504 | J52: 37254 | K52: 1 | L52: =J52-H52 -> 274 | M52: 9.06 | N52: =M52*L52*K52 -> 2482.44
D53: АТЛАНТ СПОРТ | E53: NIK2300 №20375257 | F53: Активня э.э. | G53: 45473 | H53: 325.22 | I53: 45504 | J53: 398.63 | K53: 40 | L53: =J53-H53 -> 73.41 | M53: =M52 -> 9.06 | N53: =M53*L53*K53 -> 26603.784
F54: вода | G54: 45473 | H54: 1323 | I54: 45504 | J54: 1348 | L54: =J54-H54 -> 25
M55: ИТОГО: | N55: =SUM(N52:N54) -> 29086.224
B57: Расход электроэнергии/воды за август 2024г.
B58: Местоположение: | E58: М40 магазин "Пчелка маркет". Б.Церковь, ул. Митрофанова,8
B60: № п/п | C60: Название потребителя | D60: Юридическое лицо | E60: № счетчика | F60: Энергоноситель | G60: Показатели счетчика | K60: Коэф. | L60: Потребление, кВт/ч, м3/ч | M60: Стоимость 1кВт/ч, м3/ч | N60: Итого
G61: Дата снятия | H61: Показатели | I61: Дата снятия | J61: Показатели
B62: 1 | C62: РЕНТ ЛАЙН КОМПАНІ | D62: ТОВ КИЕВСКИЙ ТРЕЙД | E62: №0075071140 | F62: Активня э.э. | G62: 45504 | H62: 37254 | I62: 45535 | J62: 37612 | K62: 1 | L62: =J62-H62 -> 358 | M62: 9.16166 | N62: =M62*L62*K62 -> 3279.8743
D63: АТЛАНТ СПОРТ | E63: NIK2300 №20375257 | F63: Активня э.э. | G63: 45504 | H63: 398.63 | I63: 45535 | J63: 456.34 | K63: 40 | L63: =J63-H63 -> 57.71 | M63: =M62 -> 9.16166 | N63: =M63*L63*K63 -> 21148.776
F64: вода | G64: 45504 | H64: 1348 | I64: 45535 | J64: 1376 | L64: =J64-H64 -> 28
M65: ИТОГО: | N65: =SUM(N62:N64) -> 24428.65
B67: Расход электроэнергии/воды за сентябрь 2024г.
B68: Местоположение: | E68: М40 магазин "Пчелка маркет". Б.Церковь, ул. Митрофанова,8
B70: № п/п | C70: Название потребителя | D70: Юридическое лицо | E70: № счетчика | F70: Энергоноситель | G70: Показатели счетчика | K70: Коэф. | L70: Потребление, кВт/ч, м3/ч | M70: Стоимость 1кВт/ч, м3/ч | N70: Итого
G71: Дата снятия | H71: Показатели | I71: Дата снятия | J71: Показатели
B72: 1 | C72: РЕНТ ЛАЙН КОМПАНІ | D72: ТОВ КИЕВСКИЙ ТРЕЙД | E72: №0075071140 | F72: Активня э.э. | G72: 45535 | H72: 37612 | I72: 45565 | J72: 37929 | K72: 1 | L72: =J72-H72 -> 317 | M72: 9.457668 | N72: =M72*L72*K72 -> 2998.0808 | R72: =1.2*7.88139 -> 9.457668
D73: АТЛАНТ СПОРТ | E73: NIK2300 №20375257 | F73: Активня э.э. | G73: 45535 | H73: 456.34 | I73: 45565 | J73: 500.02 | K73: 40 | L73: =J73-H73 -> 43.68 | M73: =M72 -> 9.457668 | N73: =M73*L73*K73 -> 16524.438
F74: вода | G74: 45535 | H74: 1376 | I74: 45565 | J74: 1400 | K74: 1 | L74: =J74-H74 -> 24
M75: ИТОГО: | N75: =SUM(N72:N74) -> 19522.518
B77: Расход электроэнергии/воды за октябрь 2024г.
B78: Местоположение: | E78: М40 магазин "Пчелка маркет". Б.Церковь, ул. Митрофанова,8
B80: № п/п | C80: Название потребителя | D80: Юридическое лицо | E80: № счетчика | F80: Энергоноситель | G80: Показатели счетчика | K80: Коэф. | L80: Потребление, кВт/ч, м3/ч | M80: Стоимость 1кВт/ч, м3/ч | N80: Итого
G81: Дата снятия | H81: Показатели | I81: Дата снятия | J81: Показатели
B82: 1 | C82: РЕНТ ЛАЙН КОМПАНІ | D82: ТОВ КИЕВСКИЙ ТРЕЙД | E82: №0075071140 | F82: Активня э.э. | G82: 45565 | H82: 37929 | I82: 45595 | J82: 38505 | K82: 1 | L82: =J82-H82 -> 576 | M82: 9.821628 | N82: =M82*L82*K82 -> 5657.2577 | R82: =1.2*8.18469 -> 9.821628
D83: АТЛАНТ СПОРТ | E83: NIK2300 №20375257 | F83: Активня э.э. | G83: 45565 | H83: 500.02 | I83: 45595 | J83: 554.48 | K83: 40 | L83: =J83-H83 -> 54.46 | M83: =M82 -> 9.821628 | N83: =M83*L83*K83 -> 21395.434
F84: вода | G84: 45565 | H84: 1400 | I84: 45595 | J84: 1427 | K84: 1 | L84: =J84-H84 -> 27
M85: ИТОГО: | N85: =SUM(N82:N84) -> 27052.692
B87: Расход электроэнергии/воды за ноябрь 2024г.
B88: Местоположение: | E88: М40 магазин "Пчелка маркет". Б.Церковь, ул. Митрофанова,8
B90: № п/п | C90: Название потребителя | D90: Юридическое лицо | E90: № счетчика | F90: Энергоноситель | G90: Показатели счетчика | K90: Коэф. | L90: Потребление, кВт/ч, м3/ч | M90: Стоимость 1кВт/ч, м3/ч | N90: Итого
G91: Дата снятия | H91: Показатели | I91: Дата снятия | J91: Показатели
B92: 1 | C92: РЕНТ ЛАЙН КОМПАНІ | D92: ТОВ КИЕВСКИЙ ТРЕЙД | E92: №0075071140 | F92: Активня э.э. | G92: 45595 | H92: 38505 | I92: 45626 | J92: 39159 | K92: 1 | L92: =J92-H92 -> 654 | M92: 9.4093561 | N92: =M92*L92*K92 -> 6153.7189
D93: АТЛАНТ СПОРТ | E93: NIK2300 №20375257 | F93: Активня э.э. | G93: 45595 | H93: 554.48 | I93: 45626 | J93: 631.75 | K93: 40 | L93: =J93-H93 -> 77.27 | M93: =M92 -> 9.4093561 | N93: =M93*L93*K93 -> 29082.438
F94: вода | G94: 45595 | H94: 1427 | I94: 45626 | J94: 1452 | K94: 1 | L94: =J94-H94 -> 25
M95: ИТОГО: | N95: =SUM(N92:N94) -> 35236.157
B97: Расход электроэнергии/воды за декабрь 2024г.
B98: Местоположение: | E98: М40 магазин "Пчелка маркет". Б.Церковь, ул. Митрофанова,8
B100: № п/п | C100: Название потребителя | D100: Юридическое лицо | E100: № счетчика | F100: Энергоноситель | G100: Показатели счетчика | K100: Коэф. | L100: Потребление, кВт/ч, м3/ч | M100: Стоимость 1кВт/ч, м3/ч | N100: Итого
G101: Дата снятия | H101: Показатели | I101: Дата снятия | J101: Показатели
B102: 1 | C102: РЕНТ ЛАЙН КОМПАНІ | D102: ТОВ КИЕВСКИЙ ТРЕЙД | E102: №0075071140 | F102: Активня э.э. | G102: 45626 | H102: 39159 | I102: 45656 | J102: 39689 | K102: 1 | L102: =J102-H102 -> 530 | M102: 10.090032 | N102: =M102*L102*K102 -> 5347.717
D103: АТЛАНТ СПОРТ | E103: NIK2300 №20375257 | F103: Активня э.э. | G103: 45626 | H103: 631.75 | I103: 45656 | J103: 739.63 | K103: 40 | L103: =J103-H103 -> 107.88 | M103: =M102 -> 10.090032 | N103: =M103*L103*K103 -> 43540.506
F104: вода | G104: 45626 | H104: 1452 | I104: 45656 | J104: 1476 | K104: 1 | L104: =J104-H104 -> 24
M105: ИТОГО: | N105: =SUM(N102:N104) -> 48888.223
B107: Расход электроэнергии/воды за январь 2025 г.
B108: Местоположение: | E108: М40 магазин "Пчелка маркет". Б.Церковь, ул. Митрофанова,8
B110: № п/п | C110: Название потребителя | D110: Юридическое лицо | E110: № счетчика | F110: Энергоноситель | G110: Показатели счетчика | K110: Коэф. | L110: Потребление, кВт/ч, м3/ч | M110: Стоимость 1кВт/ч, м3/ч | N110: Итого
G111: Дата снятия | H111: Показатели | I111: Дата снятия | J111: Показатели
B112: 1 | C112: РЕНТ ЛАЙН КОМПАНІ | D112: ТОВ КИЕВСКИЙ ТРЕЙД | E112: №0075071140 | F112: Активня э.э. | G112: 45656 | H112: 39689 | I112: 45688 | J112: 40349 | K112: 1 | L112: =J112-H112 -> 660 | M112: 10.090032 | N112: =M112*L112*K112 -> 6659.4212
D113: АТЛАНТ СПОРТ | E113: NIK2300 №20375257 | F113: Активня э.э. | G113: 45656 | H113: 739.63 | I113: 45688 | J113: 850.58 | K113: 40 | L113: =J113-H113 -> 110.95 | M113: =M112 -> 10.090032 | N113: =M113*L113*K113 -> 44779.562
F114: вода | G114: 45656 | H114: 1476 | I114: 45688 | J114: 1504 | K114: 1 | L114: =J114-H114 -> 28
M115: ИТОГО: | N115: =SUM(N112:N114) -> 51438.983
B117: Расход электроэнергии/воды за февраль 2025 г.
B118: Местоположение: | E118: М40 магазин "Пчелка маркет". Б.Церковь, ул. Митрофанова,8
B120: № п/п | C120: Название потребителя | D120: Юридическое лицо | E120: № счетчика | F120: Энергоноситель | G120: Показатели счетчика | K120: Коэф. | L120: Потребление, кВт/ч, м3/ч | M120: Стоимость 1кВт/ч, м3/ч | N120: Итого
G121: Дата снятия | H121: Показатели | I121: Дата снятия | J121: Показатели
B122: 1 | C122: РЕНТ ЛАЙН КОМПАНІ | D122: ТОВ КИЕВСКИЙ ТРЕЙД | E122: №0075071140 | F122: Активня э.э. | G122: 45688 | H122: 40349 | I122: 28,02,2025 | J122: 41009 | K122: 1 | L122: =J122-H122 -> 660 | M122: 10.18195 | N122: =M122*L122*K122 -> 6720.087
D123: АТЛАНТ СПОРТ | E123: NIK2300 №20375257 | F123: Активня э.э. | G123: 45688 | H123: 850.58 | I123: 28,02,2025 | J123: 990.58 | K123: 40 | L123: =J123-H123 -> 140 | M123: =M122 -> 10.18195 | N123: =M123*L123*K123 -> 57018.92
F124: вода | G124: 45688 | H124: 1504 | I124: 28,02,2025 | J124: 1532 | K124: 1 | L124: =J124-H124 -> 28
M125: ИТОГО: | N125: =SUM(N122:N124) -> 63739.007
...
