Workbook

Sheet Договора
B2: ФОП Бондарчук В.В. Киевводоканал | C2: о/р 7-2776 | D2: М22 | E2: Договор №10896/5-10СА від 16.11.2018р.
B3: ФОП Ковальова Л.В. Киевводоканал | C3: о/р 8-1833 | D3: М5 | E3: Договор №03789/5-09СА від 04.04.2016р.
B4: ФОП Тришапко С.Д. Киевводоканал | C4: о/р 5-1374 | D4: М10 | E4: договор №10890/5-05 від 20.11.2012р.
B5: Логин Киевводоканал (М15) | C5: 39775097 | D5: пароль | E5: Legion2015
A6: Логин | B6: Киевэнерго ЛЕГИОН 2015 М3-ул.Р.Окипной,3 ; М5-ул.Я.Коласа, 2А; М6-ул. Сикорского,1А; М10- ул.Героев Сталинграда,65Б; М12 - ул.Антоновича,115Д; М15-ул.Шолом-Алейхема, 10а; М20-ул. Бориспольская, 32А, М22-ул. Ветряные горы, 21/7; М37-пр.Воздухофлотский, 19/1-А | C6: 43305015 | D6: пароль | E6: Legion2015 (Pass11!!)
A7: РИДО | B7: ДТЕК КИЇВСКИЕ СЕТИ М26,М11 | C7: 54299019 | D7: пароль | E7: Legion2015 (Pass11!!)
A8: Логин | B8: ТОЛК Україна М1/1;М8;М21;М34;М43;М25 | C8: №10-000217
A9: РИДО | B9: ТОЛК Україна М24;М40;М41;М17/1 | C9: №10-000218
A10: ЛЕГІОН | B10: АТ"ЖИТОМЕРОБЛЕНЕРГО" ЖИТОМИРСЬКИЙ РЕМ М1/1 г.Житомир. Пр.Мира,15 | C10: 762-РЕ
A11: ЛЕГІОН | B11: ДТЕК КИЇВСЬКІ РЕГІОНАЛЬНІ МЕРЕЖІ М8г.Ирпень, 10-я линия,1Б ; М21'г.Ирпень, ул. Тургеневская, 50б | C11: 220077408 | D11: пароль | E11: Legion2015
A12: ЛЕГІОН | B12: ДТЕК КИЇВСЬКІ РЕГІОНАЛЬНІ МЕРЕЖІ (М34) п.г.т. Софиевская Борщаговка, ул. Соборная 105/7 | C12: 220102339
A13: ЛЕГІОН | B13: ДТЕК КИЇВСЬКІ РЕГІОНАЛЬНІ МЕРЕЖІ М43 Боярка ул.Бульварная2/50) М25 'с.С.Борщаговка, ул. П.Чубинского, 8в | C13: 220105913
A14: РІДО | B14: ДТЕК КИЇВСЬКІ РЕГІОНАЛЬНІ МЕРЕЖІ 'М24 с.Глеваха, ул. Ботаническая, 34 ТП 566 | C14: 220090824
A15: РІДО | B15: ДТЕК КИЇВСЬКІ РЕГІОНАЛЬНІ МЕРЕЖІ М40'Б.Церковь. Ул. Метрофанова,8 М41'Б.Церковь. Ул. Сквирское шоссе, 223 /223 -А | C15: 220104936
A16: РІДО | B16: ДТЕК КИЇВСЬКІ РЕГІОНАЛЬНІ МЕРЕЖІ М17/1 'Борисполь, Головатого 64 | C16: 220105089
B31: Логин Киевская областная ЕК (М8М21) | C31: 420077408 | D31: пароль | E31: Legion2015
B32: Логин Киевская областная ЕК (М8М21) | C32: 420077408
B33: Логин ДТЕК КИЇВСЬКІ РЕГІОНАЛЬНІ МЕРЕЖІ(М8 М21)
B34: Логин Киевская областная ЕК (М28) | C34: 420084292 | D34: пароль | E34: RidoGroup
B35: Логин Киевводоканал (М30) | C35: 2606413815 | D35: пароль | E35: Legion2015
B43: Логин Киевоблэнерго (М28) | C43: 220083760 | D43: пароль | E43: RidoGroup

Sheet Потужнісьть
C2: НАЗВАНИЕ ОБЪЕКТА | E2: АДРЕС ОБЪЕКТА | H2: ЮРИДИЧЕСКОЕ (ФИЗИЧЕСКОЕ) ЛИЦО | K2: НАИМЕНОВАНИЕ | M2: Предыдущий период | O2: Тариф | P2: август | U2: Мощность по договору | V2: Потужність Холодильних установок | BD2: Дата счета | BH2: Срок оплаты | BM2: Предыдущий период | BY2: Тариф | CC2: АВГУСТ 2021г.
M3: Показатели | N3: Сумма | P3: Показатели | Q3: Сумма | R3: Авансы | S3: Реально | T3: Бюджет | BM3: Показатели | BS3: Сумма | CC3: Показатели | CI3: Сумма | CO3: Аренда | CT3: Реально | DB3: Бюджет
C5: Магазин М1/1 "Пчелка маркет" | E5: г.Житомир, пр. Мира, 15 | H5: ТОВ ГРІН БІН Україна | K5: Вывоз ТБО | Q5: 100 | S5: =Q9+Q8+Q6+Q5+R7 -> 203696.56 | T5: 80000 | U5: 128,3 кВт/ч
K6: Экспл. расходы
H7: ООО «Житомирская областная энергетическая компания» | K7: Активная ЭЭ | O7: =Q7/P7 -> 5.6305558 | P7: 45596 | Q7: 256730.82 | R7: 200000
H8: ООО «Житомиробленерго», АТ "Житомиробленерго" Житомирський РЕМ | K8: Реактивная ЭЭ | P8: 1 | Q8: 1395.94
H9: КП "Житомирводоканал" | K9: ХВ | O9: =Q9/P9 -> 37.941724 | P9: 58 | Q9: 2200.62
C10: Магазин М2 "Пчелка маркет" | E10: г.Киев, ул.Владимирская, 73/77 | H10: ТОВ "Еко-Грінко" | K10: Вывоз ТБО | P10: =H719 -> 2 | Q10: =J719 -> 382.8 | S10: =SUM(Q10:Q14) -> 68703.216 | U10: 43 кВт/ч
H11: ІП "Альфа Консалтінг" | K11: Экспл. расходы | P11: 1 | Q11: =1.2*2899.56 -> 3479.472
K12: Активная ЭЭ | O12: =Q12/P12 -> 4.7490724 | P12: 13461 | Q12: =1.2*53272.72 -> 63927.264
K13: Реактивная ЭЭ | P13: 1 | Q13: =1.2*663.67 -> 796.404
K14: ХВ | O14: =Q14/P14 -> 30.382383 | P14: 3.86 | Q14: =1.2*97.73 -> 117.276
C15: Магазин М3 "Пчелка маркет" | E15: г.Киев, ул.Р.Окипной,3 | H15: ТОВ "Еко-Грінко" | K15: Вывоз ТБО | P15: =H720 -> 6 | Q15: =J720 -> 1148.4 | S15: =SUM(Q15:Q18) -> 97694.364 | T15: 110000 | U15: 100 кВт/ч
H16: ТОВ "Київські електричні мережи" | K16: Активная ЭЭ | O16: =Q16/P16 -> 4.6710718 | P16: 20044 | Q16: =1.2*78022.47 -> 93626.964
H17: ДТЕК "Київські електричні мережі" | K17: Реактивная ЭЭ | Q17: 889.96
H18: ФОП Воробьев А.Н. | K18: ХВ | O18: =Q18/P18 -> 32.206984 | P18: 63 | Q18: 2029.04
C19: Магазин М4/1 "Пчелка маркет" | E19: пгт.Коцюбинское, ул. Пономарева, 28а | H19: ПП "Обухівміськвторресурси" | K19: Вывоз ТБО | P19: =Q718 -> 9 | Q19: =S718 -> 1980 | S19: =SUM(Q19:Q22)+N20 -> 91127.866 | T19: 103000 | U19: 50 кВт/ч
H20: НВПФ "Казі-2" | K20: Активная ЭЭ | O20: =Q20/P20 -> 5.2324438 | P20: 15954 | Q20: =1.2*69565.34 -> 83478.408
K21: Реактивная ЭЭ | P21: 1 | Q21: =1.2*2692.49 -> 3230.988
K22: ХВ | O22: =Q22/P22 -> 35.859853 | P22: 68 | Q22: 2438.47
C23: Магазин М5 "Пчелка маркет" | E23: г.Киев, ул. Я.Колоса,2А | H23: ТОВ "Еко-Грінко" | K23: Вывоз ТБО | P23: =H717 -> 8 | Q23: =J717 -> 1531.2 | S23: =SUM(Q23:Q26) -> 90074.364 | T23: 90000 | U23: 84,3 кВт/ч (не меньше 70
H24: ТОВ "Київські електричні мережи" | K24: Активная ЭЭ | O24: =Q24/P24 -> 4.671072 | P24: 18633 | Q24: =1.2*72530.07 -> 87036.084
H25: ДТЕК "Київські електричні мережі" | K25: Реактивная ЭЭ | Q25: 837.26
H26: ФОП Ковальова Л.В. | K26: ХВ | O26: =Q26/P26 -> 30.446364 | P26: 22 | Q26: 669.82
C27: Магазин М6 "Пчелка маркет" | E27: г.Киев, ул. Сикорского,1А | H27: ТОВ "Еко-Грінко" | K27: Вывоз ТБО | P27: =H716 -> 27 | Q27: =J716 -> 5167.8 | S27: =SUM(Q27:Q32) -> 251503.33 | T27: 300000 | U27: 2*132,4 кВт
H28: ТОВ "Ковальська -Житлосервіс" | K28: Экспл. расходы | P28: 696.6 | Q28: 7280.87
P29: 465.4 | Q29: 4864.36
H30: ТОВ "Київські електричні мережи" | K30: Активная ЭЭ | O30: =Q30/P30 -> 4.6710719 | P30: 49263 | Q30: =1.2*191759.18 -> 230111.02
H31: ДТЕК "Київські електричні мережі" | K31: Реактивная ЭЭ | Q31: 2187.28
H32: ФОП Пластун В.В. | K32: ХВ | O32: =Q32/P32 -> 1892 | P32: 1 | Q32: 1892
C33: Магазин М7 "Пчелка маркет" | E33: г.Киев, ул. Коновальца,44Б | H33: ТОВ "Еко-Грінко" | K33: Вывоз ТБО | P33: =H721 -> 4 | Q33: =J721 -> 765.6 | S33: =SUM(Q33:Q39)+N36 -> 182338.56 | T33: 385000 | U33: 75 кВт/ч
H34: ТОВ "ОК "Комфорт" | K34: Экспл. расходы | P34: 1 | Q34: =17607.25+1534.43 -> 19141.68
K35: Реактивная ЭЭ | P35: 1 | Q35: =1.2*1463.16 -> 1755.792
K36: Активная ЭЭ | O36: =Q36/P36 -> 4.5406559 | P36: 31980 | Q36: =1.2*121008.48 -> 145210.18
K37: Обслуживание сетей | P37: 1 | Q37: =1.2*(8573.01+3674.15+40.77+17.47) -> 14766.48
K38: Тепловая энергия | P38: 0.41
K39: ХВ | P39: 23 | Q39: =1.2*(309.81+272.55) -> 698.832
C40: Магазин М8 "Пчелка маркет" | E40: г.Ирпень, 10-я линия,1Б | H40: ПП "Обухівміськвторресурси" | K40: Вывоз ТБО | O40: =Q40/P40 -> #DIV/0! | P40: =Q717 -> 0 | Q40: =S717 -> 0 | S40: =SUM(Q40:Q44)+N40 -> 0 | T40: 255000 | U40: 140 кВт/ч (не меньше 105)
H41: ТОВ "ТЦ "Вайт Хауз" | K41: Экспл. расходы
H42: ТОВ "Київські електричні мережи" | K42: Активная ЭЭ | O42: =Q42/P42 -> #DIV/0!
H43: ПрАТ "Київобленерго" | K43: Реактивная ЭЭ
H44: КП "Ирпеньводоканал" | K44: ХВ | O44: =Q44/P44 -> #DIV/0!
C45: Магазин М9 "Пчелка маркет" | E45: г.Бровары, ул. Шолом Алейхема,68 | H45: ПП "Обухівміськвторресурси" | K45: Вывоз ТБО | P45: =Q712 -> 5 | Q45: =S712 -> 1100 | S45: =SUM(Q45:Q48) -> 123283.95 | T45: 120000 | U45: 100 кВт/ч
H46: ЧП "Броварижитлобуд" | K46: Активная ЭЭ | O46: =Q46/P46 -> 5.0921637 | P46: 23520 | Q46: 119767.69
K47: Реактивная ЭЭ | P47: 1 | Q47: 2046.47
K48: ХВ | O48: =Q48/P48 -> 15.407917 | P48: 24 | Q48: 369.79
C49: Магазин М10 "Пчелка маркет" | E49: г.Киев, ул.Героев Сталинграда,65Б | H49: ТОВ "Еко-Грінко" | K49: Вывоз ТБО | P49: =H722 -> 7 | Q49: =J722 -> 1339.8 | S49: =SUM(Q49:Q53) -> 72374.374 | T49: 85500 | U49: 10 кВт/ч (не меньше 100)
H50: ОСББ "Кристалл-5" | K50: Экспл. расходы | P50: 1 | Q50: 6000
H51: ТОВ "Київські електричні мережи" | K51: Активная ЭЭ | O51: =Q51/P51 -> 4.6710716 | P51: 13619 | Q51: =1.2*53012.77 -> 63615.324
H52: ТОВ "Київські електричні мережи" | K52: Реактивная ЭЭ | Q52: 601.92
H53: ПАТ АК "Київводоканал" ТОВ Легион 2015 | K53: ХВ | O53: =Q53/P53 -> 30.384015 | P53: 26.9 | Q53: 817.33
C54: Магазин М12 "Пчелка маркет" | E54: г.Киев, ул.Антоновича,115Д | H54: КП "Володимирський ринок" | K54: Вывоз ТБО | P54: 39 | Q54: 7295.18 | S54: =SUM(Q54:Q60)+N57+N56+N55+N54 -> 179433.79 | T54: 270000 | U54: 120 кВт/ч
K55: Экспл. расходы | P55: 1 | Q55: =1.2*14416.67 -> 17300.004
K56: Услуги охраны | P56: 1 | Q56: =1.2*13333.33 -> 15999.996
K57: Стоянка а/транспорта | P57: 1 | Q57: =1.2*10833.33 -> 12999.996
H58: ООО "Варяг" | K58: Активная ЭЭ | O58: =Q58/P58 -> 5.124924 | P58: 24070 | Q58: 123356.92
K59: Реактивная ЭЭ | P59: 1 | Q59: 998.71
K60: ХВ | O60: =Q60/P60 -> 30.38 | P60: =Q60/30.38 -> 48.814352 | Q60: 1482.98
C61: Магазин М13/1 "Пчелка маркет" | E61: п.г.т. Тарасовка, вул. Братьев Чмилив, 3А | H61: ПП "Обухівміськвторресурси" | K61: Вывоз ТБО | P61: =Y713 -> 6 | Q61: =AA713 -> #REF! | S61: =SUM(Q61:Q63) -> #REF! | T61: 165000 | U61: 120 кВт/ч
H62: ТОВ "Житлоекономія" | K62: Активная ЭЭ | O62: =Q62/P62 -> 5.1223199 | P62: 17663 | Q62: =1.2*(59877.57+15518.71) -> 90475.536
K63: ХВ | O63: =Q63/P63 -> 0.11627907 | P63: 43 | Q63: 5
C64: Магазин М14 "Пчелка маркет" | E64: г.Киев, ул.Светлая,3Д | H64: ТОВ "Еко-Грінко" | K64: Вывоз ТБО | P64: =H718 -> 8 | Q64: =J718 -> 1531.2 | S64: =SUM(Q64:Q68)+N68 -> 104877.8 | T64: 135000 | U64: 80 кВт/ч
H65: ОК "ОБК Схидна Брама" | K65: Экспл. расходы | O65: =Q65/P65 -> 7.3199968 | P65: 632.6 | Q65: 4630.63
K66: Поточный ремонт | P66: 1 | Q66: 0
K67: Активная ЭЭ | O67: =Q67/P67 -> 4.7754601 | P67: 20258 | Q67: 96741.27
K68: ХВ | O68: =Q68/P68 -> 30.38 | P68: 65 | Q68: 1974.7
C69: Магазин М15 "Пчелка маркет" | E69: г. Киев, ул. Шолом- Алейхема, 10А | H69: ТОВ "Еко-Грінко" | K69: Вывоз ТБО | P69: =H714 -> 4 | Q69: =J714 -> 765.6 | S69: =SUM(Q69:Q73) -> 149608.15 | T69: 169000 | U69: 147,3 кВт/ч
H70: ТОВ "Київські електричні мережи" | K70: Активная ЭЭ | O70: =Q70/P70 -> 4.671072 | P70: 31117 | Q70: =1.2*121124.79 -> 145349.75
H71: ДТЕК "Київські електричні мережі" | K71: Реактивная ЭЭ | Q71: 1381.6
H72: ПАТ АК "Київводоканал" ТОВ Легион 2015 | K72: Обс. вн. ВС | P72: 1 | Q72: =500.85 -> 500.85
K73: ХВ | O73: =Q73/P73 -> 30.383962 | P73: 53 | Q73: 1610.35
C74: Магазин М16 "Пчелка маркет" | E74: г. Киев. пр. Ватутина, 11а | H74: ТОВ "Еко-Грінко" | K74: Вывоз ТБО | P74: =H715 -> 4 | Q74: =J715 -> 765.6 | S74: =SUM(Q74:Q78) -> 70681.212 | T74: 66000 | U74: 80 кВт/ч
H75: ТОВ "Сіметра" | K75: Экспл. расходы | P75: 1 | Q75: =1.2*3933.33 -> 4719.996
K76: Активная ЭЭ | O76: =Q76/P76 -> 4.671072 | P76: 13750 | Q76: 64227.24
K77: Обс. вн. ВС | Q77: =1.2*(225.75+176.11) -> 482.232
K78: ХВ | O78: =Q78/P78 -> 38.89152 | P78: 12.5 | Q78: =1.2*405.12 -> 486.144
C79: Магазин М17 "Пчелка маркет" | E79: г.Обухов, ул. Каштановая, 6/1б | H79: ПП "Обухівміськвторресурси" | K79: Вывоз ТБО | P79: =Q716 -> 17 | Q79: =S716 -> 3740 | S79: =SUM(Q79:Q83) -> 147922.59 | T79: 144000 | U79: 100 кВт/ч
H80: ФОП Вафін В.О. / ФОП Мількевич | K80: Активная ЭЭ | O80: =Q80/P80 -> 5.2324999 | P80: 27417.6 | Q80: 143462.59
K81: Уборка помещения | P81: 1 | Q81: 0
K82: Тепловая энергия
K83: ХВ | O83: =Q83/P83 -> 40 | P83: 18 | Q83: 720
C84: Магазин М18 "Пчелка маркет" | E84: г.Киев, ул. Челябинская, 15А | H84: ТОВ "Еко-Грінко" | K84: Вывоз ТБО | P84: =H713 -> 3 | Q84: =J713 -> 574.2 | S84: =SUM(Q84:Q87) -> 103184 | T84: 120000 | U84: 100 кВт/ч
H85: ТОВ "Нива В" | K85: Активная ЭЭ | O85: =Q85/P85 -> 4.97 | P85: 20100 | Q85: 99897
K86: Реактивная ЭЭ | P86: 9750 | Q86: 1360
K87: ХВ | O87: =Q87/P87 -> 32.209524 | P87: 42 | Q87: 1352.8
C88: Магазин М19 "Пчелка маркет" | E88: г.Ирпень, ул. Соборная, 1г | H88: ТОВ "Еко-Грінко" | K88: Вывоз ТБО | P88: =H723 -> 0 | Q88: =J723 -> 0 | S88: =SUM(Q88:Q92)+N90 -> 7717 | T88: 230000
H89: ПП "Мікс Лтд" | K89: Экспл. расходы | P89: 0 | Q89: 7717
H90: ТОВ "Фреш Лтд" | K90: Активная ЭЭ | P90: 0 | Q90: 0
K91: Реактивная ЭЭ | P91: 0 | Q91: 0
H92: КП "Ирпеньводоканал" | K92: ХВ | P92: 0 | Q92: 0
C93: Магазин М20 "Пчелка маркет" | E93: г.Киев, ул. Бориспольская, 32А | H93: ТОВ "Еко-Грінко" | K93: Вывоз ТБО | P93: =H712 -> 8 | Q93: =J712 -> 1531.2 | S93: =SUM(Q93:Q96) -> 60679.04 | T93: 80000 | U93: 26,9 кВт/ч
H94: ТОВ "Київські електричні мережи" | K94: Активная ЭЭ | O94: =Q94/P94 -> 4.6784785 | P94: 12304 | Q94: 57564
H95: ДТЕК "Київські електричні мережі" | K95: Реактивная ЭЭ | Q95: 546.3
H96: ТОВ "ТВК "Бориспільська" | K96: ХВ | O96: =Q96/P96 -> 30.515882 | P96: 34 | Q96: 1037.54
C97: Магазин М21 "Пчелка маркет" | E97: г.Ирпень, ул. Тургеневская, 50б | H97: ПП "Обухівміськвторресурси" | K97: Вывоз ТБО | P97: =Q715 -> 15 | Q97: =S715 -> 3300 | S97: =Q97+Q98+Q100+Q101+R99 -> 103892.52 | T97: 163000 | U97: 99 кВт/ч
H98: ОСББ "Лемонграсс" | K98: Экспл. расходы | O98: =Q98/P98 -> 7.5300091 | P98: 658.8 | Q98: 4960.77
H99: ТОВ "Київська Обласна ЕК" | K99: Активная ЭЭ | O99: =Q99/P99 -> 4.3826403 | P99: 18517 | Q99: 81153.35 | R99: 92324.21
H100: ПрАТ "Київобленерго" | K100: Реактивная ЭЭ | P100: 1 | Q100: 0
H101: КП "Ирпеньводоканал" | K101: ХВ | O101: =Q101/P101 -> 32.112 | P101: =J665 -> 103 | Q101: =L665 -> 3307.536
C102: Магазин М22 "Пчелка маркет" | E102: г.Киев, ул. Ветряные горы, 21/7 | H102: ПП "Обухівміськвторресурси" | K102: Вывоз ТБО | P102: =Q714 -> 4 | Q102: =S714 -> 880 | S102: =SUM(Q102:Q105) -> 51863.132 | T102: 53000 | U102: Не меньше 15 кВт/ч(в договоре до 45)
...

Sheet ОПЛАТИ 2023
A1: НАЗВАНИЕ ОБЪЕКТА | B1: АДРЕС ОБЪЕКТА | C1: ЮРИДИЧЕСКОЕ (ФИЗИЧЕСКОЕ) ЛИЦО | D1: НАИМЕНОВАНИЕ | E1: Столбец1 | F1: Тариф | G1: Показатели | H1: Сумма | I1: Авансы | J1: грудень 2022 | K1: Тариф | L1: Показатели | M1: Сумма | N1: Авансы | O1: січень 2023 | P1: Тариф | Q1: Показатели | R1: Сумма | S1: Авансы | T1: лютий 2023 | U1: Тариф | V1: Показатели | W1: Сумма | X1: Авансы | Y1: березень 2023 | Z1: Тариф | AA1: Показатели | AB1: Сумма | AC1: Авансы | AD1: квітень 2023 | AE1: Тариф | AF1: Показатели | AG1: Сумма | AH1: Авансы | AI1: травень 2023 | AJ1: Тариф | AK1: Показатели | AL1: Сумма | AM1: Авансы | AN1: червень 2023 | AO1: Тариф | AP1: Показатели | AQ1: Сумма | AR1: Авансы | AS1: Липень 2023 | AT1: Тариф | AU1: Показатели | AV1: Сумма | AW1: Авансы | AX1: Серпень 2023 | AY1: Тариф | AZ1: Показатели | BA1: Сумма | BB1: Авансы | BC1: Вересень 2023 | BD1: Тариф | BE1: Показатели | BF1: Сумма | BG1: Авансы | BH1: Жовтень 2023 | BI1: Тариф | BJ1: Показатели | BK1: Сумма | BL1: Авансы | BM1: Листопад 2023 | BN1: Тариф | BO1: Показатели | BP1: Сумма | BQ1: Авансы | BR1: Грудень 2023 | BS1: Тариф | BT1: Показатели | BU1: Сумма | BV1: Авансы | BW1: Січень 2024 | BX1: Тариф | BY1: Показатели | BZ1: Сумма | CA1: Авансы | CB1: Лютий 2024 | CC1: Тариф | CD1: Показатели | CE1: Сумма | CF1: Авансы | CG1: Березень 2024 | CH1: Тариф | CI1: Показатели | CJ1: Сумма | CK1: Авансы | CL1: Квітень 2024 | CM1: Тариф | CN1: Показатели | CO1: Сумма | CP1: Авансы | CQ1: Травень 2024 | CR1: Тариф | CS1: Показатели | CT1: Сумма | CU1: Авансы | CV1: червень 2024 | CW1: Тариф | CX1: Показатели | CY1: Сумма | CZ1: Авансы | DA1: Липень 2024
A3: М1/1 | B3: г.Житомир, пр. Мира, 15 | C3: ТОВ ГРІН БІН Україна | D3: Вывоз ТБО | W3: 2 913,33 | Y3: =SUM(W3:W7)*1.1 -> 266598.77 | Z3: 330000 | AB3: 100 | AD3: =SUM(AB3:AB7)*1.1 -> 254435.93 | AG3: =3277.5+600 -> 3877.5 | AI3: =AI4*1.1 -> 304938.28 | AL3: 100 | AN3: =AN4*1.2 -> 244056.49 | AQ3: 100 | AS3: =SUM(AQ3:AQ7)*1.3 -> 417523.31 | AV3: 100 | AX3: =SUM(AV3:AV7)*1 -> 339604.38 | BA3: 100 | BC3: =SUM(BA3:BA7)*1.11 -> 341852.35 | BF3: 100 | BH3: =SUM(BF3:BF7)*1.1 -> 326765.93 | BK3: 100 | BM3: =SUM(BK3:BK7)*1.1 -> 373177.56 | BP3: 100 | BR3: =SUM(BP3:BP7)*1.1 -> 407182.36 | BU3: 100 | BW3: =SUM(BU3:BU7)*1.1 -> 385830.64 | BZ3: 100 | CB3: =SUM(BZ3:BZ7)*1.1 -> 266185.5 | CE3: 100 | CG3: =SUM(CE3:CE7)*1.1 -> 266185.5 | CJ3: 100 | CL3: =SUM(CJ3:CJ7)*1.1 -> 266185.5 | CO3: 100 | CQ3: =SUM(CO3:CO7)*1.1 -> 266185.5 | CT3: 100 | CV3: =SUM(CT3:CT7)*1.1 -> 266185.5 | CY3: 100 | DA3: =SUM(CY3:CY7)*1.1 -> 266185.5
D4: Экспл. расходы | Y4: =SUM(W3:W7)*1 -> 242362.52 | AD4: =SUM(AB3:AB7)*1 -> 231305.39 | AI4: =SUM(AG6:AG7)+AH5+AG3*1 -> 277216.62 | AN4: =SUM(AL6:AL7)+AM5+AL3*1 -> 203380.41 | AS4: =SUM(AQ3:AQ7)*1 -> 321171.78 | AX4: =SUM(AV3:AV7)*1 -> 339604.38 | BC4: =SUM(BA7+BA6+BA3+BB5) -> 334718.35 | BH4: =SUM(BF3:BF7)*1 -> 297059.94 | BM4: =SUM(BK3:BK7)*1 -> 339252.33 | BR4: =SUM(BP3:BP7)*1 -> 370165.78 | BW4: =SUM(BU7+BU6+BV5+BU3)*1 -> 401619.69 | CB4: =SUM(BZ3:BZ7)*1 -> 241986.82 | CG4: =SUM(CE3:CE7)*1 -> 241986.82 | CL4: =SUM(CJ3:CJ7)*1 -> 241986.82 | CQ4: =SUM(CO3:CO7)*1 -> 241986.82 | CV4: =SUM(CT3:CT7)*1 -> 241986.82 | DA4: =SUM(CY3:CY7)*1 -> 241986.82
B5: 42095943 | C5: ООО «Житомирская областная энергетическая компания» | D5: Активная ЭЭ | F5: =H5/G5 -> 6.2021216 | G5: 38462 | H5: 238546 | I5: 270000 | K5: =M5/L5 -> 6.444444 | L5: 49797 | M5: 320913.98 | N5: 270000 | P5: =R5/Q5 -> 6.0761997 | Q5: 40623 | R5: 246833.46 | S5: 325000 | U5: =W5/V5 -> 5.1846598 | V5: 46075 | W5: 238883.2 | X5: 300000 | Z5: =AB5/AA5 -> 5.8564076 | AA5: 38871 | AB5: 227644.42 | AC5: 250000 | AE5: =AG5/AF5 -> 5.8430275 | AF5: 41718 | AG5: 243759.42 | AH5: 270000 | AJ5: =AL5/AK5 -> 5.9171158 | AK5: 41062 | AL5: 242968.61 | AM5: 200000 | AO5: =AQ5/AP5 -> 6.6963836 | AP5: 47425 | AQ5: 317575.99 | AR5: 270000 | AT5: =AV5/AU5 -> 7.303896 | AU5: 45886 | AV5: 335146.57 | AW5: =130588.31+399432.6 -> 530020.91 | AY5: =BA5/AZ5 -> 7.035096 | AZ5: 43220 | BA5: 304056.85 | BB5: 330800.11 | BD5: =BF5/BE5 -> 7.1411038 | BE5: 41329 | BF5: 295134.68 | BG5: 270000 | BI5: =BK5/BJ5 -> 7.4900641 | BJ5: 44771 | BK5: 335337.66 | BL5: 270000 | BN5: =BP5/BO5 -> 7.1331721 | BO5: 51550 | BP5: 367715.02 | BQ5: 300000 | BS5: =BU5/BT5 -> 7.067688 | BT5: 48971 | BU5: 346111.75 | BV5: 396976.31 | BX5: =BZ5/BY5 -> 6.2021216 | BY5: 38462 | BZ5: 238546 | CA5: 248322.31 | CC5: =CE5/CD5 -> 6.2021216 | CD5: 38462 | CE5: 238546 | CH5: =CJ5/CI5 -> 6.2021216 | CI5: 38462 | CJ5: 238546 | CM5: =CO5/CN5 -> 6.2021216 | CN5: 38462 | CO5: 238546 | CR5: =CT5/CS5 -> 6.2021216 | CS5: 38462 | CT5: 238546 | CW5: =CY5/CX5 -> 6.2021216 | CX5: 38462 | CY5: 238546
B6: 22048622 | C6: ООО «Житомиробленерго», АТ "Житомиробленерго" Житомирський РЕМ | D6: Реактивная ЭЭ | G6: 1 | H6: 990.06 | L6: 1 | M6: 1198.26 | Q6: 1 | R6: 1065.68 | V6: 1 | W6: 1278.7 | AA6: 1 | AB6: 1135.13 | AF6: 1 | AG6: 1251.11 | AK6: 1 | AL6: 1342.54 | AP6: 1 | AQ6: 1595.46 | AU6: 1 | AV6: 1894.44 | AZ6: 1 | BA6: 2030.52 | BE6: 1 | BF6: 1 545,68 | BJ6: 1 | BK6: 1 687,28 | BO6: 1 | BP6: 1 830,90 | BT6: 1 | BU6: 1742.18 | BY6: 1 | BZ6: 990.06 | CD6: 1 | CE6: 990.06 | CI6: 1 | CJ6: 990.06 | CN6: 1 | CO6: 990.06 | CS6: 1 | CT6: 990.06 | CX6: 1 | CY6: 990.06
B7: 03344065 | C7: КП "Житомирводоканал" | D7: ХВ | F7: 37.536 | G7: =Таблица3[[#This Row],[Сумма]]/Таблица3[[#This Row],[Тариф]] -> 59.627025 | H7: 2238.16 | K7: =M7/L7 -> 37.928167 | L7: 60 | M7: 2275.69 | P7: =R7/Q7 -> 37.928167 | Q7: 60 | R7: 2275.69 | U7: =W7/V7 -> 37.941724 | V7: 58 | W7: 2200.62 | Z7: =AB7/AA7 -> 37.90375 | AA7: 64 | AB7: 2425.84 | AE7: =AG7/AF7 -> 37.963818 | AF7: 55 | AG7: 2088.01 | AJ7: =AL7/AK7 -> 37.997451 | AK7: 51 | AL7: 1937.87 | AO7: =AQ7/AP7 -> 38.0066 | AP7: 50 | AQ7: 1900.33 | AT7: =AV7/AU7 -> 37.898 | AU7: 65 | AV7: 2463.37 | AY7: =BA7/AZ7 -> 38.036596 | AZ7: 47 | BA7: 1787.72 | BD7: =BF7/BE7 -> 38.02625 | BE7: 48 | BF7: =1825.26 -> 1825.26 | BG7: 192.61 | BI7: =BK7/BJ7 -> 37.76901 | BJ7: 101 | BK7: 3814.67 | BN7: =BP7/BO7 -> 37.915484 | BO7: 62 | BP7: 2350.76 | BS7: =BU7/BT7 -> 37.854054 | BT7: 74 | BU7: 2801.2 | BX7: =BZ7/BY7 -> 37.915484 | BY7: 62 | BZ7: 2350.76 | CC7: =CE7/CD7 -> 37.915484 | CD7: 62 | CE7: 2350.76 | CH7: =CJ7/CI7 -> 37.915484 | CI7: 62 | CJ7: 2350.76 | CM7: =CO7/CN7 -> 37.915484 | CN7: 62 | CO7: 2350.76 | CR7: =CT7/CS7 -> 37.915484 | CS7: 62 | CT7: 2350.76 | CW7: =CY7/CX7 -> 37.915484 | CX7: 62 | CY7: 2350.76
A8: М2 | B8: г.Киев, ул.Владимирская, 73/77 | C8: ТОВ "Еко-Грінко" | D8: Вывоз ТБО | W8: 1990 | Y8: =SUM(W8:W12)*1.1 -> 64870.718 | AB8: 1548 | AD8: =SUM(AB8:AB12)*1.1 -> 49751.473 | AG8: 1920 | AI8: =AI9*1.1 -> 64838.783 | AL8: 1990 | AN8: =AN9*1.2 -> 82628.328 | AQ8: 1769 | AS8: =SUM(AQ8:AQ12)*1.2 -> 101644.94 | AX8: =SUM(AV8:AV12)*1.1 -> 106741.39 | BC8: =SUM(BA8:BA12)*1.22 -> 106425.64 | BH8: =SUM(BF8:BF12)*1.1 -> 68123.642 | BM8: =SUM(BK8:BK12)*1.1 -> 104238.5 | BR8: =SUM(BP8:BP12)*1.1 -> 74189.056 | BW8: =SUM(BU8:BU12)*1.1 -> 23640.773 | CB8: =SUM(BZ8:BZ12)*1.1 -> 41354.412 | CG8: =SUM(CE8:CE12)*1.1 -> 41354.412 | CL8: =SUM(CJ8:CJ12)*1.1 -> 41354.412 | CQ8: =SUM(CO8:CO12)*1.1 -> 41354.412 | CV8: =SUM(CT8:CT12)*1.1 -> 41354.412 | DA8: =SUM(CY8:CY12)*1.1 -> 41354.412
B9: 35791356 | C9: ІП "Альфа Консалтінг" | D9: Экспл. расходы | G9: 1 | H9: =1.2*2899.56 -> 3479.472 | L9: 1 | M9: =1.2*2899.56 -> 3479.472 | Q9: 1 | R9: =1.2*2899.56 -> 3479.472 | V9: 1 | W9: =1.2*2899.56 -> 3479.472 | Y9: =SUM(W8:W12)*1 -> 58973.38 | AA9: 1 | AB9: =1.2*2899.56 -> 3479.472 | AD9: =SUM(AB8:AB12)*1 -> 45228.612 | AF9: 1 | AG9: =1.2*2899.56 -> 3479.472 | AI9: =SUM(AG8:AG12)*1 -> 58944.348 | AK9: 1 | AL9: =1.2*2899.56 -> 3479.472 | AN9: =SUM(AL8:AL12)*1 -> 68856.94 | AP9: 1 | AQ9: =1.2*2899.56 -> 3479.472 | AS9: =SUM(AQ8:AQ12)*1 -> 84704.12 | AU9: 1 | AV9: =1.2*2899.56 -> 3479.472 | AX9: =SUM(AV8:AV12)*1 -> 97037.628 | AZ9: 1 | BA9: =1.2*2899.56 -> 3479.472 | BC9: =SUM(BA8:BA12)*1 -> 87234.132 | BE9: 1 | BF9: =1.2*2899.56 -> 3479.472 | BH9: =SUM(BF8:BF12)*1 -> 61930.584 | BJ9: 1 | BK9: =1.2*2899.56 -> 3479.472 | BM9: =SUM(BK8:BK12)*1 -> 94762.274 | BO9: 1 | BP9: =1.2*2899.56 -> 3479.472 | BR9: =SUM(BP8:BP12)*1 -> 67444.596 | BT9: 1 | BU9: =1.2*2899.56 -> 3479.472 | BW9: =SUM(BU8:BU12)*1 -> 21491.612 | BY9: 1 | BZ9: =1.2*2899.56 -> 3479.472 | CB9: =SUM(BZ8:BZ12)*1 -> 37594.92 | CD9: 1 | CE9: =1.2*2899.56 -> 3479.472 | CG9: =SUM(CE8:CE12)*1 -> 37594.92 | CI9: 1 | CJ9: =1.2*2899.56 -> 3479.472 | CL9: =SUM(CJ8:CJ12)*1 -> 37594.92 | CN9: 1 | CO9: =1.2*2899.56 -> 3479.472 | CQ9: =SUM(CO8:CO12)*1 -> 37594.92 | CS9: 1 | CT9: =1.2*2899.56 -> 3479.472 | CV9: =SUM(CT8:CT12)*1 -> 37594.92 | CX9: 1 | CY9: =1.2*2899.56 -> 3479.472 | DA9: =SUM(CY8:CY12)*1 -> 37594.92
A10: ЯСНО "КИЇВСЬКІ ЕНЕРГЕТИЧНІ ПОСЛУГИ" | D10: Активная ЭЭ | F10: =H10/G10 -> 5.2317113 | G10: 6442 | H10: =1.2*28085.57 -> 33702.684 | K10: =M10/L10 -> 5.2938113 | L10: 6837 | M10: =1.2*30161.49 -> 36193.788 | P10: =R10/Q10 -> 5.331312 | Q10: 6442 | R10: =1.2*28620.26 -> 34344.312 | U10: =W10/V10 -> 5.218872 | V10: 10149 | W10: =1.2*44138.61 -> 52966.332 | Z10: =AB10/AA10 -> 5.0483036 | AA10: 7840 | AB10: =1.2*32982.25 -> 39578.7 | AE10: =AG10/AF10 -> 4.8623883 | AF10: 10848 | AG10: =1.2*43955.99 -> 52747.188 | AJ10: =AL10/AK10 -> 5.2394158 | AK10: 11942 | AL10: =1.2*52140.92 -> 62569.104 | AO10: =AQ10/AP10 -> 5.6894517 | AP10: 13796 | AQ10: =1.2*65409.73 -> 78491.676 | AT10: =AV10/AU10 -> 6.5030284 | AU10: 14191 | AV10: =1.2*76903.73 -> 92284.476 | AY10: =BA10/AZ10 -> 6.4884477 | AZ10: 12732 | BA10: =1.2*68842.43 -> 82610.916 | BD10: =BF10/BE10 -> 6.7719605 | BE10: 8508 | BF10: =1.2*48013.2 -> 57615.84 | BI10: =BK10/BJ10 -> 6.9206276 | BJ10: 13066 | BK10: =1.2*75354.1 -> 90424.92 | BN10: =BP10/BO10 -> 7.0693802 | BO10: 8964 | BP10: =1.2*52808.27 -> 63369.924 | BS10: =BU10/BT10 -> 6.1674965 | BT10: 2868 | BU10: 17688.38 | BX10: =BZ10/BY10 -> 5.2317113 | BY10: 6442 | BZ10: =1.2*28085.57 -> 33702.684 | CC10: =CE10/CD10 -> 5.2317113 | CD10: 6442 | CE10: =1.2*28085.57 -> 33702.684 | CH10: =CJ10/CI10 -> 5.2317113 | CI10: 6442 | CJ10: =1.2*28085.57 -> 33702.684 | CM10: =CO10/CN10 -> 5.2317113 | CN10: 6442 | CO10: =1.2*28085.57 -> 33702.684 | CR10: =CT10/CS10 -> 5.2317113 | CS10: 6442 | CT10: =1.2*28085.57 -> 33702.684 | CW10: =CY10/CX10 -> 5.2317113 | CX10: 6442 | CY10: =1.2*28085.57 -> 33702.684
D11: Реактивная ЭЭ | G11: 1 | H11: =1.2*235.35 -> 282.42 | L11: 1 | M11: =1.2*282.36 -> 338.832 | Q11: 1 | R11: =1.2*334.73 -> 401.676 | V11: 1 | W11: =1.2*344.42 -> 413.304 | AA11: 1 | AB11: =1.2*407.54 -> 489.048 | AF11: 1 | AG11: =1.2*556.12 -> 667.344 | AK11: 1 | AL11: =1.2*570.81 -> 684.972 | AP11: 1 | AQ11: =1.2*735.2 -> 882.24 | AU11: 1 | AV11: =1.2*909.73 -> 1091.676 | AZ11: 1 | BA11: =1.2*920.46 -> 1104.552 | BE11: 1 | BF11: =1.2*582.38 -> 698.856 | BJ11: 1 | BK11: 818.69 | BO11: 1 | BP11: =1.2*384.84 -> 461.808 | BT11: 1 | BU11: =1.2*158.64 -> 190.368 | BY11: 1 | BZ11: =1.2*235.35 -> 282.42 | CD11: 1 | CE11: =1.2*235.35 -> 282.42 | CI11: 1 | CJ11: =1.2*235.35 -> 282.42 | CN11: 1 | CO11: =1.2*235.35 -> 282.42 | CS11: 1 | CT11: =1.2*235.35 -> 282.42 | CX11: 1 | CY11: =1.2*235.35 -> 282.42
D12: ХВ | F12: =H12/G12 -> 33.767876 | G12: 3.86 | H12: =1.2*108.62 -> 130.344 | K12: =M12/L12 -> 28.797927 | L12: 3.86 | M12: 111.16 | P12: =R12/Q12 -> 34.557513 | Q12: 3.86 | R12: =1.2*111.16 -> 133.392 | U12: =W12/V12 -> 32.194819 | V12: 3.86 | W12: =1.2*103.56 -> 124.272 | Z12: =AB12/AA12 -> 34.557513 | AA12: 3.86 | AB12: =1.2*111.16 -> 133.392 | AE12: =AG12/AF12 -> 34.665957 | AF12: 3.76 | AG12: =1.2*108.62 -> 130.344 | AJ12: =AL12/AK12 -> 43.029677 | AK12: 3.1 | AL12: =1.2*111.16 -> 133.392 | AO12: =AQ12/AP12 -> 21.174093 | AP12: 3.86 | AQ12: =1.2*68.11 -> 81.732 | AT12: =AV12/AU12 -> 47.151295 | AU12: 3.86 | AV12: =1.2*151.67 -> 182.004 | AY12: =BA12/AZ12 -> 10.153368 | AZ12: 3.86 | BA12: =1.2*32.66 -> 39.192 | BD12: =BF12/BE12 -> 35.340933 | BE12: 3.86 | BF12: =1.2*113.68 -> 136.416 | BI12: =BK12/BJ12 -> 39.192 | BJ12: 1 | BK12: =1.2*32.66 -> 39.192 | BN12: =BP12/BO12 -> 133.392 | BO12: 1 | BP12: =1.2*111.16 -> 133.392 | BS12: =BU12/BT12 -> 133.392 | BT12: 1 | BU12: =1.2*111.16 -> 133.392 | BX12: =BZ12/BY12 -> 2.1023226 | BY12: 62 | BZ12: =1.2*108.62 -> 130.344 | CC12: =CE12/CD12 -> 2.1023226 | CD12: 62 | CE12: =1.2*108.62 -> 130.344 | CH12: =CJ12/CI12 -> 2.1023226 | CI12: 62 | CJ12: =1.2*108.62 -> 130.344 | CM12: =CO12/CN12 -> 2.1023226 | CN12: 62 | CO12: =1.2*108.62 -> 130.344 | CR12: =CT12/CS12 -> 2.1023226 | CS12: 62 | CT12: =1.2*108.62 -> 130.344 | CW12: =CY12/CX12 -> 2.1023226 | CX12: 62 | CY12: =1.2*108.62 -> 130.344
A13: М3 | B13: г.Киев, ул.Р.Окипной,3 | C13: ТОВ "Еко-Грінко" | D13: Вывоз ТБО | W13: 1769 | Y13: =SUM(W13:W16)*1.1 -> 69137.352 | AB13: 1769 | AD13: =SUM(AB13:AB16)*1.1 -> 64896.55 | AG13: 2211 | AI13: =AI14*1.1 -> 119705.9 | AL13: 1327 | AN13: =AN14*1.2 -> 155518.7 | AQ13: 2211 | AS13: =SUM(AQ13:AQ16)*1.2 -> 142971.74 | AX13: =SUM(AV13:AV16)*1.1 -> 145006.85 | BC13: =SUM(BA14:BA16)*1.2 -> 139319.87 | BH13: =SUM(BF13:BF16)*1.1 -> 109403.84 | BM13: =SUM(BK13:BK16)*1.1 -> 104134.14 | BR13: =SUM(BP13:BP16)*1.1 -> 104482.36 | BW13: =SUM(BU13:BU16)*1.1 -> 104340.07 | CB13: =SUM(BZ13:BZ16)*1.1 -> 24808.887 | CG13: =SUM(CE13:CE16)*1.1 -> 24808.887 | CL13: =SUM(CJ13:CJ16)*1.1 -> 24808.887 | CQ13: =SUM(CO13:CO16)*1.1 -> 24808.887 | CV13: =SUM(CT13:CT16)*1.1 -> 24808.887 | DA13: =SUM(CY13:CY16)*1.1 -> 24808.887
B14: 41916045 | C14: ТОВ "КИЇВСЬКI ЕНЕРГЕТИЧНI ПОСЛУГИ" | D14: Активная ЭЭ | F14: =H14/G14 -> 5.3077205 | G14: 3964 | H14: 21039.804 | I14: 14610.975 | K14: =M14/L14 -> 5.3685484 | L14: 8176 | M14: 43893.252 | N14: 43893.252 | P14: =R14/Q14 -> 4.9663922 | Q14: 8292 | R14: =34317.77*1.2 -> 41181.324 | S14: 41181.324 | U14: =W14/V14 -> 5.2077241 | V14: 11220 | W14: 58430.664 | X14: 58430.664 | Y14: =SUM(W13:W16)*1 -> 62852.138 | Z14: =AB14/AA14 -> 4.6829517 | AA14: 11676 | AB14: 54678.144 | AC14: 54678.144 | AD14: =SUM(AB13:AB16)*1 -> 58996.864 | AE14: =AG14/AF14 -> 4.819944 | AF14: 15136 | AG14: 72954.672 | AH14: =28777.97+74729.76 -> 103507.73 | AI14: =SUM(AG15:AG16)+AH14+AG13*1 -> 108823.55 | AJ14: =AL14/AK14 -> 4.9792203 | AK14: 17160 | AL14: 85443.42 | AM14: =37070.31+89591.256 -> 126661.57 | AN14: =SUM(AL15:AL16)+AM14+AL13*1 -> 129598.92 | AO14: =AQ14/AP14 -> 5.9466958 | AP14: 19092 | AQ14: 113534.32 | AR14: 128035 | AS14: =SUM(AQ13:AQ16)*1 -> 119143.12 | AT14: =AV14/AU14 -> 6.610763 | AU14: 19372 | AV14: 128063.7 | AW14: 14610.975 | AX14: =SUM(AV13:AV16)*1 -> 131824.41 | AY14: =BA14/AZ14 -> 6.3494518 | AZ14: 17688 | BA14: 112309.1 | BB14: 93590.92 | BC14: =(BA16+BA15+BA14)*1 -> 116099.89 | BD14: =BF14/BE14 -> 6.2594404 | BE14: 15596 | BF14: 97622.232 | BG14: 93590.92 | BH14: =SUM(BF13:BF16)*1 -> 99458.032 | BI14: =BK14/BJ14 -> 6.7596598 | BJ14: 13676 | BK14: 92445.108 | BL14: 77284.27 | BM14: =SUM(BK13:BK16)*1 -> 94667.398 | BN14: =BP14/BO14 -> 6.4951202 | BO14: 14180 | BP14: 92100.804 | BQ14: 14610.975 | BR14: =SUM(BP13:BP16)*1 -> 94983.964 | BS14: =BU14/BT14 -> 6.131988 | BT14: 15024 | BU14: 92126.988 | BV14: 93423.62 | BW14: =SUM(BU16+BU15+BV14)*1 -> 96151.24 | BX14: =BZ14/BY14 -> 5.3077205 | BY14: 3964 | BZ14: 21039.804 | CA14: 125 064,66 | CB14: =SUM(BZ13:BZ16)*1 -> 22553.534 | CC14: =CE14/CD14 -> 5.3077205 | CD14: 3964 | CE14: 21039.804 | CF14: 14610.975 | CG14: =SUM(CE13:CE16)*1 -> 22553.534 | CH14: =CJ14/CI14 -> 5.3077205 | CI14: 3964 | CJ14: 21039.804 | CK14: 14610.975 | CL14: =SUM(CJ13:CJ16)*1 -> 22553.534 | CM14: =CO14/CN14 -> 5.3077205 | CN14: 3964 | CO14: 21039.804 | CP14: 14610.975 | CQ14: =SUM(CO13:CO16)*1 -> 22553.534 | CR14: =CT14/CS14 -> 5.3077205 | CS14: 3964 | CT14: 21039.804 | CU14: 14610.975 | CV14: =SUM(CT13:CT16)*1 -> 22553.534 | CW14: =CY14/CX14 -> 5.3077205 | CX14: 3964 | CY14: 21039.804 | CZ14: 14610.975 | DA14: =SUM(CY13:CY16)*1 -> 22553.534
B15: 41946011 | C15: «ДТЕК КИЇВСЬКІ ЕЛЕКТРОМЕРЕЖІ» | D15: Реактивная ЭЭ | G15: 0 | H15: 0 | L15: 0 | M15: 651.98 | Q15: 0 | R15: 650.05 | W15: 945.504 | AA15: 0 | AB15: 1068.2 | AF15: 0 | AG15: 1462.27 | AK15: 0 | AL15: 1 525,16 | AQ15: 1761.86 | AU15: 0 | AV15: 2053.74 | AZ15: 0 | BA15: 1954.99 | BE15: 0 | BF15: 1 476,04 | BJ15: 0 | BK15: 1 115,62 | BO15: 0 | BP15: 950.74 | BT15: 1 | BU15: 988.44 | BY15: 0 | BZ15: 0 | CD15: 0 | CE15: 0 | CI15: 0 | CJ15: 0 | CN15: 0 | CO15: 0 | CS15: 0 | CT15: 0 | CX15: 0 | CY15: 0
B16: 2978013090 | C16: ФОП Воробьев А.Н. | D16: ХВ | F16: =H16/G16 -> 32.207021 | G16: 47 | H16: 1513.73 | K16: =M16/L16 -> 32.207105 | L16: 38 | M16: 1223.87 | P16: =R16/Q16 -> 32.207347 | Q16: 49 | R16: 1578.16 | U16: =W16/V16 -> 32.206981 | V16: 53 | W16: 1706.97 | Z16: =AB16/AA16 -> 32.206957 | AA16: 46 | AB16: 1481.52 | AE16: =AG16/AF16 -> 32.206863 | AF16: 51 | AG16: 1642.55 | AJ16: =AL16/AK16 -> 32.207 | AK16: 50 | AL16: 1610.35 | AO16: =AQ16/AP16 -> 34.082083 | AP16: 48 | AQ16: 1635.94 | AT16: =AV16/AU16 -> 32.206981 | AU16: 53 | AV16: 1706.97 | AY16: =BA16/AZ16 -> 32.207018 | AZ16: 57 | BA16: 1835.8 | BD16: =BF16/BE16 -> 32.207018 | BE16: 57 | BF16: 1835.8 | BI16: =BK16/BJ16 -> 32.207101 | BJ16: 69 | BK16: 2222.29 | BN16: =BP16/BO16 -> 32.207 | BO16: 60 | BP16: 1932.42 | BS16: =BU16/BT16 -> 32.207037 | BT16: 54 | BU16: 1739.18 | BX16: =BZ16/BY16 -> 32.207021 | BY16: 47 | BZ16: 1513.73 | CC16: =CE16/CD16 -> 32.207021 | CD16: 47 | CE16: 1513.73 | CH16: =CJ16/CI16 -> 32.207021 | CI16: 47 | CJ16: 1513.73 | CM16: =CO16/CN16 -> 32.207021 | CN16: 47 | CO16: 1513.73 | CR16: =CT16/CS16 -> 32.207021 | CS16: 47 | CT16: 1513.73 | CW16: =CY16/CX16 -> 32.207021 | CX16: 47 | CY16: 1513.73
A17: М4/1 | B17: пгт.Коцюбинское, ул. Пономарева, 28а | C17: ПП "Обухівміськвторресурси" | D17: Вывоз ТБО | W17: 2530 | Y17: =SUM(W17:W20)*1.2 -> 83719.562 | AB17: 2024 | AD17: =SUM(AB17:AB20)*1.2 -> 97664.035 | AG17: 2024 | AI17: =AI18*1.1 -> 98364.73 | AL17: 2530 | AN17: =AN18*1.2 -> 120776.1 | AS17: =SUM(AQ17:AQ20)*1.2 -> 143589.86 | AX17: =SUM(AV17:AV20)*1.2 -> 168735.83 | BC17: =SUM(BA17:BA20)*1.2 -> 132970.68 | BH17: =SUM(BF17:BF20)*1.2 -> 145941.81 | BM17: =SUM(BK17:BK20)*1.1 -> 150848.56 | BR17: =SUM(BP17:BP20)*1.2 -> 139827.85 | BW17: =SUM(BU17:BU20)*1.2 -> 132846.63 | CB17: =SUM(BZ17:BZ20)*1.2 -> 38836.342 | CG17: =SUM(CE17:CE20)*1.2 -> 38836.342 | CL17: =SUM(CJ17:CJ20)*1.2 -> 38836.342 | CQ17: =SUM(CO17:CO20)*1.2 -> 38836.342 | CV17: =SUM(CT17:CT20)*1.2 -> 38836.342 | DA17: =SUM(CY17:CY20)*1.2 -> 38836.342
A18: КОЕК універсал | B18: 19420118 | C18: НВПФ "Казі-2" | D18: Активная ЭЭ | F18: =H18/G18 -> 5.799529 | G18: 5291 | H18: =1.2*25571.09 -> 30685.308 | K18: =M18/L18 -> 5.7929482 | L18: 7766 | M18: =1.2*37490.03 -> 44988.036 | P18: =R18/Q18 -> 5.7364085 | Q18: 8020 | R18: =1.2*38338.33 -> 46005.996 | U18: =W18/V18 -> 5.9058732 | V18: 10679 | W18: =1.2*52557.35 -> 63068.82 | Y18: =SUM(W17:W20)*1 -> 69766.302 | Z18: =AB18/AA18 -> 5.6497683 | AA18: 13249 | AB18: =1.2*62378.15 -> 74853.78 | AD18: =SUM(AB17:AB20)*1 -> 81386.696 | AE18: =AG18/AF18 -> 5.4696957 | AF18: 15144 | AG18: =1.2*69027.56 -> 82833.072 | AI18: =SUM(AG17:AG20)*1 -> 89422.482 | AJ18: =AL18/AK18 -> 5.8678682 | AK18: 15931 | AL18: =1.2*77900.84 -> 93481.008 | AN18: =SUM(AL17:AL20)*1 -> 100646.75 | AO18: =AQ18/AP18 -> 6.762972 | AP18: 16981 | AQ18: =1.2*95701.69 -> 114842.03 | AS18: =SUM(AQ17:AQ20)*1 -> 119658.22 | AT18: =AV18/AU18 -> 7.3032483 | AU18: 18400 | AV18: =1.2*111983.14 -> 134379.77 | AX18: =SUM(AV17:AV20)*1 -> 140613.19 | AY18: =BA18/AZ18 -> 6.1660898 | AZ18: 17081 | BA18: 105322.98 | BC18: =SUM(BA17:BA20)*1 -> 110808.9 | BD18: =BF18/BE18 -> 7.5466201 | BE18: 15358 | BF18: =1.2*96584.16 -> 115900.99 | BH18: =SUM(BF17:BF20)*1 -> 121618.18 | BI18: =BK18/BJ18 -> 7.6667398 | BJ18: 17017 | BK18: =1.2*108720.76 -> 130464.91 | BM18: =SUM(BK17:BK20)*1 -> 137135.05 | BN18: =BP18/BO18 -> 7.54662 | BO18: 14530 | BP18: =1.2*91376.99 -> 109652.39 | BR18: =SUM(BP17:BP20)*1 -> 116523.21 | BS18: =BU18/BT18 -> 7.2362638 | BT18: 14193 | BU18: =1.2*85586.91 -> 102704.29 | BW18: =SUM(BU17:BU20)*1 -> 110705.52 | BX18: =BZ18/BY18 -> 2.162003 | BY18: 14193 | BZ18: =1.2*25571.09 -> 30685.308 | CB18: =SUM(BZ17:BZ20)*1 -> 32363.618 | CC18: =CE18/CD18 -> 5.799529 | CD18: 5291 | CE18: =1.2*25571.09 -> 30685.308 | CG18: =SUM(CE17:CE20)*1 -> 32363.618 | CH18: =CJ18/CI18 -> 5.799529 | CI18: 5291 | CJ18: =1.2*25571.09 -> 30685.308 | CL18: =SUM(CJ17:CJ20)*1 -> 32363.618 | CM18: =CO18/CN18 -> 5.799529 | CN18: 5291 | CO18: =1.2*25571.09 -> 30685.308 | CQ18: =SUM(CO17:CO20)*1 -> 32363.618 | CR18: =CT18/CS18 -> 5.799529 | CS18: 5291 | CT18: =1.2*25571.09 -> 30685.308 | CV18: =SUM(CT17:CT20)*1 -> 32363.618 | CW18: =CY18/CX18 -> 5.799529 | CX18: 5291 | CY18: =1.2*25571.09 -> 30685.308 | DA18: =SUM(CY17:CY20)*1 -> 32363.618
B19: НДС | C19: НВПФ "Казі-2" | D19: Реактивная ЭЭ | G19: 1 | H19: =1.2*1286.88 -> 1544.256 | L19: 6670 | M19: =1.2*1776.61 -> 2131.932 | Q19: 7112 | R19: =1.2*2008.74 -> 2410.488 | V19: 1 | W19: =1.2*2516.66 -> 3019.992 | AA19: 1 | AB19: =1.2*2950.58 -> 3540.696 | AF19: 1 | AG19: =1.2*2967.75 -> 3561.3 | AK19: 1 | AL19: =1.2*2936.71 -> 3524.052 | AP19: 1 | AQ19: =1.2*3326.2 -> 3991.44 | AU19: 1 | AV19: =1.2*4238.22 -> 5085.864 | AZ19: 1 | BA19: 4517.72 | BE19: 1 | BF19: =1.2*3837.93 -> 4605.516 | BJ19: 1 | BK19: =1.2*4691.8 -> 5630.16 | BO19: 1 | BP19: =1.2*4829.17 -> 5795.004 | BT19: 1 | BU19: =1.2*4874.65 -> 5849.58 | BY19: 1 | BZ19: 1283.88 | CD19: 1 | CE19: 1283.88 | CI19: 1 | CJ19: 1283.88 | CN19: 1 | CO19: 1283.88 | CS19: 1 | CT19: 1283.88 | CX19: 1 | CY19: 1283.88
C20: НВПФ "Казі-2" | D20: ХВ | F20: =H20/G20 -> 35.857273 | G20: 11 | H20: 394.43 | K20: =M20/L20 -> 35.86 | L20: 24 | M20: 860.64 | P20: =R20/Q20 -> 35.860606 | Q20: 33 | R20: 1183.4 | U20: =W20/V20 -> 35.859063 | V20: 32 | W20: 1147.49 | Z20: =AB20/AA20 -> 35.86 | AA20: 27 | AB20: 968.22 | AE20: =AG20/AF20 -> 35.861071 | AF20: 28 | AG20: 1004.11 | AJ20: =AL20/AK20 -> 35.860968 | AK20: 31 | AL20: 1111.69 | AO20: =AQ20/AP20 -> 35.858696 | AP20: 23 | AQ20: 824.75 | AT20: =AV20/AU20 -> 35.86125 | AU20: 32 | AV20: 1147.56 | AY20: =BA20/AZ20 -> 35.859259 | AZ20: 27 | BA20: 968.2 | BD20: =BF20/BE20 -> 35.860323 | BE20: 31 | BF20: 1111.67 | BI20: =BK20/BJ20 -> 35.861379 | BJ20: 29 | BK20: 1039.98 | BN20: =BP20/BO20 -> 35.860667 | BO20: 30 | BP20: 1075.82 | BS20: =BU20/BT20 -> 35.860833 | BT20: 60 | BU20: 2151.65 | BX20: =BZ20/BY20 -> 35.857273 | BY20: 11 | BZ20: 394.43 | CC20: =CE20/CD20 -> 35.857273 | CD20: 11 | CE20: 394.43 | CH20: =CJ20/CI20 -> 35.857273 | CI20: 11 | CJ20: 394.43 | CM20: =CO20/CN20 -> 35.857273 | CN20: 11 | CO20: 394.43 | CR20: =CT20/CS20 -> 35.857273 | CS20: 11 | CT20: 394.43 | CW20: =CY20/CX20 -> 35.857273 | CX20: 11 | CY20: 394.43
A21: М5 | B21: г.Киев, ул. Я.Колоса,2А | C21: ТОВ "Еко-Грінко" | D21: Вывоз ТБО | W21: 1990 | Y21: =SUM(W21:W24)*1.1 -> 98311.932 | AB21: 1769 | AD21: =SUM(AB21:AB24)*1.1 -> 82767.282 | AG21: 1548 | AI21: =AI22*1.1 -> 141098.17 | AL21: 1990 | AN21: =AN22*1.2 -> 57402.214 | AQ21: 1769 | AS21: =SUM(AQ21:AQ24)*1.2 -> 242190.38 | AX21: =SUM(AV21:AV24)*1.1 -> 170273.43 | BC21: =SUM(BA21:BA24)*1.1 -> 152385.61 | BH21: =SUM(BF21:BF24)*1.1 -> 144901.7 | BM21: =SUM(BK21:BK24)*1.1 -> 135790.03 | BR21: =SUM(BP21:BP24)*1.1 -> 122838.33 | BW21: =SUM(BU21:BU24)*1.1 -> 129876.05 | CB21: =SUM(BZ21:BZ24)*1.1 -> 78943.396 | CG21: =SUM(CE21:CE24)*1.1 -> 78943.396 | CL21: =SUM(CJ21:CJ24)*1.1 -> 78943.396 | CQ21: =SUM(CO21:CO24)*1.1 -> 78943.396 | CV21: =SUM(CT21:CT24)*1.1 -> 78943.396 | DA21: =SUM(CY21:CY24)*1.1 -> 78943.396
B22: 41916045 | C22: ТОВ "КИЇВСЬКI ЕНЕРГЕТИЧНI ПОСЛУГИ" | D22: Активная ЭЭ | F22: =H22/G22 -> 5.3077196 | G22: 13395 | H22: 71096.904 | I22: 49372.85 | K22: =M22/L22 -> 5.3685478 | L22: 14950 | M22: 80259.79 | N22: 80 259,79 | P22: =R22/Q22 -> 4.9663925 | Q22: 13452 | R22: 66807.912 | S22: 66807.912 | U22: =W22/V22 -> 5.207724 | V22: 16345 | W22: 85120.248 | X22: 85120.248 | Y22: =SUM(W21:W24)*1 -> 89374.484 | Z22: =AB22/AA22 -> 4.5706785 | AA22: 15555 | AB22: 71096.904 | AC22: 72843.312 | AD22: =SUM(AB21:AB24)*1 -> 75242.984 | AE22: =AG22/AF22 -> 4.8199439 | AF22: 17766 | AG22: 85631.124 | AH22: =38338.59+87714.65 -> 126053.24 | AI22: =SUM(AG23:AG24)+AH22+AG21*1 -> 128271.06 | AJ22: =AL22/AK22 -> 4.9792194 | AK22: 8517 | AL22: 42408.012 | AM22: 44466.708 | AN22: =SUM(AL23:AL24)+AM22+AL21*1 -> 47835.178 | AO22: =AQ22/AP22 -> 5.9466962 | AP22: 33010 | AQ22: 196300.44 | AR22: 221372.05 | AS22: =SUM(AQ21:AQ24)*1 -> 201825.32 | AT22: =AV22/AU22 -> 6.6107534 | AU22: 22988 | AV22: 151968 | AW22: 49372.85 | AX22: =SUM(AV21:AV24)*1 -> 154794.03 | AY22: =BA22/AZ22 -> 6.3494522 | AZ22: 21303 | BA22: 135262.38 | BB22: 112718.65 | BC22: =SUM(BA21:BA24)*1 -> 138532.37 | BD22: =BF22/BE22 -> 6.3628441 | BE22: 20210 | BF22: 128593.08 | BG22: 112718.65 | BH22: =SUM(BF21:BF24)*1 -> 131728.82 | BI22: =BK22/BJ22 -> 6.7715879 | BJ22: 18131 | BK22: 122775.66 | BL22: 101802.85 | BM22: =SUM(BK21:BK24)*1 -> 123445.48 | BN22: =BP22/BO22 -> 6.3746277 | BO22: 17413 | BP22: 111001.39 | BQ22: 49372.85 | BR22: =SUM(BP21:BP24)*1 -> 111671.21 | BS22: =BU22/BT22 -> 6.0268797 | BT22: 19110 | BU22: 115173.67 | BV22: 112 625,82 | BW22: =SUM(BU21:BU24)*1 -> 118069.13 | BX22: =BZ22/BY22 -> 5.3077196 | BY22: 13395 | BZ22: 71096.904 | CA22: 161 248,54 | CB22: =SUM(BZ21:BZ24)*1 -> 71766.724 | CC22: =CE22/CD22 -> 5.3077196 | CD22: 13395 | CE22: 71096.904 | CF22: 49372.85 | CG22: =SUM(CE21:CE24)*1 -> 71766.724 | CH22: =CJ22/CI22 -> 5.3077196 | CI22: 13395 | CJ22: 71096.904 | CK22: 49372.85 | CL22: =SUM(CJ21:CJ24)*1 -> 71766.724 | CM22: =CO22/CN22 -> 5.3077196 | CN22: 13395 | CO22: 71096.904 | CP22: 49372.85 | CQ22: =SUM(CO21:CO24)*1 -> 71766.724 | CR22: =CT22/CS22 -> 5.3077196 | CS22: 13395 | CT22: 71096.904 | CU22: 49372.85 | CV22: =SUM(CT21:CT24)*1 -> 71766.724 | CW22: =CY22/CX22 -> 5.3077196 | CX22: 13395 | CY22: 71096.904 | CZ22: 49372.85 | DA22: =SUM(CY21:CY24)*1 -> 71766.724
B23: 41946011 | C23: «ДТЕК КИЇВСЬКІ ЕЛЕКТРОМЕРЕЖІ» | D23: Реактивная ЭЭ | H23: 1 373,92 | M23: 1352.6 | R23: 1 322,12 | W23: 1594.416 | AB23: 1707.26 | AG23: 1 819,58 | AL23: 708.65 | AQ23: 3086.06 | AV23: 2156.208 | BA23: 2600.17 | BF23: 2465.92 | BK23: 2 240,89 | BP23: 2 033,00 | BT23: 1 | BU23: 2225.64 | BZ23: 1 373,92 | CE23: 1 373,92 | CJ23: 1 373,92 | CO23: 1 373,92 | CT23: 1 373,92 | CY23: 1 373,92
C24: ФОП Ковальова Л.В. НАЛІЧНІ | D24: ХВ | F24: =H24/G24 -> 31.724138 | G24: 29 | H24: 920 | K24: =M24/L24 -> 30.446364 | L24: 22 | M24: 669.82 | P24: =R24/Q24 -> 30.446364 | Q24: 22 | R24: 669.82 | U24: =W24/V24 -> 30.446364 | V24: 22 | W24: 669.82 | Z24: =AB24/AA24 -> 30.446364 | AA24: 22 | AB24: 669.82 | AE24: =AG24/AF24 -> 30.446364 | AF24: 22 | AG24: 669.82 | AJ24: =AL24/AK24 -> 18.103243 | AK24: 37 | AL24: 669.82 | AO24: =AQ24/AP24 -> 30.446364 | AP24: 22 | AQ24: 669.82 | AT24: =AV24/AU24 -> 30.446364 | AU24: 22 | AV24: 669.82 | AY24: =BA24/AZ24 -> 30.446364 | AZ24: 22 | BA24: 669.82 | BD24: =BF24/BE24 -> 30.446364 | BE24: 22 | BF24: 669.82 | BI24: =BK24/BJ24 -> 30.446364 | BJ24: 22 | BK24: 669.82 | BN24: =BP24/BO24 -> 30.446364 | BO24: 22 | BP24: 669.82 | BS24: =BU24/BT24 -> 30.446364 | BT24: 22 | BU24: 669.82 | BX24: =BZ24/BY24 -> 30.446364 | BY24: 22 | BZ24: 669.82 | CC24: =CE24/CD24 -> 30.446364 | CD24: 22 | CE24: 669.82 | CH24: =CJ24/CI24 -> 30.446364 | CI24: 22 | CJ24: 669.82 | CM24: =CO24/CN24 -> 30.446364 | CN24: 22 | CO24: 669.82 | CR24: =CT24/CS24 -> 30.446364 | CS24: 22 | CT24: 669.82 | CW24: =CY24/CX24 -> 30.446364 | CX24: 22 | CY24: 669.82
A25: М6 | B25: г.Киев, ул. Сикорского,1А | C25: ТОВ "Еко-Грінко" | D25: Вывоз ТБО | W25: 5085 | Y25: =SUM(W25:W30)*1.1 -> 259503.07 | AB25: 5306 | AD25: =SUM(AB25:AB30)*1.1 -> 245493.75 | AG25: 5085 | AI25: =AI26*1.1 -> 373563.25 | AL25: 4643 | AN25: =AN26*1.2 -> 288508.89 | AQ25: 4422 | AS25: =SUM(AQ25:AQ30)*1.2 -> 402263.06 | AX25: =SUM(AV25:AV30)*1.1 -> 374248.29 | BC25: =SUM(BA25:BA30)*1.1 -> 348933.92 | BH25: =SUM(BF25:BF30)*1.1 -> 318419.32 | BM25: =SUM(BK25:BK30)*1.1 -> 348625.39 | BR25: =SUM(BP25:BP30)*1.1 -> 331844.84 | BW25: =SUM(BU25:BU30)*1.1 -> 365511.68 | CB25: =SUM(BZ25:BZ30)*1.1 -> 172379.6 | CG25: =SUM(CE25:CE30)*1.1 -> 172379.6 | CL25: =SUM(CJ25:CJ30)*1.1 -> 172379.6 | CQ25: =SUM(CO25:CO30)*1.1 -> 172379.6 | CV25: =SUM(CT25:CT30)*1.1 -> 172379.6 | DA25: =SUM(CY25:CY30)*1.1 -> 172379.6
B26: 32912720 | C26: ТОВ "Ковальська -Житлосервіс" | D26: Экспл. расходы | G26: 696.6 | H26: 7280.87 | L26: 696.6 | M26: 7280.87 | N26: 2940 | Q26: 696.6 | R26: 7280.87 | V26: 696.6 | W26: 7280.87 | Y26: =SUM(W25:W30)*1 -> 235911.88 | AA26: 696.6 | AB26: 7280.87 | AD26: =SUM(AB25:AB30)*1 -> 223176.14 | AF26: 696.6 | AG26: 7280.87 | AI26: =SUM(AG29:AG30)+AH28+AG27+AG26+AG25*1 -> 339602.95 | AK26: 696.6 | AL26: 7280.87 | AN26: =SUM(AL29:AL30)+AM28+AL27+AL26+AL25*1 -> 240424.08 | AP26: 696.6 | AQ26: 7280.87 | AS26: =SUM(AQ25:AQ30)*1 -> 335219.22 | AU26: 696.6 | AV26: 7 789,39 | AX26: =SUM(AV25:AV30)*1 -> 340225.72 | AZ26: 696.6 | BA26: 7 789,39 | BC26: =SUM(BA25:BA30)*1 -> 317212.66 | BE26: 696.6 | BF26: 7789.39 | BH26: =SUM(BF25:BF30)*1 -> 289472.11 | BJ26: 696.6 | BK26: 7789.39 | BM26: =SUM(BK25:BK30)*1 -> 316932.17 | BO26: 696.6 | BP26: 7789.39 | BR26: =SUM(BP25:BP30)*1 -> 301677.13 | BT26: 696.6 | BU26: 7789.39 | BW26: =SUM(BU25:BU30)*1 -> 332283.35 | BY26: 696.6 | BZ26: 7280.87 | CB26: =SUM(BZ25:BZ30)*1 -> 156708.73 | CD26: 696.6 | CE26: 7280.87 | CG26: =SUM(CE25:CE30)*1 -> 156708.73 | CI26: 696.6 | CJ26: 7280.87 | CL26: =SUM(CJ25:CJ30)*1 -> 156708.73 | CN26: 696.6 | CO26: 7280.87 | CQ26: =SUM(CO25:CO30)*1 -> 156708.73 | CS26: 696.6 | CT26: 7280.87 | CV26: =SUM(CT25:CT30)*1 -> 156708.73 | CX26: 696.6 | CY26: 7280.87 | DA26: =SUM(CY25:CY30)*1 -> 156708.73
B27: 32912720 | C27: ТОВ "Ковальська -Житлосервіс" | D27: Экспл. расходы | G27: 465.4 | H27: 4864.36 | L27: 465.4 | M27: 4864.36 | Q27: 465.4 | R27: 4864.36 | V27: 465.4 | W27: 4864.36 | AA27: 465.4 | AB27: 4864.36 | AF27: 465.4 | AG27: 4864.36 | AK27: 465.4 | AL27: 4864.36 | AP27: 465.4 | AQ27: 4864.36 | AU27: 465.4 | AV27: 5 204,10 | AZ27: 465.4 | BA27: 5 204,10 | BE27: 465.4 | BF27: 5204.1 | BJ27: 465.4 | BK27: 5204.1 | BO27: 465.4 | BP27: 5 204,10 | BT27: 465.4 | BU27: 5 204,10 | BY27: 465.4 | BZ27: 4864.36 | CD27: 465.4 | CE27: 4864.36 | CI27: 465.4 | CJ27: 4864.36 | CN27: 465.4 | CO27: 4864.36 | CS27: 465.4 | CT27: 4864.36 | CX27: 465.4 | CY27: 4864.36
B28: 41916045 | C28: ТОВ "КИЇВСЬКI ЕНЕРГЕТИЧНI ПОСЛУГИ" | D28: Активная ЭЭ | F28: =H28/G28 -> 5.3077195 | G28: 26880 | H28: 142671.5 | I28: 99077.44 | K28: =M28/L28 -> 5.3685477 | L28: 35276 | M28: =132566.62+56814.27 -> 189380.89 | N28: 189380.89 | P28: =R28/Q28 -> 4.966392 | Q28: 33553 | R28: 166637.35 | S28: 166637.35 | U28: =W28/V28 -> 5.2077239 | V28: 41331 | W28: 215240.44 | X28: 215240.44 | Z28: =AB28/AA28 -> 4.6829521 | AA28: 42840 | AB28: 200617.67 | AC28: 200617.67 | AE28: =AG28/AF28 -> 4.8199441 | AF28: 43525 | AG28: 209788.07 | AH28: =73911.77+31676.47+139680.1+75212.38 -> 320480.72 | AJ28: =AL28/AK28 -> 4.9792201 | AK28: 42360 | AL28: 210919.76 | AM28: 221158.85 | AO28: =AQ28/AP28 -> 5.946696 | AP28: 52776 | AQ28: 313842.83 | AR28: 353927.04 | AT28: =AV28/AU28 -> 6.6107622 | AU28: 50640 | AV28: 334769 | AW28: 99077.44 | AY28: =BA28/AZ28 -> 6.349452 | AZ28: 49132 | BA28: 311961.28 | BB28: 259967.73 | BD28: =BF28/BE28 -> 6.3628442 | BE28: 42815 | BF28: 272425.18 | BG28: 259967.73 | BI28: =BK28/BJ28 -> 6.771588 | BJ28: 44605 | BK28: 302046.68 | BL28: 215669.93 | BN28: =BP28/BO28 -> 6.374628 | BO28: 45060 | BP28: 287240.74 | BQ28: 99077.44 | BS28: =BU28/BT28 -> 6.0268801 | BT28: 53040 | BU28: 319665.72 | BV28: 291 444,30 | BX28: =BZ28/BY28 -> 5.3077195 | BY28: 26880 | BZ28: 142671.5 | CA28: 345590.5 | CC28: =CE28/CD28 -> 5.3077195 | CD28: 26880 | CE28: 142671.5 | CF28: 99077.44 | CH28: =CJ28/CI28 -> 5.3077195 | CI28: 26880 | CJ28: 142671.5 | CK28: 99077.44 | CM28: =CO28/CN28 -> 5.3077195 | CN28: 26880 | CO28: 142671.5 | CP28: 99077.44 | CR28: =CT28/CS28 -> 5.3077195 | CS28: 26880 | CT28: 142671.5 | CU28: 99077.44 | CW28: =CY28/CX28 -> 5.3077195 | CX28: 26880 | CY28: 142671.5 | CZ28: 99077.44
B29: 41946011 | C29: «ДТЕК КИЇВСЬКІ ЕЛЕКТРОМЕРЕЖІ» | D29: Реактивная ЭЭ | H29: 1 208,50 | M29: 1608.624 | R29: 1 481,46 | W29: 1705.212 | AB29: 2015.24 | AG29: 2 055,08 | AL29: 2 183,15 | AQ29: 2431.16 | AV29: 2940.72 | BA29: 3359.38 | BF29: 2161.44 | BK29: 2 950,96 | BP29: 2 275,88 | BT29: 1 | BU29: 2431.86 | BZ29: 1 208,50 | CE29: 1 208,50 | CJ29: 1 208,50 | CO29: 1 208,50 | CT29: 1 208,50 | CY29: 1 208,50
B30: 2839404073 | C30: ФОП Пластун В.В. | D30: ХВ | F30: =H30/G30 -> 32.446667 | G30: 57 | H30: 1849.46 | K30: =M30/L30 -> 33.254545 | L30: 55 | M30: 1829 | P30: =R30/Q30 -> 32.343667 | Q30: 60 | R30: 1940.62 | U30: =W30/V30 -> 33.384615 | V30: 52 | W30: 1736 | Z30: =AB30/AA30 -> 33.247312 | AA30: 93 | AB30: 3092 | AE30: =AG30/AF30 -> 1892 | AF30: 1 | AG30: 1892 | AJ30: =AL30/AK30 -> 33.472973 | AK30: 74 | AL30: 2477 | AO30: =AQ30/AP30 -> 32.135135 | AP30: 74 | AQ30: 2378 | AT30: =AV30/AU30 -> 35.43662 | AU30: 71 | AV30: 2516 | AY30: =BA30/AZ30 -> 1892 | AZ30: 1 | BA30: 1892 | BD30: =BF30/BE30 -> 1892 | BE30: 1 | BF30: 1892 | BI30: =BK30/BJ30 -> 35.037037 | BJ30: 54 | BK30: 1892 | BN30: =BP30/BO30 -> 48.518248 | BO30: 137 | BP30: 6647 | BS30: =BU30/BT30 -> 31.951733 | BT30: 75 | BU30: 2396.38 | BX30: =BZ30/BY30 -> 1892 | BY30: 1 | BZ30: 1892 | CC30: =CE30/CD30 -> 1892 | CD30: 1 | CE30: 1892 | CH30: =CJ30/CI30 -> 1892 | CI30: 1 | CJ30: 1892 | CM30: =CO30/CN30 -> 1892 | CN30: 1 | CO30: 1892 | CR30: =CT30/CS30 -> 1892 | CS30: 1 | CT30: 1892 | CW30: =CY30/CX30 -> 1892 | CX30: 1 | CY30: 1892
A31: М7 | B31: г.Киев, ул. Коновальца,44Б | C31: ТОВ "Еко-Грінко" | D31: Вывоз ТБО | W31: 1769 | Y31: =SUM(W31:W37)*1.1 -> 128568.93 | AB31: 1327 | AD31: =SUM(AB31:AB37)*1.1 -> 145940.86 | AG31: 1769 | AI31: =AI32*1.1 -> 167258.3 | AL31: 1106 | AN31: =AN32*1.2 -> 243742.02 | AQ31: 1990 | AS31: =SUM(AQ31:AQ37)*1.2 -> 249696.68 | AX31: =SUM(AV31:AV37)*1.1 -> 335982.68 | BC31: =SUM(BA31:BA37)*1.1 -> 249573.1 | BH31: =SUM(BF31:BF37)*1.1 -> 240436.79 | BM31: =SUM(BK31:BK37)*1.1 -> 250447.47 | BR31: =SUM(BP31:BP37)*1.1 -> 228835.35 | BW31: =SUM(BU31:BU37)*1.1 -> 181035.97 | CB31: =SUM(BZ31:BZ37)*1.1 -> 106588.73 | CG31: =SUM(CE31:CE37)*1.1 -> 106588.73 | CL31: =SUM(CJ31:CJ37)*1.1 -> 106588.73 | CQ31: =SUM(CO31:CO37)*1.1 -> 106588.73 | CV31: =SUM(CT31:CT37)*1.1 -> 106588.73 | DA31: =SUM(CY31:CY37)*1.1 -> 106588.73
C32: ТОВ "ОК "Комфорт" | D32: Послуга із забезпечення технічної | V32: 1 | W32: 9274.13 | Y32: =SUM(W31:W37)*1 -> 116880.84 | AA32: 1 | AB32: 9974.36 | AD32: =SUM(AB31:AB37)*1 -> 132673.51 | AG32: 11967.32 | AI32: =SUM(AG31:AG37)*1 -> 152053 | AL32: 16764.1 | AN32: =SUM(AL31:AL37)*1 -> 203118.35 | AQ32: 18754.75 | AS32: =SUM(AQ31:AQ37)*1 -> 208080.56 | AV32: 26166.5 | AX32: =SUM(AV31:AV37)*1 -> 305438.8 | BA32: 18885.72 | BC32: =SUM(BA31:BA37)*1 -> 226884.64 | BF32: 17254.72 | BH32: =SUM(BF31:BF37)*1 -> 218578.9 | BK32: =17675.04+94.188+286.76 -> 18055.988 | BM32: =SUM(BK31:BK37)*1 -> 227679.52 | BP32: 17 384,99 | BR32: =SUM(BP31:BP37)*1 -> 208032.14 | BU32: 15130.36 | BW32: =SUM(BU31:BU37)*1 -> 164578.16 | CB32: =SUM(BZ31:BZ37)*1 -> 96898.848 | CG32: =SUM(CE31:CE37)*1 -> 96898.848 | CL32: =SUM(CJ31:CJ37)*1 -> 96898.848 | CQ32: =SUM(CO31:CO37)*1 -> 96898.848 | CV32: =SUM(CT31:CT37)*1 -> 96898.848 | DA32: =SUM(CY31:CY37)*1 -> 96898.848
B33: 39397773 | C33: ТОВ "ОК "Комфорт" | D33: Экспл. расходы | G33: 1 | H33: =17607.25+1534.43 -> 19141.68 | L33: 1 | M33: =17607.25+1534.43 -> 19141.68 | Q33: 1 | R33: =17607.25+1534.43 -> 19141.68 | V33: 1 | W33: =17607.25+1534.43 -> 19141.68 | AA33: 1 | AB33: =17607.25+1534.43 -> 19141.68 | AF33: 1 | AG33: 17607.25 | AK33: 1 | AL33: 17607.25 | AP33: 1 | AQ33: 17607.25 | AU33: 1 | AV33: =17607.25 -> 17607.25 | AZ33: 1 | BA33: =17607.25+1534.43 -> 19141.68 | BE33: 1 | BF33: 28776.97 | BJ33: 1 | BK33: 28776.97 | BO33: 1 | BP33: 28776.97 | BT33: 1 | BU33: 28 776,97 | BY33: 1 | BZ33: =17607.25+1534.43 -> 19141.68 | CD33: 1 | CE33: =17607.25+1534.43 -> 19141.68 | CI33: 1 | CJ33: =17607.25+1534.43 -> 19141.68 | CN33: 1 | CO33: =17607.25+1534.43 -> 19141.68 | CS33: 1 | CT33: =17607.25+1534.43 -> 19141.68 | CX33: 1 | CY33: =17607.25+1534.43 -> 19141.68
C34: ТОВ "ОК "Комфорт" | D34: Реактивная ЭЭ | G34: 1 | H34: =1.2*639.79 -> 767.748 | L34: 1 | M34: =1.2*639.79 -> 767.748 | Q34: 5880 | R34: =1.2*712.83 -> 855.396 | V34: 1 | W34: =1.2*943.49 -> 1132.188 | AA34: 1 | AB34: =1.2*1096.02 -> 1315.224 | AF34: 1 | AG34: =1.2*1281.77 -> 1538.124 | AK34: 1 | AL34: =1.2*1566.38 -> 1879.656 | AP34: 1 | AQ34: =1.2*1547.34 -> 1856.808 | AU34: 1 | AV34: =1.2*2205.75 -> 2646.9 | AZ34: 1 | BA34: =1.2*1978.19 -> 2373.828 | BE34: 1 | BF34: =1.2*1724.34 -> 2069.208 | BJ34: 1 | BK34: =1.2*1652.95 -> 1983.54 | BO34: 1 | BP34: =1.2*1098.73 -> 1318.476 | BT34: 1 | BU34: 1546.49 | BY34: 1 | BZ34: =1.2*639.79 -> 767.748 | CD34: 1 | CE34: =1.2*639.79 -> 767.748 | CI34: 1 | CJ34: =1.2*639.79 -> 767.748 | CN34: 1 | CO34: =1.2*639.79 -> 767.748 | CS34: 1 | CT34: =1.2*639.79 -> 767.748 | CX34: 1 | CY34: =1.2*639.79 -> 767.748
A35: ЯСНО "КИЇВСЬКІ ЕНЕРГЕТИЧНІ ПОСЛУГИ" | C35: ТОВ "ОК "Комфорт" | D35: Активная ЭЭ | F35: =H35/G35 -> 5.0962317 | G35: 14970 | H35: =63575.49*1.2 -> 76290.588 | K35: =M35/L35 -> 5.875313 | L35: 14790 | M35: 86895.88 | P35: =R35/Q35 -> 5.5478991 | Q35: 18390 | R35: =9352.84+77227.52*1.2 -> 102025.86 | U35: =W35/V35 -> 5.089392 | V35: 18000 | W35: =1.2*76340.88 -> 91609.056 | Z35: =AB35/AA35 -> 4.7757601 | AA35: 20610 | AB35: =82023.68*1.2 -> 98428.416 | AE35: =AG35/AF35 -> 4.7047078 | AF35: 25110 | AG35: =98446.01*1.2 -> 118135.21 | AJ35: =AL35/AK35 -> 4.955496 | AK35: 33450 | AL35: =1.2*138134.45 -> 165761.34 | AO35: =AQ35/AP35 -> 5.867004 | AP35: 31650 | AQ35: =154742.23*1.2 -> 185690.68 | AT35: =AV35/AU35 -> 6.5161799 | AU35: 39750 | AV35: =1.2*215848.46 -> 259018.15 | AY35: =BA35/AZ35 -> 6.3494521 | AZ35: 29370 | BA35: =1.2*155402.84 -> 186483.41 | BD35: =BF35/BE35 -> 6.6 | BE35: 25830 | BF35: =1.2*142065 -> 170478 | BI35: =BK35/BJ35 -> 6.8055598 | BJ35: 25680 | BK35: =1.2*145638.98 -> 174766.78 | BN35: =BP35/BO35 -> 6.7185121 | BO35: 25680 | BP35: =1.2*143776.16 -> 172531.39 | BS35: =BU35/BT35 -> 5.9659799 | BT35: 25050 | BU35: =124539.83*1.2 -> 149447.8 | BX35: =BZ35/BY35 -> 5.0962317 | BY35: 14970 | BZ35: =63575.49*1.2 -> 76290.588 | CC35: =CE35/CD35 -> 5.0962317 | CD35: 14970 | CE35: =63575.49*1.2 -> 76290.588 | CH35: =CJ35/CI35 -> 5.0962317 | CI35: 14970 | CJ35: =63575.49*1.2 -> 76290.588 | CM35: =CO35/CN35 -> 5.0962317 | CN35: 14970 | CO35: =63575.49*1.2 -> 76290.588 | CR35: =CT35/CS35 -> 5.0962317 | CS35: 14970 | CT35: =63575.49*1.2 -> 76290.588 | CW35: =CY35/CX35 -> 5.0962317 | CX35: 14970 | CY35: =63575.49*1.2 -> 76290.588
C36: ТОВ "ОК "Комфорт" | D36: Тепловая энергия | G36: 0.41 | L36: 0.940 | M36: 2682.91 | Q36: 0.89 | R36: 2540.18 | V36: 0.78 | W36: 2226.25 | AA36: 0 | AB36: 1484.16 | AF36: 0 | AK36: 0 | AP36: 0 | AU36: 0 | AZ36: 0 | BE36: 0.41 | BK36: 3154.34 | BO36: 0.94 | BP36: 4706.47 | BT36: 0.41 | BU36: 5 006,88 | BY36: 0.41 | CD36: 0.41 | CI36: 0.41 | CN36: 0.41 | CS36: 0.41 | CX36: 0.41
C37: ТОВ "ОК "Комфорт" | D37: ХВ | G37: 22 | H37: =1.2*(309.81+272.55) -> 698.832 | L37: 23 | M37: 768.72 | Q37: 25 | R37: 835.56 | U37: =W37/V37 -> 33.422333 | V37: 30 | W37: 1002.67 | Z37: =AB37/AA37 -> 33.422333 | AA37: 30 | AB37: 1002.67 | AF37: 31 | AG37: 1036.09 | AK37: 33 | AL37: 1102.94 | AP37: 28 | AQ37: 935.83 | AU37: 30 | AV37: 1002.67 | AZ37: 30 | BA37: 1002.67 | BE37: 26 | BF37: 868.98 | BI37: =BK37/BJ37 -> 30.384 | BJ37: 31 | BK37: =1.2*784.92 -> 941.904 | BO37: 23 | BP37: =1.2*(309.81+272.55) -> 698.832 | BT37: 31 | BU37: 1 036,09 | BY37: 23 | BZ37: =1.2*(309.81+272.55) -> 698.832 | CD37: 23 | CE37: =1.2*(309.81+272.55) -> 698.832 | CI37: 23 | CJ37: =1.2*(309.81+272.55) -> 698.832 | CN37: 23 | CO37: =1.2*(309.81+272.55) -> 698.832 | CS37: 23 | CT37: =1.2*(309.81+272.55) -> 698.832 | CX37: 23 | CY37: =1.2*(309.81+272.55) -> 698.832
A38: М8 | B38: г.Ирпень, 10-я линия,1Б | C38: ПП "Обухівміськвторресурси" | D38: Вывоз ТБО | W38: 2277 | Y38: =SUM(W38:W43)*1.1 -> 207970.84 | AB38: 2530 | AD38: =SUM(AB38:AB43)*1.1 -> 182839.66 | AG38: 4301 | AI38: =AI39*1.1 -> 30482.903 | AL38: 4048 | AN38: =AN39*1.2 -> 213801.05 | AS38: =SUM(AQ38:AQ43)*1.2 -> 279236.06 | AX38: =SUM(AV38:AV43)*1.1 -> 296544.54 | BC38: =SUM(BA38:BA43)*1.1 -> 120848.06 | BH38: =SUM(BF38:BF43)*1.1 -> 237060.42 | BM38: =SUM(BK38:BK43)*1.1 -> 236698.6 | BR38: =SUM(BP38:BP43)*1.1 -> 279330.39 | BW38: =SUM(BU38:BU43)*1.1 -> 269576.14 | CB38: =SUM(BZ38:BZ43)*1.1 -> 117959.87 | CG38: =SUM(CE38:CE43)*1.1 -> 117959.87 | CL38: =SUM(CJ38:CJ43)*1.1 -> 117959.87 | CQ38: =SUM(CO38:CO43)*1.1 -> 117959.87 | CV38: =SUM(CT38:CT43)*1.1 -> 117959.87 | DA38: =SUM(CY38:CY43)*1.1 -> 117959.87
B39: 40397750 | C39: ТОВ "ТЦ "Вайт Хауз" | D39: Экспл. расходы | H39: 17000 | L39: 1 | M39: 17000 | Q39: 1 | R39: 19000 | V39: 1 | W39: 19000 | Y39: =SUM(W38:W43)*1 -> 189064.4 | AA39: 1 | AB39: 19000 | AD39: =SUM(AB38:AB42)*1 -> 164925.2 | AF39: 1 | AG39: 19000 | AI39: =SUM(AG42:AG43)+AH41+AG40+AG39+AG38*1 -> 27711.73 | AK39: 1 | AL39: 19000 | AN39: =SUM(AL43)+AM41+AL40+AL39+AL38+AM42*1 -> 178167.54 | AP39: 1 | AQ39: 19000 | AS39: =SUM(AQ38:AQ43)*1 -> 232696.72 | AU39: 1 | AV39: 19000 | AX39: =SUM(AV38:AV43)*1 -> 269585.95 | AZ39: 1 | BA39: 19000 | BC39: =SUM(BA38:BA43)*1 -> 109861.87 | BE39: 1 | BF39: 19000 | BH39: =SUM(BF38:BF43)*1 -> 215509.48 | BJ39: 1 | BK39: 19000 | BM39: =SUM(BK38:BK43)*1 -> 215180.54 | BO39: 1 | BP39: 19000 | BR39: =SUM(BP38:BP43)*1 -> 253936.72 | BT39: 1 | BU39: 21 000 | BW39: =SUM(BU38:BU43)*1 -> 245069.22 | BY39: 1 | BZ39: 21000 | CB39: =SUM(BZ38:BZ43)*1 -> 107236.24 | CD39: 1 | CE39: 21000 | CG39: =SUM(CE38:CE43)*1 -> 107236.24 | CI39: 1 | CJ39: 21000 | CL39: =SUM(CJ38:CJ43)*1 -> 107236.24 | CN39: 1 | CO39: 21000 | CQ39: =SUM(CO38:CO43)*1 -> 107236.24 | CS39: 1 | CT39: 21000 | CV39: =SUM(CT38:CT43)*1 -> 107236.24 | CX39: 1 | CY39: 21000 | DA39: =SUM(CY38:CY43)*1 -> 107236.24
B40: 40397750 | C40: ТОВ "ТЦ "Вайт Хауз" | D40: ХВ | G40: 2 | H40: 67.43 | L40: 4 | M40: 134.86 | V40: 1 | W40: 33.72 | AA40: 1 | AB40: 303.44 | AF40: 7 | AG40: 236.01 | AI40: =AG38+AG39+AG40+AG41+AG42+AG43 -> 170318.36 | AK40: 5 | AL40: 185.38 | AN40: =AL38+AL39+AL40+AM42+AM41 -> 178167.54 | AP40: 6 | AQ40: 219.09 | AU40: 6 | AV40: 219.64 | AZ40: 7 | BA40: 253.44 | BE40: 7 | BF40: 253.44 | BJ40: 7 | BK40: 253.44 | BO40: 7 | BP40: 253.44 | BT40: 8 | BU40: 287.24
B41: 44878589 | C41: ТОВ ТОЛК | D41: Активная ЭЭ | F41: =H41/G41 -> 5.834472 | G41: 14641 | H41: 85422.504 | I41: 59321.18 | K41: =M41/L41 -> 0 | L41: 21940 | M41: 0 | P41: =R41/Q41 -> 5.463492 | Q41: 21598 | R41: 118000.5 | S41: 118000.5 | U41: =W41/V41 -> 5.6633998 | V41: 28737 | W41: 162749.12 | X41: 118000.5 | Z41: =AB41/AA41 -> 5.2304759 | AA41: 26894 | AB41: 140668.42 | AC41: 0 | AE41: =AG41/AF41 -> 5.3864638 | AF41: 26475 | AG41: 142606.63 | AH41: 0 | AJ41: =AL41/AK41 -> 5.651892 | AK41: 26882 | AL41: 151934.16 | AM41: 151934.16 | AO41: =AQ41/AP41 -> 6.821652 | AP41: 30774 | AQ41: 209929.52 | AR41: 230791.34 | AT41: =AV41/AU41 -> 7.5147962 | AU41: 32646 | AV41: =1.2*204440.03 -> 245328.04 | AW41: 59321.18 | AY41: =BA41/AZ41 -> 2.9535476 | AZ41: 28922 | BA41: 85422.504 | BB41: 59321.18 | BD41: =BF41/BE41 -> 7.2173641 | BE41: 26581 | BF41: 191844.76 | BG41: 0 | BI41: =BK41/BJ41 -> 7.5240961 | BJ41: 25728 | BK41: =1.2*161316.62 -> 193579.94 | BL41: 151877.1 | BN41: =BP41/BO41 -> 7.0861201 | BO41: 32311 | BP41: =1.2*190799.69 -> 228959.63 | BQ41: 0 | BS41: =BU41/BT41 -> 7.0129999 | BT41: 34788 | BU41: 243968.24 | BV41: =157195.68+86772.56 -> 243968.24 | BX41: =BZ41/BY41 -> 4.2711252 | BY41: 20000 | BZ41: 85422.504 | CA41: 105341.6 | CC41: =CE41/CD41 -> 5.834472 | CD41: 14641 | CE41: 85422.504 | CF41: 0 | CH41: =CJ41/CI41 -> 5.834472 | CI41: 14641 | CJ41: 85422.504 | CK41: 0 | CM41: =CO41/CN41 -> 5.834472 | CN41: 14641 | CO41: 85422.504 | CP41: 0 | CR41: =CT41/CS41 -> 5.834472 | CS41: 14641 | CT41: 85422.504 | CU41: 0 | CW41: =CY41/CX41 -> 5.834472 | CX41: 14641 | CY41: 85422.504 | CZ41: 0
B42: 23243188 | C42: ПрАТ "Київобленерго" | D42: Реактивная ЭЭ | G42: 1 | H42: 813.74 | L42: 4855 | M42: 1239.67 | N42: 1239.67 | Q42: 5746 | R42: 1540 | S42: 1540.42 | V42: 1 | W42: 2020.87 | X42: 2020.87 | AA42: 1 | AB42: 2423.34 | AC42: 2423.34 | AF42: 1 | AG42: =2386.75+319.53 -> 2706.28 | AK42: 1 | AL42: 2516.45 | AM42: 3000 | AP42: 1 | AQ42: 3548.11 | AU42: 1 | AV42: =3777.36+1260.91 -> 5038.27 | AZ42: 1 | BA42: 3748.4 | BB42: =3748.4+585.75 -> 4334.15 | BE42: 1 | BF42: 2877.42 | BG42: 2877.42 | BJ42: 1 | BK42: 2347.16 | BL42: 2 347,16 | BO42: 1 | BP42: 2616.3 | BT42: 1 | BU42: 813.74 | BV42: 2 583,85 | BY42: 1 | BZ42: 813.74 | CD42: 1 | CE42: 813.74 | CI42: 1 | CJ42: 813.74 | CN42: 1 | CO42: 813.74 | CS42: 1 | CT42: 813.74 | CX42: 1 | CY42: 813.74
B43: 03362471 | C43: КП "Ирпеньводоканал" | D43: ХВ | G43: 2 | H43: 67.43 | L43: 182 | M43: 4883.65 | U43: =W43/V43 -> 26.88009 | V43: 111 | W43: 2983.69 | Z43: =AB43/AA43 -> 32.3169 | AA43: 40 | AB43: =1.2*(413.6+656.8+6.83) -> 1292.676 | AE43: =AG43/AF43 -> 32.632 | AF43: 45 | AG43: 1468.44 | AJ43: =AL43/AK43 -> #DIV/0! | AO43: =AQ43/AP43 -> #DIV/0! | AT43: =AV43/AU43 -> #DIV/0! | AY43: =BA43/AZ43 -> 32.671136 | AZ43: 44 | BA43: 1437.53 | BD43: =BF43/BE43 -> 32.635319 | BE43: 47 | BF43: 1533.86 | BN43: =BP43/BO43 -> 32.368229 | BO43: 96 | BP43: 3107.35 | BS43: =BU43/BT43 -> #DIV/0! | BX43: =BZ43/BY43 -> #DIV/0! | CC43: =CE43/CD43 -> #DIV/0! | CH43: =CJ43/CI43 -> #DIV/0! | CM43: =CO43/CN43 -> #DIV/0! | CR43: =CT43/CS43 -> #DIV/0! | CW43: =CY43/CX43 -> #DIV/0!
A44: М9 | B44: г.Бровары, ул. Шолом Алейхема,68 | C44: ПП "Обухівміськвторресурси" | D44: Вывоз ТБО | W44: 2024 | Y44: =SUM(W44:W47)*1.1 -> 121511.3 | AB44: 1012 | AD44: =SUM(AB44:AB47)*1.1 -> 85408.917 | AG44: 1012 | AI44: =AI45*1.1 -> 111330.64 | AL44: 1518 | AN44: =AN45*1.2 -> 132606.43 | AS44: =SUM(AQ44:AQ47)*1.2 -> 176431.82 | AX44: =SUM(AV44:AV47)*1.1 -> 212285.56 | BC44: =SUM(BA44:BA47)*1.1 -> 139916.51 | BH44: =SUM(BF44:BF47)*1.1 -> 121380.59 | BM44: =SUM(BK44:BK47)*1.1 -> 150350.12 | BR44: =SUM(BP44:BP47)*1.1 -> 124480.94 | BW44: =SUM(BU44:BU47)*1.1 -> 184602.01 | CB44: =SUM(BZ44:BZ47)*1.1 -> 80707.495 | CG44: =SUM(CE44:CE47)*1.1 -> 80707.495 | CL44: =SUM(CJ44:CJ47)*1.1 -> 80707.495 | CQ44: =SUM(CO44:CO47)*1.1 -> 80707.495 | CV44: =SUM(CT44:CT47)*1.1 -> 80707.495 | DA44: =SUM(CY44:CY47)*1.1 -> 80707.495
A45: ЕНЕРГУМ | B45: 35116016 | C45: ЧП "Броварижитлобуд" | D45: Активная ЭЭ | F45: =H45/G45 -> 5.522772 | G45: 12980 | H45: 71685.58 | K45: =M45/L45 -> 5.6584567 | L45: 9698.8 | M45: 54880.24 | P45: =R45/Q45 -> 5.3252043 | Q45: 16540.4 | R45: 88081.01 | U45: =W45/V45 -> 5.5242116 | V45: 19140.4 | W45: 105735.62 | Y45: =SUM(W44:W47)*1 -> 110464.82 | Z45: =AB45/AA45 -> 5.1137163 | AA45: 14877.2 | AB45: 76077.78 | AD45: =SUM(AB44:AB47)*1 -> 77644.47 | AE45: =AG45/AF45 -> 5.1882185 | AF45: 18967 | AG45: 98404.94 | AI45: =SUM(AG44:AG47)*1 -> 101209.67 | AJ45: =AL45/AK45 -> 5.4686757 | AK45: 19502.4 | AL45: 106652.3 | AN45: =SUM(AL44:AL47)*1 -> 110505.36 | AO45: =AQ45/AP45 -> 6.5835123 | AP45: 21918.8 | AQ45: 144302.69 | AS45: =SUM(AQ44:AQ47)*1 -> 147026.52 | AT45: =AV45/AU45 -> 7.2405599 | AU45: 26167.2 | AV45: 189465.18 | AX45: =SUM(AV44:AV47)*1 -> 192986.87 | AY45: =BA45/AZ45 -> 6.9380999 | AZ45: 18237.6 | BA45: 126534.29 | BC45: =SUM(BA44:BA47)*1 -> 127196.83 | BD45: =BF45/BE45 -> 7.0001637 | BE45: 15451.2 | BF45: 108160.93 | BH45: =SUM(BF44:BF47)*1 -> 110345.99 | BI45: =BK45/BJ45 -> 7.3157642 | BJ45: 18402.4 | BK45: 134627.62 | BM45: =SUM(BK44:BK47)*1 -> 136681.93 | BN45: =BP45/BO45 -> 6.842244 | BO45: 16299.6 | BP45: 111525.84 | BR45: =SUM(BP44:BP47)*1 -> 113164.49 | BS45: =BU45/BT45 -> 6.6790681 | BT45: 24874 | BU45: 166135.14 | BW45: =SUM(BU44:BU47)*1 -> 167820.01 | BX45: =BZ45/BY45 -> 5.522772 | BY45: 12980 | BZ45: 71685.58 | CB45: =SUM(BZ44:BZ47)*1 -> 73370.45 | CC45: =CE45/CD45 -> 5.522772 | CD45: 12980 | CE45: 71685.58 | CG45: =SUM(CE44:CE47)*1 -> 73370.45 | CH45: =CJ45/CI45 -> 5.522772 | CI45: 12980 | CJ45: 71685.58 | CL45: =SUM(CJ44:CJ47)*1 -> 73370.45 | CM45: =CO45/CN45 -> 5.522772 | CN45: 12980 | CO45: 71685.58 | CQ45: =SUM(CO44:CO47)*1 -> 73370.45 | CR45: =CT45/CS45 -> 5.522772 | CS45: 12980 | CT45: 71685.58 | CV45: =SUM(CT44:CT47)*1 -> 73370.45 | CW45: =CY45/CX45 -> 5.522772 | CX45: 12980 | CY45: 71685.58 | DA45: =SUM(CY44:CY47)*1 -> 73370.45
D46: Реактивная ЭЭ | G46: 1 | H46: 1099.37 | L46: 1 | M46: 893.9 | Q46: 1 | R46: 1673.39 | V46: 1 | W46: 1857.76 | AA46: 1 | AB46: 1'393,91 | AF46: 1 | AG46: 1099.37 | AK46: 1 | AL46: 1641.7 | AP46: 1 | AQ46: 1968.84 | AU46: 1 | AV46: 2720.47 | AZ46: 1 | BA46: 2 176,07 | BE46: 1 | BF46: 1460.88 | BJ46: 1 | BK46: 1607.48 | BO46: 1 | BP46: 1099.37 | BT46: 1 | BU46: 1099.37 | BY46: 1 | BZ46: 1099.37 | CD46: 1 | CE46: 1099.37 | CI46: 1 | CJ46: 1099.37 | CN46: 1 | CO46: 1099.37 | CS46: 1 | CT46: 1099.37 | CX46: 1 | CY46: 1099.37
D47: ХВ | F47: =H47/G47 -> 15.407895 | G47: 38 | H47: 585.5 | K47: =M47/L47 -> 15.407879 | L47: 33 | M47: 508.46 | P47: =R47/Q47 -> 15.407907 | Q47: 43 | R47: 662.54 | U47: =W47/V47 -> 15.408 | V47: 55 | W47: 847.44 | Z47: =AB47/AA47 -> 15.408056 | AA47: 36 | AB47: 554.69 | AE47: =AG47/AF47 -> 15.408 | AF47: 45 | AG47: 693.36 | AJ47: =AL47/AK47 -> 15.408 | AK47: 45 | AL47: 693.36 | AO47: =AQ47/AP47 -> 15.407959 | AP47: 49 | AQ47: 754.99 | AT47: =AV47/AU47 -> 15.408077 | AU47: 52 | AV47: 801.22 | AY47: =BA47/AZ47 -> 15.407907 | AZ47: 43 | BA47: 662.54 | BD47: =BF47/BE47 -> 15.408085 | BE47: 47 | BF47: 724.18 | BI47: =BK47/BJ47 -> 15.407931 | BJ47: 29 | BK47: 446.83 | BN47: =BP47/BO47 -> 15.408 | BO47: 35 | BP47: 539.28 | BS47: =BU47/BT47 -> 15.407895 | BT47: 38 | BU47: 585.5 | BX47: =BZ47/BY47 -> 15.407895 | BY47: 38 | BZ47: 585.5 | CC47: =CE47/CD47 -> 15.407895 | CD47: 38 | CE47: 585.5 | CH47: =CJ47/CI47 -> 15.407895 | CI47: 38 | CJ47: 585.5 | CM47: =CO47/CN47 -> 15.407895 | CN47: 38 | CO47: 585.5 | CR47: =CT47/CS47 -> 15.407895 | CS47: 38 | CT47: 585.5 | CW47: =CY47/CX47 -> 15.407895 | CX47: 38 | CY47: 585.5
A48: М10 | B48: г.Киев, ул.Героев Сталинграда,65Б | C48: ТОВ "Еко-Грінко" | D48: Вывоз ТБО | W48: 1990 | Y48: =SUM(W48:W52)*1.1 -> 100305.79 | AB48: 1769 | AD48: =SUM(AB48:AB52)*1.1 -> 74879.44 | AG48: 1990 | AI48: =AI49*1.1 -> 127966.28 | AL48: 1769 | AN48: =AN49*1.2 -> 45928.231 | AQ48: 1548 | AS48: =SUM(AQ48:AQ52)*1.1 -> 180831.55 | AX48: =SUM(AV48:AV52)*1.1 -> 154779.08 | BC48: =SUM(BA48:BA52)*1.1 -> 120349.83 | BH48: =SUM(BF48:BF52)*1.1 -> 111317.5 | BM48: =SUM(BK48:BK52)*1.1 -> 135062.39 | BR48: =SUM(BP48:BP52)*1.1 -> 141526.09 | BW48: =SUM(BU48:BU52)*1.1 -> 174851.23 | CB48: =SUM(BZ48:BZ52)*1.1 -> 55866.859 | CG48: =SUM(CE48:CE52)*1.1 -> 55866.859 | CL48: =SUM(CJ48:CJ52)*1.1 -> 55866.859 | CQ48: =SUM(CO48:CO52)*1.1 -> 55866.859 | CV48: =SUM(CT48:CT52)*1.1 -> 55866.859 | DA48: =SUM(CY48:CY52)*1.1 -> 55866.859
C49: ОСББ "Кристалл-5" | D49: Экспл. расходы | G49: 1 | H49: 6000 | J49: 6000 | L49: 1 | M49: 6000 | O49: 6000 | Q49: 1 | R49: 6000 | S49: 6000 | V49: 1 | W49: 6000 | Y49: =SUM(W48:W52)*1 -> 91187.078 | AA49: 1 | AB49: 6000 | AD49: =SUM(AB48:AB52)*1 -> 68072.218 | AF49: 0 | AG49: 0 | AI49: =SUM(AG51:AG52)+AH50+AG48*1 -> 116332.98 | AK49: 1 | AL49: 0 | AN49: =SUM(AL51:AL52)+AM50+AL48*1 -> 38273.526 | AP49: 1 | AQ49: 0 | AS49: =SUM(AQ48:AQ52)*1 -> 164392.32 | AU49: 1 | AV49: 6000 | AX49: =SUM(AV48:AV52)*1 -> 140708.25 | AZ49: 1 | BA49: 6000 | BC49: =SUM(BA48:BA52)*1 -> 109408.93 | BE49: 1 | BF49: 6000 | BH49: =SUM(BF48:BF52)*1 -> 101197.73 | BJ49: 1 | BK49: 6000 | BM49: =SUM(BK48:BK52)*1 -> 122783.99 | BO49: 1 | BP49: 6000 | BR49: =SUM(BP48:BP52)*1 -> 128660.08 | BT49: 1 | BU49: 6000 | BW49: =SUM(BU48:BU52)*1 -> 158955.66 | BY49: 1 | BZ49: 6000 | CB49: =SUM(BZ48:BZ52)*1 -> 50788.054 | CD49: 1 | CE49: 6000 | CG49: =SUM(CE48:CE52)*1 -> 50788.054 | CI49: 1 | CJ49: 6000 | CL49: =SUM(CJ48:CJ52)*1 -> 50788.054 | CN49: 1 | CO49: 6000 | CQ49: =SUM(CO48:CO52)*1 -> 50788.054 | CS49: 1 | CT49: 6000 | CV49: =SUM(CT48:CT52)*1 -> 50788.054 | CX49: 1 | CY49: 6000 | DA49: =SUM(CY48:CY52)*1 -> 50788.054
B50: 41916045 | C50: ТОВ "КИЇВСЬКI ЕНЕРГЕТИЧНI ПОСЛУГИ" | D50: Активная ЭЭ | F50: =H50/G50 -> 5.3077197 | G50: 8278 | H50: 43937.304 | I50: 30512.02 | K50: =M50/L50 -> 5.3685484 | L50: 13524 | M50: 72604.248 | N50: 72604.25 | P50: =R50/Q50 -> 4.9663923 | Q50: 13659 | R50: 67835.952 | S50: 67835.952 | U50: =W50/V50 -> 5.2077243 | V50: 15754 | W50: 82042.488 | X50: 82042.488 | Z50: =AB50/AA50 -> 4.6829513 | AA50: 12702 | AB50: 59482.848 | AC50: 65912.544 | AE50: =AG50/AF50 -> 4.0166202 | AF50: 15566 | AG50: 62522.71 | AH50: =34690.81+79652.17 -> 114342.98 | AJ50: =AL50/AK50 -> 4.9792216 | AK50: 6367 | AL50: 31702.704 | AM50: 35653.776 | AO50: =AQ50/AP50 -> 5.9466959 | AP50: 27384 | AQ50: 162844.32 | AR50: 183193.6 | AT50: =AV50/AU50 -> 6.6107615 | AU50: 20276 | AV50: 134039.8 | AW50: 30512.02 | AY50: =BA50/AZ50 -> 6.3494521 | AZ50: 16181 | BA50: 102740.48 | BB50: 86 823,47 | BD50: =BF50/BE50 -> 6.3628446 | BE50: 14866 | BF50: 94590.048 | BG50: 86 823,47 | BI50: =BK50/BJ50 -> 6.771588 | BJ50: =14445+2689 -> 17134 | BK50: 116024.39 | BL50: 79855.556 | BN50: =BP50/BO50 -> 6.374626 | BO50: 19118 | BP50: 121870.1 | BQ50: 30512.02 | BS50: =BU50/BT50 -> 6.0268803 | BT50: 25268 | BU50: 152287.21 | BV50: 123 653,62 | BX50: =BZ50/BY50 -> 5.3077197 | BY50: 8278 | BZ50: 43937.304 | CA50: 128 434,97 | CC50: =CE50/CD50 -> 5.3077197 | CD50: 8278 | CE50: 43937.304 | CF50: 30512.02 | CH50: =CJ50/CI50 -> 5.3077197 | CI50: 8278 | CJ50: 43937.304 | CK50: 30512.02 | CM50: =CO50/CN50 -> 5.3077197 | CN50: 8278 | CO50: 43937.304 | CP50: 30512.02 | CR50: =CT50/CS50 -> 5.3077197 | CS50: 8278 | CT50: 43937.304 | CU50: 30512.02 | CW50: =CY50/CX50 -> 5.3077197 | CX50: 8278 | CY50: 43937.304 | CZ50: 30512.02
B51: 41946011 | C51: «ДТЕК КИЇВСЬКІ ЕЛЕКТРОМЕРЕЖІ» | D51: Реактивная ЭЭ | G51: 0 | H51: 0
A52: 27204/5-09 від 21.12.2022 | B52: 03327629 | C52: ПАТ АК "Київводоканал" ТОВ Легион 2015 | D52: ХВ | F52: =H52/G52 -> 30.383929 | G52: 28 | H52: 850.75 | K52: =M52/L52 -> 30.384091 | L52: 22 | M52: 668.45 | P52: =R52/Q52 -> 30.383929 | Q52: 28 | R52: 850.75 | U52: =W52/V52 -> 30.383947 | V52: 38 | W52: 1154.59 | Z52: =AB52/AA52 -> 30.384074 | AA52: 27 | AB52: 820.37 | AE52: =AG52/AF52 -> #VALUE! | AF52: 33 | AG52: 1 002,67 | AJ52: =AL52/AK52 -> 30.383929 | AK52: 28 | AL52: 850.75 | AO52: =AQ52/AP52 -> #VALUE! | AP52: 45 | AQ52: 1 367,28 | AT52: =AV52/AU52 -> 30.384091 | AU52: 22 | AV52: 668.45 | AY52: =BA52/AZ52 -> 30.384091 | AZ52: 22 | BA52: 668.45 | BD52: =BF52/BE52 -> 30.384 | BE52: 20 | BF52: 607.68 | BI52: =BK52/BJ52 -> 30.384 | BJ52: 25 | BK52: 759.6 | BN52: =BP52/BO52 -> 30.383846 | BO52: 26 | BP52: 789.98 | BS52: =BU52/BT52 -> 30.384091 | BT52: 22 | BU52: 668.45 | BX52: =BZ52/BY52 -> 30.383929 | BY52: 28 | BZ52: 850.75 | CC52: =CE52/CD52 -> 30.383929 | CD52: 28 | CE52: 850.75 | CH52: =CJ52/CI52 -> 30.383929 | CI52: 28 | CJ52: 850.75 | CM52: =CO52/CN52 -> 30.383929 | CN52: 28 | CO52: 850.75 | CR52: =CT52/CS52 -> 30.383929 | CS52: 28 | CT52: 850.75 | CW52: =CY52/CX52 -> 30.383929 | CX52: 28 | CY52: 850.75
A53: М11/1 | B53: Автозаводська,27 | C53: ПП "Обухівміськвторресурси" | D53: Вывоз ТБО | W53: 506 | Y53: =SUM(W53+W55)*1.1 -> 115524.2 | AB53: 1012 | AD53: =SUM(AB53+AB54)*1.1 -> 77490.736 | AG53: 2277 | AI53: =AI54*1.1 -> 86390.249 | AL53: 1771 | AN53: =AN54*1.2 -> 98743.596 | AQ53: 2277 | AS53: =AS54*1.2 -> 147933.95 | AX53: =SUM(AV53+AV55)*1.1 -> 0 | BC53: =SUM(BA53+BA55)*1.1 -> 0 | BH53: =SUM(BF53+BF55)*1.1 -> 0 | BM53: =SUM(BK53+BK55)*1.1 -> 0 | BR53: =SUM(BP53+BP55)*1.1 -> 0 | BW53: =SUM(BU53+BU55)*1.1 -> 0 | CB53: =SUM(BZ53+BZ55)*1.1 -> 0 | CG53: =SUM(CE53+CE55)*1.1 -> 0 | CL53: =SUM(CJ53+CJ55)*1.1 -> 0 | CQ53: =SUM(CO53+CO55)*1.1 -> 0 | CV53: =SUM(CT53+CT55)*1.1 -> 0 | DA53: =SUM(CY53+CY55)*1.1 -> 0
B54: 41916045 | C54: ТОВ "КИЇВСЬКI ЕНЕРГЕТИЧНI ПОСЛУГИ" | D54: Активная ЭЭ | P54: =R54/Q54 -> 5.0443882 | Q54: 850 | R54: 4287.73 | U54: =W54/V54 -> 5.2257608 | V54: 5770 | W54: 30152.64 | X54: =154432.8+77216.4 -> 231649.2 | Y54: =SUM(W53:W57)*1 -> 135174.64 | Z54: =AB54/AA54 -> 4.6829516 | AA54: 14827 | AB54: 69434.124 | AC54: 68 030,67 | AD54: =SUM(AB53:AB57)*1 -> 72647.414 | AE54: =AG54/AF54 -> 4.819943 | AF54: 32970 | AG54: 158913.52 | AH54: 74058.3 | AI54: =SUM(AG55:AG57)+AH54+AG53*1 -> 78536.59 | AJ54: =AL54/AK54 -> 4.9792202 | AK54: 31930 | AL54: =1.2*132488.75 -> 158986.5 | AM54: =1.2*65261.7 -> 78314.04 | AN54: =SUM(AL55:AL57)+AM54+AL53*1 -> 82286.33 | AO54: =AQ54/AP54 -> 5.94 | AP54: 20000 | AQ54: 118800 | AR54: 89 200,44 | AS54: =SUM(AQ55:AQ57)+AQ54+AQ53*1 -> 123278.29 | AT54: =AV54/AU54 -> 6.6757121 | AU54: 22800 | AV54: =1.2*(125604.52+1234.01) -> 152206.24 | AX54: =SUM(AV53:AV57)*1 -> 152206.24 | AY54: =BA54/AZ54 -> 6.2413445 | AZ54: =19800+166 -> 19966 | BA54: =(102982.18+863.39)*1.2 -> 124614.68 | BB54: 95 000 | BC54: =SUM(BA53:BA57)*1 -> 127114.68 | BD54: =BF54/BE54 -> 6.3628439 | BE54: =16041+310 -> 16351 | BF54: =1.2*(85055.32+1643.73) -> 104038.86 | BG54: 95 000 | BH54: =SUM(BF53:BF57)*1 -> 104038.86 | BI54: =BK54/BJ54 -> 6.7715883 | BJ54: =15518+300 -> 15818 | BK54: =1.2*(87567.92+1692.9) -> 107112.98 | BL54: 99699.41 | BM54: =SUM(BK53:BK57)*1 -> 107112.98 | BN54: =BP54/BO54 -> 6.3746284 | BO54: 26302 | BP54: 167665.48 | BQ54: 48 983,82 | BR54: =SUM(BP53:BP57)*1 -> 167665.48 | BV54: 170119.12 | BW54: =SUM(BU53:BU57)*1 -> 2200 | CB54: =SUM(BZ53:BZ57)*1 -> 0 | CG54: =SUM(CE53:CE57)*1 -> 0 | CL54: =SUM(CJ53:CJ57)*1 -> 0 | CQ54: =SUM(CO53:CO57)*1 -> 0 | CV54: =SUM(CT53:CT57)*1 -> 0 | DA54: =SUM(CY53:CY57)*1 -> 0
B55: 41946011 | C55: «ДТЕК КИЇВСЬКІ ЕЛЕКТРОМЕРЕЖІ» | D55: Реактивная ЭЭ | U55: 5.2258 | V55: 20000 | W55: =V55*U55 -> 104516
B56: 3160204992 | C56: ФОП ЧАХОЯН ГАЙК ЕДВАРДОВИЧ | D56: ХВ | AA56: 156.75 | AB56: 2201.29 | AE56: =AG56/AF56 -> 33.352879 | AF56: 66 | AG56: 2201.29 | AJ56: =AL56/AK56 -> 33.352879 | AK56: 66 | AL56: 2201.29 | AO56: =AQ56/AP56 -> 33.352879 | AP56: 66 | AQ56: 2201.29 | BA56: 2500 | BK56: 2 800,00 | BP56: 1 800,00 | BT56: 1 | BU56: 2200
A58: М12 | B58: г.Киев, ул.Антоновича,115Д | C58: КП "Володимирський ринок" | D58: Вывоз ТБО | G58: 37 | H58: 6921.07 | L58: 38 | M58: =1.2*5923 -> 7107.6 | Q58: 38 | R58: 7108.13 | V58: 41 | W58: 7669.3 | Y58: =SUM(W58:W64)*1.1 -> 236737.79 | AA58: 40 | AB58: 7482.24 | AD58: =SUM(AB58:AB64)*1.1 -> 221437.65 | AF58: 37 | AG58: 7856.35 | AI58: =AI59*1.1 -> 308203.92 | AK58: 40 | AL58: 7482.24 | AN58: =AN59*1.2 -> 538476.49 | AP58: 43 | AQ58: 8043.41 | AS58: =SUM(AQ58:AQ64)*1.1 -> 93424.243 | AU58: 43 | AV58: 8043.41 | AX58: =SUM(AV58:AV64)*1.1 -> 327846.32 | AZ58: 45 | BA58: 8417.52 | BC58: =SUM(BA58:BA64)*1.1 -> 288493.65 | BE58: 52 | BF58: 9726.91 | BH58: =SUM(BF58:BF64)*1.1 -> 66187.392 | BJ58: 45 | BK58: 8417.52 | BM58: =SUM(BK58:BK64)*1.1 -> 537334.32 | BO58: 48 | BP58: 8978.69 | BR58: =SUM(BP58:BP64)*1.1 -> 336321.73 | BT58: 36 | BU58: 6734.02 | BW58: =SUM(BU58:BU64)*1.1 -> 347215.86 | BY58: 37 | BZ58: 6921.07 | CB58: =SUM(BZ58:BZ64)*1.1 -> 220641.52 | CD58: 37 | CE58: 6921.07 | CG58: =SUM(CE58:CE64)*1.1 -> 220641.52 | CI58: 37 | CJ58: 6921.07 | CL58: =SUM(CJ58:CJ64)*1.1 -> 220641.52 | CN58: 37 | CO58: 6921.07 | CQ58: =SUM(CO58:CO64)*1.1 -> 220641.52 | CS58: 37 | CT58: 6921.07 | CV58: =SUM(CT58:CT64)*1.1 -> 220641.52 | CX58: 37 | CY58: 6921.07 | DA58: =SUM(CY58:CY64)*1.1 -> 220641.52
B59: 01565129 | C59: КП "Володимирський ринок" | D59: Экспл. расходы | G59: 1 | H59: =1.2*14416.67 -> 17300.004 | L59: 1 | M59: =1.2*14416.67 -> 17300.004 | Q59: 1 | R59: =1.2*14416.67 -> 17300.004 | V59: 1 | W59: =1.2*14416.67 -> 17300.004 | Y59: =SUM(W58:W64)*1 -> 215216.17 | AA59: 1 | AB59: =1.2*14416.67 -> 17300.004 | AD59: =SUM(AB58:AB64)*1 -> 201306.96 | AF59: 1 | AG59: =1.2*14416.67 -> 17300.004 | AI59: =SUM(AG63:AG64)+AH62+AG61+AG60+AG59+AG58*1 -> 280185.39 | AK59: 1 | AL59: =1.2*14416.67 -> 17300.004 | AN59: =SUM(AL63:AL64)+AM62+AL61+AL60+AL59+AL58*1 -> 448730.41 | AP59: 1 | AQ59: =1.2*14416.67 -> 17300.004 | AS59: =SUM(AQ58:AQ64)*1 -> 84931.13 | AU59: 1 | AV59: =1.2*14416.67 -> 17300.004 | AX59: =SUM(AV58:AV64)*1 -> 298042.11 | AZ59: 1 | BA59: =1.2*14416.67 -> 17300.004 | BC59: =SUM(BA58:BA64)*1 -> 262266.95 | BE59: 1 | BF59: =1.2*14416.67 -> 17300.004 | BH59: =SUM(BF58:BF64)*1 -> 60170.356 | BJ59: 1 | BK59: =1.2*14416.67 -> 17300.004 | BM59: =SUM(BK58:BK64)*1 -> 488485.74 | BO59: 1 | BP59: =1.2*14416.67 -> 17300.004 | BR59: =SUM(BP58:BP64)*1 -> 305747.03 | BT59: 1 | BU59: =1.2*14416.67 -> 17300.004 | BW59: =SUM(BU58:BU64)*1 -> 315650.79 | BY59: 1 | BZ59: =1.2*14416.67 -> 17300.004 | CB59: =SUM(BZ58:BZ64)*1 -> 200583.2 | CD59: 1 | CE59: =1.2*14416.67 -> 17300.004 | CG59: =SUM(CE58:CE64)*1 -> 200583.2 | CI59: 1 | CJ59: =1.2*14416.67 -> 17300.004 | CL59: =SUM(CJ58:CJ64)*1 -> 200583.2 | CN59: 1 | CO59: =1.2*14416.67 -> 17300.004 | CQ59: =SUM(CO58:CO64)*1 -> 200583.2 | CS59: 1 | CT59: =1.2*14416.67 -> 17300.004 | CV59: =SUM(CT58:CT64)*1 -> 200583.2 | CX59: 1 | CY59: =1.2*14416.67 -> 17300.004 | DA59: =SUM(CY58:CY64)*1 -> 200583.2
C60: КП "Володимирський ринок" | D60: Услуги охраны | G60: 1 | H60: =1.2*13333.33 -> 15999.996 | L60: 1 | M60: =1.2*13333.33 -> 15999.996 | Q60: 1 | R60: =1.2*13333.33 -> 15999.996 | V60: 1 | W60: =1.2*13333.33 -> 15999.996 | AA60: 1 | AB60: =1.2*13333.33 -> 15999.996 | AF60: 1 | AG60: =1.2*13333.33 -> 15999.996 | AK60: 1 | AL60: =1.2*13333.33 -> 15999.996 | AP60: 1 | AQ60: =1.2*13333.33 -> 15999.996 | AU60: 1 | AV60: =1.2*13333.33 -> 15999.996 | AZ60: 1 | BA60: =1.2*13333.33 -> 15999.996 | BE60: 1 | BF60: =1.2*13333.33 -> 15999.996 | BJ60: 1 | BK60: =1.2*13333.33 -> 15999.996 | BO60: 1 | BP60: =1.2*13333.33 -> 15999.996 | BT60: 1 | BU60: =1.2*13333.33 -> 15999.996 | BY60: 1 | BZ60: =1.2*13333.33 -> 15999.996 | CD60: 1 | CE60: =1.2*13333.33 -> 15999.996 | CI60: 1 | CJ60: =1.2*13333.33 -> 15999.996 | CN60: 1 | CO60: =1.2*13333.33 -> 15999.996 | CS60: 1 | CT60: =1.2*13333.33 -> 15999.996 | CX60: 1 | CY60: =1.2*13333.33 -> 15999.996
C61: КП "Володимирський ринок" | D61: Стоянка а/транспорта | G61: 1 | H61: =1.2*10833.33 -> 12999.996 | L61: 1 | M61: =1.2*10833.33 -> 12999.996 | Q61: 1 | R61: =1.2*10833.33 -> 12999.996 | V61: 1 | W61: =1.2*10833.33 -> 12999.996 | AA61: 1 | AB61: =1.2*10833.33 -> 12999.996 | AF61: 1 | AG61: =1.2*10833.33 -> 12999.996 | AK61: 1 | AL61: =1.2*10833.33 -> 12999.996 | AP61: 1 | AQ61: =1.2*10833.33 -> 12999.996 | AU61: 1 | AV61: =1.2*10833.33 -> 12999.996 | AZ61: 1 | BA61: =1.2*10833.33 -> 12999.996 | BE61: 1 | BF61: =1.2*10833.33 -> 12999.996 | BJ61: 1 | BK61: =1.2*10833.33 -> 12999.996 | BO61: 1 | BP61: =1.2*10833.33 -> 12999.996 | BT61: 1 | BU61: =1.2*10833.33 -> 12999.996 | BY61: 1 | BZ61: =1.2*10833.33 -> 12999.996 | CD61: 1 | CE61: =1.2*10833.33 -> 12999.996 | CI61: 1 | CJ61: =1.2*10833.33 -> 12999.996 | CN61: 1 | CO61: =1.2*10833.33 -> 12999.996 | CS61: 1 | CT61: =1.2*10833.33 -> 12999.996 | CX61: 1 | CY61: =1.2*10833.33 -> 12999.996
B62: 41916045 | C62: ТОВ "КИЇВСЬКI ЕНЕРГЕТИЧНI ПОСЛУГИ" | D62: Активная ЭЭ | F62: =H62/G62 -> 5.2443958 | G62: 24371 | H62: 127811.17 | K62: =M62/L62 -> 5.3410318 | L62: 26933 | M62: 143850.01 | P62: =R62/Q62 -> 4.966392 | Q62: 47754 | R62: 237165.08 | S62: 148991.76 | T62: =2*187067.16 -> 374134.32 | U62: =W62/V62 -> 5.207724 | V62: 30000 | W62: 156231.72 | X62: 156231.72 | Z62: =AB62/AA62 -> 5.3410318 | AA62: 26933 | AB62: 143850.01 | AC62: 140488.56 | AE62: =AG62/AF62 -> 4.8199439 | AF62: 66721 | AG62: 321591.48 | AH62: =73941.42+148116.6 -> 222058.02 | AJ62: =AL62/AK62 -> 4.97922 | AK62: 64568 | AL62: 321498.28 | AM62: =233669.91+156628.08 -> 390297.99 | AO62: =AQ62/AP62 -> 5.9466953 | AP62: 4332 | AQ62: 25761.084 | AR62: 201186.36 | AT62: =AV62/AU62 -> 6.6107642 | AU62: 36064 | AV62: 238410.6 | AY62: =BA62/AZ62 -> 6.3494522 | AZ62: 31418 | BA62: 199487.09 | BB62: 185 192,35 | BD62: =BF62/BE62 -> 0 | BE62: 31387.6 | BF62: 0 | BG62: 176303.8 | BI62: =BK62/BJ62 -> 6.7715879 | BJ62: 63312 | BK62: 428722.78 | BL62: 176303.8 | BN62: =BP62/BO62 -> 6.3746279 | BO62: 38426 | BP62: 244951.45 | BS62: =BU62/BT62 -> 6.0268799 | BT62: 42672 | BU62: 257179.02 | BV62: 248 536,13 | BX62: =BZ62/BY62 -> 5.3410318 | BY62: 26933 | BZ62: 143850.01 | CA62: 248728.57 | CC62: =CE62/CD62 -> 5.3410318 | CD62: 26933 | CE62: 143850.01 | CH62: =CJ62/CI62 -> 5.3410318 | CI62: 26933 | CJ62: 143850.01 | CM62: =CO62/CN62 -> 5.3410318 | CN62: 26933 | CO62: 143850.01 | CR62: =CT62/CS62 -> 5.3410318 | CS62: 26933 | CT62: 143850.01 | CW62: =CY62/CX62 -> 5.3410318 | CX62: 26933 | CY62: 143850.01
C63: «ДТЕК КИЇВСЬКІ ЕЛЕКТРОМЕРЕЖІ» | D63: Реактивная ЭЭ | G63: 1 | H63: 1108 | L63: 1 | M63: 1091.08 | Q63: 1 | R63: 1 294,27 | V63: 1 | W63: 1454.496 | AA63: 1 | AB63: 1091.08 | AF63: 1 | AG63: 2 607,61 | AK63: 1 | AL63: 2 395,73 | AP63: 1 | AQ63: 1361.26 | AU63: 1 | AV63: 1662.31 | AZ63: 1 | BA63: 1533.29 | BE63: 1 | BF63: 1091.08 | BJ63: 1 | BK63: 2 586,88 | BO63: 1 | BP63: 1 472,59 | BT63: 1 | BU63: 1925.63 | BY63: 1 | BZ63: 1091.08 | CD63: 1 | CE63: 1091.08 | CI63: 1 | CJ63: 1091.08 | CN63: 1 | CO63: 1091.08 | CS63: 1 | CT63: 1091.08 | CX63: 1 | CY63: 1091.08
B64: 16290738 | C64: ООО "Варяг" | D64: ХВ | F64: =H64/G64 -> 30.38 | G64: =H64/30.38 -> 115.60632 | H64: 3512.12 | K64: =M64/L64 -> 31.062308 | L64: 104 | M64: 3230.48 | P64: =R64/Q64 -> 30.38 | Q64: =R64/30.38 -> 104.78473 | R64: 3183.36 | U64: =W64/V64 -> 30.175085 | V64: 118 | W64: 3560.66 | Z64: =AB64/AA64 -> 30.369504 | AA64: 121 | AB64: 3674.71 | AE64: =AG64/AF64 -> 30.546308 | AF64: 130 | AG64: 3971.02 | AJ64: =AL64/AK64 -> 30.38 | AK64: =AL64/30.38 -> 153.06715 | AL64: 4650.18 | AO64: =AQ64/AP64 -> 31.503455 | AP64: 110 | AQ64: 3465.38 | AT64: =AV64/AU64 -> 31.528609 | AU64: 115 | AV64: 3625.79 | AY64: =BA64/AZ64 -> 30.38 | AZ64: =BA64/30.38 -> 214.9131 | BA64: 6529.06 | BD64: =BF64/BE64 -> 30.38 | BE64: =BF64/30.38 -> 136.38743 | BF64: 4143.45 | BI64: =BK64/BJ64 -> 30.38 | BJ64: =BK64/30.38 -> 166.07801 | BK64: 5045.45 | BN64: =BP64/BO64 -> 30.37935 | BO64: 181.6 | BP64: 5516.89 | BS64: =BU64/BT64 -> 30.38 | BT64: =BU64/30.38 -> 115.60632 | BU64: 3512.12 | BX64: =BZ64/BY64 -> 30.38 | BY64: =BZ64/30.38 -> 115.60632 | BZ64: 3512.12 | CC64: =CE64/CD64 -> 30.38 | CD64: =CE64/30.38 -> 115.60632 | CE64: 3512.12 | CH64: =CJ64/CI64 -> 30.38 | CI64: =CJ64/30.38 -> 115.60632 | CJ64: 3512.12 | CM64: =CO64/CN64 -> 30.38 | CN64: =CO64/30.38 -> 115.60632 | CO64: 3512.12 | CR64: =CT64/CS64 -> 30.38 | CS64: =CT64/30.38 -> 115.60632 | CT64: 3512.12 | CW64: =CY64/CX64 -> 30.38 | CX64: =CY64/30.38 -> 115.60632 | CY64: 3512.12
A65: М13/1 | B65: п.г.т. Тарасовка, вул. Братьев Чмилив, 3А | C65: ПП "Обухівміськвторресурси" | D65: Вывоз ТБО | W65: 3289 | Y65: =SUM(W65:W67)*1.1 -> 123425.49 | AD65: =SUM(AB65:AB67)*1.1 -> 108251.23 | AG65: 1771 | AI65: =SUM(AG65:AG67)*1.1 -> 107204.24 | AL65: 1771 | AN65: =AN66*1.2 -> 137687.75 | AS65: =SUM(AQ65:AQ67)*1.1 -> 146356.85 | AX65: =SUM(AV65:AV67)*1.1 -> 162764.58 | BC65: =SUM(BA65:BA67)*1.1 -> 149687.97 | BH65: =SUM(BF65:BF67)*1.1 -> 143502.98 | BM65: =SUM(BK65:BK67)*1.1 -> 151008.01 | BR65: =SUM(BP65:BP67)*1.1 -> 146654.44 | BW65: =SUM(BU65:BU67)*1.1 -> 163767.16 | CB65: =SUM(BZ65:BZ67)*1.1 -> 99528.59 | CG65: =SUM(CE65:CE67)*1.1 -> 99528.59 | CL65: =SUM(CJ65:CJ67)*1.1 -> 99528.59 | CQ65: =SUM(CO65:CO67)*1.1 -> 99528.59 | CV65: =SUM(CT65:CT67)*1.1 -> 99528.59 | DA65: =SUM(CY65:CY67)*1.1 -> 99528.59
A66: Житлоекономія | B66: 32212775 | C66: ТОВ "Житлоекономія" | D66: Активная ЭЭ | F66: =H66/G66 -> 5.8423198 | G66: 15905 | H66: =1.2*(63460.95+13974.13) -> 92922.096 | K66: =M66/L66 -> 6.0346078 | L66: 12309 | M66: =1.2*(12048.54+49851.45) -> 74279.988 | P66: =R66/Q66 -> 5.7226078 | Q66: 14963 | R66: 85627.38 | U66: =W66/V66 -> 5.8906077 | V66: 17706 | W66: 104299.1 | Y66: =SUM(W65:W67)*1 -> 112204.99 | Z66: =AB66/AA66 -> 5.4826079 | AA66: 16592 | AB66: 90967.43 | AD66: =SUM(AB65:AB67)*1 -> 98410.21 | AE66: =AG66/AF66 -> 5.4466081 | AF66: 16742 | AG66: =1.2*(59601.52+16387.74) -> 91187.112 | AI66: =SUM(AG65:AG67)*1 -> 97458.402 | AJ66: =AL66/AK66 -> 5.9406242 | AK66: 17880 | AL66: 106218.36 | AN66: =SUM(AL65:AL67)*1 -> 114739.79 | AO66: =AQ66/AP66 -> 6.8646121 | AP66: 18588 | AQ66: 127599.41 | AS66: =SUM(AQ65:AQ67)*1 -> 133051.68 | AT66: =AV66/AU66 -> 7.4406122 | AU66: 19177 | AV66: 142688.62 | AX66: =SUM(AV65:AV67)*1 -> 147967.8 | AY66: =BA66/AZ66 -> 7.4286119 | AZ66: 17398 | BA66: 129242.99 | BC66: =SUM(BA65:BA67)*1 -> 136079.97 | BD66: =BF66/BE66 -> 7.6086117 | BE66: 17146 | BF66: =1.2*(83843.94+24870.44) -> 130457.26 | BH66: =SUM(BF65:BF67)*1 -> 130457.26 | BI66: =BK66/BJ66 -> 7.8380159 | BJ66: 17514 | BK66: 137275.01 | BM66: =SUM(BK65:BK67)*1 -> 137280.01 | BN66: =BP66/BO66 -> 7.2802925 | BO66: 17231 | BP66: 125446.72 | BR66: =SUM(BP65:BP67)*1 -> 133322.22 | BS66: =BU66/BT66 -> 7.6692004 | BT66: 18397 | BU66: 141090.28 | BW66: =SUM(BU65:BU67)*1 -> 148879.24 | BX66: =BZ66/BY66 -> 5.1223199 | BY66: 17663 | BZ66: =1.2*(59877.57+15518.71) -> 90475.536 | CB66: =SUM(BZ65:BZ67)*1 -> 90480.536 | CC66: =CE66/CD66 -> 5.1223199 | CD66: 17663 | CE66: =1.2*(59877.57+15518.71) -> 90475.536 | CG66: =SUM(CE65:CE67)*1 -> 90480.536 | CH66: =CJ66/CI66 -> 5.1223199 | CI66: 17663 | CJ66: =1.2*(59877.57+15518.71) -> 90475.536 | CL66: =SUM(CJ65:CJ67)*1 -> 90480.536 | CM66: =CO66/CN66 -> 5.1223199 | CN66: 17663 | CO66: =1.2*(59877.57+15518.71) -> 90475.536 | CQ66: =SUM(CO65:CO67)*1 -> 90480.536 | CR66: =CT66/CS66 -> 5.1223199 | CS66: 17663 | CT66: =1.2*(59877.57+15518.71) -> 90475.536 | CV66: =SUM(CT65:CT67)*1 -> 90480.536 | CW66: =CY66/CX66 -> 5.1223199 | CX66: 17663 | CY66: =1.2*(59877.57+15518.71) -> 90475.536 | DA66: =SUM(CY65:CY67)*1 -> 90480.536
B67: 30687118 | C67: КП "Боярка -Водоканал" | D67: ХВ | F67: =H67/G67 -> 62.387941 | G67: 68 | H67: 4242.38 | K67: =M67/L67 -> 62.388 | L67: 55 | M67: 3431.34 | Q67: 31 | R67: 4616.89 | U67: =W67/V67 -> 74.465968 | V67: 62 | W67: 4616.89 | Z67: =AB67/AA67 -> 86.543953 | AA67: 86 | AB67: 7442.78 | AE67: =AG67/AF67 -> 86.544038 | AF67: 52 | AG67: 4500.29 | AJ67: =AL67/AK67 -> 86.543974 | AK67: 78 | AL67: 6750.43 | AO67: =AQ67/AP67 -> 86.543968 | AP67: 63 | AQ67: 5452.27 | AT67: =AV67/AU67 -> 86.543934 | AU67: 61 | AV67: 5279.18 | AY67: =BA67/AZ67 -> 86.544051 | AZ67: 79 | BA67: 6836.98 | BD67: =BF67/BE67 -> #VALUE! | BE67: 80 | BF67: 6 923,52 | BI67: =BK67/BJ67 -> 0.11627907 | BJ67: 43 | BK67: 5 | BN67: =BP67/BO67 -> 86.543956 | BO67: 91 | BP67: 7875.5 | BS67: =BU67/BT67 -> 86.544 | BT67: 90 | BU67: 7788.96 | BX67: =BZ67/BY67 -> 0.11627907 | BY67: 43 | BZ67: 5 | CC67: =CE67/CD67 -> 0.11627907 | CD67: 43 | CE67: 5 | CH67: =CJ67/CI67 -> 0.11627907 | CI67: 43 | CJ67: 5 | CM67: =CO67/CN67 -> 0.11627907 | CN67: 43 | CO67: 5 | CR67: =CT67/CS67 -> 0.11627907 | CS67: 43 | CT67: 5 | CW67: =CY67/CX67 -> 0.11627907 | CX67: 43 | CY67: 5
A68: М14 | B68: г.Киев, ул.Светлая,3Д | C68: ТОВ "Еко-Грінко" | D68: Вывоз ТБО | W68: 2211 | Y68: =SUM(W68:W72)*1.1 -> 113247.2 | AD68: =SUM(AB68:AB72)*1.1 -> 112196.02 | AG68: 2211 | AI68: =SUM(AG68:AG72)*1.1 -> 107102.4 | AL68: 1769 | AN68: =AN69*1.2 -> 133473.36 | AQ68: 1769 | AS68: =SUM(AQ68:AQ72)*1.1 -> 142492.46 | AX68: =SUM(AV68:AV72)*1.1 -> 163428.6 | BC68: =SUM(BA68:BA72)*1.1 -> 161806.14 | BH68: =SUM(BF68:BF72)*1.1 -> 147748.41 | BM68: =SUM(BK68:BK72)*1.1 -> 157973.55 | BR68: =SUM(BP68:BP72)*1.1 -> 167296.38 | BW68: =SUM(BU68:BU72)*1.1 -> 178834.66 | CB68: =SUM(BZ68:BZ72)*1.1 -> 75968.321 | CG68: =SUM(CE68:CE72)*1.1 -> 75968.321 | CL68: =SUM(CJ68:CJ72)*1.1 -> 75968.321 | CQ68: =SUM(CO68:CO72)*1.1 -> 75968.321 | CV68: =SUM(CT68:CT72)*1.1 -> 75968.321 | DA68: =SUM(CY68:CY72)*1.1 -> 75968.321
B69: 41305755 | C69: ОК "ОБК Схидна Брама" | D69: Экспл. расходы | F69: =H69/G69 -> 9.1199968 | G69: 632.6 | H69: 5769.31 | K69: =M69/L69 -> 9.1600063 | L69: 632.6 | M69: 5794.62 | P69: =R69/Q69 -> 9.0100063 | Q69: 632.6 | R69: 5699.73 | U69: =W69/V69 -> 9.1199968 | V69: 632.6 | W69: 5769.31 | Y69: =SUM(W68:W72)*1 -> 102952 | Z69: =AB69/AA69 -> 9.4199968 | AA69: 632.6 | AB69: 5959.09 | AD69: =SUM(AB68:AB72)*1 -> 101996.38 | AE69: =AG69/AF69 -> 9.2899937 | AF69: 632.6 | AG69: 5876.85 | AI69: =SUM(AG68:AG72)*1 -> 97365.82 | AJ69: =AL69/AK69 -> 9.25 | AK69: 632.6 | AL69: 5851.55 | AN69: =SUM(AL68:AL72)*1 -> 111227.8 | AO69: =AQ69/AP69 -> 9.4199968 | AP69: 632.6 | AQ69: 5959.09 | AS69: =SUM(AQ68:AQ72)*1 -> 129538.6 | AT69: =AV69/AU69 -> 8.8300032 | AU69: 632.6 | AV69: 5585.86 | AX69: =SUM(AV68:AV72)*1 -> 148571.45 | AY69: =BA69/AZ69 -> 9.1100063 | AZ69: 632.6 | BA69: 5762.99 | BC69: =SUM(BA68:BA72)*1 -> 147096.49 | BD69: =BF69/BE69 -> 9.9699968 | BE69: 632.6 | BF69: 6307.02 | BH69: =SUM(BF68:BF72)*1 -> 134316.74 | BI69: =BK69/BJ69 -> 10.010006 | BJ69: 632.6 | BK69: 6332.33 | BM69: =SUM(BK68:BK72)*1 -> 143612.32 | BN69: =BP69/BO69 -> 10.139994 | BO69: 632.6 | BP69: 6414.56 | BR69: =SUM(BP68:BP72)*1 -> 152087.62 | BS69: =BU69/BT69 -> 10.060006 | BT69: 632.6 | BU69: 6363.96 | BW69: =SUM(BU68:BU72)*1 -> 162576.96 | BX69: =BZ69/BY69 -> 9.1199968 | BY69: 632.6 | BZ69: 5769.31 | CB69: =SUM(BZ68:BZ72)*1 -> 69062.11 | CC69: =CE69/CD69 -> 9.1199968 | CD69: 632.6 | CE69: 5769.31 | CG69: =SUM(CE68:CE72)*1 -> 69062.11 | CH69: =CJ69/CI69 -> 9.1199968 | CI69: 632.6 | CJ69: 5769.31 | CL69: =SUM(CJ68:CJ72)*1 -> 69062.11 | CM69: =CO69/CN69 -> 9.1199968 | CN69: 632.6 | CO69: 5769.31 | CQ69: =SUM(CO68:CO72)*1 -> 69062.11 | CR69: =CT69/CS69 -> 9.1199968 | CS69: 632.6 | CT69: 5769.31 | CV69: =SUM(CT68:CT72)*1 -> 69062.11 | CW69: =CY69/CX69 -> 9.1199968 | CX69: 632.6 | CY69: 5769.31 | DA69: =SUM(CY68:CY72)*1 -> 69062.11
C70: ОК "ОБК Схидна Брама" | D70: Поточный ремонт | G70: 0 | H70: 0 | L70: 0 | M70: 0 | Q70: 0 | R70: 0 | V70: 1 | W70: 0 | AA70: 1 | AB70: 0 | AF70: 1 | AG70: 0 | AK70: 1 | AL70: 0 | AP70: 0 | AQ70: 0 | AU70: 0 | AV70: 0 | AZ70: 1 | BA70: 0 | BE70: 1 | BF70: 0 | BJ70: 1 | BK70: 0 | BO70: 1 | BP70: 0 | BT70: 1 | BU70: 0 | BY70: 1 | BZ70: 0 | CD70: 1 | CE70: 0 | CI70: 1 | CJ70: 0 | CN70: 1 | CO70: 0 | CS70: 1 | CT70: 0 | CX70: 1 | CY70: 0
A71: ЯСНО "КИЇВСЬКІ ЕНЕРГЕТИЧНІ ПОСЛУГИ" | C71: ОК "ОБК Схидна Брама" | D71: Активная ЭЭ | F71: =H71/G71 -> 5.345604 | G71: 11556 | H71: 61773.8 | K71: =M71/L71 -> 5.4421202 | L71: 14664 | M71: 79803.25 | P71: =R71/Q71 -> 5.4227759 | Q71: 15912 | R71: 86287.21 | U71: =W71/V71 -> 5.3173321 | V71: 17358 | W71: 92298.25 | Z71: =AB71/AA71 -> 5.1471122 | AA71: 18204 | AB71: 93698.03 | AE71: =AG71/AF71 -> 4.9689001 | AF71: 17466 | AG71: 86786.81 | AJ71: =AL71/AK71 -> 5.3541959 | AK71: 18840 | AL71: 100873.05 | AO71: =AQ71/AP71 -> 5.8093438 | AP71: 20466 | AQ71: 118894.03 | AT71: =AV71/AU71 -> 6.5771759 | AU71: 21384 | AV71: 140646.33 | AY71: =BA71/AZ71 -> 6.6156478 | AZ71: 20964 | BA71: 138690.44 | BD71: =BF71/BE71 -> 6.8845677 | BE71: 18276 | BF71: 125822.36 | BI71: =BK71/BJ71 -> 7.0311479 | BJ71: 19140 | BK71: 134576.17 | BN71: =BP71/BO71 -> 7.1635918 | BO71: 19962 | BP71: 142999.62 | BS71: =BU71/BT71 -> 6.3568918 | BT71: 24072 | BU71: 153023.1 | BX71: =BZ71/BY71 -> 5.345604 | BY71: 11556 | BZ71: 61773.8 | CC71: =CE71/CD71 -> 5.345604 | CD71: 11556 | CE71: 61773.8 | CH71: =CJ71/CI71 -> 5.345604 | CI71: 11556 | CJ71: 61773.8 | CM71: =CO71/CN71 -> 5.345604 | CN71: 11556 | CO71: 61773.8 | CR71: =CT71/CS71 -> 5.345604 | CS71: 11556 | CT71: 61773.8 | CW71: =CY71/CX71 -> 5.345604 | CX71: 11556 | CY71: 61773.8
C72: ОК "ОБК Схидна Брама" | D72: ХВ | F72: =H72/G72 -> 30.38 | G72: 50 | H72: 1519 | K72: =M72/L72 -> 30.38 | L72: 69 | M72: =1115.04+981.18 -> 2096.22 | P72: =R72/Q72 -> 30.38 | Q72: 67 | R72: =1082.72+952.74 -> 2035.46 | U72: =W72/V72 -> 30.38 | V72: 88 | W72: 2673.44 | Z72: =AB72/AA72 -> 30.38 | AA72: 77 | AB72: =1244.32+1094.94 -> 2339.26 | AE72: =AG72/AF72 -> 30.38 | AF72: 82 | AG72: =1325.12+1166.04 -> 2491.16 | AJ72: =AL72/AK72 -> 30.38 | AK72: 90 | AL72: =1454.4+1279.8 -> 2734.2 | AO72: =AQ72/AP72 -> 30.38 | AP72: 96 | AQ72: =1551.36+1365.12 -> 2916.48 | AT72: =AV72/AU72 -> 30.38 | AU72: 77 | AV72: =(1244.32+1094.94) -> 2339.26 | AY72: =BA72/AZ72 -> 30.38 | AZ72: 87 | BA72: =1405.92+1237.14 -> 2643.06 | BD72: =BF72/BE72 -> 30.38 | BE72: 72 | BF72: =1163.52+1023.84 -> 2187.36 | BI72: =BK72/BJ72 -> 30.38 | BJ72: 89 | BK72: =1438.24+1265.58 -> 2703.82 | BN72: =BP72/BO72 -> 30.38 | BO72: 88 | BP72: =1422.08+1251.36 -> 2673.44 | BS72: =BU72/BT72 -> 30.38 | BT72: 105 | BU72: =1696.8+1493.1 -> 3189.9 | BX72: =BZ72/BY72 -> 30.38 | BY72: 50 | BZ72: 1519 | CC72: =CE72/CD72 -> 30.38 | CD72: 50 | CE72: 1519 | CH72: =CJ72/CI72 -> 30.38 | CI72: 50 | CJ72: 1519 | CM72: =CO72/CN72 -> 30.38 | CN72: 50 | CO72: 1519 | CR72: =CT72/CS72 -> 30.38 | CS72: 50 | CT72: 1519 | CW72: =CY72/CX72 -> 30.38 | CX72: 50 | CY72: 1519
B73: г. Киев, ул. Шолом- Алейхема, 10А | C73: ТОВ "Еко-Грінко" | D73: Вывоз ТБО | W73: 2211 | Y73: =SUM(W73:W77)*1.1 -> 210001.92 | AB73: 1769 | AD73: =SUM(AB73:AB77)*1.1 -> 89267.51 | AG73: 1769 | AI73: =AI74*1.1 -> 192016.27 | AL73: 1769 | AN73: =AN74*1.2 -> 352684.47 | AQ73: 2211 | AS73: =SUM(AQ73:AQ77)*1.1 -> 234785.44 | AX73: =SUM(AV73:AV77)*1.1 -> 270527.26 | BC73: =SUM(BA73:BA77)*1.1 -> 243299.26 | BH73: =SUM(BF73:BF77)*1.1 -> 255604.02 | BM73: =SUM(BK73:BK77)*1.1 -> 294671.57 | BR73: =SUM(BP73:BP77)*1.1 -> 311357.82 | BW73: =SUM(BU73:BU77)*1.1 -> 276504.81 | CB73: =SUM(BZ73:BZ77)*1.1 -> 139423.59 | CG73: =SUM(CE73:CE77)*1.1 -> 139423.59 | CL73: =SUM(CJ73:CJ77)*1.1 -> 139423.59 | CQ73: =SUM(CO73:CO77)*1.1 -> 139423.59 | CV73: =SUM(CT73:CT77)*1.1 -> 139423.59 | DA73: =SUM(CY73:CY77)*1.1 -> 139423.59
A74: М15 | B74: 41916045 | C74: ТОВ "КИЇВСЬКI ЕНЕРГЕТИЧНI ПОСЛУГИ" | D74: Активная ЭЭ | F74: =H74/G74 -> 5.3077199 | G74: 23162 | H74: 122937.41 | I74: 85373.2 | K74: =M74/L74 -> 5.3685481 | L74: 25010 | M74: 134267.39 | N74: 134267.38 | P74: =R74/Q74 -> 4.9663921 | Q74: 29958 | R74: 148783.18 | S74: 148783.18 | U74: =W74/V74 -> 5.2077238 | V74: 35580 | W74: 185290.81 | X74: 185290.81 | Y74: =SUM(W73:W77)*1 -> 190910.84 | Z74: =AB74/AA74 -> 4.6829522 | AA74: 15308 | AB74: 71686.632 | AC74: 71686.632 | AD74: =SUM(AB73:AB77)*1 -> 81152.282 | AE74: =AG74/AF74 -> 4.8199443 | AF74: 26842 | AG74: 129376.94 | AH74: =37729.81+132524.86 -> 170254.67 | AI74: =SUM(AG75:AG77)+AH74+AG73*1 -> 174560.25 | AJ74: =AL74/AK74 -> 4.9792202 | AK74: 32794 | AL74: 163288.55 | AM74: =118200.47+171215.376 -> 289415.85 | AN74: =SUM(AL75:AL77)+AM74+AL73*1 -> 293903.73 | AO74: =AQ74/AP74 -> 5.9466959 | AP74: 34712 | AQ74: 206421.71 | AR74: 232786.03 | AS74: =SUM(AQ73:AQ77)*1 -> 213441.31 | AT74: =AV74/AU74 -> 6.6107651 | AU74: 36479 | AV74: 241154.1 | AW74: 85373.2 | AX74: =SUM(AV73:AV77)*1 -> 245933.87 | AY74: =BA74/AZ74 -> 6.3494519 | AZ74: 34060 | BA74: 216262.33 | BB74: 180 218,61 | BC74: =SUM(BA73:BA77)*1 -> 221181.14 | BD74: =BF74/BE74 -> 6.2037238 | BE74: 36670 | BF74: 227490.55 | BG74: 180096.69 | BH74: =SUM(BF73:BF77)*1 -> 232367.29 | BI74: =BK74/BJ74 -> 6.6640678 | BJ74: 40123 | BK74: 267382.39 | BL74: 275 067,72 | BM74: =SUM(BK73:BK77)*1 -> 267883.24 | BN74: =BP74/BO74 -> 6.299292 | BO74: 44459 | BP74: 280060.22 | BQ74: 85373.2 | BR74: =SUM(BP73:BP77)*1 -> 283052.56 | BS74: =BU74/BT74 -> 5.8837799 | BT74: 41909 | BU74: 246583.33 | BV74: 284207.71 | BW74: =SUM(BU73:BU77)*1 -> 251368.01 | BX74: =BZ74/BY74 -> 5.3077199 | BY74: 23162 | BZ74: 122937.41 | CA74: 305 296,48 | CB74: =SUM(BZ73:BZ77)*1 -> 126748.72 | CC74: =CE74/CD74 -> 5.3077199 | CD74: 23162 | CE74: 122937.41 | CF74: 85373.2 | CG74: =SUM(CE73:CE77)*1 -> 126748.72 | CH74: =CJ74/CI74 -> 5.3077199 | CI74: 23162 | CJ74: 122937.41 | CK74: 85373.2 | CL74: =SUM(CJ73:CJ77)*1 -> 126748.72 | CM74: =CO74/CN74 -> 5.3077199 | CN74: 23162 | CO74: 122937.41 | CP74: 85373.2 | CQ74: =SUM(CO73:CO77)*1 -> 126748.72 | CR74: =CT74/CS74 -> 5.3077199 | CS74: 23162 | CT74: 122937.41 | CU74: 85373.2 | CV74: =SUM(CT73:CT77)*1 -> 126748.72 | CW74: =CY74/CX74 -> 5.3077199 | CX74: 23162 | CY74: 122937.41 | CZ74: 85373.2 | DA74: =SUM(CY73:CY77)*1 -> 126748.72
B75: 41946011 | C75: «ДТЕК КИЇВСЬКІ ЕЛЕКТРОМЕРЕЖІ» | D75: Реактивная ЭЭ | H75: 818.97 | M75: 1142.66 | R75: 1 383,67 | W75: 416.688 | AB75: 2790.12 | AG75: 1 581,78 | AL75: 1 692,90 | AQ75: 1968.18 | AV75: 2273.58 | AZ75: 1 | BA75: 2412.62 | BF75: 2157.86 | BK75: 2 166,12 | BP75: 1 980,15 | BU75: 1944.26 | BZ75: 818.97 | CE75: 818.97 | CJ75: 818.97 | CO75: 818.97 | CT75: 818.97 | CY75: 818.97
B76: 26112340 | C76: ПАТ АК "Київводоканал" ТОВ Легион 2015 | D76: Обс. вн. ВС | G76: 1 | H76: =500.85 -> 500.85 | L76: 1 | M76: =500.85 -> 500.85 | Q76: 1 | R76: =500.85 -> 500.85 | V76: 1 | W76: =500.85 -> 500.85 | AA76: 1 | AB76: =500.85 -> 500.85 | AF76: 1 | AG76: =500.85 -> 500.85 | AK76: 1 | AL76: =500.85 -> 500.85 | AP76: 1 | AQ76: =500.85 -> 500.85 | AU76: 1 | AV76: =500.85 -> 500.85 | AZ76: 1 | BA76: =500.85 -> 500.85 | BE76: 1 | BF76: =500.85 -> 500.85 | BJ76: 1 | BK76: =500.85 -> 500.85 | BO76: 1 | BP76: =500.85 -> 500.85 | BT76: 1 | BU76: =500.85 -> 500.85 | BY76: 1 | BZ76: =500.85 -> 500.85 | CD76: 1 | CE76: =500.85 -> 500.85 | CI76: 1 | CJ76: =500.85 -> 500.85 | CN76: 1 | CO76: =500.85 -> 500.85 | CS76: 1 | CT76: =500.85 -> 500.85 | CX76: 1 | CY76: =500.85 -> 500.85
A77: 24791/5-10 від 26.03.2021 | B77: 03327629 | C77: ПАТ АК "Київводоканал" ТОВ Легион 2015 | D77: ХВ | F77: =H77/G77 -> 32.607195 | G77: 82 | H77: 2673.79 | K77: =M77/L77 -> 30.384024 | L77: 82 | M77: 2491.49 | P77: =R77/Q77 -> 30.384024 | Q77: 82 | R77: 2491.49 | U77: =W77/V77 -> 30.384024 | V77: 82 | W77: 2491.49 | Z77: =AB77/AA77 -> 30.384 | AA77: 145 | AB77: 4405.68 | AE77: =AG77/AF77 -> 30.38403 | AF77: 67 | AG77: 2035.73 | AJ77: =AL77/AK77 -> 30.383973 | AK77: 73 | AL77: 2218.03 | AO77: =AQ77/AP77 -> 30.384026 | AP77: 77 | AQ77: 2339.57 | AT77: =AV77/AU77 -> 30.383939 | AU77: 66 | AV77: 2005.34 | AY77: =BA77/AZ77 -> 30.383939 | AZ77: 66 | BA77: 2005.34 | BB77: 34 412,40 | BD77: =BF77/BE77 -> 30.383973 | BE77: 73 | BF77: 2218.03 | BI77: =BK77/BJ77 -> #VALUE! | BJ77: 147 | BK77: 4 466,45 | BN77: =BP77/BO77 -> 33.668784 | BO77: 74 | BP77: 2491.49 | BS77: =BU77/BT77 -> 30.384026 | BT77: 77 | BU77: 2339.57 | BX77: =BZ77/BY77 -> 30.384024 | BY77: 82 | BZ77: 2491.49 | CC77: =CE77/CD77 -> 30.384024 | CD77: 82 | CE77: 2491.49 | CH77: =CJ77/CI77 -> 30.384024 | CI77: 82 | CJ77: 2491.49 | CM77: =CO77/CN77 -> 30.384024 | CN77: 82 | CO77: 2491.49 | CR77: =CT77/CS77 -> 30.384024 | CS77: 82 | CT77: 2491.49 | CW77: =CY77/CX77 -> 30.384024 | CX77: 82 | CY77: 2491.49
A78: М16 | B78: г. Киев. пр. Ватутина, 11а | C78: ТОВ "Еко-Грінко" | D78: Вывоз ТБО | W78: 1106 | Y78: =SUM(W78:W82)*1.1 -> 72387.146 | AB78: 442 | AD78: =SUM(AB78:AB82)*1.1 -> 65922.881 | AG78: 1327 | AI78: =SUM(AG78:AG82)*1.1 -> 74654.93 | AL78: 442 | AN78: =AN79*1.2 -> 88780.733 | AQ78: 663 | AS78: =SUM(AQ78:AQ82)*1.1 -> 88698.85 | AX78: =SUM(AV78:AV82)*1.1 -> 114018.47 | BC78: =SUM(BA78:BA82)*1.1 -> 104214.11 | BH78: =SUM(BF78:BF82)*1.1 -> 98438.538 | BM78: =SUM(BK78:BK82)*1.1 -> 106565.7 | BR78: =SUM(BP78:BP82)*1.1 -> 101917.94 | BW78: =SUM(BU78:BU82)*1.1 -> 121155.61 | CB78: =SUM(BZ78:BZ82)*1.1 -> 50789.457 | CG78: =SUM(CE78:CE82)*1.1 -> 50789.457 | CL78: =SUM(CJ78:CJ82)*1.1 -> 50789.457 | CQ78: =SUM(CO78:CO82)*1.1 -> 50789.457 | CV78: =SUM(CT78:CT82)*1.1 -> 50789.457 | DA78: =SUM(CY78:CY82)*1.1 -> 50789.457
A79: ЯСНО "КИЇВСЬКІ ЕНЕРГЕТИЧНІ ПОСЛУГИ" | B79: 37985767 | C79: ТОВ "Сіметра" | D79: Экспл. расходы | G79: 1 | H79: 4720 | L79: 1 | M79: =3933.33*1.2 -> 4719.996 | Q79: 1 | R79: =1.2*3933.33 -> 4719.996 | V79: 1 | W79: =3933.33*1.2 -> 4719.996 | Y79: =SUM(W78:W82)*1 -> 65806.496 | AA79: 1 | AB79: =1.2*3933.33 -> 4719.996 | AD79: =SUM(AB78:AB82)*1 -> 59929.892 | AF79: 1 | AG79: =1.2*3933.33 -> 4719.996 | AI79: =SUM(AG78:AG82)*1 -> 67868.118 | AK79: 1 | AL79: =1.2*3933.33 -> 4719.996 | AN79: =SUM(AL78:AL82)*1 -> 73983.944 | AP79: 1 | AQ79: =1.2*3933.33 -> 4719.996 | AS79: =SUM(AQ78:AQ82)*1 -> 80635.318 | AU79: 1 | AV79: =1.2*4070.54 -> 4884.648 | AX79: =SUM(AV78:AV82)*1 -> 103653.15 | AZ79: 1 | BA79: =1.2*3933.33 -> 4719.996 | BC79: =SUM(BA78:BA82)*1 -> 94740.1 | BE79: 1 | BF79: =1.2*3933.33 -> 4719.996 | BH79: =SUM(BF78:BF82)*1 -> 89489.58 | BJ79: 1 | BK79: =1.2*(3933.33+88.27+341.88+68.87) -> 5318.82 | BM79: =SUM(BK78:BK82)*1 -> 96877.912 | BO79: 1 | BP79: =1.2*(3933.33+108.83) -> 4850.592 | BR79: =SUM(BP78:BP82)*1 -> 92652.676 | BT79: 1 | BU79: =1.2*(3933.33+108.83) -> 4850.592 | BW79: =SUM(BU78:BU82)*1 -> 110141.46 | BY79: 1 | BZ79: 4720 | CB79: =SUM(BZ78:BZ82)*1 -> 46172.234 | CD79: 1 | CE79: 4720 | CG79: =SUM(CE78:CE82)*1 -> 46172.234 | CI79: 1 | CJ79: 4720 | CL79: =SUM(CJ78:CJ82)*1 -> 46172.234 | CN79: 1 | CO79: 4720 | CQ79: =SUM(CO78:CO82)*1 -> 46172.234 | CS79: 1 | CT79: 4720 | CV79: =SUM(CT78:CT82)*1 -> 46172.234 | CX79: 1 | CY79: 4720 | DA79: =SUM(CY78:CY82)*1 -> 46172.234
A80: ЯСНО "КИЇВСЬКІ ЕНЕРГЕТИЧНІ ПОСЛУГИ" | D80: Активная ЭЭ | F80: =H80/G80 -> 5.2053482 | G80: 7870 | H80: 40966.09 | K80: =M80/L80 -> 5.3685476 | L80: 10080 | M80: 54114.96 | P80: =R80/Q80 -> 4.9663919 | Q80: 10640 | R80: 52842.41 | U80: =W80/V80 -> 5.1477604 | V80: 11520 | W80: 59302.2 | Z80: =AB80/AA80 -> 4.6829527 | AA80: 11576 | AB80: 54209.86 | AE80: =AG80/AF80 -> 4.819944 | AF80: 12680 | AG80: 61116.89 | AJ80: =AL80/AK80 -> 4.9792201 | AK80: 13720 | AL80: 68314.9 | AO80: =AQ80/AP80 -> 5.9466959 | AP80: 12560 | AQ80: 74690.5 | AT80: =AV80/AU80 -> 6.6107643 | AU80: 14890 | AV80: 98434.28 | AY80: =BA80/AZ80 -> 6.3350523 | AZ80: 14140 | BA80: 89577.64 | BD80: =BF80/BE80 -> 6.4589279 | BE80: 13058 | BF80: 84340.68 | BI80: =BK80/BJ80 -> 6.8756886 | BJ80: 13281 | BK80: 91316.02 | BN80: =BP80/BO80 -> 6.4709521 | BO80: 13517 | BP80: 87467.86 | BS80: =BU80/BT80 -> 6.1145402 | BT80: 17180 | BU80: 105047.8 | BX80: =BZ80/BY80 -> 5.2053482 | BY80: 7870 | BZ80: 40966.09 | CC80: =CE80/CD80 -> 5.2053482 | CD80: 7870 | CE80: 40966.09 | CH80: =CJ80/CI80 -> 5.2053482 | CI80: 7870 | CJ80: 40966.09 | CM80: =CO80/CN80 -> 5.2053482 | CN80: 7870 | CO80: 40966.09 | CR80: =CT80/CS80 -> 5.2053482 | CS80: 7870 | CT80: 40966.09 | CW80: =CY80/CX80 -> 5.2053482 | CX80: 7870 | CY80: 40966.09
D81: Обс. вн. ВС | H81: 0 | M81: 0 | R81: =1.2*166.94 -> 200.328 | W81: =1.2*160.13 -> 192.156 | AB81: =1.2*110.55 -> 132.66 | AG81: =1.2*(116.31+90.75) -> 248.472 | AL81: =1.2*118.7 -> 142.44 | AQ81: =1.2*130.41+101.73 -> 258.222 | AV81: 0 | BA81: =1.2*90.2 -> 108.24 | BF81: 0 | BK81: 0 | BP81: 0 | BU81: 0 | BZ81: 0 | CE81: 0 | CJ81: 0 | CO81: 0 | CT81: 0 | CY81: 0
D82: ХВ | F82: =H82/G82 -> 38.89152 | G82: 12.5 | H82: =1.2*405.12 -> 486.144 | K82: =M82/L82 -> 36.169714 | L82: 14 | M82: =1.2*(278.52+143.46) -> 506.376 | P82: =R82/Q82 -> 35.908364 | Q82: 11 | R82: =1.2*329.16 -> 394.992 | U82: =W82/V82 -> 38.89152 | V82: 12.5 | W82: =1.2*405.12 -> 486.144 | Z82: =AB82/AA82 -> 34.03008 | AA82: 12.5 | AB82: =1.2*354.48 -> 425.376 | AE82: =AG82/AF82 -> 41.432727 | AF82: 11 | AG82: =1.2*379.8 -> 455.76 | AJ82: =AL82/AK82 -> 30.384 | AK82: 12 | AL82: =1.2*303.84 -> 364.608 | AO82: =AQ82/AP82 -> 30.36 | AP82: 10 | AQ82: =1.2*253 -> 303.6 | AT82: =AV82/AU82 -> 30.384 | AU82: 11 | AV82: =1.2*278.52 -> 334.224 | AY82: =BA82/AZ82 -> 30.384 | AZ82: 11 | BA82: =1.2*278.52 -> 334.224 | BD82: =BF82/BE82 -> 34.31232 | BE82: 12.5 | BF82: =1.2*278.52+94.68 -> 428.904 | BI82: =BK82/BJ82 -> 41.908966 | BJ82: 5.8 | BK82: =1.2*202.56 -> 243.072 | BN82: =BP82/BO82 -> 26.73792 | BO82: 12.5 | BP82: =1.2*(278.52) -> 334.224 | BS82: =BU82/BT82 -> 30.384 | BT82: 8 | BU82: =1.2*202.56 -> 243.072 | BX82: =BZ82/BY82 -> 38.89152 | BY82: 12.5 | BZ82: =1.2*405.12 -> 486.144 | CC82: =CE82/CD82 -> 38.89152 | CD82: 12.5 | CE82: =1.2*405.12 -> 486.144 | CH82: =CJ82/CI82 -> 38.89152 | CI82: 12.5 | CJ82: =1.2*405.12 -> 486.144 | CM82: =CO82/CN82 -> 38.89152 | CN82: 12.5 | CO82: =1.2*405.12 -> 486.144 | CR82: =CT82/CS82 -> 38.89152 | CS82: 12.5 | CT82: =1.2*405.12 -> 486.144 | CW82: =CY82/CX82 -> 38.89152 | CX82: 12.5 | CY82: =1.2*405.12 -> 486.144
A83: М17 | B83: г.Обухов, ул. Каштановая, 6/1б | C83: ПП "Обухівміськвторресурси" | D83: Вывоз ТБО | W83: 1518 | Y83: =SUM(W83:W87)*1.1 -> 195191.02 | AB83: 506 | AD83: =SUM(AB83:AB87)*1.1 -> 126136.44 | AG83: 506 | AI83: =SUM(AG83:AG87)*1.1 -> 148567.55 | AL83: 506 | AN83: =AN84*1.2 -> 180732.62 | AS83: =SUM(AQ83:AQ87)*1.1 -> 205262.87 | AX83: =SUM(AV83:AV87)*1.1 -> 198965.16 | BC83: =SUM(BA83:BA87)*1.1 -> 243802.49 | BH83: =SUM(BF83:BF87)*1.1 -> 243802.49 | BM83: =SUM(BK83:BK87)*1.1 -> 243802.49 | BR83: =SUM(BP83:BP87)*1.1 -> 243802.49 | BW83: =SUM(BU83:BU87)*1.1 -> 243802.49 | CB83: =SUM(BZ83:BZ87)*1.1 -> 243802.49 | CG83: =SUM(CE83:CE87)*1.1 -> 243802.49 | CL83: =SUM(CJ83:CJ87)*1.1 -> 243802.49 | CQ83: =SUM(CO83:CO87)*1.1 -> 243802.49 | CV83: =SUM(CT83:CT87)*1.1 -> 243802.49 | DA83: =SUM(CY83:CY87)*1.1 -> 243802.49
B84: 2988918516 | C84: ФОП Вафін В.О. / ФОП Мількевич | D84: Активная ЭЭ | F84: =H84/G84 -> 5.7999999 | G84: 15783.04 | H84: 91541.63 | K84: =M84/L84 -> 5.87 | L84: 17024 | M84: 99930.88 | P84: =R84/Q84 -> 5.5923 | Q84: 20697.6 | R84: 115747.19 | U84: =W84/V84 -> 5.7965 | V84: 22713.6 | W84: 131659.38 | Y84: =SUM(W83:W87)*1 -> 177446.38 | Z84: =AB84/AA84 -> 5.4100001 | AA84: 20876.8 | AB84: 112943.49 | AD84: =SUM(AB83:AB87)*1 -> 114669.49 | AE84: =AG84/AF84 -> 5.4700001 | AF84: 24326.4 | AG84: 133065.41 | AI84: =SUM(AG83:AG87)*1 -> 135061.41 | AJ84: =AL84/AK84 -> 5.7479999 | AK84: 25939.2 | AL84: 149098.52 | AN84: =SUM(AL83:AL87)*1 -> 150610.52 | AO84: =AQ84/AP84 -> 6.964 | AP84: 26566.4 | AQ84: 185008.41 | AS84: =SUM(AQ83:AQ87)*1 -> 186602.61 | AT84: =AV84/AU84 -> 6.964 | AU84: 25760 | AV84: 179392.64 | AX84: =SUM(AV83:AV87)*1 -> 180877.42 | AY84: =BA84/AZ84 -> 5.7999999 | AZ84: 15783.04 | BA84: 91541.63 | BC84: =SUM(BA83:BA87)*1 -> 221638.63 | BD84: =BF84/BE84 -> 5.7999999 | BE84: 15783.04 | BF84: 91541.63 | BH84: =SUM(BF83:BF87)*1 -> 221638.63 | BI84: =BK84/BJ84 -> 5.7999999 | BJ84: 15783.04 | BK84: 91541.63 | BM84: =SUM(BK83:BK87)*1 -> 221638.63 | BN84: =BP84/BO84 -> 5.7999999 | BO84: 15783.04 | BP84: 91541.63 | BR84: =SUM(BP83:BP87)*1 -> 221638.63 | BS84: =BU84/BT84 -> 5.7999999 | BT84: 15783.04 | BU84: 91541.63 | BW84: =SUM(BU83:BU87)*1 -> 221638.63 | BX84: =BZ84/BY84 -> 5.7999999 | BY84: 15783.04 | BZ84: 91541.63 | CB84: =SUM(BZ83:BZ87)*1 -> 221638.63 | CC84: =CE84/CD84 -> 5.7999999 | CD84: 15783.04 | CE84: 91541.63 | CG84: =SUM(CE83:CE87)*1 -> 221638.63 | CH84: =CJ84/CI84 -> 5.7999999 | CI84: 15783.04 | CJ84: 91541.63 | CL84: =SUM(CJ83:CJ87)*1 -> 221638.63 | CM84: =CO84/CN84 -> 5.7999999 | CN84: 15783.04 | CO84: 91541.63 | CQ84: =SUM(CO83:CO87)*1 -> 221638.63 | CR84: =CT84/CS84 -> 5.7999999 | CS84: 15783.04 | CT84: 91541.63 | CV84: =SUM(CT83:CT87)*1 -> 221638.63 | CW84: =CY84/CX84 -> 5.7999999 | CX84: 15783.04 | CY84: 91541.63 | DA84: =SUM(CY83:CY87)*1 -> 221638.63
D85: Уборка помещения | G85: 1 | H85: 500 | L85: 1 | M85: 500 | Q85: 1 | R85: 500 | V85: 1 | W85: 500 | AA85: 1 | AB85: 500 | AF85: 1 | AG85: 500 | AK85: 1 | AL85: 500 | AP85: 1 | AQ85: 500 | AU85: 1 | AV85: 500 | AZ85: 1 | BA85: 500 | BE85: 1 | BF85: 500 | BJ85: 1 | BK85: 500 | BO85: 1 | BP85: 500 | BT85: 1 | BU85: 500 | BY85: 1 | BZ85: 500 | CD85: 1 | CE85: 500 | CI85: 1 | CJ85: 500 | CN85: 1 | CO85: 500 | CS85: 1 | CT85: 500 | CX85: 1 | CY85: 500
D86: Тепловая энергия | F86: 850 | G86: 151.62 | H86: 128877 | K86: 850 | L86: 151.62 | M86: 128877 | P86: 850 | Q86: 151.62 | R86: 128877 | U86: 850 | V86: 50.54 | W86: 42959 | Z86: 850 | AA86: 0 | AB86: 0 | AE86: 850 | AF86: 0 | AG86: 0 | AJ86: 850 | AK86: 0 | AL86: 0 | AO86: 850 | AP86: 0 | AT86: 850 | AU86: 0 | AV86: 0 | AY86: 850 | AZ86: 151.62 | BA86: 128877 | BD86: 850 | BE86: 151.62 | BF86: 128877 | BI86: 850 | BJ86: 151.62 | BK86: 128877 | BN86: 850 | BO86: 151.62 | BP86: 128877 | BS86: 850 | BT86: 151.62 | BU86: 128877 | BX86: 850 | BY86: 151.62 | BZ86: 128877 | CC86: 850 | CD86: 151.62 | CE86: 128877 | CH86: 850 | CI86: 151.62 | CJ86: 128877 | CM86: 850 | CN86: 151.62 | CO86: 128877 | CR86: 850 | CS86: 151.62 | CT86: 128877 | CW86: 850 | CX86: 151.62 | CY86: 128877
D87: ХВ | F87: =H87/G87 -> 45 | G87: 16 | H87: 720 | K87: =M87/L87 -> 45 | L87: 18 | M87: 810 | P87: =R87/Q87 -> 45 | Q87: 21 | R87: 945 | U87: =W87/V87 -> 45 | V87: 18 | W87: 810 | Z87: =AB87/AA87 -> 45 | AA87: 16 | AB87: 720 | AE87: =AG87/AF87 -> 45 | AF87: 22 | AG87: 990 | AJ87: =AL87/AK87 -> 46 | AK87: 11 | AL87: 506 | AO87: =AQ87/AP87 -> 54.71 | AP87: 20 | AQ87: 1094.2 | AT87: =AV87/AU87 -> 54.71 | AU87: 18 | AV87: 984.78 | AY87: =BA87/AZ87 -> 45 | AZ87: 16 | BA87: 720 | BD87: =BF87/BE87 -> 45 | BE87: 16 | BF87: 720 | BI87: =BK87/BJ87 -> 45 | BJ87: 16 | BK87: 720 | BN87: =BP87/BO87 -> 45 | BO87: 16 | BP87: 720 | BS87: =BU87/BT87 -> 45 | BT87: 16 | BU87: 720 | BX87: =BZ87/BY87 -> 45 | BY87: 16 | BZ87: 720 | CC87: =CE87/CD87 -> 45 | CD87: 16 | CE87: 720 | CH87: =CJ87/CI87 -> 45 | CI87: 16 | CJ87: 720 | CM87: =CO87/CN87 -> 45 | CN87: 16 | CO87: 720 | CR87: =CT87/CS87 -> 45 | CS87: 16 | CT87: 720 | CW87: =CY87/CX87 -> 45 | CX87: 16 | CY87: 720
BW88: =SUM(BU88:BU92)*1.1 -> 96750.852
A89: М17/1 | B89: 45178042 | C89: ТОВ "ГТ РІТЕЙЛ" | D89: Активная ЭЭ | BT89: 11612 | BU89: 87955.32 | BW89: =SUM(BU88:BU91)*1 -> 87955.32
A92: М18 | B92: г.Киев, ул. Челябинская, 15А | C92: ТОВ "Еко-Грінко" | D92: Вывоз ТБО | W92: 1990 | Y92: =SUM(W92:W95)*1.1 -> 115984 | AB92: 1769 | AD92: =SUM(AB92:AB95)*1.1 -> 99605 | AG92: 1990 | AI92: =AI93*1.1 -> 109983.5 | AL92: 1990 | AN92: =AN93*1.2 -> 144234.6 | AQ92: 1990 | AS92: =SUM(AQ92:AQ95)*1.1 -> 133791.68 | AX92: =SUM(AV92:AV95)*1.1 -> 168974.66 | BC92: =SUM(BA92:BA95)*1.1 -> 152255.51 | BH92: =SUM(BF92:BF95)*1.1 -> 139715.4 | BM92: =SUM(BK92:BK95)*1.1 -> 144445.84 | BR92: =SUM(BP92:BP95)*1.1 -> 142052.15 | CB92: =SUM(BZ92:BZ95)*1.1 -> 68658.26 | CG92: =SUM(CE92:CE95)*1.1 -> 68658.26 | CL92: =SUM(CJ92:CJ95)*1.1 -> 68658.26 | CQ92: =SUM(CO92:CO95)*1.1 -> 68658.26 | CV92: =SUM(CT92:CT95)*1.1 -> 68658.26 | DA92: =SUM(CY92:CY95)*1.1 -> 68658.26
B93: 22912463 | C93: ТОВ "Нива В" | D93: Активная ЭЭ | F93: =H93/G93 -> 5.4341463 | G93: 11070 | H93: 60156 | K93: =M93/L93 -> 5.66 | L93: 13110 | M93: 74202.6 | P93: =R93/Q93 -> 5.64 | Q93: 12900 | R93: 72756 | U93: =W93/V93 -> 5.5299835 | V93: 18210 | W93: 100701 | Y93: =SUM(W92:W95)*1 -> 105440 | Z93: =AB93/AA93 -> 5.36 | AA93: 16110 | AB93: 86349.6 | AD93: =SUM(AB92:AB95)*1 -> 90550 | AE93: =AG93/AF93 -> 5.1710005 | AF93: 18390 | AG93: 95094.7 | AI93: =SUM(AG92:AG95)*1 -> 99985 | AJ93: =AL93/AK93 -> 5.574001 | AK93: 20670 | AL93: 115214.6 | AN93: =SUM(AL92:AL95)*1 -> 120195.5 | AO93: =AQ93/AP93 -> 6.05 | AP93: 19200 | AQ93: 116160 | AS93: =SUM(AQ92:AQ95)+AR95*1 -> 136663.08 | AT93: =AV93/AU93 -> 6.85 | AU93: 21840 | AV93: 149604 | AX93: =SUM(AV92:AV95)*1 -> 153613.33 | AY93: =BA93/AZ93 -> 6.89 | AZ93: 19560 | BA93: 134768.4 | BC93: =SUM(BA92:BA95)*1 -> 138414.1 | BD93: =BF93/BE93 -> 7.17 | BE93: 17310 | BF93: 124112.7 | BH93: =SUM(BF92:BF95)*1 -> 127014 | BI93: =BK93/BJ93 -> 7.32 | BJ93: 17640 | BK93: 129124.8 | BM93: =SUM(BK92:BK95)*1 -> 131314.4 | BN93: =BP93/BO93 -> 7.46 | BO93: 17040 | BP93: 127118.4 | BR93: =SUM(BP92:BP95)*1 -> 129138.32 | BS93: =BU93/BT93 -> 6.62 | BT93: 18870 | BU93: 124919.4 | BW93: =SUM(BU92:BU95)*1 -> 126713.2 | BX93: =BZ93/BY93 -> 5.4341463 | BY93: 11070 | BZ93: 60156 | CB93: =SUM(BZ92:BZ95)*1 -> 62416.6 | CC93: =CE93/CD93 -> 5.4341463 | CD93: 11070 | CE93: 60156 | CG93: =SUM(CE92:CE95)*1 -> 62416.6 | CH93: =CJ93/CI93 -> 5.4341463 | CI93: 11070 | CJ93: 60156 | CL93: =SUM(CJ92:CJ95)*1 -> 62416.6 | CM93: =CO93/CN93 -> 5.4341463 | CN93: 11070 | CO93: 60156 | CQ93: =SUM(CO92:CO95)*1 -> 62416.6 | CR93: =CT93/CS93 -> 5.4341463 | CS93: 11070 | CT93: 60156 | CV93: =SUM(CT92:CT95)*1 -> 62416.6 | CW93: =CY93/CX93 -> 5.4341463 | CX93: 11070 | CY93: 60156 | DA93: =SUM(CY92:CY95)*1 -> 62416.6
D94: Реактивная ЭЭ | G94: 3690 | H94: 553.5 | L94: 4620 | M94: 739.2 | Q94: 4410 | R94: 749.7 | V94: 6900 | W94: 1138.5 | AA94: 6540 | AB94: 1046.4 | AF94: 7860 | AG94: 1257.6 | AK94: 9030 | AL94: 1444.8 | AP94: 9060 | AQ94: 1449.6 | AU94: 1 | AV94: 1658 | AZ94: 1 | BA94: 1391 | BE94: 1 | BF94: 1580.7 | BI94: 6.908 | BJ94: 3690 | BK94: 1448.8 | BN94: 7.038 | BO94: 5580 | BP94: 1311.3 | BT94: 3690 | BU94: 1117.4 | BY94: 3690 | BZ94: 553.5 | CD94: 3690 | CE94: 553.5 | CI94: 3690 | CJ94: 553.5 | CN94: 3690 | CO94: 553.5 | CS94: 3690 | CT94: 553.5 | CX94: 3690 | CY94: 553.5
D95: ХВ | F95: =H95/G95 -> 32.209434 | G95: 53 | H95: 1707.1 | K95: =M95/L95 -> 32.209756 | L95: 41 | M95: 1320.6 | P95: =R95/Q95 -> 32.210256 | Q95: 39 | R95: 1256.2 | U95: =W95/V95 -> 32.21 | V95: 50 | W95: 1610.5 | Z95: =AB95/AA95 -> 32.209302 | AA95: 43 | AB95: 1385 | AE95: =AG95/AF95 -> 30.99434 | AF95: 53 | AG95: 1642.7 | AJ95: =AL95/AK95 -> 32.210417 | AK95: 48 | AL95: 1546.1 | AO95: =AQ95/AP95 -> 32.209524 | AP95: 63 | AQ95: 2029.2 | AR95: 15034.28 | AT95: =AV95/AU95 -> 32.21 | AU95: 73 | AV95: 2351.33 | AY95: =BA95/AZ95 -> 56.3675 | AZ95: 40 | BA95: 2254.7 | BD95: =BF95/BE95 -> 32.209756 | BE95: 41 | BF95: 1320.6 | BI95: =BK95/BJ95 -> 32.208696 | BJ95: 23 | BK95: 740.8 | BN95: =BP95/BO95 -> 32.21 | BO95: 22 | BP95: 708.62 | BS95: =BU95/BT95 -> 32.209524 | BT95: 21 | BU95: 676.4 | BX95: =BZ95/BY95 -> 32.209434 | BY95: 53 | BZ95: 1707.1 | CC95: =CE95/CD95 -> 32.209434 | CD95: 53 | CE95: 1707.1 | CH95: =CJ95/CI95 -> 32.209434 | CI95: 53 | CJ95: 1707.1 | CM95: =CO95/CN95 -> 32.209434 | CN95: 53 | CO95: 1707.1 | CR95: =CT95/CS95 -> 32.209434 | CS95: 53 | CT95: 1707.1 | CW95: =CY95/CX95 -> 32.209434 | CX95: 53 | CY95: 1707.1
A96: М19 | B96: г.Ирпень, ул. Соборная, 1г | C96: ТОВ "Еко-Грінко" | D96: Вывоз ТБО
C97: ПП "Мікс Лтд" | D97: Экспл. расходы | G97: 0 | H97: 7717 | L97: 0 | M97: 7717 | Q97: 0 | R97: 7717 | V97: 0 | W97: 7717 | AA97: 0 | AB97: 7717 | AF97: 0 | AG97: 7717 | AK97: 0 | AL97: 7717 | AP97: 0 | AQ97: 7717 | AU97: 0 | AV97: 7717 | AZ97: 0 | BA97: 7717 | BE97: 0 | BF97: 7717 | BJ97: 0 | BK97: 7717 | BO97: 0 | BP97: 7717 | BT97: 0 | BU97: 7717 | BY97: 0 | BZ97: 7717 | CD97: 0 | CE97: 7717 | CI97: 0 | CJ97: 7717 | CN97: 0 | CO97: 7717 | CS97: 0 | CT97: 7717 | CX97: 0 | CY97: 7717
C98: ТОВ "Фреш Лтд" | D98: Активная ЭЭ | G98: 0 | H98: 0 | L98: 0 | M98: 0 | Q98: 0 | R98: 0 | V98: 0 | W98: 0 | AA98: 0 | AB98: 0 | AF98: 0 | AG98: 0 | AK98: 0 | AL98: 0 | AP98: 0 | AQ98: 0 | AU98: 0 | AV98: 0 | AZ98: 0 | BA98: 0 | BE98: 0 | BF98: 0 | BJ98: 0 | BK98: 0 | BO98: 0 | BP98: 0 | BT98: 0 | BU98: 0 | BY98: 0 | BZ98: 0 | CD98: 0 | CE98: 0 | CI98: 0 | CJ98: 0 | CN98: 0 | CO98: 0 | CS98: 0 | CT98: 0 | CX98: 0 | CY98: 0
D99: Реактивная ЭЭ | G99: 0 | H99: 0 | L99: 0 | M99: 0 | Q99: 0 | R99: 0 | V99: 0 | W99: 0 | AA99: 0 | AB99: 0 | AF99: 0 | AG99: 0 | AK99: 0 | AL99: 0 | AP99: 0 | AQ99: 0 | AU99: 0 | AV99: 0 | AZ99: 0 | BA99: 0 | BE99: 0 | BF99: 0 | BJ99: 0 | BK99: 0 | BO99: 0 | BP99: 0 | BT99: 0 | BU99: 0 | BY99: 0 | BZ99: 0 | CD99: 0 | CE99: 0 | CI99: 0 | CJ99: 0 | CN99: 0 | CO99: 0 | CS99: 0 | CT99: 0 | CX99: 0 | CY99: 0
C100: КП "Ирпеньводоканал" | D100: ХВ | G100: 0 | H100: 0 | L100: 0 | M100: 0 | Q100: 0 | R100: 0 | V100: 0 | W100: 0 | AA100: 0 | AB100: 0 | AF100: 0 | AG100: 0 | AK100: 0 | AL100: 0 | AP100: 0 | AQ100: 0 | AU100: 0 | AV100: 0 | AZ100: 0 | BA100: 0 | BE100: 0 | BF100: 0 | BJ100: 0 | BK100: 0 | BO100: 0 | BP100: 0 | BT100: 0 | BU100: 0 | BY100: 0 | BZ100: 0 | CD100: 0 | CE100: 0 | CI100: 0 | CJ100: 0 | CN100: 0 | CO100: 0 | CS100: 0 | CT100: 0 | CX100: 0 | CY100: 0
A101: М20 | B101: г.Киев, ул. Бориспольская, 32А | C101: ТОВ "Еко-Грінко" | D101: Вывоз ТБО | W101: 2211 | Y101: =SUM(W101:W104)*1.1 -> 80055.331 | AB101: 1769 | AD101: =SUM(AB101:AB104)*1.1 -> 56726.725 | AG101: 2211 | AI101: =AI102*1.1 -> 87115.787 | AL101: 1769 | AN101: =AN102*1.2 -> 89589.065 | AQ101: 1769 | AS101: =SUM(AQ101:AQ104)*1.1 -> 93187.662 | AX101: =SUM(AV101:AV104)*1.1 -> 102500.83 | BC101: =SUM(BA101:BA104)*1.1 -> 81796.253 | BH101: =SUM(BF101:BF104)*1.1 -> 91563.069 | BM101: =SUM(BK101:BK104)*1.1 -> 95993.902 | BR101: =SUM(BP101:BP104)*1.1 -> 96265.052 | BW101: =SUM(BU101:BU104)*1.1 -> 114366.07 | CB101: =SUM(BZ101:BZ104)*1.1 -> 42267.636 | CG101: =SUM(CE101:CE104)*1.1 -> 42267.636 | CL101: =SUM(CJ101:CJ104)*1.1 -> 42267.636 | CQ101: =SUM(CO101:CO104)*1.1 -> 42267.636 | CV101: =SUM(CT101:CT104)*1.1 -> 42267.636 | DA101: =SUM(CY101:CY104)*1.1 -> 42267.636
B102: 41916045 | C102: ТОВ "КИЇВСЬКI ЕНЕРГЕТИЧНI ПОСЛУГИ" | D102: Активная ЭЭ | F102: =H102/G102 -> 5.3077206 | G102: 7044 | H102: 37387.584 | I102: 25963.6 | K102: =M102/L102 -> 5.3685481 | L102: 10480 | M102: 56262.384 | N102: 56262.384 | P102: =R102/Q102 -> 4.9663919 | Q102: 9365 | R102: 46510.26 | S102: 46510.26 | U102: =W102/V102 -> 5.2077241 | V102: 13307 | W102: 69299.184 | X102: 69299.184 | Y102: =SUM(W101:W104)*1 -> 72777.574 | Z102: =AB102/AA102 -> 4.6829522 | AA102: 10345 | AB102: 48445.14 | AC102: 48445.14 | AD102: =SUM(AB101:AB104)*1 -> 51569.75 | AE102: =AG102/AF102 -> 4.8199442 | AF102: 10539 | AG102: 50797.392 | AH102: =25497.44+50354.71 -> 75852.15 | AI102: =SUM(AG103:AG104)+AH102+AG101*1 -> 79196.17 | AJ102: =AL102/AK102 -> 4.9792197 | AK102: 11887 | AL102: 59187.984 | AM102: =10423.49+62061.264 -> 72484.754 | AN102: =SUM(AL103:AL104)+AM102+AL101*1 -> 74657.554 | AO102: =AQ102/AP102 -> 5.9466956 | AP102: 13447 | AQ102: 79965.216 | AR102: 90178.428 | AS102: =SUM(AQ101:AQ104)*1 -> 84716.056 | AT102: =AV102/AU102 -> 6.6107638 | AU102: 13825 | AV102: 91393.81 | AW102: 25963.6 | AX102: =SUM(AV101:AV104)*1 -> 93182.57 | AY102: =BA102/AZ102 -> 6.3494518 | AZ102: 11456 | BA102: 72739.32 | BB102: 60 616,10 | BC102: =SUM(BA101:BA104)*1 -> 74360.23 | BD102: =BF102/BE102 -> 6.3628437 | BE102: 12921 | BF102: 82214.304 | BG102: 65086.324 | BH102: =SUM(BF101:BF104)*1 -> 83239.154 | BI102: =BK102/BJ102 -> 6.7715883 | BJ102: 12708 | BK102: 86053.344 | BL102: 65086.324 | BM102: =SUM(BK101:BK104)*1 -> 87267.184 | BN102: =BP102/BO102 -> 6.3746283 | BO102: 13496 | BP102: 86031.984 | BQ102: 25963.6 | BR102: =SUM(BP101:BP104)*1 -> 87513.684 | BS102: =BU102/BT102 -> 6.0268799 | BT102: 17017 | BU102: 102559.42 | BV102: 87291 | BW102: =SUM(BU101:BU104)*1 -> 103969.16 | BX102: =BZ102/BY102 -> 5.3077206 | BY102: 7044 | BZ102: 37387.584 | CA102: 118 487,48 | CB102: =SUM(BZ101:BZ104)*1 -> 38425.124 | CC102: =CE102/CD102 -> 5.3077206 | CD102: 7044 | CE102: 37387.584 | CF102: 25963.6 | CG102: =SUM(CE101:CE104)*1 -> 38425.124 | CH102: =CJ102/CI102 -> 5.3077206 | CI102: 7044 | CJ102: 37387.584 | CK102: 25963.6 | CL102: =SUM(CJ101:CJ104)*1 -> 38425.124 | CM102: =CO102/CN102 -> 5.3077206 | CN102: 7044 | CO102: 37387.584 | CP102: 25963.6 | CQ102: =SUM(CO101:CO104)*1 -> 38425.124 | CR102: =CT102/CS102 -> 5.3077206 | CS102: 7044 | CT102: 37387.584 | CU102: 25963.6 | CV102: =SUM(CT101:CT104)*1 -> 38425.124 | CW102: =CY102/CX102 -> 5.3077206 | CX102: 7044 | CY102: 37387.584 | CZ102: 25963.6 | DA102: =SUM(CY101:CY104)*1 -> 38425.124
B103: 41946011 | C103: «ДТЕК КИЇВСЬКІ ЕЛЕКТРОМЕРЕЖІ» | D103: Реактивная ЭЭ | G103: 0 | H103: 0 | L103: 0 | M103: 0
B104: 33495259 | C104: ТОВ "ТВК "Бориспільська" | D104: ХВ | F104: =H104/G104 -> 37.497241 | G104: 29 | H104: 1087.42 | K104: =M104/L104 -> 37.497241 | L104: 29 | M104: 1087.42 | P104: =R104/Q104 -> 31.378919 | Q104: 37 | R104: 1161.02 | U104: =W104/V104 -> 31.68475 | V104: 40 | W104: 1267.39 | Z104: 30.38 | AA104: =41+4.97 -> 45.97 | AB104: =1284.94+70.67 -> 1355.61 | AE104: =AG104/AF104 -> 30.622162 | AF104: 37 | AG104: 1133.02 | AJ104: =AL104/AK104 -> 33.65 | AK104: 12 | AL104: 403.8 | AO104: =AQ104/AP104 -> 33.131556 | AP104: 90 | AQ104: 2981.84 | AT104: =AV104/AU104 -> 31.942143 | AU104: 56 | AV104: 1788.76 | AY104: =BA104/AZ104 -> 31.782549 | AZ104: 51 | BA104: 1620.91 | BD104: =BF104/BE104 -> 31.056061 | BE104: 33 | BF104: 1024.85 | BI104: =BK104/BJ104 -> 34.681143 | BJ104: 35 | BK104: 1213.84 | BN104: =BP104/BO104 -> 35.278571 | BO104: 42 | BP104: 1481.7 | BS104: =BU104/BT104 -> 35.2435 | BT104: 40 | BU104: 1409.74 | BX104: =BZ104/BY104 -> 30.515882 | BY104: 34 | BZ104: 1037.54 | CC104: =CE104/CD104 -> 30.515882 | CD104: 34 | CE104: 1037.54 | CH104: =CJ104/CI104 -> 30.515882 | CI104: 34 | CJ104: 1037.54 | CM104: =CO104/CN104 -> 30.515882 | CN104: 34 | CO104: 1037.54 | CR104: =CT104/CS104 -> 30.515882 | CS104: 34 | CT104: 1037.54 | CW104: =CY104/CX104 -> 30.515882 | CX104: 34 | CY104: 1037.54
...

Sheet ОПЛАТИ 2024-2025-2026 
B1: НАЗВАНИЕ ОБЪЕКТА | C1: АДРЕС ОБЪЕКТА | D1: ЮРИДИЧЕСКОЕ (ФИЗИЧЕСКОЕ) ЛИЦО | E1: НАИМЕНОВАНИЕ | F1: Столбец1 | G1: Тариф | H1: Показатели | I1: Сумма | J1: Авансы | K1: грудень 2022 | L1: Тариф | M1: Показатели | N1: Сумма | O1: Авансы | P1: січень 2023 | Q1: Тариф | R1: Показатели | S1: Сумма | T1: Авансы | U1: лютий 2023 | V1: Тариф | W1: Показатели | X1: Сумма | Y1: Авансы | Z1: березень 2023 | AA1: Тариф | AB1: Показатели | AC1: Сумма | AD1: Авансы | AE1: квітень 2023 | AF1: Тариф | AG1: Показатели | AH1: Сумма | AI1: Авансы | AJ1: травень 2023 | AK1: Тариф | AL1: Показатели | AM1: Сумма | AN1: Авансы | AO1: червень 2023 | AP1: Тариф | AQ1: Показатели | AR1: Сумма | AS1: Авансы | AT1: Липень 2023 | AU1: Тариф | AV1: Показатели | AW1: Сумма | AX1: Авансы | AY1: Серпень 2023 | AZ1: Тариф | BA1: Показатели | BB1: Сумма | BC1: Авансы | BD1: Вересень 2023 | BE1: Тариф | BF1: Показатели | BG1: Сумма | BH1: Авансы | BI1: Жовтень 2023 | BJ1: Тариф | BK1: Показатели | BL1: Сумма | BM1: Авансы | BN1: Листопад 2023 | BO1: Тариф | BP1: Показатели | BQ1: Сумма | BR1: Авансы | BS1: Грудень 2023 | BT1: Тариф | BU1: Показатели | BV1: Сумма | BW1: Авансы | BX1: Січень 2024 | BY1: Тариф | BZ1: Показатели | CA1: Сумма | CB1: Авансы | CC1: Лютий 2024 | CD1: Тариф | CE1: Показатели | CF1: Сумма | CG1: Авансы | CH1: Березень 2024 | CI1: Тариф | CJ1: Показатели | CK1: Сумма | CL1: Авансы | CM1: Квітень 2024 | CN1: Тариф | CO1: Показатели | CP1: Сумма | CQ1: Авансы | CR1: Травень 2024 | CS1: Тариф | CT1: Показатели | CU1: Сумма | CV1: Авансы | CW1: червень 2024 | CX1: Тариф | CY1: Показатели | CZ1: Сумма | DA1: Авансы | DB1: Липень 2024 | DC1: Тариф | DD1: Показатели | DE1: Сумма | DF1: Авансы | DG1: Серпень 2024 | DH1: Тариф | DI1: Показатели | DJ1: Сумма | DK1: Авансы | DL1: Вересен 2024 | DM1: Тариф | DN1: Показатели | DO1: Сумма | DP1: Авансы | DQ1: Жовтень 2024 | DR1: Тариф | DS1: Показатели | DT1: Сумма | DU1: Авансы | DV1: Листопад 2024 | DW1: Тариф | DX1: Показатели | DY1: Сумма | DZ1: Авансы | EA1: Грудень 2024 | EB1: Тариф | EC1: Показатели | ED1: Сумма | EE1: Авансы | EF1: Січень 2025 | EG1: Тариф | EH1: Показатели | EI1: Сумма | EJ1: Авансы | EK1: Лютий 2025 | EL1: Тариф | EM1: Показатели | EN1: Сумма | EO1: Авансы | EP1: Березень 2025 | EQ1: Тариф | ER1: Показатели | ES1: Сумма | ET1: Авансы | EU1: Квітень 2025 | EV1: Тариф | EW1: Показатели | EX1: Сумма | EY1: Авансы | EZ1: Травень 2025 | FA1: Тариф | FB1: Показатели | FC1: Сумма | FD1: Авансы | FE1: червень 2025 | FF1: Тариф | FG1: Показатели | FH1: Сумма | FI1: Авансы | FJ1: Липень 2025 | FK1: Тариф | FL1: Показатели | FM1: Сумма | FN1: Авансы | FO1: Серпень 2025 | FP1: Тариф | FQ1: Показатели | FR1: Сумма | FS1: Авансы | FT1: Вересен 2025 | FU1: Тариф | FV1: Показатели | FW1: Сумма | FX1: Авансы | FY1: Жовтень 2025 | FZ1: Тариф | GA1: Показатели | GB1: Сумма | GC1: Авансы | GD1: Листопад 2025 | GE1: Тариф | GF1: Показатели | GG1: Сумма | GH1: Авансы | GI1: Грудень 2025 | GJ1: Тариф | GK1: Показатели | GL1: Сумма | GM1: Авансы | GN1: Січень 2026 | GO1: Тариф | GP1: Показатели | GQ1: Сумма | GR1: Авансы | GS1: Лютий 2026 | GT1: Тариф | GU1: Показатели | GV1: Сумма | GW1: Авансы | GX1: Березень 2026 | GY1: Тариф | GZ1: Показатели | HA1: Сумма | HB1: Авансы | HC1: Квітень 2026 | HD1: Тариф | HE1: Показатели | HF1: Сумма | HG1: Авансы | HH1: Травень 2026 | HI1: Тариф | HJ1: Показатели | HK1: Сумма | HL1: Авансы | HM1: червень 2026 | HN1: Тариф | HO1: Показатели | HP1: Сумма | HQ1: Авансы | HR1: Липень 2026 | HS1: Тариф | HT1: Показатели | HU1: Сумма | HV1: Авансы | HW1: Серпень 2026 | HX1: Тариф | HY1: Показатели | HZ1: Сумма | IA1: Авансы | IB1: Вересен 2026 | IC1: Тариф | ID1: Показатели | IE1: Сумма | IF1: Авансы | IG1: Жовтень 2026 | IH1: Тариф | II1: Показатели | IJ1: Сумма | IK1: Авансы | IL1: Листопад 2026 | IM1: Тариф | IN1: Показатели | IO1: Сумма | IP1: Авансы | IQ1: Грудень 2026
B2: РЦ | C2: Білогородка, Аграрна 1
C3: 44878589 | D3: ТОВ ТОЛК | E3: Активная ЭЭ | EW3: 67210 | EX3: 559858.76 | FB3: 88730 | FC3: 794292.86 | FG3: 89720 | FH3: 855837.29 | FI3: 620 620,56 | FL3: 75890 | FM3: 735882.26 | FN3: 546986.88 | FS3: 312287.23 | GT3: =GV3/GU3 -> 11.233164 | GU3: =18310+950 -> 19260 | GV3: 216350.74 | HE3: 67210 | HF3: 559858.76 | HJ3: 88730 | HK3: 794292.86 | HO3: 89720 | HP3: 855837.29 | HQ3: 620 620,56 | HT3: 75890 | HU3: 735882.26 | HV3: 546986.88 | IA3: 312287.23
C4: 23243188 | D4: «ДТЕК КИЇВСЬКІ РЕГІОНАЛЬНІ ЕЛЕКТРОМЕРЕЖІ» | E4: Реактивная ЭЭ | FN4: 16 569,92 | FW4: 10688.9 | GV4: 22972.92 | GW4: 22972.92 | HV4: 16 569,92 | IE4: 10688.9
C5: 40635553 | D5: ТОВ "Сервіс-Енергія ЛТД" | E5: КОМЕРЦІЙНИЙ ОБЛІК | FE5: 812 214,78 | FG5: 1 | FH5: 1 440,00 | FL5: 1 | FM5: 1 440,00 | FQ5: 1 | FR5: 1 440,00 | FV5: 1 | FW5: 1 440,00 | GV5: 1440 | HM5: 812 214,78 | HO5: 1 | HP5: 1 440,00 | HT5: 1 | HU5: 1 440,00 | HY5: 1 | HZ5: 1 440,00 | ID5: 1 | IE5: 1 440,00
B8: М1/1 | C8: г.Житомир, пр. Мира, 15 | D8: ТОВ ГРІН БІН Україна | E8: Вывоз ТБО | X8: 2 913,33 | Z8: =SUM(X8:X12)*1.1 -> 266598.77 | AA8: 330000 | AC8: 100 | AE8: =SUM(AC8:AC12)*1.1 -> 254435.93 | AH8: =3277.5+600 -> 3877.5 | AJ8: =AJ9*1.1 -> 304938.28 | AM8: 100 | AO8: =AO9*1.2 -> 244056.49 | AR8: 100 | AT8: =SUM(AR8:AR12)*1.3 -> 417523.31 | AW8: 100 | AY8: =SUM(AW8:AW12)*1 -> 339604.38 | BB8: 100 | BD8: =SUM(BB8:BB12)*1.11 -> 341852.35 | BG8: 100 | BI8: =SUM(BG8:BG12)*1.1 -> 326765.93 | BL8: 100 | BN8: =SUM(BL8:BL12)*1.1 -> 373177.56 | BQ8: 100 | BS8: =SUM(BQ8:BQ12)*1.1 -> 407182.36 | BV8: 100 | BX8: =SUM(BV8:BV12)*1.1 -> 385830.64 | CA8: 100 | CC8: =SUM(CA8:CA12)*1.1 -> 332482.38 | CF8: 100 | CH8: =SUM(CF8:CF12)*1.1 -> 334293.7 | CK8: 100 | CM8: =SUM(CK8:CK12)*1.1 -> 310806.02 | CP8: 100 | CR8: =SUM(CP8:CP12)*1.1 -> 374522.28 | CU8: 100 | CW8: =SUM(CU8:CU12)*1.1 -> 465603.58 | CZ8: 100 | DB8: =SUM(CZ8:CZ12)*1.1 -> 524540.47 | DE8: 100 | DG8: =SUM(DE8:DE12)*1.1 -> 492256.18 | DJ8: 100 | DL8: =SUM(DJ8:DJ12)*1.1 -> 463958.34 | DO8: 100 | DQ8: =SUM(DO8:DO12)*1.1 -> 509103.65 | DT8: 100 | DV8: =SUM(DT8:DT12)*1.1 -> 506792.51 | DY8: 100 | EA8: =SUM(DY8:DY12)*1.1 -> 550649.62 | ED8: 100 | EF8: =SUM(ED8:ED12)*1.1 -> 548888.81 | EI8: 100 | EK8: =SUM(EI8:EI12)*1.1 -> 589577.05 | EN8: 100 | EP8: =SUM(EN8:EN12)*1.1 -> 396906.58 | ES8: 100 | EU8: =SUM(ES8:ES12)*1.1 -> 532550.17 | EX8: 100 | EZ8: =SUM(EX8:EX12)*1.1 -> 503620.55 | FC8: 100 | FE8: =SUM(FC8:FC12)*1.1 -> 453684.69 | FH8: 100 | FJ8: =SUM(FH8:FH12)*1.1 -> 522971.69 | FM8: 100 | FO8: =SUM(FM8:FM12)*1.1 -> 566179.69 | FR8: 100 | FT8: =SUM(FR8:FR12)*1.1 -> 478467.72 | FW8: 100 | FY8: =SUM(FW8:FW12)*1.1 -> 595643.42 | GB8: 100 | GD8: =SUM(GB8:GB12)*1.1 -> 588465.13 | GG8: 100 | GI8: =SUM(GG8:GG12)*1.1 -> 676933.99 | GL8: 100 | GN8: =SUM(GL8:GL12)*1.1 -> 548888.81 | GQ8: 100 | GS8: =SUM(GQ8:GQ12)*1.1 -> 752381.14 | GV8: 100 | GX8: =SUM(GV8:GV12)*1.1 -> 655159.43 | HA8: 100 | HC8: =SUM(HA8:HA12)*1.1 -> 532550.17 | HF8: 100 | HH8: =SUM(HF8:HF12)*1.1 -> 503620.55 | HK8: 100 | HM8: =SUM(HK8:HK12)*1.1 -> 453684.69 | HP8: 100 | HR8: =SUM(HP8:HP12)*1.1 -> 522971.69 | HU8: 100 | HW8: =SUM(HU8:HU12)*1.1 -> 566179.69 | HZ8: 100 | IB8: =SUM(HZ8:HZ12)*1.1 -> 478467.72 | IE8: 100 | IG8: =SUM(IE8:IE12)*1.1 -> 595643.42 | IJ8: 100 | IL8: =SUM(IJ8:IJ12)*1.1 -> 272793.49 | IO8: 100 | IQ8: =SUM(IO8:IO12)*1.1 -> 266185.5
C9: 45812183 | D9: ОСББ"Проспект Миру 15 | E9: Экспл. расходы | Z9: =SUM(X8:X12)*1 -> 242362.52 | AE9: =SUM(AC8:AC12)*1 -> 231305.39 | AJ9: =SUM(AH11:AH12)+AI10+AH8*1 -> 277216.62 | AO9: =SUM(AM11:AM12)+AN10+AM8*1 -> 203380.41 | AT9: =SUM(AR8:AR12)*1 -> 321171.78 | AY9: =SUM(AW8:AW12)*1 -> 339604.38 | BD9: =SUM(BB12+BB11+BB8+BC10) -> 334718.35 | BI9: =SUM(BG8:BG12)*1 -> 297059.94 | BN9: =SUM(BL8:BL12)*1 -> 339252.33 | BS9: =SUM(BQ8:BQ12)*1 -> 370165.78 | BX9: =SUM(BV12+BV11+BW10+BV8)*1 -> 401619.69 | CC9: =SUM(CA8:CA12)*1 -> 302256.71 | CH9: =SUM(CF8:CF12)*1 -> 303903.36 | CM9: =SUM(CK8:CK12)*1 -> 282550.92 | CR9: =SUM(CP8:CP12)*1 -> 340474.8 | CW9: =SUM(CU8:CU12)*1 -> 423275.98 | DB9: =SUM(CZ8:CZ12)*1 -> 476854.97 | DG9: =SUM(DE8:DE12)*1 -> 447505.62 | DL9: =SUM(DJ8:DJ12)*1 -> 421780.31 | DQ9: =SUM(DO8:DO12)*1 -> 462821.5 | DV9: =SUM(DT8:DT12)*1 -> 460720.46 | EA9: =SUM(DY8:DY12)*1 -> 500590.57 | EF9: =SUM(ED12+ED11+EE10+ED8)*1 -> 635649.8 | EK9: =SUM(EI8:EI12)*1 -> 535979.13 | EP9: =SUM(EN8:EN12)*1 -> 360824.16 | EU9: =SUM(ES8:ES12)*1 -> 484136.52 | EZ9: =SUM(EX8:EX12)*1 -> 457836.87 | FC9: 10 076,95 | FE9: =SUM(FC8:FC12)*1 -> 412440.63 | FH9: 10 076,95 | FJ9: =SUM(FH8:FH12)*1 -> 475428.81 | FM9: 10 076,95 | FO9: =SUM(FM8:FM12)*1 -> 514708.81 | FR9: 10 076,95 | FT9: =SUM(FR8:FR12)*1 -> 434970.65 | FW9: 10 076,95 | FY9: =SUM(FW8:FW12)*1 -> 541494.01 | GB9: 10076.95 | GD9: =SUM(GB8:GB12)*1 -> 534968.3 | GG9: 10076.95 | GI9: =SUM(GG8:GG12)*1 -> 615394.54 | GN9: =SUM(GL12+GL11+GM10+GL8)*1 -> 635649.8 | GS9: =SUM(GQ8:GQ12)*1 -> 683982.86 | GX9: =SUM(GV8:GV12)*1 -> 595599.48 | HC9: =SUM(HA8:HA12)*1 -> 484136.52 | HH9: =SUM(HF8:HF12)*1 -> 457836.87 | HK9: 10 076,95 | HM9: =SUM(HK8:HK12)*1 -> 412440.63 | HP9: 10 076,95 | HR9: =SUM(HP8:HP12)*1 -> 475428.81 | HU9: 10 076,95 | HW9: =SUM(HU8:HU12)*1 -> 514708.81 | HZ9: 10 076,95 | IB9: =SUM(HZ8:HZ12)*1 -> 434970.65 | IG9: =SUM(IE8:IE12)*1 -> 541494.01 | IL9: =SUM(IJ8:IJ12)*1 -> 247994.08 | IQ9: =SUM(IO8:IO12)*1 -> 241986.82
A10: 1 | C10: 44878589 | D10: ТОВ ТОЛК | E10: Активная ЭЭ | G10: =I10/H10 -> 6.2021216 | H10: 38462 | I10: 238546 | J10: 270000 | L10: =N10/M10 -> 6.444444 | M10: 49797 | N10: 320913.98 | O10: 270000 | Q10: =S10/R10 -> 6.0761997 | R10: 40623 | S10: 246833.46 | T10: 325000 | V10: =X10/W10 -> 5.1846598 | W10: 46075 | X10: 238883.2 | Y10: 300000 | AA10: =AC10/AB10 -> 5.8564076 | AB10: 38871 | AC10: 227644.42 | AD10: 250000 | AF10: =AH10/AG10 -> 5.8430275 | AG10: 41718 | AH10: 243759.42 | AI10: 270000 | AK10: =AM10/AL10 -> 5.9171158 | AL10: 41062 | AM10: 242968.61 | AN10: 200000 | AP10: =AR10/AQ10 -> 6.6963836 | AQ10: 47425 | AR10: 317575.99 | AS10: 270000 | AU10: =AW10/AV10 -> 7.303896 | AV10: 45886 | AW10: 335146.57 | AX10: =130588.31+399432.6 -> 530020.91 | AZ10: =BB10/BA10 -> 7.035096 | BA10: 43220 | BB10: 304056.85 | BC10: 330800.11 | BE10: =BG10/BF10 -> 7.1411038 | BF10: 41329 | BG10: 295134.68 | BH10: 270000 | BJ10: =BL10/BK10 -> 7.4900641 | BK10: 44771 | BL10: 335337.66 | BM10: 270000 | BO10: =BQ10/BP10 -> 7.1331721 | BP10: 51550 | BQ10: 367715.02 | BR10: 300000 | BT10: =BV10/BU10 -> 7.067688 | BU10: 48971 | BV10: 346111.75 | BW10: 396976.31 | BY10: =CA10/BZ10 -> 6.5105519 | BZ10: 45678 | CA10: 297388.99 | CB10: 248322.31 | CD10: =CF10/CE10 -> 6.384912 | CE10: 47178 | CF10: 301227.38 | CG10: 300000 | CI10: =CK10/CJ10 -> 6.813636 | CJ10: 40700 | CK10: =1.2*231095.82 -> 277314.98 | CL10: =186088.56+59259.76+27886.94 -> 273235.26 | CN10: =CP10/CO10 -> 7.817256 | CO10: 43032 | CP10: =1.2*280326.8 -> 336392.16 | CQ10: 335931.84 | CS10: =CU10/CT10 -> 8.9189039 | CT10: 46407 | CU10: 413899.57 | CV10: =167720.76+149085.12+55906.92 -> 372712.8 | CX10: =CZ10/CY10 -> 9.7384921 | CY10: 47482 | CZ10: =1.2*385335.9 -> 462403.08 | DA10: =227455.02+202182.24+75818.34 -> 505455.6 | DC10: =DE10/DD10 -> 9.6512641 | DD10: 45006 | DE10: =1.2*361970.66 -> 434364.79 | DF10: =385756.43+198723.01 -> 584479.44 | DH10: =DJ10/DI10 -> 9.9899453 | DI10: 41125 | DJ10: =1.2*342363.75 -> 410836.5 | DK10: 405693.5 | DM10: =DO10/DN10 -> 9.8642881 | DN10: 45944 | DO10: =1.2*377670.71 -> 453204.85 | DP10: 500996.66 | DR10: =DT10/DS10 -> 9.840588 | DS10: 45937 | DT10: =1.2*376705.91 -> 452047.09 | DU10: 324720.06 | DW10: =DY10/DX10 -> 10.386 | DX10: 47508 | DY10: =411181.74*1.2 -> 493418.09 | DZ10: 321785.1 | EB10: =ED10/EC10 -> 10.464576 | EC10: 46772 | ED10: =1.2*407874.29 -> 489449.15 | EE10: =469581.84+156527.28 -> 626109.12 | EG10: =EI10/EH10 -> 10.774824 | EH10: 48896 | EI10: =1.2*439038.16 -> 526845.79 | EJ10: 248322.31 | EL10: =EN10/EM10 -> 9.705708 | EM10: 36125 | EN10: =1.2*292182.25 -> 350618.7 | EO10: 300000 | EQ10: =ES10/ER10 -> 8.754744 | ER10: 54491 | ES10: =1.2*397545.63 -> 477054.76 | ET10: =186088.56+59259.76+27886.94 -> 273235.26 | EV10: =EX10/EW10 -> 8.961024 | EW10: 49931 | EX10: =1.2*372860.74 -> 447432.89 | EY10: 425549.16 | FA10: =FC10/FB10 -> 8.965596 | FB10: 44849 | FC10: =1.2*335081.68 -> 402098.02 | FD10: 564847.13 | FF10: =FH10/FG10 -> 9.7384921 | FG10: 47482 | FH10: =1.2*385335.9 -> 462403.08 | FI10: =227455.02+202182.24+75818.34 -> 505455.6 | FK10: =FM10/FL10 -> 9.916068 | FL10: 50876 | FM10: =1.2*420408.23 -> 504489.88 | FN10: 511153.5 | FP10: =FR10/FQ10 -> 9.3381599 | FQ10: 45397 | FR10: =1.2*353270.37 -> 423924.44 | FS10: 457678.1 | FU10: =FW10/FV10 -> 11.593908 | FV10: 45994 | FW10: =1.2*444375.17 -> 533250.2 | FX10: 500996.66 | FZ10: =GB10/GA10 -> 12.129504 | GA10: 42495 | GB10: =1.2*429536.06 -> 515443.27 | GC10: 324720.06 | GE10: =GG10/GF10 -> 12.287652 | GF10: 48693 | GG10: =1.2*498602.2 -> 598322.64 | GJ10: =GL10/GK10 -> 10.464576 | GK10: 46772 | GL10: =1.2*407874.29 -> 489449.15 | GM10: =469581.84+156527.28 -> 626109.12 | GO10: =GQ10/GP10 -> 16.413912 | GP10: 41045 | GQ10: =1.2*561424.18 -> 673709.02 | GR10: 248322.31 | GT10: =GV10/GU10 -> 13.515144 | GU10: 42913 | GV10: =1.2*483312.81 -> 579975.37 | GW10: 300000 | GY10: =HA10/GZ10 -> 8.754744 | GZ10: 54491 | HA10: =1.2*397545.63 -> 477054.76 | HB10: =186088.56+59259.76+27886.94 -> 273235.26 | HD10: =HF10/HE10 -> 8.961024 | HE10: 49931 | HF10: =1.2*372860.74 -> 447432.89 | HG10: 425549.16 | HI10: =HK10/HJ10 -> 8.965596 | HJ10: 44849 | HK10: =1.2*335081.68 -> 402098.02 | HL10: 564847.13 | HN10: =HP10/HO10 -> 9.7384921 | HO10: 47482 | HP10: =1.2*385335.9 -> 462403.08 | HQ10: =227455.02+202182.24+75818.34 -> 505455.6 | HS10: =HU10/HT10 -> 9.916068 | HT10: 50876 | HU10: =1.2*420408.23 -> 504489.88 | HV10: 511153.5 | HX10: =HZ10/HY10 -> 9.3381599 | HY10: 45397 | HZ10: =1.2*353270.37 -> 423924.44 | IA10: 457678.1 | IC10: =IE10/ID10 -> 11.593908 | ID10: 45994 | IE10: =1.2*444375.17 -> 533250.2 | IF10: 500996.66 | IH10: =IJ10/II10 -> 6.2021216 | II10: 38462 | IJ10: 238546 | IK10: 324720.06 | IM10: =IO10/IN10 -> 6.2021216 | IN10: 38462 | IO10: 238546
C11: 22048622 | D11: ООО «Житомиробленерго», АТ "Житомиробленерго" Житомирський РЕМ | E11: Реактивная ЭЭ | H11: 1 | I11: 990.06 | M11: 1 | N11: 1198.26 | R11: 1 | S11: 1065.68 | W11: 1 | X11: 1278.7 | AB11: 1 | AC11: 1135.13 | AG11: 1 | AH11: 1251.11 | AL11: 1 | AM11: 1342.54 | AQ11: 1 | AR11: 1595.46 | AV11: 1 | AW11: 1894.44 | BA11: 1 | BB11: 2030.52 | BF11: 1 | BG11: 1 545,68 | BK11: 1 | BL11: 1 687,28 | BP11: 1 | BQ11: 1 830,90 | BU11: 1 | BV11: 1742.18 | BZ11: 1 | CA11: 1553.63 | CE11: 1 | CF11: 1 372,51 | CJ11: 1 | CK11: 1208.66 | CO11: 1 | CP11: 1444.2 | CT11: 1 | CU11: 2794.79 | CY11: 1 | CZ11: 3553.74 | DD11: 1 | DE11: 3759.11 | DI11: 1 | DJ11: 3238.14 | DN11: 1 | DO11: 3187.97 | DS11: 1 | DT11: 2164.88 | DX11: 1 | DY11: 2340.04 | EC11: 1 | ED11: 3446 | EH11: 1 | EI11: 2879.94 | EM11: 1 | EN11: 3040.87 | ER11: 1 | ES11: 0 | EW11: 1 | EX11: 3570.73 | FB11: 1 | FC11: 4172.05 | FG11: 1 | FH11: 4535.76 | FL11: 1 | FM11: 4711.12 | FQ11: 1 | FR11: 4295.8 | FV11: 1 | FW11: 2570.27 | GA11: 1 | GB11: 3608.86 | GF11: 1 | GG11: 990.06 | GK11: 1 | GL11: 3446 | GP11: 1 | GQ11: 4195.72 | GU11: 1 | GV11: 8057.34 | GZ11: 1 | HA11: 0 | HE11: 1 | HF11: 3570.73 | HJ11: 1 | HK11: 4172.05 | HO11: 1 | HP11: 4535.76 | HT11: 1 | HU11: 4711.12 | HY11: 1 | HZ11: 4295.8 | ID11: 1 | IE11: 2570.27 | II11: 1 | IJ11: 3608.86 | IN11: 1 | IO11: 990.06
C12: 03344065 | D12: КП "Житомирводоканал" | E12: ХВ | G12: 37.536 | H12: =Таблица32[[#This Row],[Сумма]]/Таблица32[[#This Row],[Тариф]] -> 59.627025 | I12: 2238.16 | L12: =N12/M12 -> 37.928167 | M12: 60 | N12: 2275.69 | Q12: =S12/R12 -> 37.928167 | R12: 60 | S12: 2275.69 | V12: =X12/W12 -> 37.941724 | W12: 58 | X12: 2200.62 | AA12: =AC12/AB12 -> 37.90375 | AB12: 64 | AC12: 2425.84 | AF12: =AH12/AG12 -> 37.963818 | AG12: 55 | AH12: 2088.01 | AK12: =AM12/AL12 -> 37.997451 | AL12: 51 | AM12: 1937.87 | AP12: =AR12/AQ12 -> 38.0066 | AQ12: 50 | AR12: 1900.33 | AU12: =AW12/AV12 -> 37.898 | AV12: 65 | AW12: 2463.37 | AZ12: =BB12/BA12 -> 38.036596 | BA12: 47 | BB12: 1787.72 | BE12: =BG12/BF12 -> 38.02625 | BF12: 48 | BG12: =1825.26 -> 1825.26 | BH12: 192.61 | BJ12: =BL12/BK12 -> 37.76901 | BK12: 101 | BL12: 3814.67 | BO12: =BQ12/BP12 -> 37.915484 | BP12: 62 | BQ12: 2350.76 | BT12: =BV12/BU12 -> 37.854054 | BU12: 74 | BV12: 2801.2 | BY12: =CA12/BZ12 -> 37.812824 | BZ12: 85 | CA12: 3214.09 | CD12: =CF12/CE12 -> 37.882059 | CE12: 68 | CF12: 2575.98 | CI12: =CK12/CJ12 -> 37.762308 | CJ12: 104 | CK12: 3927.28 | CN12: =CP12/CO12 -> 37.887164 | CO12: 67 | CP12: 2538.44 | CS12: =CU12/CT12 -> 65.470909 | CT12: 99 | CU12: 6481.62 | CX12: =CZ12/CY12 -> 79.986296 | CY12: 135 | CZ12: 10798.15 | DC12: =DE12/DD12 -> 80.014828 | DD12: 116 | DE12: 9281.72 | DH12: =DJ12/DI12 -> 80.059684 | DI12: 95 | DJ12: 7605.67 | DM12: =DO12/DN12 -> 80.109873 | DN12: 79 | DO12: 6328.68 | DR12: =DT12/DS12 -> 80.106125 | DS12: 80 | DT12: 6408.49 | DW12: =DY12/DX12 -> 80.210847 | DX12: 59 | DY12: 4732.44 | EB12: =ED12/EC12 -> 82.118904 | EC12: 73 | ED12: 5994.68 | EG12: =EI12/EH12 -> 83.154054 | EH12: 74 | EI12: 6153.4 | EL12: =EN12/EM12 -> 83.112824 | EM12: 85 | EN12: 7064.59 | EQ12: =ES12/ER12 -> 83.11619 | ER12: 84 | ES12: 6981.76 | EV12: =EX12/EW12 -> 83.126543 | EW12: 81 | EX12: 6733.25 | FA12: =FC12/FB12 -> 83.158356 | FB12: 73 | FC12: 6070.56 | FF12: =FH12/FG12 -> 83.06901 | FG12: 101 | FH12: 8389.97 | FK12: =FM12/FL12 -> 83.197077 | FL12: 65 | FM12: 5407.81 | FP12: =FR12/FQ12 -> 83.130125 | FQ12: 80 | FR12: 6650.41 | FU12: =FW12/FV12 -> 83.187164 | FV12: 67 | FW12: 5573.54 | FZ12: =GB12/GA12 -> 83.177101 | GA12: 69 | GB12: 5739.22 | GE12: =GG12/GF12 -> 83.167465 | GF12: 71 | GG12: 5904.89 | GJ12: =GL12/GK12 -> 82.118904 | GK12: 73 | GL12: 5994.68 | GO12: =GQ12/GP12 -> 106.75214 | GP12: 56 | GQ12: 5978.12 | GT12: =GV12/GU12 -> 106.66814 | GU12: 70 | GV12: 7466.77 | GY12: =HA12/GZ12 -> 83.11619 | GZ12: 84 | HA12: 6981.76 | HD12: =HF12/HE12 -> 83.126543 | HE12: 81 | HF12: 6733.25 | HI12: =HK12/HJ12 -> 83.158356 | HJ12: 73 | HK12: 6070.56 | HN12: =HP12/HO12 -> 83.06901 | HO12: 101 | HP12: 8389.97 | HS12: =HU12/HT12 -> 83.197077 | HT12: 65 | HU12: 5407.81 | HX12: =HZ12/HY12 -> 83.130125 | HY12: 80 | HZ12: 6650.41 | IC12: =IE12/ID12 -> 83.187164 | ID12: 67 | IE12: 5573.54 | IH12: =IJ12/II12 -> 83.177101 | II12: 69 | IJ12: 5739.22 | IM12: =IO12/IN12 -> 37.915484 | IN12: 62 | IO12: 2350.76
B13: М2 | C13: г.Киев, ул.Владимирская, 73/77 | D13: ТОВ "Еко-Грінко" | E13: Вывоз ТБО | X13: 1990 | Z13: =SUM(X13:X17)*1.1 -> 64870.718 | AC13: 1548 | AE13: =SUM(AC13:AC17)*1.1 -> 49751.473 | AH13: 1920 | AJ13: =AJ14*1.1 -> 64838.783 | AM13: 1990 | AO13: =AO14*1.2 -> 82628.328 | AR13: 1769 | AT13: =SUM(AR13:AR17)*1.2 -> 101644.94 | AY13: =SUM(AW13:AW17)*1.1 -> 106741.39 | BD13: =SUM(BB13:BB17)*1.22 -> 106425.64 | BI13: =SUM(BG13:BG17)*1.1 -> 68123.642 | BN13: =SUM(BL13:BL17)*1.1 -> 104238.5 | BS13: =SUM(BQ13:BQ17)*1.1 -> 74185.703 | BX13: =SUM(BV13:BV17)*1.1 -> 19813.354 | CC13: =SUM(CA13:CA17)*1.1 -> 100292.54 | CH13: =SUM(CF13:CF17)*1.1 -> 54633.044 | CM13: =SUM(CK13:CK17)*1.1 -> 56634.758 | CR13: =SUM(CP13:CP17)*1.1 -> 81742.914 | CW13: =SUM(CU13:CU17)*1.1 -> 107989 | DB13: =SUM(CZ13:CZ17)*1.1 -> 128841.65 | DG13: =SUM(DE13:DE17)*1.1 -> 125271.88 | DL13: =SUM(DJ13:DJ17)*1.1 -> 111571.32 | DQ13: =SUM(DO13:DO17)*1.1 -> 114805.57 | DV13: =SUM(DT13:DT17)*1.1 -> 111955.27 | EA13: =SUM(DY13:DY17)*1.1 -> 98577.442 | EF13: =SUM(ED13:ED17)*1.1 -> 7901.3088 | EK13: =SUM(EI13:EI17)*1.1 -> 218455.62 | EP13: =SUM(EN13:EN17)*1.1 -> 101002.02 | EU13: =SUM(ES13:ES17)*1.1 -> 86848.579 | EZ13: =SUM(EX13:EX17)*1.1 -> 85650.061 | FE13: =SUM(FC13:FC17)*1.1 -> 114027.59 | FJ13: =SUM(FH13:FH17)*1.1 -> 119724.75 | FO13: =SUM(FM13:FM17)*1.1 -> 153187.47 | FT13: =SUM(FR13:FR17)*1.1 -> 98465.994 | FY13: =SUM(FW13:FW17)*1.1 -> 96821.578 | GD13: =SUM(GB13:GB17)*1.1 -> 105971.37 | GI13: =SUM(GG13:GG17)*1.1 -> 41354.412 | GN13: =SUM(GL13:GL17)*1.1 -> 67396.045 | GS13: =SUM(GQ13:GQ17)*1.1 -> 92150.124 | GX13: =SUM(GV13:GV17)*1.1 -> 97660.834 | HC13: =SUM(HA13:HA17)*1.1 -> 86848.579 | HH13: =SUM(HF13:HF17)*1.1 -> 85650.061 | HM13: =SUM(HK13:HK17)*1.1 -> 114027.59 | HR13: =SUM(HP13:HP17)*1.1 -> 119724.75 | HW13: =SUM(HU13:HU17)*1.1 -> 153187.47 | IB13: =SUM(HZ13:HZ17)*1.1 -> 98465.994 | IG13: =SUM(IE13:IE17)*1.1 -> 93823.726 | IL13: =SUM(IJ13:IJ17)*1.1 -> 41354.412 | IQ13: =SUM(IO13:IO17)*1.1 -> 41354.412
C14: 35791356 | D14: ІП "Альфа Консалтінг" | E14: Экспл. расходы | H14: 1 | I14: =1.2*2899.56 -> 3479.472 | M14: 1 | N14: =1.2*2899.56 -> 3479.472 | R14: 1 | S14: =1.2*2899.56 -> 3479.472 | W14: 1 | X14: =1.2*2899.56 -> 3479.472 | Z14: =SUM(X13:X17)*1 -> 58973.38 | AB14: 1 | AC14: =1.2*2899.56 -> 3479.472 | AE14: =SUM(AC13:AC17)*1 -> 45228.612 | AG14: 1 | AH14: =1.2*2899.56 -> 3479.472 | AJ14: =SUM(AH13:AH17)*1 -> 58944.348 | AL14: 1 | AM14: =1.2*2899.56 -> 3479.472 | AO14: =SUM(AM13:AM17)*1 -> 68856.94 | AQ14: 1 | AR14: =1.2*2899.56 -> 3479.472 | AT14: =SUM(AR13:AR17)*1 -> 84704.12 | AV14: 1 | AW14: =1.2*2899.56 -> 3479.472 | AY14: =SUM(AW13:AW17)*1 -> 97037.628 | BA14: 1 | BB14: =1.2*2899.56 -> 3479.472 | BD14: =SUM(BB13:BB17)*1 -> 87234.132 | BF14: 1 | BG14: =1.2*2899.56 -> 3479.472 | BI14: =SUM(BG13:BG17)*1 -> 61930.584 | BK14: 1 | BL14: =1.2*2899.56 -> 3479.472 | BN14: =SUM(BL13:BL17)*1 -> 94762.274 | BP14: 1 | BQ14: =1.2*2899.56 -> 3479.472 | BS14: =SUM(BQ13:BQ17)*1 -> 67441.548 | BU14: 1 | BV14: 0 | BX14: =SUM(BV13:BV17)*1 -> 18012.14 | BZ14: 1 | CA14: 0 | CC14: =SUM(CA13:CA17)*1 -> 91175.04 | CE14: 1 | CF14: 10 438,414 | CH14: =SUM(CF13:CF17)*1 -> 49666.404 | CJ14: 1 | CK14: =1.2*2899.56 -> 3479.472 | CM14: =SUM(CK13:CK17)*1 -> 51486.144 | CO14: 1 | CP14: =1.2*2899.56 -> 3479.472 | CR14: =SUM(CP13:CP17)*1 -> 74311.74 | CT14: 1 | CU14: =(1.2*2899.56)*2 -> 6958.944 | CW14: =SUM(CU13:CU17)*1 -> 98171.818 | CY14: 1 | CZ14: =1.2*2899.56 -> 3479.472 | DB14: =SUM(CZ13:CZ17)*1 -> 117128.77 | DD14: 1 | DE14: =1.2*(2899.56*2) -> 6958.944 | DG14: =SUM(DE13:DE17)*1 -> 113883.53 | DI14: 1 | DJ14: =1.2*2899.56 -> 3479.472 | DL14: =SUM(DJ13:DJ17)*1 -> 101428.48 | DN14: 1 | DO14: =1.2*2899.56 -> 3479.472 | DQ14: =SUM(DO13:DO17)*1 -> 104368.7 | DS14: 1 | DT14: =1.2*2899.56 -> 3479.472 | DV14: =SUM(DT13:DT17)*1 -> 101777.52 | DX14: 1 | DY14: =1.2*2899.56 -> 3479.472 | EA14: =SUM(DY13:DY17)*1 -> 89615.856 | EC14: 1 | ED14: =1.2*2899.56 -> 3479.472 | EF14: =SUM(ED13:ED17)*1 -> 7183.008 | EH14: 1 | EI14: 0 | EK14: =SUM(EI13:EI17)*1 -> 198596.02 | EM14: 1 | EN14: 10 438,414 | EP14: =SUM(EN13:EN17)*1 -> 91820.022 | ER14: 1 | ES14: 6204.79 | EU14: =SUM(ES13:ES17)*1 -> 78953.254 | EW14: 1 | EX14: =1.2*5170.66 -> 6204.792 | EZ14: =SUM(EX13:EX17)*1 -> 77863.692 | FB14: 1 | FC14: =(1.2*2899.56)*2 -> 6958.944 | FE14: =SUM(FC13:FC17)*1 -> 103661.45 | FG14: 1 | FH14: =1.2*2899.56 -> 3479.472 | FJ14: =SUM(FH13:FH17)*1 -> 108840.68 | FL14: 1 | FM14: =1.2*(5170.66*3) -> 18614.376 | FO14: =SUM(FM13:FM17)*1 -> 139261.33 | FQ14: 1 | FR14: =1.2*5170.66 -> 6204.792 | FT14: =SUM(FR13:FR17)*1 -> 89514.54 | FV14: 1 | FW14: 6204.792 | FY14: =SUM(FW13:FW17)*1 -> 88019.616 | GA14: 1 | GB14: =1.2*(5170.66*2) -> 12409.584 | GD14: =SUM(GB13:GB17)*1 -> 96337.608 | GF14: 1 | GG14: =1.2*2899.56 -> 3479.472 | GI14: =SUM(GG13:GG17)*1 -> 37594.92 | GK14: 1 | GL14: =1.2*2899.56 -> 3479.472 | GN14: =SUM(GL13:GL17)*1 -> 61269.132 | GP14: 1 | GQ14: =1.2*5170.66 -> 6204.792 | GS14: =SUM(GQ13:GQ17)*1 -> 83772.84 | GU14: 1 | GV14: 10 438,414 | GX14: =SUM(GV13:GV17)*1 -> 88782.576 | GZ14: 1 | HA14: 6204.79 | HC14: =SUM(HA13:HA17)*1 -> 78953.254 | HE14: 1 | HF14: =1.2*5170.66 -> 6204.792 | HH14: =SUM(HF13:HF17)*1 -> 77863.692 | HJ14: 1 | HK14: =(1.2*2899.56)*2 -> 6958.944 | HM14: =SUM(HK13:HK17)*1 -> 103661.45 | HO14: 1 | HP14: =1.2*2899.56 -> 3479.472 | HR14: =SUM(HP13:HP17)*1 -> 108840.68 | HT14: 1 | HU14: =1.2*(5170.66*3) -> 18614.376 | HW14: =SUM(HU13:HU17)*1 -> 139261.33 | HY14: 1 | HZ14: =1.2*5170.66 -> 6204.792 | IB14: =SUM(HZ13:HZ17)*1 -> 89514.54 | ID14: 1 | IE14: =1.2*2899.56 -> 3479.472 | IG14: =SUM(IE13:IE17)*1 -> 85294.296 | II14: 1 | IJ14: =1.2*2899.56 -> 3479.472 | IL14: =SUM(IJ13:IJ17)*1 -> 37594.92 | IN14: 1 | IO14: =1.2*2899.56 -> 3479.472 | IQ14: =SUM(IO13:IO17)*1 -> 37594.92
A15: 1 | B15: ЯСНО "КИЇВСЬКІ ЕНЕРГЕТИЧНІ ПОСЛУГИ" | E15: Активная ЭЭ | G15: =I15/H15 -> 5.2317113 | H15: 6442 | I15: =1.2*28085.57 -> 33702.684 | L15: =N15/M15 -> 5.2938113 | M15: 6837 | N15: =1.2*30161.49 -> 36193.788 | Q15: =S15/R15 -> 5.331312 | R15: 6442 | S15: =1.2*28620.26 -> 34344.312 | V15: =X15/W15 -> 5.218872 | W15: 10149 | X15: =1.2*44138.61 -> 52966.332 | AA15: =AC15/AB15 -> 5.0483036 | AB15: 7840 | AC15: =1.2*32982.25 -> 39578.7 | AF15: =AH15/AG15 -> 4.8623883 | AG15: 10848 | AH15: =1.2*43955.99 -> 52747.188 | AK15: =AM15/AL15 -> 5.2394158 | AL15: 11942 | AM15: =1.2*52140.92 -> 62569.104 | AP15: =AR15/AQ15 -> 5.6894517 | AQ15: 13796 | AR15: =1.2*65409.73 -> 78491.676 | AU15: =AW15/AV15 -> 6.5030284 | AV15: 14191 | AW15: =1.2*76903.73 -> 92284.476 | AZ15: =BB15/BA15 -> 6.4884477 | BA15: 12732 | BB15: =1.2*68842.43 -> 82610.916 | BE15: =BG15/BF15 -> 6.7719605 | BF15: 8508 | BG15: =1.2*48013.2 -> 57615.84 | BJ15: =BL15/BK15 -> 6.9206276 | BK15: 13066 | BL15: =1.2*75354.1 -> 90424.92 | BO15: =BQ15/BP15 -> 7.0693802 | BP15: 8964 | BQ15: =1.2*52808.27 -> 63369.924 | BT15: =BV15/BU15 -> 6.1674965 | BU15: 2868 | BV15: 17688.38 | BY15: =CA15/BZ15 -> 5.9139361 | BZ15: 15280 | CA15: =1.2*75304.12 -> 90364.944 | CD15: =CF15/CE15 -> 5.5426084 | CE15: 8873 | CF15: =1.2*40982.97 -> 49179.564 | CI15: =CK15/CJ15 -> 5.1429726 | CJ15: 9025 | CK15: =1.2*38679.44 -> 46415.328 | CN15: =CP15/CO15 -> 6.6155035 | CO15: 10392 | CP15: =1.2*57290.26 -> 68748.312 | CS15: =CU15/CT15 -> 7.7378878 | CT15: 11334 | CU15: =1.2*73084.35 -> 87701.22 | CX15: =CZ15/CY15 -> 8.2090805 | CY15: 13431 | CZ15: 110256.16 | DC15: =DE15/DD15 -> 8.2691876 | DD15: 12519 | DE15: =1.2*86268.3 -> 103521.96 | DH15: =DJ15/DI15 -> 8.4385195 | DI15: 11426 | DJ15: =1.2*80348.77 -> 96418.524 | DM15: =DO15/DN15 -> 8.4963717 | DN15: 11395 | DO15: =80680.13*1.2 -> 96816.156 | DR15: =DT15/DS15 -> 8.4418802 | DS15: 11122 | DT15: =1.2*78242.16 -> 93890.592 | DW15: =DY15/DX15 -> 9.0018269 | DX15: 9452 | DY15: =1.2*70904.39 -> 85085.268 | EB15: =ED15/EC15 -> #DIV/0! | EC15: 0 | ED15: 0 | EG15: =EI15/EH15 -> 9.5795037 | EH15: 20481 | EI15: =1.2*163498.18 -> 196197.82 | EL15: =EN15/EM15 -> 8.4257518 | EM15: 9693 | EN15: =1.2*68059.01 -> 81670.812 | EQ15: =ES15/ER15 -> 7.3465445 | ER15: 9055 | ES15: =1.2*55435.8 -> 66522.96 | EV15: =EX15/EW15 -> 7.4830799 | EW15: 8873 | EX15: =1.2*55331.14 -> 66397.368 | FA15: =FC15/FB15 -> 7.4432159 | FB15: 12519 | FC15: =1.2*77651.35 -> 93181.62 | FF15: =FH15/FG15 -> 8.1897123 | FG15: 12428 | FH15: =1.2*84818.12 -> 101781.74 | FK15: =FM15/FL15 -> 8.237832 | FL15: 13856 | FM15: =1.2*95119.5 -> 114143.4 | FP15: =FR15/FQ15 -> 7.415952 | FQ15: 10240 | FR15: =1.2*63282.79 -> 75939.348 | FU15: =FW15/FV15 -> 9.8454961 | FV15: 8144 | FW15: =66818.1*1.2 -> 80181.72 | FZ15: =GB15/GA15 -> 10.449936 | GA15: 7749 | GB15: =1.2*67480.46 -> 80976.552 | GE15: =GG15/GF15 -> 5.2317113 | GF15: 6442 | GG15: =1.2*28085.57 -> 33702.684 | GJ15: =GL15/GK15 -> 12.606744 | GK15: 4406 | GL15: =1.2*46287.76 -> 55545.312 | GO15: =GQ15/GP15 -> 14.579173 | GP15: 5105 | GQ15: =1.2*62022.23 -> 74426.676 | GT15: =GV15/GU15 -> 11.077344 | GU15: 7658 | GV15: =1.2*70691.92 -> 84830.304 | GY15: =HA15/GZ15 -> 7.3465445 | GZ15: 9055 | HA15: =1.2*55435.8 -> 66522.96 | HD15: =HF15/HE15 -> 7.4830799 | HE15: 8873 | HF15: =1.2*55331.14 -> 66397.368 | HI15: =HK15/HJ15 -> 7.4432159 | HJ15: 12519 | HK15: =1.2*77651.35 -> 93181.62 | HN15: =HP15/HO15 -> 8.1897123 | HO15: 12428 | HP15: =1.2*84818.12 -> 101781.74 | HS15: =HU15/HT15 -> 8.237832 | HT15: 13856 | HU15: =1.2*95119.5 -> 114143.4 | HX15: =HZ15/HY15 -> 7.415952 | HY15: 10240 | HZ15: =1.2*63282.79 -> 75939.348 | IC15: =IE15/ID15 -> 9.8454961 | ID15: 8144 | IE15: =66818.1*1.2 -> 80181.72 | IH15: =IJ15/II15 -> 5.2317113 | II15: 6442 | IJ15: =1.2*28085.57 -> 33702.684 | IM15: =IO15/IN15 -> 5.2317113 | IN15: 6442 | IO15: =1.2*28085.57 -> 33702.684
E16: Реактивная ЭЭ | H16: 1 | I16: =1.2*235.35 -> 282.42 | M16: 1 | N16: =1.2*282.36 -> 338.832 | R16: 1 | S16: =1.2*334.73 -> 401.676 | W16: 1 | X16: =1.2*344.42 -> 413.304 | AB16: 1 | AC16: =1.2*407.54 -> 489.048 | AG16: 1 | AH16: =1.2*556.12 -> 667.344 | AL16: 1 | AM16: =1.2*570.81 -> 684.972 | AQ16: 1 | AR16: =1.2*735.2 -> 882.24 | AV16: 1 | AW16: =1.2*909.73 -> 1091.676 | BA16: 1 | BB16: =1.2*920.46 -> 1104.552 | BF16: 1 | BG16: =1.2*582.38 -> 698.856 | BK16: 1 | BL16: 818.69 | BP16: 1 | BQ16: =1.2*384.84 -> 461.808 | BU16: 1 | BV16: =1.2*158.64 -> 190.368 | BZ16: 1 | CA16: =1.2*563.92 -> 676.704 | CE16: 1 | CF16: =1.2*299.62 -> 359.544 | CJ16: 1 | CK16: =1.2*404.98 -> 485.976 | CO16: 1 | CP16: =1.2*101.87 -> 122.244 | CT16: 1 | CU16: 1731.79 | CY16: 1 | CZ16: 1470.74 | DD16: 1 | DE16: =1.2*1311.64 -> 1573.968 | DI16: 1 | DJ16: =1.2*1166.78 -> 1400.136 | DN16: 1 | DO16: =1089.14*1.2 -> 1306.968 | DS16: 1 | DT16: =1.2*860.02 -> 1032.024 | DX16: 1 | DY16: =1.2*767.31 -> 920.772 | EC16: 0 | ED16: 0 | EH16: 1 | EI16: =1.2*1887.34 -> 2264.808 | EM16: 1 | EN16: 955.35 | ER16: 1 | ES16: =1.2*941.67 -> 1130.004 | EW16: 1 | EX16: =1.2*929.71 -> 1115.652 | FB16: 1 | FC16: =1.2*1450.85 -> 1741.02 | FG16: 1 | FH16: =1.2*1380.89 -> 1657.068 | FL16: 1 | FM16: =1.2*1756.48 -> 2107.776 | FQ16: 1 | FR16: =1.2*1479.25 -> 1775.1 | FV16: 1 | FW16: 816.552 | GA16: 1 | GB16: =1.2*968.81 -> 1162.572 | GF16: 1 | GG16: =1.2*235.35 -> 282.42 | GK16: 1 | GL16: =1.2*456.24 -> 547.488 | GP16: 1 | GQ16: =1.2*664.45 -> 797.34 | GU16: 1 | GV16: =1.2*1446.52 -> 1735.824 | GZ16: 1 | HA16: =1.2*941.67 -> 1130.004 | HE16: 1 | HF16: =1.2*929.71 -> 1115.652 | HJ16: 1 | HK16: =1.2*1450.85 -> 1741.02 | HO16: 1 | HP16: =1.2*1380.89 -> 1657.068 | HT16: 1 | HU16: =1.2*1756.48 -> 2107.776 | HY16: 1 | HZ16: =1.2*1479.25 -> 1775.1 | ID16: 1 | IE16: 816.552 | II16: 1 | IJ16: =1.2*235.35 -> 282.42 | IN16: 1 | IO16: =1.2*235.35 -> 282.42
E17: ХВ | G17: =I17/H17 -> 33.767876 | H17: 3.86 | I17: =1.2*108.62 -> 130.344 | L17: =N17/M17 -> 28.797927 | M17: 3.86 | N17: 111.16 | Q17: =S17/R17 -> 34.557513 | R17: 3.86 | S17: =1.2*111.16 -> 133.392 | V17: =X17/W17 -> 32.194819 | W17: 3.86 | X17: =1.2*103.56 -> 124.272 | AA17: =AC17/AB17 -> 34.557513 | AB17: 3.86 | AC17: =1.2*111.16 -> 133.392 | AF17: =AH17/AG17 -> 34.665957 | AG17: 3.76 | AH17: =1.2*108.62 -> 130.344 | AK17: =AM17/AL17 -> 43.029677 | AL17: 3.1 | AM17: =1.2*111.16 -> 133.392 | AP17: =AR17/AQ17 -> 21.174093 | AQ17: 3.86 | AR17: =1.2*68.11 -> 81.732 | AU17: =AW17/AV17 -> 47.151295 | AV17: 3.86 | AW17: =1.2*151.67 -> 182.004 | AZ17: =BB17/BA17 -> 10.153368 | BA17: 3.86 | BB17: =1.2*32.66 -> 39.192 | BE17: =BG17/BF17 -> 35.340933 | BF17: 3.86 | BG17: =1.2*113.68 -> 136.416 | BJ17: =BL17/BK17 -> 39.192 | BK17: 1 | BL17: =1.2*32.66 -> 39.192 | BO17: =BQ17/BP17 -> 2.1023226 | BP17: 62 | BQ17: =1.2*108.62 -> 130.344 | BT17: =BV17/BU17 -> 133.392 | BU17: 1 | BV17: =1.2*111.16 -> 133.392 | BY17: =CA17/BZ17 -> 133.392 | BZ17: 1 | CA17: =1.2*111.16 -> 133.392 | CD17: =CF17/CE17 -> 127.296 | CE17: 1 | CF17: 127.296 | CI17: =CK17/CJ17 -> 31.581943 | CJ17: 35 | CK17: =1.2*921.14 -> 1105.368 | CN17: =CP17/CO17 -> 31.138286 | CO17: 63 | CP17: =1.2*1634.76 -> 1961.712 | CS17: =CU17/CT17 -> 31.783286 | CT17: 56 | CU17: 1779.864 | CX17: =CZ17/CY17 -> 48.06 | CY17: 40 | CZ17: 1922.4 | DC17: =DE17/DD17 -> 48.122526 | DD17: 38 | DE17: =1.2*1523.88 -> 1828.656 | DH17: =DJ17/DI17 -> 2.1023226 | DI17: 62 | DJ17: =1.2*108.62 -> 130.344 | DM17: =DO17/DN17 -> 47.691379 | DN17: 58 | DO17: 2766.1 | DR17: =DT17/DS17 -> 47.541268 | DS17: 71 | DT17: 3375.43 | DW17: =DY17/DX17 -> 2.1023226 | DX17: 62 | DY17: =1.2*108.62 -> 130.344 | EB17: =ED17/EC17 -> 3703.536 | EC17: 1 | ED17: =1.2*3086.28 -> 3703.536 | EG17: =EI17/EH17 -> 133.392 | EH17: 1 | EI17: =1.2*111.16 -> 133.392 | EL17: =EN17/EM17 -> 50.239672 | EM17: 183 | EN17: 9193.86 | EQ17: =ES17/ER17 -> 50.450495 | ER17: 101 | ES17: =1.2*4246.25 -> 5095.5 | EV17: =EX17/EW17 -> 50.559512 | EW17: 82 | EX17: =1.2*3454.9 -> 4145.88 | FA17: =FC17/FB17 -> 31.783286 | FB17: 56 | FC17: 1779.864 | FF17: =FH17/FG17 -> 48.06 | FG17: 40 | FH17: 1922.4 | FK17: =FM17/FL17 -> 50.526207 | FL17: 87 | FM17: =1.2*3663.15 -> 4395.78 | FP17: =FR17/FQ17 -> 50.408108 | FQ17: 111 | FR17: =1.2*4662.75 -> 5595.3 | FU17: =FW17/FV17 -> 14.078483 | FV17: 58 | FW17: =680.46*1.2 -> 816.552 | FZ17: =GB17/GA17 -> 49.691667 | GA17: 36 | GB17: 1788.9 | GE17: =GG17/GF17 -> 2.1023226 | GF17: 62 | GG17: =1.2*108.62 -> 130.344 | GJ17: =GL17/GK17 -> 51.42 | GK17: 33 | GL17: =1.2*1414.05 -> 1696.86 | GO17: =GQ17/GP17 -> 65.112 | GP17: 36 | GQ17: =1.2*1953.36 -> 2344.032 | GT17: =GV17/GU17 -> 65.189647 | GU17: 34 | GV17: =1.2*1847.04 -> 2216.448 | GY17: =HA17/GZ17 -> 50.450495 | GZ17: 101 | HA17: =1.2*4246.25 -> 5095.5 | HD17: =HF17/HE17 -> 50.559512 | HE17: 82 | HF17: =1.2*3454.9 -> 4145.88 | HI17: =HK17/HJ17 -> 31.783286 | HJ17: 56 | HK17: 1779.864 | HN17: =HP17/HO17 -> 48.06 | HO17: 40 | HP17: 1922.4 | HS17: =HU17/HT17 -> 50.526207 | HT17: 87 | HU17: =1.2*3663.15 -> 4395.78 | HX17: =HZ17/HY17 -> 50.408108 | HY17: 111 | HZ17: =1.2*4662.75 -> 5595.3 | IC17: =IE17/ID17 -> 14.078483 | ID17: 58 | IE17: =680.46*1.2 -> 816.552 | IH17: =IJ17/II17 -> 2.1023226 | II17: 62 | IJ17: =1.2*108.62 -> 130.344 | IM17: =IO17/IN17 -> 2.1023226 | IN17: 62 | IO17: =1.2*108.62 -> 130.344
B18: М3 | C18: г.Киев, ул.Р.Окипной,3 | D18: ТОВ "Еко-Грінко" | E18: Вывоз ТБО | X18: 1769 | Z18: =SUM(X18:X21)*1.1 -> 69137.352 | AC18: 1769 | AE18: =SUM(AC18:AC21)*1.1 -> 64896.55 | AH18: 2211 | AJ18: =AJ19*1.1 -> 119705.9 | AM18: 1327 | AO18: =AO19*1.2 -> 155518.7 | AR18: 2211 | AT18: =SUM(AR18:AR21)*1.2 -> 142971.74 | AY18: =SUM(AW18:AW21)*1.1 -> 145006.85 | BD18: =SUM(BB19:BB21)*1.2 -> 139319.87 | BI18: =SUM(BG18:BG21)*1.1 -> 109403.84 | BN18: =SUM(BL18:BL21)*1.1 -> 104134.14 | BS18: =SUM(BQ18:BQ21)*1.1 -> 104482.36 | BX18: =SUM(BV18:BV21)*1.1 -> 104340.07 | CC18: =SUM(CA18:CA21)*1.1 -> 83764.371 | CH18: =SUM(CF18:CF21)*1.1 -> 90739.235 | CM18: =SUM(CK18:CK21)*1.1 -> 96036.882 | CR18: =SUM(CP18:CP21)*1.1 -> 126888.25 | CW18: =SUM(CU18:CU21)*1.1 -> 135817.14 | DB18: =SUM(CZ18:CZ21)*1.1 -> 149448.1 | DG18: =SUM(DE18:DE21)*1.1 -> 24808.887 | DL18: =SUM(DJ18:DJ21)*1.1 -> 162784.47 | DQ18: =SUM(DO18:DO21)*1.1 -> 191292.29 | DV18: =SUM(DT18:DT21)*1.1 -> 118509.72 | EA18: =SUM(DY18:DY21)*1.1 -> 133850.99 | EF18: =SUM(ED18:ED21)*1.1 -> 149790.99 | EK18: =SUM(EI18:EI21)*1.1 -> 144563.29 | EP18: =SUM(EN18:EN21)*1.1 -> 135036.11 | EU18: =SUM(ES18:ES21)*1.1 -> 119963.48 | EZ18: =SUM(EX18:EX21)*1.1 -> 154610.05 | FE18: =SUM(FC18:FC21)*1.1 -> 169315.23 | FJ18: =SUM(FH18:FH21)*1.1 -> 206414.76 | FO18: =SUM(FM18:FM21)*1.1 -> 199860.4 | FT18: =SUM(FR18:FR21)*1.1 -> 156441.11 | FY18: =SUM(FW18:FW21)*1.1 -> 156314.82 | GD18: =SUM(GB18:GB21)*1.1 -> 127580.88 | GI18: =SUM(GG18:GG21)*1.1 -> 112941.22 | GN18: =SUM(GL18:GL21)*1.1 -> 149790.99 | GS18: =SUM(GQ18:GQ21)*1.1 -> 152367.51 | GX18: =SUM(GV18:GV21)*1.1 -> 168134.52 | HC18: =SUM(HA18:HA21)*1.1 -> 119963.48 | HH18: =SUM(HF18:HF21)*1.1 -> 154610.05 | HM18: =SUM(HK18:HK21)*1.1 -> 169315.23 | HR18: =SUM(HP18:HP21)*1.1 -> 206414.76 | HW18: =SUM(HU18:HU21)*1.1 -> 199860.4 | IB18: =SUM(HZ18:HZ21)*1.1 -> 156441.11 | IG18: =SUM(IE18:IE21)*1.1 -> 156314.82 | IL18: =SUM(IJ18:IJ21)*1.1 -> 25472.704 | IQ18: =SUM(IO18:IO21)*1.1 -> 24808.887
A19: 1 | C19: 45179093 | D19: ЯСНО+ | E19: Активная ЭЭ | G19: =I19/H19 -> 5.3077205 | H19: 3964 | I19: 21039.804 | J19: 14610.975 | L19: =N19/M19 -> 5.3685484 | M19: 8176 | N19: 43893.252 | O19: 43893.252 | Q19: =S19/R19 -> 4.9663922 | R19: 8292 | S19: =34317.77*1.2 -> 41181.324 | T19: 41181.324 | V19: =X19/W19 -> 5.2077241 | W19: 11220 | X19: 58430.664 | Y19: 58430.664 | Z19: =SUM(X18:X21)*1 -> 62852.138 | AA19: =AC19/AB19 -> 4.6829517 | AB19: 11676 | AC19: 54678.144 | AD19: 54678.144 | AE19: =SUM(AC18:AC21)*1 -> 58996.864 | AF19: =AH19/AG19 -> 4.819944 | AG19: 15136 | AH19: 72954.672 | AI19: =28777.97+74729.76 -> 103507.73 | AJ19: =SUM(AH20:AH21)+AI19+AH18*1 -> 108823.55 | AK19: =AM19/AL19 -> 4.9792203 | AL19: 17160 | AM19: 85443.42 | AN19: =37070.31+89591.256 -> 126661.57 | AO19: =SUM(AM20:AM21)+AN19+AM18*1 -> 129598.92 | AP19: =AR19/AQ19 -> 5.9466958 | AQ19: 19092 | AR19: 113534.32 | AS19: 128035 | AT19: =SUM(AR18:AR21)*1 -> 119143.12 | AU19: =AW19/AV19 -> 6.610763 | AV19: 19372 | AW19: 128063.7 | AX19: 14610.975 | AY19: =SUM(AW18:AW21)*1 -> 131824.41 | AZ19: =BB19/BA19 -> 6.3494518 | BA19: 17688 | BB19: 112309.1 | BC19: 93590.92 | BD19: =(BB21+BB20+BB19)*1 -> 116099.89 | BE19: =BG19/BF19 -> 6.2594404 | BF19: 15596 | BG19: 97622.232 | BH19: 93590.92 | BI19: =SUM(BG18:BG21)*1 -> 99458.032 | BJ19: =BL19/BK19 -> 6.7596598 | BK19: 13676 | BL19: 92445.108 | BM19: 77284.27 | BN19: =SUM(BL18:BL21)*1 -> 94667.398 | BO19: =BQ19/BP19 -> 6.4951202 | BP19: 14180 | BQ19: 92100.804 | BR19: 14610.975 | BS19: =SUM(BQ18:BQ21)*1 -> 94983.964 | BT19: =BV19/BU19 -> 6.131988 | BU19: 15024 | BV19: 92126.988 | BW19: 93423.62 | BX19: =SUM(BV21+BV20+BW19)*1 -> 96151.24 | BY19: =CA19/BZ19 -> 5.5075804 | BZ19: 13412 | CA19: 73867.668 | CB19: 125 064,66 | CC19: =SUM(CA18:CA21)*1 -> 76149.428 | CD19: =CF19/CE19 -> 5.50758 | CE19: 14515 | CF19: =66618.77*1.2 -> 79942.524 | CG19: 48984.39 | CH19: =SUM(CF18:CF21)*1 -> 82490.214 | CI19: =CK19/CJ19 -> 5.428992 | CJ19: 15560 | CK19: 84475.116 | CL19: 14610.975 | CM19: =SUM(CK18:CK21)*1 -> 87306.256 | CN19: =CP19/CO19 -> 6.4400163 | CO19: 17432 | CP19: 112262.36 | CQ19: 79503.06 | CR19: =SUM(CP18:CP21)*1 -> 115352.95 | CS19: =CU19/CT19 -> 7.4135397 | CT19: 16076 | CU19: 119180.06 | CV19: 142053.88 | CW19: =SUM(CU18:CU21)*1 -> 123470.12 | CX19: =CZ19/CY19 -> 7.888284 | CY19: 17028 | CZ19: =1.2*111934.75 -> 134321.7 | DA19: 142347.38 | DB19: =SUM(CZ18:CZ21)*1 -> 135861.91 | DC19: =DE19/DD19 -> 5.3077205 | DD19: 3964 | DE19: 21039.804 | DF19: 144116.22 | DG19: =SUM(DE18:DE21)*1 -> 22553.534 | DH19: =DJ19/DI19 -> 8.0664362 | DI19: 17964 | DJ19: =1.2*120754.55 -> 144905.46 | DK19: 133428.44 | DL19: =SUM(DJ18:DJ21)*1 -> 147985.88 | DM19: =DO19/DN19 -> 7.9066802 | DN19: 21785 | DO19: 172247.03 | DP19: 127547.46 | DQ19: =SUM(DO18:DO21)*1 -> 173902.08 | DR19: =DT19/DS19 -> 8.0964361 | DS19: 12896 | DT19: 104411.64 | DU19: 143539.2 | DV19: =SUM(DT18:DT21)*1 -> 107736.11 | DW19: =DY19/DX19 -> 8.7321838 | DX19: 13688 | DY19: 119526.13 | DZ19: 84833.105 | EA19: =SUM(DY18:DY21)*1 -> 121682.72 | EB19: =ED19/EC19 -> 8.7025561 | EC19: 15300 | ED19: 133149.11 | EE19: 122848.87 | EF19: =SUM(ED21+ED20+EE19)*1 -> 125873.39 | EG19: =EI19/EH19 -> 8.943156 | EH19: 14308 | EI19: =1.2*106632.23 -> 127958.68 | EJ19: 133149.11 | EK19: =SUM(EI18:EI21)*1 -> 131421.18 | EL19: =EN19/EM19 -> 7.9463519 | EM19: 15128 | EN19: 120212.41 | EO19: 127958.68 | EP19: =SUM(EN18:EN21)*1 -> 122760.1 | EQ19: =ES19/ER19 -> 6.7961337 | ER19: 15560 | ES19: =88123.2*1.2 -> 105747.84 | ET19: 127958.68 | EU19: =SUM(ES18:ES21)*1 -> 109057.71 | EV19: =EX19/EW19 -> 6.9424921 | EW19: 19656 | EX19: 136461.62 | EY19: 79503.06 | EZ19: =SUM(EX18:EX21)*1 -> 140554.59 | FA19: =FC19/FB19 -> 7.0390202 | FB19: 21208 | FC19: 149283.54 | FD19: 136462 | FE19: =SUM(FC18:FC21)*1 -> 153922.94 | FF19: =FH19/FG19 -> 7.7927402 | FG19: 23984 | FH19: 186901.08 | FI19: 149284 | FJ19: =SUM(FH18:FH21)*1 -> 187649.78 | FK19: =FM19/FL19 -> 7.7835238 | FL19: 23240 | FM19: 180889.09 | FN19: 186901 | FO19: =SUM(FM18:FM21)*1 -> 181691.27 | FP19: =FR19/FQ19 -> 6.8583121 | FQ19: 20612 | FR19: 141363.53 | FS19: 183339.61 | FT19: =SUM(FR18:FR21)*1 -> 142219.19 | FU19: =FW19/FV19 -> 9.1250878 | FV19: 15444 | FW19: 140927.86 | FX19: 127547.46 | FY19: =SUM(FW18:FW21)*1 -> 142104.39 | FZ19: =GB19/GA19 -> 9.7088523 | GA19: 11728 | GB19: 113865.42 | GC19: 140927.86 | GD19: =SUM(GB18:GB21)*1 -> 115982.62 | GE19: =GG19/GF19 -> 9.9062164 | GF19: 10316 | GG19: =1.2*85160.44 -> 102192.53 | GH19: 157030.97 | GI19: =SUM(GG18:GG21)*1 -> 102673.84 | GJ19: =GL19/GK19 -> 8.7025561 | GK19: 15300 | GL19: 133149.11 | GM19: 122848.87 | GN19: =SUM(GL21+GL20+GM19)*1 -> 125873.39 | GO19: =GQ19/GP19 -> 14.042856 | GP19: 9732 | GQ19: 136665.07 | GR19: 133149.11 | GS19: =SUM(GQ18:GQ21)*1 -> 138515.92 | GT19: =GV19/GU19 -> 10.461684 | GU19: 14436 | GV19: 151024.87 | GW19: 127958.68 | GX19: =SUM(GV18:GV21)*1 -> 152849.56 | GY19: =HA19/GZ19 -> 6.7961337 | GZ19: 15560 | HA19: =88123.2*1.2 -> 105747.84 | HB19: 127958.68 | HC19: =SUM(HA18:HA21)*1 -> 109057.71 | HD19: =HF19/HE19 -> 6.9424921 | HE19: 19656 | HF19: 136461.62 | HG19: 79503.06 | HH19: =SUM(HF18:HF21)*1 -> 140554.59 | HI19: =HK19/HJ19 -> 7.0390202 | HJ19: 21208 | HK19: 149283.54 | HL19: 136462 | HM19: =SUM(HK18:HK21)*1 -> 153922.94 | HN19: =HP19/HO19 -> 7.7927402 | HO19: 23984 | HP19: 186901.08 | HQ19: 149284 | HR19: =SUM(HP18:HP21)*1 -> 187649.78 | HS19: =HU19/HT19 -> 7.7835238 | HT19: 23240 | HU19: 180889.09 | HV19: 186901 | HW19: =SUM(HU18:HU21)*1 -> 181691.27 | HX19: =HZ19/HY19 -> 6.8583121 | HY19: 20612 | HZ19: 141363.53 | IA19: 183339.61 | IB19: =SUM(HZ18:HZ21)*1 -> 142219.19 | IC19: =IE19/ID19 -> 9.1250878 | ID19: 15444 | IE19: 140927.86 | IF19: 127547.46 | IG19: =SUM(IE18:IE21)*1 -> 142104.39 | IH19: =IJ19/II19 -> 5.3077205 | II19: 3964 | IJ19: 21039.804 | IK19: 143539.2 | IL19: =SUM(IJ18:IJ21)*1 -> 23157.004 | IM19: =IO19/IN19 -> 5.3077205 | IN19: 3964 | IO19: 21039.804 | IP19: 14610.975 | IQ19: =SUM(IO18:IO21)*1 -> 22553.534
C20: 41946011 | D20: «ДТЕК КИЇВСЬКІ ЕЛЕКТРОМЕРЕЖІ» | E20: Реактивная ЭЭ | H20: 0 | I20: 0 | M20: 0 | N20: 651.98 | R20: 0 | S20: 650.05 | X20: 945.504 | AB20: 0 | AC20: 1068.2 | AG20: 0 | AH20: 1462.27 | AL20: 0 | AM20: 1 525,16 | AR20: 1761.86 | AV20: 0 | AW20: 2053.74 | BA20: 0 | BB20: 1954.99 | BF20: 0 | BG20: 1 476,04 | BK20: 0 | BL20: 1 115,62 | BP20: 0 | BQ20: 950.74 | BU20: 1 | BV20: 988.44 | BZ20: 1 | CA20: 735.82 | CE20: 0 | CF20: 937.34 | CJ20: 0 | CK20: 1103.87 | CO20: 0 | CP20: 1419.04 | CT20: 0 | CU20: 1858.4 | CY20: 0 | CZ20: 0 | DD20: 0 | DE20: 0 | DI20: 0 | DJ20: 0 | DN20: 0 | DO20: 0 | DS20: 1 | DT20: 1368.5 | DX20: 0 | DY20: 0 | EC20: 1 | ED20: 1285.34 | EH20: 1 | EI20: 963.5 | EM20: 0 | EN20: 937.34 | ER20: 1 | ES20: 1582.6 | EW20: 0 | EX20: 1419.04 | FB20: 0 | FC20: 1858.4 | FG20: 0 | FH20: 0 | FI20: 2316.9 | FL20: 0 | FM20: 0 | FQ20: 0 | FR20: 0 | FV20: 0 | FW20: 0 | GA20: 1 | GB20: 1368.5 | GF20: 0 | GG20: 0 | GK20: 1 | GL20: 1285.34 | GP20: 1 | GQ20: 963.5 | GU20: 0 | GV20: 937.34 | GZ20: 1 | HA20: 1582.6 | HE20: 0 | HF20: 1419.04 | HJ20: 0 | HK20: 1858.4 | HO20: 0 | HP20: 0 | HQ20: 2316.9 | HT20: 0 | HU20: 0 | HY20: 0 | HZ20: 0 | ID20: 0 | IE20: 0 | II20: 1 | IJ20: 1368.5 | IN20: 0 | IO20: 0
C21: 2978013090 | D21: ФОП Воробьев А.Н. | E21: ХВ | G21: =I21/H21 -> 32.207021 | H21: 47 | I21: 1513.73 | L21: =N21/M21 -> 32.207105 | M21: 38 | N21: 1223.87 | Q21: =S21/R21 -> 32.207347 | R21: 49 | S21: 1578.16 | V21: =X21/W21 -> 32.206981 | W21: 53 | X21: 1706.97 | AA21: =AC21/AB21 -> 32.206957 | AB21: 46 | AC21: 1481.52 | AF21: =AH21/AG21 -> 32.206863 | AG21: 51 | AH21: 1642.55 | AK21: =AM21/AL21 -> 32.207 | AL21: 50 | AM21: 1610.35 | AP21: =AR21/AQ21 -> 34.082083 | AQ21: 48 | AR21: 1635.94 | AU21: =AW21/AV21 -> 32.206981 | AV21: 53 | AW21: 1706.97 | AZ21: =BB21/BA21 -> 32.207018 | BA21: 57 | BB21: 1835.8 | BE21: =BG21/BF21 -> 32.207018 | BF21: 57 | BG21: 1835.8 | BJ21: =BL21/BK21 -> 32.207101 | BK21: 69 | BL21: 2222.29 | BO21: =BQ21/BP21 -> 32.207 | BP21: 60 | BQ21: 1932.42 | BT21: =BV21/BU21 -> 32.207037 | BU21: 54 | BV21: 1739.18 | BY21: =CA21/BZ21 -> 32.207083 | BZ21: 48 | CA21: 1545.94 | CD21: =CF21/CE21 -> 32.207 | CE21: 50 | CF21: 1610.35 | CI21: =CK21/CJ21 -> 32.20716 | CJ21: 53.63 | CK21: 1727.27 | CN21: =CP21/CO21 -> 32.207129 | CO21: 51.9 | CP21: 1671.55 | CS21: =CU21/CT21 -> 42.863741 | CT21: 56.73 | CU21: 2431.66 | CX21: =CZ21/CY21 -> 49.684194 | CY21: 31 | CZ21: 1540.21 | DC21: =DE21/DD21 -> 32.207021 | DD21: 47 | DE21: 1513.73 | DH21: =DJ21/DI21 -> 49.684194 | DI21: 62 | DJ21: 3080.42 | DM21: =DO21/DN21 -> 50.15303 | DN21: 33 | DO21: 1655.05 | DR21: =DT21/DS21 -> 50.153077 | DS21: 39 | DT21: 1955.97 | DW21: =DY21/DX21 -> 50.153256 | DX21: 43 | DY21: 2156.59 | EB21: =ED21/EC21 -> 32.207037 | EC21: 54 | ED21: 1739.18 | EG21: =EI21/EH21 -> 49.98 | EH21: 50 | EI21: 2499 | EL21: =EN21/EM21 -> 32.207 | EM21: 50 | EN21: 1610.35 | EQ21: =ES21/ER21 -> 32.20716 | ER21: 53.63 | ES21: 1727.27 | EV21: =EX21/EW21 -> 53.4786 | EW21: 50 | EX21: 2673.93 | FA21: =FC21/FB21 -> 53.480769 | FB21: 52 | FC21: 2781 | FF21: =FH21/FG21 -> 53.478571 | FG21: 14 | FH21: 748.7 | FK21: =FM21/FL21 -> 53.478667 | FL21: 15 | FM21: 802.18 | FP21: =FR21/FQ21 -> 53.47875 | FQ21: 16 | FR21: 855.66 | FU21: =FW21/FV21 -> 53.478636 | FV21: 22 | FW21: 1176.53 | FZ21: =GB21/GA21 -> 53.478571 | GA21: 14 | GB21: 748.7 | GE21: =GG21/GF21 -> 53.478889 | GF21: 9 | GG21: 481.31 | GJ21: =GL21/GK21 -> 32.207037 | GK21: 54 | GL21: 1739.18 | GO21: =GQ21/GP21 -> 68.257692 | GP21: 13 | GQ21: 887.35 | GT21: =GV21/GU21 -> 68.257692 | GU21: 13 | GV21: 887.35 | GY21: =HA21/GZ21 -> 32.20716 | GZ21: 53.63 | HA21: 1727.27 | HD21: =HF21/HE21 -> 53.4786 | HE21: 50 | HF21: 2673.93 | HI21: =HK21/HJ21 -> 53.480769 | HJ21: 52 | HK21: 2781 | HN21: =HP21/HO21 -> 53.478571 | HO21: 14 | HP21: 748.7 | HS21: =HU21/HT21 -> 53.478667 | HT21: 15 | HU21: 802.18 | HX21: =HZ21/HY21 -> 53.47875 | HY21: 16 | HZ21: 855.66 | IC21: =IE21/ID21 -> 53.478636 | ID21: 22 | IE21: 1176.53 | IH21: =IJ21/II21 -> 53.478571 | II21: 14 | IJ21: 748.7 | IM21: =IO21/IN21 -> 32.207021 | IN21: 47 | IO21: 1513.73
B22: М4/1 | C22: пгт.Коцюбинское, ул. Пономарева, 28а | D22: ПП "Обухівміськвторресурси" | E22: Вывоз ТБО | X22: 2530 | Z22: =SUM(X22:X25)*1.2 -> 83719.562 | AC22: 2024 | AE22: =SUM(AC22:AC25)*1.2 -> 97664.035 | AH22: 2024 | AJ22: =AJ23*1.1 -> 98364.73 | AM22: 2530 | AO22: =AO23*1.2 -> 120776.1 | AT22: =SUM(AR22:AR25)*1.2 -> 143589.86 | AY22: =SUM(AW22:AW25)*1.2 -> 168735.83 | BD22: =SUM(BB22:BB25)*1.2 -> 132970.68 | BI22: =SUM(BG22:BG25)*1.2 -> 145941.81 | BN22: =SUM(BL22:BL25)*1.1 -> 150848.56 | BS22: =SUM(BQ22:BQ25)*1.2 -> 139827.85 | BX22: =SUM(BV22:BV25)*1.2 -> 132846.63 | CC22: =SUM(CA22:CA25)*1.2 -> 113805.97 | CH22: =SUM(CF22:CF25)*1.2 -> 110010.41 | CM22: =SUM(CK22:CK25)*1.2 -> 116878.16 | CR22: =SUM(CP22:CP25)*1.2 -> 140467.24 | CW22: =SUM(CU22:CU25)*1.2 -> 147358.96 | DB22: =SUM(CZ22:CZ25)*1.2 -> 128861.5 | DG22: =SUM(DE22:DE25)*1.2 -> 180745.98 | DL22: =SUM(DJ22:DJ25)*1.2 -> 166849.69 | DQ22: =SUM(DO22:DO25)*1.2 -> 156890.48 | DV22: =SUM(DT22:DT25)*1.2 -> 156247.51 | EA22: =SUM(DY22:DY25)*1.2 -> 148471.32 | EF22: =SUM(ED22:ED25)*1.2 -> 170532.05 | EK22: =SUM(EI22:EI25)*1.2 -> 195644.3 | EP22: =SUM(EN22:EN25)*1.2 -> 160930.14 | EU22: =SUM(ES22:ES25)*1.2 -> 157088.46 | EZ22: =SUM(EX22:EX25)*1.2 -> 135008.94 | FE22: =SUM(FC22:FC25)*1.2 -> 143923.82 | FJ22: =SUM(FH22:FH25)*1.2 -> 157970.89 | FO22: =SUM(FM22:FM25)*1.2 -> 182269.09 | FT22: =SUM(FR22:FR25)*1.2 -> 157105.08 | FY22: =SUM(FW22:FW25)*1.2 -> 170410.96 | GD22: =SUM(GB22:GB25)*1.2 -> 142361.21 | GI22: =SUM(GG22:GG25)*1.2 -> 147351.05 | GN22: =SUM(GL22:GL25)*1.2 -> 110355.49 | GS22: =SUM(GQ22:GQ25)*1.2 -> 80914.469 | GX22: =SUM(GV22:GV25)*1.2 -> 107672.18 | HC22: =SUM(HA22:HA25)*1.2 -> 157088.46 | HH22: =SUM(HF22:HF25)*1.2 -> 135008.94 | HM22: =SUM(HK22:HK25)*1.2 -> 143923.82 | HR22: =SUM(HP22:HP25)*1.2 -> 157970.89 | HW22: =SUM(HU22:HU25)*1.2 -> 182269.09 | IB22: =SUM(HZ22:HZ25)*1.2 -> 157105.08 | IG22: =SUM(IE22:IE25)*1.2 -> 170410.96 | IL22: =SUM(IJ22:IJ25)*1.2 -> 280048.9 | IQ22: =SUM(IO22:IO25)*1.2 -> 38836.342
A23: 1 | B23: КОЕК універсал | C23: 19420118 | D23: НВПФ "Казі-2" | E23: Активная ЭЭ | G23: =I23/H23 -> 5.799529 | H23: 5291 | I23: =1.2*25571.09 -> 30685.308 | L23: =N23/M23 -> 5.7929482 | M23: 7766 | N23: =1.2*37490.03 -> 44988.036 | Q23: =S23/R23 -> 5.7364085 | R23: 8020 | S23: =1.2*38338.33 -> 46005.996 | V23: =X23/W23 -> 5.9058732 | W23: 10679 | X23: =1.2*52557.35 -> 63068.82 | Z23: =SUM(X22:X25)*1 -> 69766.302 | AA23: =AC23/AB23 -> 5.6497683 | AB23: 13249 | AC23: =1.2*62378.15 -> 74853.78 | AE23: =SUM(AC22:AC25)*1 -> 81386.696 | AF23: =AH23/AG23 -> 5.4696957 | AG23: 15144 | AH23: =1.2*69027.56 -> 82833.072 | AJ23: =SUM(AH22:AH25)*1 -> 89422.482 | AK23: =AM23/AL23 -> 5.8678682 | AL23: 15931 | AM23: =1.2*77900.84 -> 93481.008 | AO23: =SUM(AM22:AM25)*1 -> 100646.75 | AP23: =AR23/AQ23 -> 6.762972 | AQ23: 16981 | AR23: =1.2*95701.69 -> 114842.03 | AT23: =SUM(AR22:AR25)*1 -> 119658.22 | AU23: =AW23/AV23 -> 7.3032483 | AV23: 18400 | AW23: =1.2*111983.14 -> 134379.77 | AY23: =SUM(AW22:AW25)*1 -> 140613.19 | AZ23: =BB23/BA23 -> 6.1660898 | BA23: 17081 | BB23: 105322.98 | BD23: =SUM(BB22:BB25)*1 -> 110808.9 | BE23: =BG23/BF23 -> 7.5466201 | BF23: 15358 | BG23: =1.2*96584.16 -> 115900.99 | BI23: =SUM(BG22:BG25)*1 -> 121618.18 | BJ23: =BL23/BK23 -> 7.6667398 | BK23: 17017 | BL23: =1.2*108720.76 -> 130464.91 | BN23: =SUM(BL22:BL25)*1 -> 137135.05 | BO23: =BQ23/BP23 -> 7.54662 | BP23: 14530 | BQ23: =1.2*91376.99 -> 109652.39 | BS23: =SUM(BQ22:BQ25)*1 -> 116523.21 | BT23: =BV23/BU23 -> 7.2362638 | BU23: 14193 | BV23: =1.2*85586.91 -> 102704.29 | BX23: =SUM(BV22:BV25)*1 -> 110705.52 | BY23: =CA23/BZ23 -> 6.6959042 | BZ23: 13271 | CA23: =1.2*74051.12 -> 88861.344 | CC23: =SUM(CA22:CA25)*1 -> 94838.308 | CD23: =CF23/CE23 -> 6.0954956 | CE23: 14180 | CF23: =72028.44*1.2 -> 86434.128 | CH23: =SUM(CF22:CF25)*1 -> 91675.342 | CI23: =CK23/CJ23 -> 6.6573483 | CJ23: 13987 | CK23: 93116.33 | CM23: =SUM(CK22:CK25)*1 -> 97398.47 | CN23: =CP23/CO23 -> 7.7616725 | CO23: 14517 | CP23: 112676.2 | CR23: =SUM(CP22:CP25)*1 -> 117056.03 | CS23: =CU23/CT23 -> 8.6139119 | CT23: 13615 | CU23: 117278.41 | CW23: =SUM(CU22:CU25)*1 -> 122799.13 | CX23: =CZ23/CY23 -> 9.4557603 | CY23: 10720 | CZ23: 101365.75 | DB23: =SUM(CZ22:CZ25)*1 -> 107384.58 | DC23: =DE23/DD23 -> 9.4797717 | DD23: 14982 | DE23: 142025.94 | DG23: =SUM(DE22:DE25)*1 -> 150621.65 | DH23: =DJ23/DI23 -> 9.635844 | DI23: 13614 | DJ23: 131182.38 | DL23: =SUM(DJ22:DJ25)*1 -> 139041.41 | DM23: =DO23/DN23 -> 8.9188081 | DN23: 13676 | DO23: 121973.62 | DQ23: =SUM(DO22:DO25)*1 -> 130742.07 | DR23: =DT23/DS23 -> 9.7955402 | DS23: 12541 | DT23: 122845.87 | DV23: =SUM(DT22:DT25)*1 -> 130206.26 | DW23: =DY23/DX23 -> 9.8796126 | DX23: 11693 | DY23: 115522.31 | EA23: =SUM(DY22:DY25)*1 -> 123726.1 | EB23: =ED23/EC23 -> 10.011984 | EC23: 13328 | ED23: 133439.72 | EF23: =SUM(ED22:ED25)*1 -> 142110.04 | EG23: =EI23/EH23 -> 10.19208 | EH23: 15410 | EI23: 157059.95 | EK23: =SUM(EI22:EI25)*1 -> 163036.91 | EL23: =EN23/EM23 -> 9.4716958 | EM23: 13881 | EN23: 131476.61 | EP23: =SUM(EN22:EN25)*1 -> 134108.45 | EQ23: =ES23/ER23 -> 8.6886715 | ER23: 14829 | ES23: 128844.31 | EU23: =SUM(ES22:ES25)*1 -> 130907.05 | EV23: =EX23/EW23 -> 8.6286602 | EW23: 12793 | EX23: 110386.45 | EZ23: =SUM(EX22:EX25)*1 -> 112507.45 | FA23: =FC23/FB23 -> 8.6286596 | FB23: 13735 | FC23: 118514.64 | FE23: =SUM(FC22:FC25)*1 -> 119936.52 | FF23: =FH23/FG23 -> 9.2297154 | FG23: 13597 | FH23: 125496.44 | FJ23: =SUM(FH22:FH25)*1 -> 131642.41 | FK23: =FM23/FL23 -> 9.6498601 | FL23: 14655 | FM23: 141418.7 | FN23: 0.05 | FO23: =SUM(FM22:FM25)*1 -> 151890.91 | FP23: =FR23/FQ23 -> 8.6646236 | FQ23: 14255 | FR23: 123514.21 | FT23: =SUM(FR22:FR25)*1 -> 130920.9 | FU23: =FW23/FV23 -> 11.1885 | FV23: 12017 | FW23: 134452.2 | FY23: =SUM(FW22:FW25)*1 -> 142009.13 | FZ23: =GB23/GA23 -> 11.728836 | GA23: 9894 | GB23: 116045.1 | GD23: =SUM(GB22:GB25)*1 -> 118634.34 | GE23: =GG23/GF23 -> 11.524704 | GF23: 10425 | GG23: 120145.04 | GI23: =SUM(GG22:GG25)*1 -> 122792.54 | GJ23: =GL23/GK23 -> 13.54302 | GK23: 6202 | GL23: 83993.81 | GN23: =SUM(GL22:GL25)*1 -> 91962.91 | GO23: =GQ23/GP23 -> 15.163992 | GP23: 4113 | GQ23: 62369.5 | GS23: =SUM(GQ22:GQ25)*1 -> 67428.724 | GT23: =GV23/GU23 -> 12.402336 | GU23: 7167 | GV23: 88887.54 | GX23: =SUM(GV22:GV25)*1 -> 89726.82 | GY23: =HA23/GZ23 -> 8.6886715 | GZ23: 14829 | HA23: 128844.31 | HC23: =SUM(HA22:HA25)*1 -> 130907.05 | HD23: =HF23/HE23 -> 8.6286602 | HE23: 12793 | HF23: 110386.45 | HH23: =SUM(HF22:HF25)*1 -> 112507.45 | HI23: =HK23/HJ23 -> 8.6286596 | HJ23: 13735 | HK23: 118514.64 | HM23: =SUM(HK22:HK25)*1 -> 119936.52 | HN23: =HP23/HO23 -> 9.2297154 | HO23: 13597 | HP23: 125496.44 | HR23: =SUM(HP22:HP25)*1 -> 131642.41 | HS23: =HU23/HT23 -> 9.6498601 | HT23: 14655 | HU23: 141418.7 | HV23: 0.05 | HW23: =SUM(HU22:HU25)*1 -> 151890.91 | HX23: =HZ23/HY23 -> 8.6646236 | HY23: 14255 | HZ23: 123514.21 | IB23: =SUM(HZ22:HZ25)*1 -> 130920.9 | IC23: =IE23/ID23 -> 11.1885 | ID23: 12017 | IE23: 134452.2 | IG23: =SUM(IE22:IE25)*1 -> 142009.13 | IH23: =IJ23/II23 -> 11.728836 | II23: 9894 | IJ23: 116045.1 | IL23: =SUM(IJ22:IJ25)*1 -> 233374.08 | IM23: =IO23/IN23 -> 5.799529 | IN23: 5291 | IO23: =1.2*25571.09 -> 30685.308 | IQ23: =SUM(IO22:IO25)*1 -> 32363.618
C24: НДС | D24: НВПФ "Казі-2" | E24: Реактивная ЭЭ | H24: 1 | I24: =1.2*1286.88 -> 1544.256 | M24: 6670 | N24: =1.2*1776.61 -> 2131.932 | R24: 7112 | S24: =1.2*2008.74 -> 2410.488 | W24: 1 | X24: =1.2*2516.66 -> 3019.992 | AB24: 1 | AC24: =1.2*2950.58 -> 3540.696 | AG24: 1 | AH24: =1.2*2967.75 -> 3561.3 | AL24: 1 | AM24: =1.2*2936.71 -> 3524.052 | AQ24: 1 | AR24: =1.2*3326.2 -> 3991.44 | AV24: 1 | AW24: =1.2*4238.22 -> 5085.864 | BA24: 1 | BB24: 4517.72 | BF24: 1 | BG24: =1.2*3837.93 -> 4605.516 | BK24: 1 | BL24: =1.2*4691.8 -> 5630.16 | BP24: 1 | BQ24: =1.2*4829.17 -> 5795.004 | BU24: 1 | BV24: =1.2*4874.65 -> 5849.58 | BZ24: 1 | CA24: =1.2*3905.02 -> 4686.024 | CE24: 1 | CF24: =1.2*3261.97 -> 3914.364 | CJ24: 1 | CK24: 3134.58 | CO24: 1 | CP24: 3333.92 | CT24: 1 | CU24: 4480.79 | CY24: 1 | CZ24: 4374.53 | DD24: 1 | DE24: 6894.71 | DI24: 1 | DJ24: 6101.33 | DN24: 1 | DO24: 6193.31 | DS24: 1 | DT24: 5352.25 | DX24: 1 | DY24: 5515.25 | EC24: 1 | ED24: 6605.48 | EH24: 1 | EI24: =1.2*3905.02 -> 4686.024 | FB24: 1 | FG24: 1 | FH24: 4374.53 | FL24: 1 | FM24: 6894.71 | FQ24: 1 | FR24: 6101.33 | FV24: 1 | FW24: 6193.31 | GA24: 1 | GB24: 1283.88 | GF24: 1 | GG24: 1283.88 | GK24: 1 | GL24: 6605.48 | GP24: 1 | GQ24: =1.2*3905.02 -> 4686.024 | HJ24: 1 | HO24: 1 | HP24: 4374.53 | HT24: 1 | HU24: 6894.71 | HY24: 1 | HZ24: 6101.33 | ID24: 1 | IE24: 6193.31 | II24: 1 | IJ24: 1283.88 | IN24: 1 | IO24: 1283.88
D25: НВПФ "Казі-2" | E25: ХВ | G25: =I25/H25 -> 35.857273 | H25: 11 | I25: 394.43 | L25: =N25/M25 -> 35.86 | M25: 24 | N25: 860.64 | Q25: =S25/R25 -> 35.860606 | R25: 33 | S25: 1183.4 | V25: =X25/W25 -> 35.859063 | W25: 32 | X25: 1147.49 | AA25: =AC25/AB25 -> 35.86 | AB25: 27 | AC25: 968.22 | AF25: =AH25/AG25 -> 35.861071 | AG25: 28 | AH25: 1004.11 | AK25: =AM25/AL25 -> 35.860968 | AL25: 31 | AM25: 1111.69 | AP25: =AR25/AQ25 -> 35.858696 | AQ25: 23 | AR25: 824.75 | AU25: =AW25/AV25 -> 35.86125 | AV25: 32 | AW25: 1147.56 | AZ25: =BB25/BA25 -> 35.859259 | BA25: 27 | BB25: 968.2 | BE25: =BG25/BF25 -> 35.860323 | BF25: 31 | BG25: 1111.67 | BJ25: =BL25/BK25 -> 35.861379 | BK25: 29 | BL25: 1039.98 | BO25: =BQ25/BP25 -> 35.860667 | BP25: 30 | BQ25: 1075.82 | BT25: =BV25/BU25 -> 35.860833 | BU25: 60 | BV25: 2151.65 | BY25: =CA25/BZ25 -> 35.859444 | BZ25: 36 | CA25: 1290.94 | CD25: =CF25/CE25 -> 35.860811 | CE25: 37 | CF25: 1326.85 | CI25: =CK25/CJ25 -> 32.787429 | CJ25: 35 | CK25: 1147.56 | CN25: =CP25/CO25 -> 29.883143 | CO25: 35 | CP25: =553.58+492.33 -> 1045.91 | CS25: =CU25/CT25 -> 35.859655 | CT25: 29 | CU25: 1039.93 | CX25: =CZ25/CY25 -> 56.7 | CY25: 29 | CZ25: 1644.3 | DC25: =DE25/DD25 -> 56.7 | DD25: 30 | DE25: 1701 | DH25: =DJ25/DI25 -> 56.7 | DI25: 31 | DJ25: 1757.7 | DM25: =DO25/DN25 -> 57.225333 | DN25: 45 | DO25: 2575.14 | DR25: =DT25/DS25 -> 57.375429 | DS25: 35 | DT25: 2008.14 | DW25: =DY25/DX25 -> 57.202979 | DX25: 47 | DY25: 2688.54 | EB25: =ED25/EC25 -> 57.356667 | EC25: 36 | ED25: 2064.84 | EG25: =EI25/EH25 -> 35.859444 | EH25: 36 | EI25: 1290.94 | EL25: =EN25/EM25 -> 57.213913 | EM25: 46 | EN25: 2631.84 | EQ25: =ES25/ER25 -> 58.935429 | ER25: 35 | ES25: 2062.74 | EV25: =EX25/EW25 -> 58.916667 | EW25: 36 | EX25: 2121 | FA25: =FC25/FB25 -> 59.245 | FB25: 24 | FC25: 1421.88 | FF25: =FH25/FG25 -> 59.048 | FG25: 30 | FH25: 1771.44 | FK25: =FM25/FL25 -> 58.647541 | FL25: 61 | FM25: 3577.5 | FP25: =FR25/FQ25 -> 59.334545 | FQ25: 22 | FR25: 1305.36 | FU25: =FW25/FV25 -> 59.287826 | FV25: 23 | FW25: 1363.62 | FZ25: =GB25/GA25 -> 59.334545 | GA25: 22 | GB25: 1305.36 | GE25: =GG25/GF25 -> 59.287826 | GF25: 23 | GG25: 1363.62 | GJ25: =GL25/GK25 -> 59.287826 | GK25: 23 | GL25: 1363.62 | GO25: =GQ25/GP25 -> 62.2 | GP25: 6 | GQ25: 373.2 | GT25: =GV25/GU25 -> 59.948571 | GU25: 14 | GV25: 839.28 | GY25: =HA25/GZ25 -> 58.935429 | GZ25: 35 | HA25: 2062.74 | HD25: =HF25/HE25 -> 58.916667 | HE25: 36 | HF25: 2121 | HI25: =HK25/HJ25 -> 59.245 | HJ25: 24 | HK25: 1421.88 | HN25: =HP25/HO25 -> 59.048 | HO25: 30 | HP25: 1771.44 | HS25: =HU25/HT25 -> 58.647541 | HT25: 61 | HU25: 3577.5 | HX25: =HZ25/HY25 -> 59.334545 | HY25: 22 | HZ25: 1305.36 | IC25: =IE25/ID25 -> 59.287826 | ID25: 23 | IE25: 1363.62 | IH25: =IJ25/II25 -> 10549.555 | II25: 11 | IJ25: 116045.1 | IM25: =IO25/IN25 -> 35.857273 | IN25: 11 | IO25: 394.43
B26: М5 | C26: г.Киев, ул. Я.Колоса,2А | D26: ТОВ "Еко-Грінко" | E26: Вывоз ТБО | X26: 1990 | Z26: =SUM(X26:X29)*1.1 -> 98311.932 | AC26: 1769 | AE26: =SUM(AC26:AC29)*1.1 -> 82767.282 | AH26: 1548 | AJ26: =AJ27*1.1 -> 141098.17 | AM26: 1990 | AO26: =AO27*1.2 -> 57402.214 | AR26: 1769 | AT26: =SUM(AR26:AR29)*1.2 -> 242190.38 | AY26: =SUM(AW26:AW29)*1.1 -> 170273.43 | BD26: =SUM(BB26:BB29)*1.1 -> 152385.61 | BI26: =SUM(BG26:BG29)*1.1 -> 144901.7 | BN26: =SUM(BL26:BL29)*1.1 -> 135790.03 | BS26: =SUM(BQ26:BQ29)*1.1 -> 122838.33 | BX26: =SUM(BV26:BV29)*1.1 -> 129876.05 | CC26: =SUM(CA26:CA29)*1.1 -> 107222.73 | CH26: =SUM(CF26:CF29)*1.1 -> 105025.01 | CM26: =SUM(CK26:CK29)*1.1 -> 130367.93 | CR26: =SUM(CP26:CP29)*1.1 -> 145745.89 | CW26: =SUM(CU26:CU29)*1.1 -> 176572.78 | DB26: =SUM(CZ26:CZ29)*1.1 -> 173972.92 | DG26: =SUM(DE26:DE29)*1.1 -> 78943.396 | DL26: =SUM(DJ26:DJ29)*1.1 -> 214749.54 | DQ26: =SUM(DO26:DO29)*1.1 -> 268141.19 | DV26: =SUM(DT26:DT29)*1.1 -> 138960.38 | EA26: =SUM(DY26:DY29)*1.1 -> 137978.79 | EF26: =SUM(ED26:ED29)*1.1 -> 162611.17 | EK26: =SUM(EI26:EI29)*1.1 -> 110101.32 | EP26: =SUM(EN26:EN29)*1.1 -> 172725.96 | EU26: =SUM(ES26:ES29)*1.1 -> 158316.22 | EZ26: =SUM(EX26:EX29)*1.1 -> 147778.02 | FE26: =SUM(FC26:FC29)*1.1 -> 171019.49 | FJ26: =SUM(FH26:FH29)*1.1 -> 189584.46 | FO26: =SUM(FM26:FM29)*1.1 -> 170018.29 | FT26: =SUM(FR26:FR29)*1.1 -> 168756.59 | FY26: =SUM(FW26:FW29)*1.1 -> 167194.41 | GD26: =SUM(GB26:GB29)*1.1 -> 128919.52 | GI26: =SUM(GG26:GG29)*1.1 -> 78943.396 | GN26: =SUM(GL26:GL29)*1.1 -> 162611.17 | GS26: =SUM(GQ26:GQ29)*1.1 -> 140307.66 | GX26: =SUM(GV26:GV29)*1.1 -> 177401.54 | HC26: =SUM(HA26:HA29)*1.1 -> 158316.22 | HH26: =SUM(HF26:HF29)*1.1 -> 147778.02 | HM26: =SUM(HK26:HK29)*1.1 -> 171019.49 | HR26: =SUM(HP26:HP29)*1.1 -> 189584.46 | HW26: =SUM(HU26:HU29)*1.1 -> 170018.29 | IB26: =SUM(HZ26:HZ29)*1.1 -> 168756.59 | IG26: =SUM(IE26:IE29)*1.1 -> 167194.41 | IL26: =SUM(IJ26:IJ29)*1.1 -> 78943.396 | IQ26: =SUM(IO26:IO29)*1.1 -> 78943.396
A27: 1 | C27: 45179093 | D27: ЯСНО+ | E27: Активная ЭЭ | G27: =I27/H27 -> 5.3077196 | H27: 13395 | I27: 71096.904 | J27: 49372.85 | L27: =N27/M27 -> 5.3685478 | M27: 14950 | N27: 80259.79 | O27: 80 259,79 | Q27: =S27/R27 -> 4.9663925 | R27: 13452 | S27: 66807.912 | T27: 66807.912 | V27: =X27/W27 -> 5.207724 | W27: 16345 | X27: 85120.248 | Y27: 85120.248 | Z27: =SUM(X26:X29)*1 -> 89374.484 | AA27: =AC27/AB27 -> 4.5706785 | AB27: 15555 | AC27: 71096.904 | AD27: 72843.312 | AE27: =SUM(AC26:AC29)*1 -> 75242.984 | AF27: =AH27/AG27 -> 4.8199439 | AG27: 17766 | AH27: 85631.124 | AI27: =38338.59+87714.65 -> 126053.24 | AJ27: =SUM(AH28:AH29)+AI27+AH26*1 -> 128271.06 | AK27: =AM27/AL27 -> 4.9792194 | AL27: 8517 | AM27: 42408.012 | AN27: 44466.708 | AO27: =SUM(AM28:AM29)+AN27+AM26*1 -> 47835.178 | AP27: =AR27/AQ27 -> 5.9466962 | AQ27: 33010 | AR27: 196300.44 | AS27: 221372.05 | AT27: =SUM(AR26:AR29)*1 -> 201825.32 | AU27: =AW27/AV27 -> 6.6107534 | AV27: 22988 | AW27: 151968 | AX27: 49372.85 | AY27: =SUM(AW26:AW29)*1 -> 154794.03 | AZ27: =BB27/BA27 -> 6.3494522 | BA27: 21303 | BB27: 135262.38 | BC27: 112718.65 | BD27: =SUM(BB26:BB29)*1 -> 138532.37 | BE27: =BG27/BF27 -> 6.3628441 | BF27: 20210 | BG27: 128593.08 | BH27: 112718.65 | BI27: =SUM(BG26:BG29)*1 -> 131728.82 | BJ27: =BL27/BK27 -> 6.7715879 | BK27: 18131 | BL27: 122775.66 | BM27: 101802.85 | BN27: =SUM(BL26:BL29)*1 -> 123445.48 | BO27: =BQ27/BP27 -> 6.3746277 | BP27: 17413 | BQ27: 111001.39 | BR27: 49372.85 | BS27: =SUM(BQ26:BQ29)*1 -> 111671.21 | BT27: =BV27/BU27 -> 6.0268797 | BU27: 19110 | BV27: 115173.67 | BW27: 112 625,82 | BX27: =SUM(BV26:BV29)*1 -> 118069.13 | BY27: =CA27/BZ27 -> 5.480688 | BZ27: 17663 | CA27: 96805.392 | CB27: 161 248,54 | CC27: =SUM(CA26:CA29)*1 -> 97475.212 | CD27: =CF27/CE27 -> 5.2738675 | CE27: =8105+9512 -> 17617 | CF27: =(41804.19+35620.58)*1.2 -> 92909.724 | CG27: 64196.588 | CH27: =SUM(CF26:CF29)*1 -> 95477.284 | CI27: =CK27/CJ27 -> 5.5512116 | CJ27: =9648+11230 -> 20878 | CK27: 115898.2 | CL27: 95536.12 | CM27: =SUM(CK26:CK29)*1 -> 118516.3 | CN27: =CP27/CO27 -> 6.5632803 | CO27: 19774 | CP27: 129782.3 | CQ27: 109 076,68 | CR27: =SUM(CP26:CP29)*1 -> 132496.26 | CS27: =CU27/CT27 -> 7.5064682 | CT27: 20916 | CU27: 157005.29 | CV27: 204641.93 | CW27: =SUM(CU26:CU29)*1 -> 160520.71 | CX27: =CZ27/CY27 -> 7.9506957 | CY27: 19808 | CZ27: 157487.38 | DA27: 224251.64 | DB27: =SUM(CZ26:CZ29)*1 -> 158157.2 | DC27: =DE27/DD27 -> 5.3077196 | DD27: 13395 | DE27: 71096.904 | DF27: 173969.85 | DG27: =SUM(DE26:DE29)*1 -> 71766.724 | DH27: =DJ27/DI27 -> 8.1712319 | DI27: 23810 | DJ27: 194557.03 | DK27: 159302.12 | DL27: =SUM(DJ26:DJ29)*1 -> 195226.85 | DM27: =DO27/DN27 -> 8.22684 | DN27: 29549 | DO27: 243094.9 | DP27: 180253.09 | DQ27: =SUM(DO26:DO29)*1 -> 243764.72 | DR27: =DT27/DS27 -> 8.1744598 | DS27: 15372 | DT27: 125657.8 | DU27: 202579.08 | DV27: =SUM(DT26:DT29)*1 -> 126327.62 | DW27: =DY27/DX27 -> 8.7144961 | DX27: 14317 | DY27: 124765.44 | DZ27: 110421.28 | EA27: =SUM(DY26:DY29)*1 -> 125435.26 | EB27: =ED27/EC27 -> 8.5936439 | EC27: 16724 | ED27: 143720.1 | EE27: 128864.86 | EF27: =SUM(ED26:ED29)*1 -> 147828.34 | EG27: =EI27/EH27 -> 5.480688 | EH27: 17663 | EI27: 96805.392 | EJ27: 147667.24 | EK27: =SUM(EI26:EI29)*1 -> 100092.11 | EL27: =EN27/EM27 -> 8.1683878 | EM27: 18909 | EN27: 154456.04 | EO27: 132452.46 | EP27: =SUM(EN26:EN29)*1 -> 157023.6 | EQ27: =ES27/ER27 -> 7.131084 | ER27: =8930+10642 -> 19572 | ES27: =(63240.83+53067.15)*1.2 -> 139569.58 | ET27: 132452.46 | EU27: =SUM(ES26:ES29)*1 -> 143923.84 | EV27: =EX27/EW27 -> 7.2623278 | EW27: 18125 | EX27: 131629.69 | EY27: 109 076,68 | EZ27: =SUM(EX26:EX29)*1 -> 134343.65 | FA27: =FC27/FB27 -> 7.224 | FB27: 21035 | FC27: 151956.84 | FD27: 133 167,20 | FE27: =SUM(FC26:FC29)*1 -> 155472.26 | FF27: =FH27/FG27 -> 7.941516 | FG27: =15994+5624 -> 21618 | FH27: =(105847.17+37219.24)*1.2 -> 171679.69 | FI27: 171804 | FJ27: =SUM(FH26:FH29)*1 -> 172349.51 | FK27: =FM27/FL27 -> 7.9877639 | FL27: 19266 | FM27: 153892.26 | FN27: 192484 | FO27: =SUM(FM26:FM29)*1 -> 154562.08 | FP27: =FR27/FQ27 -> 7.2019079 | FQ27: 21209 | FR27: 152745.26 | FS27: 167088.48 | FT27: =SUM(FR26:FR29)*1 -> 153415.08 | FU27: =FW27/FV27 -> 9.5370959 | FV27: 15867 | FW27: 151325.1 | FX27: 180253.09 | FY27: =SUM(FW26:FW29)*1 -> 151994.92 | FZ27: =GB27/GA27 -> 10.118064 | GA27: 11517 | GB27: 116529.74 | GC27: 151325.1 | GD27: =SUM(GB26:GB29)*1 -> 117199.56 | GE27: =GG27/GF27 -> 5.3077196 | GF27: 13395 | GG27: 71096.904 | GH27: 164479.02 | GI27: =SUM(GG26:GG29)*1 -> 71766.724 | GJ27: =GL27/GK27 -> 8.5936439 | GK27: 16724 | GL27: 143720.1 | GM27: 128864.86 | GN27: =SUM(GL26:GL29)*1 -> 147828.34 | GO27: =GQ27/GP27 -> 13.755335 | GP27: 9034 | GQ27: 124265.7 | GR27: 147667.24 | GS27: =SUM(GQ26:GQ29)*1 -> 127552.42 | GT27: =GV27/GU27 -> 10.4826 | GU27: 15140 | GV27: 158706.56 | GW27: 132452.46 | GX27: =SUM(GV26:GV29)*1 -> 161274.12 | GY27: =HA27/GZ27 -> 7.131084 | GZ27: =8930+10642 -> 19572 | HA27: =(63240.83+53067.15)*1.2 -> 139569.58 | HB27: 132452.46 | HC27: =SUM(HA26:HA29)*1 -> 143923.84 | HD27: =HF27/HE27 -> 7.2623278 | HE27: 18125 | HF27: 131629.69 | HG27: 109 076,68 | HH27: =SUM(HF26:HF29)*1 -> 134343.65 | HI27: =HK27/HJ27 -> 7.224 | HJ27: 21035 | HK27: 151956.84 | HL27: 133 167,20 | HM27: =SUM(HK26:HK29)*1 -> 155472.26 | HN27: =HP27/HO27 -> 7.941516 | HO27: =15994+5624 -> 21618 | HP27: =(105847.17+37219.24)*1.2 -> 171679.69 | HQ27: 171804 | HR27: =SUM(HP26:HP29)*1 -> 172349.51 | HS27: =HU27/HT27 -> 7.9877639 | HT27: 19266 | HU27: 153892.26 | HV27: 192484 | HW27: =SUM(HU26:HU29)*1 -> 154562.08 | HX27: =HZ27/HY27 -> 7.2019079 | HY27: 21209 | HZ27: 152745.26 | IA27: 167088.48 | IB27: =SUM(HZ26:HZ29)*1 -> 153415.08 | IC27: =IE27/ID27 -> 9.5370959 | ID27: 15867 | IE27: 151325.1 | IF27: 180253.09 | IG27: =SUM(IE26:IE29)*1 -> 151994.92 | IH27: =IJ27/II27 -> 5.3077196 | II27: 13395 | IJ27: 71096.904 | IK27: 202579.08 | IL27: =SUM(IJ26:IJ29)*1 -> 71766.724 | IM27: =IO27/IN27 -> 5.3077196 | IN27: 13395 | IO27: 71096.904 | IP27: 49372.85 | IQ27: =SUM(IO26:IO29)*1 -> 71766.724
C28: 41946011 | D28: «ДТЕК КИЇВСЬКІ ЕЛЕКТРОМЕРЕЖІ» | E28: Реактивная ЭЭ | I28: 1 373,92 | N28: 1352.6 | S28: 1 322,12 | X28: 1594.416 | AC28: 1707.26 | AH28: 1 819,58 | AM28: 708.65 | AR28: 3086.06 | AW28: 2156.208 | BB28: 2600.17 | BG28: 2465.92 | BL28: 2 240,89 | BQ28: 2 033,00 | BU28: 1 | BV28: 2225.64 | CA28: 2 077,98 | CF28: 1897.74 | CK28: 1948.28 | CP28: 2044.14 | CU28: 2845.6 | CZ28: 1 373,92 | DE28: 1 373,92 | DJ28: 1 373,92 | DO28: 1 373,92 | DT28: 1 373,92 | DY28: 1 373,92 | EC28: 1 | ED28: 3438.42 | EI28: 2616.9 | EN28: 1897.74 | ES28: 3684.44 | EX28: 2044.14 | FC28: 2845.6 | FH28: 1 373,92 | FM28: 1 373,92 | FR28: 1 373,92 | FW28: 1 373,92 | GB28: 1 373,92 | GG28: 1 373,92 | GK28: 1 | GL28: 3438.42 | GQ28: 2616.9 | GV28: 1897.74 | HA28: 3684.44 | HF28: 2044.14 | HK28: 2845.6 | HP28: 1 373,92 | HU28: 1 373,92 | HZ28: 1 373,92 | IE28: 1 373,92 | IJ28: 1 373,92 | IO28: 1 373,92
D29: ФОП Ковальова Л.В. НАЛІЧНІ | E29: ХВ | G29: =I29/H29 -> 31.724138 | H29: 29 | I29: 920 | L29: =N29/M29 -> 30.446364 | M29: 22 | N29: 669.82 | Q29: =S29/R29 -> 30.446364 | R29: 22 | S29: 669.82 | V29: =X29/W29 -> 30.446364 | W29: 22 | X29: 669.82 | AA29: =AC29/AB29 -> 30.446364 | AB29: 22 | AC29: 669.82 | AF29: =AH29/AG29 -> 30.446364 | AG29: 22 | AH29: 669.82 | AK29: =AM29/AL29 -> 18.103243 | AL29: 37 | AM29: 669.82 | AP29: =AR29/AQ29 -> 30.446364 | AQ29: 22 | AR29: 669.82 | AU29: =AW29/AV29 -> 30.446364 | AV29: 22 | AW29: 669.82 | AZ29: =BB29/BA29 -> 30.446364 | BA29: 22 | BB29: 669.82 | BE29: =BG29/BF29 -> 30.446364 | BF29: 22 | BG29: 669.82 | BJ29: =BL29/BK29 -> 30.446364 | BK29: 22 | BL29: 669.82 | BO29: =BQ29/BP29 -> 30.446364 | BP29: 22 | BQ29: 669.82 | BT29: =BV29/BU29 -> 30.446364 | BU29: 22 | BV29: 669.82 | BY29: =CA29/BZ29 -> 30.446364 | BZ29: 22 | CA29: 669.82 | CD29: =CF29/CE29 -> 30.446364 | CE29: 22 | CF29: 669.82 | CI29: =CK29/CJ29 -> 30.446364 | CJ29: 22 | CK29: 669.82 | CN29: =CP29/CO29 -> 30.446364 | CO29: 22 | CP29: 669.82 | CS29: =CU29/CT29 -> 30.446364 | CT29: 22 | CU29: 669.82 | CX29: =CZ29/CY29 -> 30.446364 | CY29: 22 | CZ29: 669.82 | DC29: =DE29/DD29 -> 30.446364 | DD29: 22 | DE29: 669.82 | DH29: =DJ29/DI29 -> 30.446364 | DI29: 22 | DJ29: 669.82 | DM29: =DO29/DN29 -> 30.446364 | DN29: 22 | DO29: 669.82 | DR29: =DT29/DS29 -> 30.446364 | DS29: 22 | DT29: 669.82 | DW29: =DY29/DX29 -> 30.446364 | DX29: 22 | DY29: 669.82 | EB29: =ED29/EC29 -> 30.446364 | EC29: 22 | ED29: 669.82 | EG29: =EI29/EH29 -> 30.446364 | EH29: 22 | EI29: 669.82 | EL29: =EN29/EM29 -> 30.446364 | EM29: 22 | EN29: 669.82 | EQ29: =ES29/ER29 -> 30.446364 | ER29: 22 | ES29: 669.82 | EV29: =EX29/EW29 -> 30.446364 | EW29: 22 | EX29: 669.82 | FA29: =FC29/FB29 -> 30.446364 | FB29: 22 | FC29: 669.82 | FF29: =FH29/FG29 -> 30.446364 | FG29: 22 | FH29: 669.82 | FK29: =FM29/FL29 -> 30.446364 | FL29: 22 | FM29: 669.82 | FP29: =FR29/FQ29 -> 30.446364 | FQ29: 22 | FR29: 669.82 | FU29: =FW29/FV29 -> 30.446364 | FV29: 22 | FW29: 669.82 | FZ29: =GB29/GA29 -> 30.446364 | GA29: 22 | GB29: 669.82 | GE29: =GG29/GF29 -> 30.446364 | GF29: 22 | GG29: 669.82 | GJ29: =GL29/GK29 -> 30.446364 | GK29: 22 | GL29: 669.82 | GO29: =GQ29/GP29 -> 30.446364 | GP29: 22 | GQ29: 669.82 | GT29: =GV29/GU29 -> 30.446364 | GU29: 22 | GV29: 669.82 | GY29: =HA29/GZ29 -> 30.446364 | GZ29: 22 | HA29: 669.82 | HD29: =HF29/HE29 -> 30.446364 | HE29: 22 | HF29: 669.82 | HI29: =HK29/HJ29 -> 30.446364 | HJ29: 22 | HK29: 669.82 | HN29: =HP29/HO29 -> 30.446364 | HO29: 22 | HP29: 669.82 | HS29: =HU29/HT29 -> 30.446364 | HT29: 22 | HU29: 669.82 | HX29: =HZ29/HY29 -> 30.446364 | HY29: 22 | HZ29: 669.82 | IC29: =IE29/ID29 -> 30.446364 | ID29: 22 | IE29: 669.82 | IH29: =IJ29/II29 -> 30.446364 | II29: 22 | IJ29: 669.82 | IM29: =IO29/IN29 -> 30.446364 | IN29: 22 | IO29: 669.82
B30: М6 | C30: г.Киев, ул. Сикорского,1А | D30: ТОВ "Еко-Грінко" | E30: Вывоз ТБО | X30: 5085 | Z30: =SUM(X30:X35)*1.1 -> 259503.07 | AC30: 5306 | AE30: =SUM(AC30:AC35)*1.1 -> 245493.75 | AH30: 5085 | AJ30: =AJ31*1.1 -> 373563.25 | AM30: 4643 | AO30: =AO31*1.2 -> 288508.89 | AR30: 4422 | AT30: =SUM(AR30:AR35)*1.2 -> 402263.06 | AY30: =SUM(AW30:AW35)*1.1 -> 374248.29 | BD30: =SUM(BB30:BB35)*1.1 -> 348933.92 | BI30: =SUM(BG30:BG35)*1.1 -> 318419.32 | BN30: =SUM(BL30:BL35)*1.1 -> 348625.39 | BS30: =SUM(BQ30:BQ35)*1.1 -> 331405.76 | BX30: =SUM(BV30:BV35)*1.1 -> 365511.68 | CC30: =SUM(CA30:CA35)*1.1 -> 274810.81 | CH30: =SUM(CF30:CF35)*1.1 -> 233079.5 | CM30: =SUM(CK30:CK35)*1.1 -> 275231.46 | CR30: =SUM(CP30:CP35)*1.1 -> 332501.33 | CW30: =SUM(CU30:CU35)*1.1 -> 346458.26 | DB30: =SUM(CZ30:CZ35)*1.1 -> 338065.03 | DG30: =SUM(DE30:DE35)*1.1 -> 174961.57 | DL30: =SUM(DJ30:DJ35)*1.1 -> 368275.78 | DQ30: =SUM(DO30:DO35)*1.1 -> 570140.84 | DV30: =SUM(DT30:DT35)*1.1 -> 435939.41 | EA30: =SUM(DY30:DY35)*1.1 -> 427837.79 | EF30: =SUM(ED30:ED35)*1.1 -> 474062.36 | EK30: =SUM(EI30:EI35)*1.1 -> 276469.59 | EP30: =SUM(EN30:EN35)*1.1 -> 412175.99 | EU30: =SUM(ES30:ES35)*1.1 -> 278120.33 | EZ30: =SUM(EX30:EX35)*1.1 -> 367264.98 | FE30: =SUM(FC30:FC35)*1.1 -> 372427.09 | FJ30: =SUM(FH30:FH35)*1.1 -> 433882.47 | FO30: =SUM(FM30:FM35)*1.1 -> 413670.1 | FT30: =SUM(FR30:FR35)*1.1 -> 345641.12 | FY30: =SUM(FW30:FW35)*1.1 -> 376028.95 | GD30: =SUM(GB30:GB35)*1.1 -> 371315.33 | GI30: =SUM(GG30:GG35)*1.1 -> 172379.6 | GN30: =SUM(GL30:GL35)*1.1 -> 474062.36 | GS30: =SUM(GQ30:GQ35)*1.1 -> 381294.13 | GX30: =SUM(GV30:GV35)*1.1 -> 437584.48 | HC30: =SUM(HA30:HA35)*1.1 -> 278120.33 | HH30: =SUM(HF30:HF35)*1.1 -> 367264.98 | HM30: =SUM(HK30:HK35)*1.1 -> 372427.09 | HR30: =SUM(HP30:HP35)*1.1 -> 433882.47 | HW30: =SUM(HU30:HU35)*1.1 -> 413670.1 | IB30: =SUM(HZ30:HZ35)*1.1 -> 345641.12 | IG30: =SUM(IE30:IE35)*1.1 -> 376028.95 | IL30: =SUM(IJ30:IJ35)*1.1 -> 210809.47 | IQ30: =SUM(IO30:IO35)*1.1 -> 172379.6
C31: 2839404073 | D31: ФОП Пластун В.В. | E31: Экспл. расходы | H31: 696.6 | I31: 7280.87 | M31: 696.6 | N31: 7280.87 | O31: 2940 | R31: 696.6 | S31: 7280.87 | W31: 696.6 | X31: 7280.87 | Z31: =SUM(X30:X35)*1 -> 235911.88 | AB31: 696.6 | AC31: 7280.87 | AE31: =SUM(AC30:AC35)*1 -> 223176.14 | AG31: 696.6 | AH31: 7280.87 | AJ31: =SUM(AH34:AH35)+AI33+AH32+AH31+AH30*1 -> 339602.95 | AL31: 696.6 | AM31: 7280.87 | AO31: =SUM(AM34:AM35)+AN33+AM32+AM31+AM30*1 -> 240424.08 | AQ31: 696.6 | AR31: 7280.87 | AT31: =SUM(AR30:AR35)*1 -> 335219.22 | AV31: 696.6 | AW31: 7 789,39 | AY31: =SUM(AW30:AW35)*1 -> 340225.72 | BA31: 696.6 | BB31: 7 789,39 | BD31: =SUM(BB30:BB35)*1 -> 317212.66 | BF31: 696.6 | BG31: 7789.39 | BI31: =SUM(BG30:BG35)*1 -> 289472.11 | BK31: 696.6 | BL31: 7789.39 | BN31: =SUM(BL30:BL35)*1 -> 316932.17 | BP31: 696.6 | BQ31: 7280.87 | BS31: =SUM(BQ30:BQ35)*1 -> 301277.97 | BU31: 696.6 | BV31: 7789.39 | BX31: =SUM(BV30:BV35)*1 -> 332283.35 | BZ31: 696.6 | CA31: 7789.39 | CC31: =SUM(CA30:CA35)*1 -> 249828.01 | CE31: 696.6 | CF31: 7 789,39 | CH31: =SUM(CF30:CF35)*1 -> 211890.45 | CJ31: 696.6 | CK31: 7789.39 | CM31: =SUM(CK30:CK35)*1 -> 250210.42 | CO31: 696.6 | CP31: 7789.39 | CR31: =SUM(CP30:CP35)*1 -> 302273.94 | CT31: 696.6 | CU31: 8688 | CW31: =SUM(CU30:CU35)*1 -> 314962.05 | CY31: 696.6 | CZ31: 8688 | DB31: =SUM(CZ30:CZ35)*1 -> 307331.85 | DD31: 696.6 | DE31: 8688 | DG31: =SUM(DE30:DE35)*1 -> 159055.97 | DL31: =SUM(DJ30:DJ35)*1 -> 334796.17 | DQ31: =SUM(DO30:DO35)*1 -> 518309.85 | DS31: 696.6 | DT31: 26206.08 | DV31: =SUM(DT30:DT35)*1 -> 396308.56 | DX31: 696.6 | DY31: 9259.48 | EA31: =SUM(DY30:DY35)*1 -> 388943.45 | EC31: 696.6 | ED31: 9259.48 | EF31: =SUM(ED30:ED35)*1 -> 430965.78 | EH31: 696.6 | EI31: 7789.39 | EK31: =SUM(EI30:EI35)*1 -> 251335.99 | EM31: 696.6 | EN31: 7 789,39 | EP31: =SUM(EN30:EN35)*1 -> 374705.45 | ER31: 696.6 | ES31: 7789.39 | EU31: =SUM(ES30:ES35)*1 -> 252836.66 | EW31: 696.6 | EX31: 7789.39 | EZ31: =SUM(EX30:EX35)*1 -> 333877.26 | FB31: 696.6 | FC31: =8688*1.064 -> 9244.032 | FE31: =SUM(FC30:FC35)*1 -> 338570.08 | FG31: 696.6 | FH31: =8688*1.064 -> 9244.032 | FJ31: =SUM(FH30:FH35)*1 -> 394438.61 | FL31: 696.6 | FM31: =8735.36*1.06 -> 9259.4816 | FO31: =SUM(FM30:FM35)*1 -> 376063.73 | FQ31: 696.6 | FR31: =8735.36*1.064 -> 9294.423 | FT31: =SUM(FR30:FR35)*1 -> 314219.2 | FY31: =SUM(FW30:FW35)*1 -> 341844.5 | GA31: 696.6 | GB31: 26206.08 | GD31: =SUM(GB30:GB35)*1 -> 337559.39 | GF31: 696.6 | GG31: 7280.87 | GI31: =SUM(GG30:GG35)*1 -> 156708.73 | GK31: 696.6 | GL31: 9259.48 | GN31: =SUM(GL30:GL35)*1 -> 430965.78 | GP31: 696.6 | GQ31: 7789.39 | GS31: =SUM(GQ30:GQ35)*1 -> 346631.02 | GU31: 696.6 | GV31: 7 789,39 | GX31: =SUM(GV30:GV35)*1 -> 397804.07 | GZ31: 696.6 | HA31: 7789.39 | HC31: =SUM(HA30:HA35)*1 -> 252836.66 | HE31: 696.6 | HF31: 7789.39 | HH31: =SUM(HF30:HF35)*1 -> 333877.26 | HJ31: 696.6 | HK31: =8688*1.064 -> 9244.032 | HM31: =SUM(HK30:HK35)*1 -> 338570.08 | HO31: 696.6 | HP31: =8688*1.064 -> 9244.032 | HR31: =SUM(HP30:HP35)*1 -> 394438.61 | HT31: 696.6 | HU31: =8735.36*1.06 -> 9259.4816 | HW31: =SUM(HU30:HU35)*1 -> 376063.73 | HY31: 696.6 | HZ31: =8735.36*1.064 -> 9294.423 | IB31: =SUM(HZ30:HZ35)*1 -> 314219.2 | IG31: =SUM(IE30:IE35)*1 -> 341844.5 | II31: 696.6 | IJ31: 26206.08 | IL31: =SUM(IJ30:IJ35)*1 -> 191644.97 | IN31: 696.6 | IO31: 7280.87 | IQ31: =SUM(IO30:IO35)*1 -> 156708.73
C32: 2839404073 | D32: ФОП Пластун В.В. | E32: Экспл. расходы | H32: 465.4 | I32: 4864.36 | M32: 465.4 | N32: 4864.36 | R32: 465.4 | S32: 4864.36 | W32: 465.4 | X32: 4864.36 | AB32: 465.4 | AC32: 4864.36 | AG32: 465.4 | AH32: 4864.36 | AL32: 465.4 | AM32: 4864.36 | AQ32: 465.4 | AR32: 4864.36 | AV32: 465.4 | AW32: 5 204,10 | BA32: 465.4 | BB32: 5 204,10 | BF32: 465.4 | BG32: 5204.1 | BK32: 465.4 | BL32: 5204.1 | BP32: 465.4 | BQ32: 4864.36 | BU32: 465.4 | BV32: 5 204,10 | BZ32: 465.4 | CA32: 5 204,10 | CE32: 465.4 | CF32: 5 204,10 | CJ32: 465.4 | CK32: 5204.1 | CO32: 465.4 | CP32: 5204.1 | CT32: 465.4 | CU32: 5 804,47 | CY32: 465.4 | CZ32: 5804.47 | DD32: 465.4 | DE32: 5804.47 | DS32: 465.4 | DT32: 17508.36 | DX32: 465.4 | DY32: 6243.52 | EC32: 465.4 | ED32: 6243.52 | EH32: 465.4 | EI32: 5 204,10 | EM32: 465.4 | EN32: 5 204,10 | ER32: 465.4 | ES32: 5204.1 | EW32: 465.4 | EX32: 5204.1 | FB32: 465.4 | FC32: =5804.47*1.064 -> 6175.9561 | FG32: 465.4 | FH32: =5804.47*1.064 -> 6175.9561 | FL32: 465.4 | FM32: =5836.12*1.06 -> 6186.2872 | FQ32: 465.4 | FR32: =5836.12*1.064 -> 6209.6317 | GA32: 465.4 | GB32: 17508.36 | GF32: 465.4 | GG32: 4864.36 | GK32: 465.4 | GL32: 6243.52 | GP32: 465.4 | GQ32: 5 204,10 | GU32: 465.4 | GV32: 5 204,10 | GZ32: 465.4 | HA32: 5204.1 | HE32: 465.4 | HF32: 5204.1 | HJ32: 465.4 | HK32: =5804.47*1.064 -> 6175.9561 | HO32: 465.4 | HP32: =5804.47*1.064 -> 6175.9561 | HT32: 465.4 | HU32: =5836.12*1.06 -> 6186.2872 | HY32: 465.4 | HZ32: =5836.12*1.064 -> 6209.6317 | II32: 465.4 | IJ32: 17508.36 | IN32: 465.4 | IO32: 4864.36
A33: 1 | C33: 45179093 | D33: ЯСНО+ | E33: Активная ЭЭ | G33: =I33/H33 -> 5.3077195 | H33: 26880 | I33: 142671.5 | J33: 99077.44 | L33: =N33/M33 -> 5.3685477 | M33: 35276 | N33: =132566.62+56814.27 -> 189380.89 | O33: 189380.89 | Q33: =S33/R33 -> 4.966392 | R33: 33553 | S33: 166637.35 | T33: 166637.35 | V33: =X33/W33 -> 5.2077239 | W33: 41331 | X33: 215240.44 | Y33: 215240.44 | AA33: =AC33/AB33 -> 4.6829521 | AB33: 42840 | AC33: 200617.67 | AD33: 200617.67 | AF33: =AH33/AG33 -> 4.8199441 | AG33: 43525 | AH33: 209788.07 | AI33: =73911.77+31676.47+139680.1+75212.38 -> 320480.72 | AK33: =AM33/AL33 -> 4.9792201 | AL33: 42360 | AM33: 210919.76 | AN33: 221158.85 | AP33: =AR33/AQ33 -> 5.946696 | AQ33: 52776 | AR33: 313842.83 | AS33: 353927.04 | AU33: =AW33/AV33 -> 6.6107622 | AV33: 50640 | AW33: 334769 | AX33: 99077.44 | AZ33: =BB33/BA33 -> 6.349452 | BA33: 49132 | BB33: 311961.28 | BC33: 259967.73 | BE33: =BG33/BF33 -> 6.3628442 | BF33: 42815 | BG33: 272425.18 | BH33: 259967.73 | BJ33: =BL33/BK33 -> 6.771588 | BK33: 44605 | BL33: 302046.68 | BM33: 215669.93 | BO33: =BQ33/BP33 -> 6.374628 | BP33: 45060 | BQ33: 287240.74 | BR33: 99077.44 | BT33: =BV33/BU33 -> 6.0268801 | BU33: 53040 | BV33: 319665.72 | BW33: 291 444,30 | BY33: =CA33/BZ33 -> 5.4806881 | BZ33: 43320 | CA33: 237423.41 | CB33: 345590.5 | CD33: =CF33/CE33 -> 4.3948899 | CE33: =44340+2700 -> 47040 | CF33: =194869.42+11866.2 -> 206735.62 | CG33: 157448.88 | CI33: =CK33/CJ33 -> 5.5512121 | CJ33: =23940+17700 -> 41640 | CK33: 231152.47 | CL33: 99077.44 | CN33: =CP33/CO33 -> 6.5632801 | CO33: 43239 | CP33: 283789.67 | CQ33: 217552 | CS33: =CU33/CT33 -> 7.506468 | CT33: 40102 | CU33: 301024.38 | CV33: =286380.27+147664.83+13424.08 -> 447469.18 | CX33: =CZ33/CY33 -> 7.950696 | CY33: 36318 | CZ33: 288753.38 | DA33: 429957.02 | DC33: =DE33/DD33 -> 5.3077195 | DD33: 26880 | DE33: 142671.5 | DF33: 318968.33 | DH33: =DJ33/DI33 -> 8.1712321 | DI33: 40741 | DJ33: 332904.17 | DK33: 322481.86 | DM33: =DO33/DN33 -> 8.2268399 | DN33: 62101 | DO33: 510894.98 | DP33: 308425.39 | DR33: =DT33/DS33 -> 8.17446 | DS33: 41970 | DT33: 343082.09 | DU33: =272477.32+140496.12+12772.37 -> 425745.81 | DW33: =DY33/DX33 -> 8.7144959 | DX33: 42218 | DY33: 367908.59 | DZ33: 344555.47 | EB33: =ED33/EC33 -> 8.6892839 | EC33: 47021 | ED33: 408578.82 | EE33: 379996.96 | EG33: =EI33/EH33 -> 5.4806881 | EH33: 43320 | EI33: 237423.41 | EJ33: 408578.82 | EL33: =EN33/EM33 -> 8.040876 | EM33: 45959 | EN33: 369550.62 | EO33: 409496.62 | EQ33: =ES33/ER33 -> 5.5512121 | ER33: =23940+17700 -> 41640 | ES33: 231152.47 | ET33: 409496.61 | EV33: =EX33/EW33 -> 6.7581721 | EW33: 46202 | EX33: 312241.07 | EY33: 217552 | FA33: =FC33/FB33 -> 6.800796 | FB33: 46258 | FC33: 314591.22 | FD33: 312241 | FF33: =FH33/FG33 -> 7.6570318 | FG33: 48648 | FH33: 372499.28 | FI33: 314591 | FK33: =FM33/FL33 -> 7.4661599 | FL33: 47636 | FM33: 355657.99 | FN33: 372499 | FP33: =FR33/FQ33 -> 6.641184 | FQ33: 44053 | FR33: 292564.08 | FS33: 360680.93 | FU33: =FW33/FV33 -> 8.864472 | FV33: 38350 | FW33: 339952.5 | FX33: 308425.39 | FZ33: =GB33/GA33 -> 9.5111042 | GA33: 30342 | GB33: 288585.92 | GC33: 339952.5 | GE33: =GG33/GF33 -> 5.3077195 | GF33: 26880 | GG33: 142671.5 | GH33: 397982.64 | GJ33: =GL33/GK33 -> 8.6892839 | GK33: 47021 | GL33: 408578.82 | GM33: 379996.96 | GO33: =GQ33/GP33 -> 13.722612 | GP33: 24246 | GQ33: 332718.44 | GR33: 408578.82 | GT33: =GV33/GU33 -> 10.354128 | GU33: 37922 | GV33: 392649.24 | GW33: 409496.62 | GY33: =HA33/GZ33 -> 5.5512121 | GZ33: =23940+17700 -> 41640 | HA33: 231152.47 | HB33: 409496.61 | HD33: =HF33/HE33 -> 6.7581721 | HE33: 46202 | HF33: 312241.07 | HG33: 217552 | HI33: =HK33/HJ33 -> 6.800796 | HJ33: 46258 | HK33: 314591.22 | HL33: 312241 | HN33: =HP33/HO33 -> 7.6570318 | HO33: 48648 | HP33: 372499.28 | HQ33: 314591 | HS33: =HU33/HT33 -> 7.4661599 | HT33: 47636 | HU33: 355657.99 | HV33: 372499 | HX33: =HZ33/HY33 -> 6.641184 | HY33: 44053 | HZ33: 292564.08 | IA33: 360680.93 | IC33: =IE33/ID33 -> 8.864472 | ID33: 38350 | IE33: 339952.5 | IF33: 308425.39 | IH33: =IJ33/II33 -> 5.3077195 | II33: 26880 | IJ33: 142671.5 | IK33: =272477.32+140496.12+12772.37 -> 425745.81 | IM33: =IO33/IN33 -> 5.3077195 | IN33: 26880 | IO33: 142671.5 | IP33: 99077.44
C34: 41946011 | D34: «ДТЕК КИЇВСЬКІ ЕЛЕКТРОМЕРЕЖІ» | E34: Реактивная ЭЭ | I34: 1 208,50 | N34: 1608.624 | S34: 1 481,46 | X34: 1705.212 | AC34: 2015.24 | AH34: 2 055,08 | AM34: 2 183,15 | AR34: 2431.16 | AW34: 2940.72 | BB34: 3359.38 | BG34: 2161.44 | BL34: 2 950,96 | BQ34: 2 275,88 | BU34: 1 | BV34: 2431.86 | CA34: 2327.21 | CF34: 2089.07 | CK34: 1751.46 | CP34: 1902.78 | CU34: 2431.67 | CZ34: 1 208,50 | DE34: 1 208,50 | DJ34: 1 208,50 | DO34: 1 208,50 | DS34: 1 | DT34: 3367.03 | DY34: 1 208,50 | EC34: 1 | ED34: 4487.58 | EI34: 3835.19 | EN34: 2089.07 | ES34: 4377.7 | EX34: 1902.78 | FC34: 2431.67 | FH34: 1 208,50 | FI34: 4983.94 | FM34: 1 208,50 | FR34: 1 208,50 | FW34: 1 208,50 | GA34: 1 | GB34: 3367.03 | GG34: 1 208,50 | GK34: 1 | GL34: 4487.58 | GQ34: 3835.19 | GV34: 2089.07 | HA34: 4377.7 | HF34: 1902.78 | HK34: 2431.67 | HP34: 1 208,50 | HQ34: 4983.94 | HU34: 1 208,50 | HZ34: 1 208,50 | IE34: 1 208,50 | II34: 1 | IJ34: 3367.03 | IO34: 1 208,50
